// class version 49.0 (49)
// access flags 0x1
public class EE__Slash__177280648321 extends com/saxonica/ee/bytecode/GeneratedCode  {


  // access flags 0x1
  public <init>()V
    LINENUMBER 8 L0
    ALOAD 0
    INVOKESPECIAL com/saxonica/ee/bytecode/GeneratedCode.<init> ()V
    RETURN
    MAXSTACK = 0
    MAXLOCALS = 0

  // access flags 0x1
  public process(Lnet/sf/saxon/expr/XPathContext;)V throws net/sf/saxon/trans/XPathException 
    ALOAD 1
    INVOKEINTERFACE net/sf/saxon/expr/XPathContext.getReceiver ()Lnet/sf/saxon/event/SequenceReceiver;
    ASTORE 2
    LINENUMBER 8 L0
   L1
    LDC "FixedElement-out"
    INVOKESTATIC com/saxonica/ee/bytecode/util/ByteCodeTrace.showMessage (Ljava/lang/String;)V
   L2
    LDC "ElementCreator-push"
    INVOKESTATIC com/saxonica/ee/bytecode/util/ByteCodeTrace.showMessage (Ljava/lang/String;)V
    ALOAD 2
    DUP
    LDC "Receiver: "
    SWAP
    DUP
    IFNULL L3
    INVOKEVIRTUAL java/lang/Object.toString ()Ljava/lang/String;
    INVOKESTATIC com/saxonica/ee/bytecode/util/ByteCodeTrace.showObjectVariable (Ljava/lang/String;Ljava/lang/String;)V
    GOTO L4
   L3
    SIPUSH 400
    INVOKESTATIC com/saxonica/ee/bytecode/util/ByteCodeTrace.trace (I)V
    POP
    LDC "null"
    INVOKESTATIC com/saxonica/ee/bytecode/util/ByteCodeTrace.showObjectVariable (Ljava/lang/String;Ljava/lang/String;)V
   L4
    SIPUSH 401
    INVOKESTATIC com/saxonica/ee/bytecode/util/ByteCodeTrace.trace (I)V
    INVOKEINTERFACE net/sf/saxon/event/Receiver.getSystemId ()Ljava/lang/String;
    IFNONNULL L5
    ALOAD 2
    LDC "file:/Users/mike/w3c/xslt30-test-B/tests/attr/avt/avt-1205.xsl"
    INVOKEINTERFACE net/sf/saxon/event/Receiver.setSystemId (Ljava/lang/String;)V
   L5
    SIPUSH 402
    INVOKESTATIC com/saxonica/ee/bytecode/util/ByteCodeTrace.trace (I)V
    ALOAD 2
    GETSTATIC EE__Slash__177280648321.nNoNamespaceName178 : Lnet/sf/saxon/om/NoNamespaceName;
    GETSTATIC EE__Slash__177280648321.nUntyped179 : Lnet/sf/saxon/type/Untyped;
    GETSTATIC EE__Slash__177280648321.nLiteralResultElement180 : Lnet/sf/saxon/style/LiteralResultElement;
    ICONST_0
    INVOKEINTERFACE net/sf/saxon/event/Receiver.startElement (Lnet/sf/saxon/om/NodeName;Lnet/sf/saxon/type/SchemaType;Lnet/sf/saxon/expr/parser/Location;I)V
    ALOAD 2
    GETSTATIC EE__Slash__177280648321.nNamespaceBinding181 : Lnet/sf/saxon/om/NamespaceBinding;
    ICONST_0
    INVOKEINTERFACE net/sf/saxon/event/Receiver.namespace (Lnet/sf/saxon/om/NamespaceBinding;I)V
    ALOAD 2
    GETSTATIC EE__Slash__177280648321.nFingerprintedQName182 : Lnet/sf/saxon/om/FingerprintedQName;
    GETSTATIC net/sf/saxon/type/BuiltInAtomicType.UNTYPED_ATOMIC : Lnet/sf/saxon/type/BuiltInAtomicType;
   L6
    LDC "Concat-item"
    INVOKESTATIC com/saxonica/ee/bytecode/util/ByteCodeTrace.showMessage (Ljava/lang/String;)V
    NEW net/sf/saxon/tree/util/FastStringBuffer
    DUP
    BIPUSH 64
    INVOKESPECIAL net/sf/saxon/tree/util/FastStringBuffer.<init> (I)V
    ASTORE 4
    ALOAD 4
   L7
    LDC "StringJoin-Item"
    INVOKESTATIC com/saxonica/ee/bytecode/util/ByteCodeTrace.showMessage (Ljava/lang/String;)V
   L8
    LDC "AtomicSequenceConverterCompiler-Itr"
    INVOKESTATIC com/saxonica/ee/bytecode/util/ByteCodeTrace.showMessage (Ljava/lang/String;)V
   L9
    LDC "AtomicSequenceConverterCompiler-string"
    INVOKESTATIC com/saxonica/ee/bytecode/util/ByteCodeTrace.showMessage (Ljava/lang/String;)V
    NEW net/sf/saxon/expr/ItemMappingIterator
    DUP
   L10
    LDC "AtomizerCompiler-Itr"
    INVOKESTATIC com/saxonica/ee/bytecode/util/ByteCodeTrace.showMessage (Ljava/lang/String;)V
    NEW net/sf/saxon/tree/iter/AdjacentTextNodeMergingIterator
    DUP
    ICONST_1
    ANEWARRAY net/sf/saxon/om/Sequence
    ASTORE 5
    ALOAD 5
    ICONST_0
   L11
    LDC "LiteralCompiler-item"
    INVOKESTATIC com/saxonica/ee/bytecode/util/ByteCodeTrace.showMessage (Ljava/lang/String;)V
    LCONST_0
    INVOKESTATIC net/sf/saxon/value/Int64Value.makeIntegerValue (J)Lnet/sf/saxon/value/Int64Value;
    DUP
    IFNONNULL L12
    POP
    INVOKESTATIC net/sf/saxon/value/EmptySequence.getInstance ()Lnet/sf/saxon/value/EmptySequence;
   L12
    SIPUSH 403
    INVOKESTATIC com/saxonica/ee/bytecode/util/ByteCodeTrace.trace (I)V
    AASTORE
    ALOAD 1
    INVOKEINTERFACE net/sf/saxon/expr/XPathContext.newCleanContext ()Lnet/sf/saxon/expr/XPathContextMajor;
    ASTORE 6
    ALOAD 6
    GETSTATIC EE__Slash__177280648321.nUserFunctionCall183 : Lnet/sf/saxon/expr/UserFunctionCall;
    INVOKEVIRTUAL net/sf/saxon/expr/XPathContextMajor.setOrigin (Lnet/sf/saxon/expr/ContextOriginator;)V
    ALOAD 6
    SIPUSH 158
    INVOKEINTERFACE net/sf/saxon/expr/XPathContext.setTemporaryOutputState (I)V
    ALOAD 6
    ALOAD 1
    ICONST_0
    INVOKEINTERFACE net/sf/saxon/expr/XPathContext.getTargetComponent (I)Lnet/sf/saxon/expr/Component;
    DUP_X1
    INVOKEVIRTUAL net/sf/saxon/expr/XPathContextMajor.setCurrentComponent (Lnet/sf/saxon/expr/Component;)V
    INVOKEVIRTUAL net/sf/saxon/expr/Component.getCode ()Lnet/sf/saxon/expr/instruct/ComponentCode;
    CHECKCAST net/sf/saxon/expr/instruct/UserFunction
    ALOAD 6
    ALOAD 5
    INVOKEVIRTUAL net/sf/saxon/expr/instruct/UserFunction.call (Lnet/sf/saxon/expr/XPathContext;[Lnet/sf/saxon/om/Sequence;)Lnet/sf/saxon/om/Sequence;
   L13
    SIPUSH 404
    INVOKESTATIC com/saxonica/ee/bytecode/util/ByteCodeTrace.trace (I)V
   L14
    LDC "UserFunctionCallCompiler -Itr"
    INVOKESTATIC com/saxonica/ee/bytecode/util/ByteCodeTrace.showMessage (Ljava/lang/String;)V
    INVOKEINTERFACE net/sf/saxon/om/Sequence.iterate ()Lnet/sf/saxon/om/SequenceIterator;
    INVOKESPECIAL net/sf/saxon/tree/iter/AdjacentTextNodeMergingIterator.<init> (Lnet/sf/saxon/om/SequenceIterator;)V
    ICONST_1
    INVOKESTATIC net/sf/saxon/expr/Atomizer.getAtomizingIterator (Lnet/sf/saxon/om/SequenceIterator;Z)Lnet/sf/saxon/om/SequenceIterator;
    GETSTATIC net/sf/saxon/expr/AtomicSequenceConverter.TO_STRING_MAPPER : Lnet/sf/saxon/expr/AtomicSequenceConverter$ToStringMappingFunction;
    ICONST_1
    INVOKESPECIAL net/sf/saxon/expr/ItemMappingIterator.<init> (Lnet/sf/saxon/om/SequenceIterator;Lnet/sf/saxon/expr/ItemMappingFunction;Z)V
   L15
    LDC "StringJoin-Item-1"
    INVOKESTATIC com/saxonica/ee/bytecode/util/ByteCodeTrace.showMessage (Ljava/lang/String;)V
    ASTORE 7
    ALOAD 7
    INVOKEINTERFACE net/sf/saxon/om/SequenceIterator.next ()Lnet/sf/saxon/om/Item;
    DUP
    IFNONNULL L16
    POP
    LDC ""
    GOTO L17
   L16
    SIPUSH 405
    INVOKESTATIC com/saxonica/ee/bytecode/util/ByteCodeTrace.trace (I)V
    INVOKEINTERFACE net/sf/saxon/om/Item.getStringValueCS ()Ljava/lang/CharSequence;
    ASTORE 8
    ALOAD 7
    INVOKEINTERFACE net/sf/saxon/om/SequenceIterator.next ()Lnet/sf/saxon/om/Item;
    DUP
    IFNONNULL L18
    POP
    ALOAD 8
    GOTO L17
   L18
    SIPUSH 406
    INVOKESTATIC com/saxonica/ee/bytecode/util/ByteCodeTrace.trace (I)V
    NEW net/sf/saxon/tree/util/FastStringBuffer
    DUP
    BIPUSH 64
    INVOKESPECIAL net/sf/saxon/tree/util/FastStringBuffer.<init> (I)V
    ASTORE 9
    ALOAD 9
    ALOAD 8
    INVOKEVIRTUAL net/sf/saxon/tree/util/FastStringBuffer.append (Ljava/lang/CharSequence;)V
   L19
    LDC "LiteralCompiler-Primitive"
    INVOKESTATIC com/saxonica/ee/bytecode/util/ByteCodeTrace.showMessage (Ljava/lang/String;)V
    LDC " "
    ASTORE 10
    ALOAD 9
    ALOAD 10
    INVOKEVIRTUAL net/sf/saxon/tree/util/FastStringBuffer.append (Ljava/lang/CharSequence;)V
    ALOAD 9
    SWAP
    INVOKEINTERFACE net/sf/saxon/om/Item.getStringValueCS ()Ljava/lang/CharSequence;
    INVOKEVIRTUAL net/sf/saxon/tree/util/FastStringBuffer.append (Ljava/lang/CharSequence;)V
   L20
    SIPUSH 407
    INVOKESTATIC com/saxonica/ee/bytecode/util/ByteCodeTrace.trace (I)V
    ALOAD 7
    INVOKEINTERFACE net/sf/saxon/om/SequenceIterator.next ()Lnet/sf/saxon/om/Item;
    DUP
    IFNULL L21
    ALOAD 9
    ALOAD 10
    INVOKEVIRTUAL net/sf/saxon/tree/util/FastStringBuffer.append (Ljava/lang/CharSequence;)V
    ALOAD 9
    SWAP
    INVOKEINTERFACE net/sf/saxon/om/Item.getStringValueCS ()Ljava/lang/CharSequence;
    INVOKEVIRTUAL net/sf/saxon/tree/util/FastStringBuffer.append (Ljava/lang/CharSequence;)V
    GOTO L20
   L21
    SIPUSH 408
    INVOKESTATIC com/saxonica/ee/bytecode/util/ByteCodeTrace.trace (I)V
    POP
    ALOAD 9
    INVOKEVIRTUAL net/sf/saxon/tree/util/FastStringBuffer.condense ()Ljava/lang/CharSequence;
   L17
    SIPUSH 409
    INVOKESTATIC com/saxonica/ee/bytecode/util/ByteCodeTrace.trace (I)V
    INVOKEVIRTUAL net/sf/saxon/tree/util/FastStringBuffer.append (Ljava/lang/CharSequence;)V
    ALOAD 4
   L22
    LDC "StringJoin-Item"
    INVOKESTATIC com/saxonica/ee/bytecode/util/ByteCodeTrace.showMessage (Ljava/lang/String;)V
   L23
    LDC "AtomicSequenceConverterCompiler-Itr"
    INVOKESTATIC com/saxonica/ee/bytecode/util/ByteCodeTrace.showMessage (Ljava/lang/String;)V
   L24
    LDC "AtomicSequenceConverterCompiler-string"
    INVOKESTATIC com/saxonica/ee/bytecode/util/ByteCodeTrace.showMessage (Ljava/lang/String;)V
    NEW net/sf/saxon/expr/ItemMappingIterator
    DUP
   L25
    LDC "AtomizerCompiler-Itr"
    INVOKESTATIC com/saxonica/ee/bytecode/util/ByteCodeTrace.showMessage (Ljava/lang/String;)V
    NEW net/sf/saxon/tree/iter/AdjacentTextNodeMergingIterator
    DUP
    ICONST_1
    ANEWARRAY net/sf/saxon/om/Sequence
    ASTORE 5
    ALOAD 5
    ICONST_0
   L26
    LDC "LiteralCompiler-item"
    INVOKESTATIC com/saxonica/ee/bytecode/util/ByteCodeTrace.showMessage (Ljava/lang/String;)V
    LCONST_1
    INVOKESTATIC net/sf/saxon/value/Int64Value.makeIntegerValue (J)Lnet/sf/saxon/value/Int64Value;
    DUP
    IFNONNULL L27
    POP
    INVOKESTATIC net/sf/saxon/value/EmptySequence.getInstance ()Lnet/sf/saxon/value/EmptySequence;
   L27
    SIPUSH 410
    INVOKESTATIC com/saxonica/ee/bytecode/util/ByteCodeTrace.trace (I)V
    AASTORE
    ALOAD 1
    INVOKEINTERFACE net/sf/saxon/expr/XPathContext.newCleanContext ()Lnet/sf/saxon/expr/XPathContextMajor;
    ASTORE 6
    ALOAD 6
    GETSTATIC EE__Slash__177280648321.nUserFunctionCall184 : Lnet/sf/saxon/expr/UserFunctionCall;
    INVOKEVIRTUAL net/sf/saxon/expr/XPathContextMajor.setOrigin (Lnet/sf/saxon/expr/ContextOriginator;)V
    ALOAD 6
    SIPUSH 158
    INVOKEINTERFACE net/sf/saxon/expr/XPathContext.setTemporaryOutputState (I)V
    ALOAD 6
    ALOAD 1
    ICONST_1
    INVOKEINTERFACE net/sf/saxon/expr/XPathContext.getTargetComponent (I)Lnet/sf/saxon/expr/Component;
    DUP_X1
    INVOKEVIRTUAL net/sf/saxon/expr/XPathContextMajor.setCurrentComponent (Lnet/sf/saxon/expr/Component;)V
    INVOKEVIRTUAL net/sf/saxon/expr/Component.getCode ()Lnet/sf/saxon/expr/instruct/ComponentCode;
    CHECKCAST net/sf/saxon/expr/instruct/UserFunction
    ALOAD 6
    ALOAD 5
    INVOKEVIRTUAL net/sf/saxon/expr/instruct/UserFunction.call (Lnet/sf/saxon/expr/XPathContext;[Lnet/sf/saxon/om/Sequence;)Lnet/sf/saxon/om/Sequence;
   L28
    SIPUSH 411
    INVOKESTATIC com/saxonica/ee/bytecode/util/ByteCodeTrace.trace (I)V
   L29
    LDC "UserFunctionCallCompiler -Itr"
    INVOKESTATIC com/saxonica/ee/bytecode/util/ByteCodeTrace.showMessage (Ljava/lang/String;)V
    INVOKEINTERFACE net/sf/saxon/om/Sequence.iterate ()Lnet/sf/saxon/om/SequenceIterator;
    INVOKESPECIAL net/sf/saxon/tree/iter/AdjacentTextNodeMergingIterator.<init> (Lnet/sf/saxon/om/SequenceIterator;)V
    ICONST_1
    INVOKESTATIC net/sf/saxon/expr/Atomizer.getAtomizingIterator (Lnet/sf/saxon/om/SequenceIterator;Z)Lnet/sf/saxon/om/SequenceIterator;
    GETSTATIC net/sf/saxon/expr/AtomicSequenceConverter.TO_STRING_MAPPER : Lnet/sf/saxon/expr/AtomicSequenceConverter$ToStringMappingFunction;
    ICONST_1
    INVOKESPECIAL net/sf/saxon/expr/ItemMappingIterator.<init> (Lnet/sf/saxon/om/SequenceIterator;Lnet/sf/saxon/expr/ItemMappingFunction;Z)V
   L30
    LDC "StringJoin-Item-1"
    INVOKESTATIC com/saxonica/ee/bytecode/util/ByteCodeTrace.showMessage (Ljava/lang/String;)V
    ASTORE 7
    ALOAD 7
    INVOKEINTERFACE net/sf/saxon/om/SequenceIterator.next ()Lnet/sf/saxon/om/Item;
    DUP
    IFNONNULL L31
    POP
    LDC ""
    GOTO L32
   L31
    SIPUSH 412
    INVOKESTATIC com/saxonica/ee/bytecode/util/ByteCodeTrace.trace (I)V
    INVOKEINTERFACE net/sf/saxon/om/Item.getStringValueCS ()Ljava/lang/CharSequence;
    ASTORE 10
    ALOAD 7
    INVOKEINTERFACE net/sf/saxon/om/SequenceIterator.next ()Lnet/sf/saxon/om/Item;
    DUP
    IFNONNULL L33
    POP
    ALOAD 10
    GOTO L32
   L33
    SIPUSH 413
    INVOKESTATIC com/saxonica/ee/bytecode/util/ByteCodeTrace.trace (I)V
    NEW net/sf/saxon/tree/util/FastStringBuffer
    DUP
    BIPUSH 64
    INVOKESPECIAL net/sf/saxon/tree/util/FastStringBuffer.<init> (I)V
    ASTORE 9
    ALOAD 9
    ALOAD 10
    INVOKEVIRTUAL net/sf/saxon/tree/util/FastStringBuffer.append (Ljava/lang/CharSequence;)V
   L34
    LDC "LiteralCompiler-Primitive"
    INVOKESTATIC com/saxonica/ee/bytecode/util/ByteCodeTrace.showMessage (Ljava/lang/String;)V
    LDC " "
    ASTORE 11
    ALOAD 9
    ALOAD 11
    INVOKEVIRTUAL net/sf/saxon/tree/util/FastStringBuffer.append (Ljava/lang/CharSequence;)V
    ALOAD 9
    SWAP
    INVOKEINTERFACE net/sf/saxon/om/Item.getStringValueCS ()Ljava/lang/CharSequence;
    INVOKEVIRTUAL net/sf/saxon/tree/util/FastStringBuffer.append (Ljava/lang/CharSequence;)V
   L35
    SIPUSH 414
    INVOKESTATIC com/saxonica/ee/bytecode/util/ByteCodeTrace.trace (I)V
    ALOAD 7
    INVOKEINTERFACE net/sf/saxon/om/SequenceIterator.next ()Lnet/sf/saxon/om/Item;
    DUP
    IFNULL L36
    ALOAD 9
    ALOAD 11
    INVOKEVIRTUAL net/sf/saxon/tree/util/FastStringBuffer.append (Ljava/lang/CharSequence;)V
    ALOAD 9
    SWAP
    INVOKEINTERFACE net/sf/saxon/om/Item.getStringValueCS ()Ljava/lang/CharSequence;
    INVOKEVIRTUAL net/sf/saxon/tree/util/FastStringBuffer.append (Ljava/lang/CharSequence;)V
    GOTO L35
   L36
    SIPUSH 415
    INVOKESTATIC com/saxonica/ee/bytecode/util/ByteCodeTrace.trace (I)V
    POP
    ALOAD 9
    INVOKEVIRTUAL net/sf/saxon/tree/util/FastStringBuffer.condense ()Ljava/lang/CharSequence;
   L32
    SIPUSH 416
    INVOKESTATIC com/saxonica/ee/bytecode/util/ByteCodeTrace.trace (I)V
    INVOKEVIRTUAL net/sf/saxon/tree/util/FastStringBuffer.append (Ljava/lang/CharSequence;)V
    ALOAD 4
   L37
    LDC "StringJoin-Item"
    INVOKESTATIC com/saxonica/ee/bytecode/util/ByteCodeTrace.showMessage (Ljava/lang/String;)V
   L38
    LDC "AtomicSequenceConverterCompiler-Itr"
    INVOKESTATIC com/saxonica/ee/bytecode/util/ByteCodeTrace.showMessage (Ljava/lang/String;)V
   L39
    LDC "AtomicSequenceConverterCompiler-string"
    INVOKESTATIC com/saxonica/ee/bytecode/util/ByteCodeTrace.showMessage (Ljava/lang/String;)V
    NEW net/sf/saxon/expr/ItemMappingIterator
    DUP
   L40
    LDC "AtomizerCompiler-Itr"
    INVOKESTATIC com/saxonica/ee/bytecode/util/ByteCodeTrace.showMessage (Ljava/lang/String;)V
    NEW net/sf/saxon/tree/iter/AdjacentTextNodeMergingIterator
    DUP
    ICONST_1
    ANEWARRAY net/sf/saxon/om/Sequence
    ASTORE 5
    ALOAD 5
    ICONST_0
   L41
    LDC "LiteralCompiler-item"
    INVOKESTATIC com/saxonica/ee/bytecode/util/ByteCodeTrace.showMessage (Ljava/lang/String;)V
    LDC 2
    INVOKESTATIC net/sf/saxon/value/Int64Value.makeIntegerValue (J)Lnet/sf/saxon/value/Int64Value;
    DUP
    IFNONNULL L42
    POP
    INVOKESTATIC net/sf/saxon/value/EmptySequence.getInstance ()Lnet/sf/saxon/value/EmptySequence;
   L42
    SIPUSH 417
    INVOKESTATIC com/saxonica/ee/bytecode/util/ByteCodeTrace.trace (I)V
    AASTORE
    ALOAD 1
    INVOKEINTERFACE net/sf/saxon/expr/XPathContext.newCleanContext ()Lnet/sf/saxon/expr/XPathContextMajor;
    ASTORE 6
    ALOAD 6
    GETSTATIC EE__Slash__177280648321.nUserFunctionCall185 : Lnet/sf/saxon/expr/UserFunctionCall;
    INVOKEVIRTUAL net/sf/saxon/expr/XPathContextMajor.setOrigin (Lnet/sf/saxon/expr/ContextOriginator;)V
    ALOAD 6
    SIPUSH 158
    INVOKEINTERFACE net/sf/saxon/expr/XPathContext.setTemporaryOutputState (I)V
    ALOAD 6
    ALOAD 1
    ICONST_2
    INVOKEINTERFACE net/sf/saxon/expr/XPathContext.getTargetComponent (I)Lnet/sf/saxon/expr/Component;
    DUP_X1
    INVOKEVIRTUAL net/sf/saxon/expr/XPathContextMajor.setCurrentComponent (Lnet/sf/saxon/expr/Component;)V
    INVOKEVIRTUAL net/sf/saxon/expr/Component.getCode ()Lnet/sf/saxon/expr/instruct/ComponentCode;
    CHECKCAST net/sf/saxon/expr/instruct/UserFunction
    ALOAD 6
    ALOAD 5
    INVOKEVIRTUAL net/sf/saxon/expr/instruct/UserFunction.call (Lnet/sf/saxon/expr/XPathContext;[Lnet/sf/saxon/om/Sequence;)Lnet/sf/saxon/om/Sequence;
   L43
    SIPUSH 418
    INVOKESTATIC com/saxonica/ee/bytecode/util/ByteCodeTrace.trace (I)V
   L44
    LDC "UserFunctionCallCompiler -Itr"
    INVOKESTATIC com/saxonica/ee/bytecode/util/ByteCodeTrace.showMessage (Ljava/lang/String;)V
    INVOKEINTERFACE net/sf/saxon/om/Sequence.iterate ()Lnet/sf/saxon/om/SequenceIterator;
    INVOKESPECIAL net/sf/saxon/tree/iter/AdjacentTextNodeMergingIterator.<init> (Lnet/sf/saxon/om/SequenceIterator;)V
    ICONST_1
    INVOKESTATIC net/sf/saxon/expr/Atomizer.getAtomizingIterator (Lnet/sf/saxon/om/SequenceIterator;Z)Lnet/sf/saxon/om/SequenceIterator;
    GETSTATIC net/sf/saxon/expr/AtomicSequenceConverter.TO_STRING_MAPPER : Lnet/sf/saxon/expr/AtomicSequenceConverter$ToStringMappingFunction;
    ICONST_1
    INVOKESPECIAL net/sf/saxon/expr/ItemMappingIterator.<init> (Lnet/sf/saxon/om/SequenceIterator;Lnet/sf/saxon/expr/ItemMappingFunction;Z)V
   L45
    LDC "StringJoin-Item-1"
    INVOKESTATIC com/saxonica/ee/bytecode/util/ByteCodeTrace.showMessage (Ljava/lang/String;)V
    ASTORE 7
    ALOAD 7
    INVOKEINTERFACE net/sf/saxon/om/SequenceIterator.next ()Lnet/sf/saxon/om/Item;
    DUP
    IFNONNULL L46
    POP
    LDC ""
    GOTO L47
   L46
    SIPUSH 419
    INVOKESTATIC com/saxonica/ee/bytecode/util/ByteCodeTrace.trace (I)V
    INVOKEINTERFACE net/sf/saxon/om/Item.getStringValueCS ()Ljava/lang/CharSequence;
    ASTORE 11
    ALOAD 7
    INVOKEINTERFACE net/sf/saxon/om/SequenceIterator.next ()Lnet/sf/saxon/om/Item;
    DUP
    IFNONNULL L48
    POP
    ALOAD 11
    GOTO L47
   L48
    SIPUSH 420
    INVOKESTATIC com/saxonica/ee/bytecode/util/ByteCodeTrace.trace (I)V
    NEW net/sf/saxon/tree/util/FastStringBuffer
    DUP
    BIPUSH 64
    INVOKESPECIAL net/sf/saxon/tree/util/FastStringBuffer.<init> (I)V
    ASTORE 9
    ALOAD 9
    ALOAD 11
    INVOKEVIRTUAL net/sf/saxon/tree/util/FastStringBuffer.append (Ljava/lang/CharSequence;)V
   L49
    LDC "LiteralCompiler-Primitive"
    INVOKESTATIC com/saxonica/ee/bytecode/util/ByteCodeTrace.showMessage (Ljava/lang/String;)V
    LDC " "
    ASTORE 12
    ALOAD 9
    ALOAD 12
    INVOKEVIRTUAL net/sf/saxon/tree/util/FastStringBuffer.append (Ljava/lang/CharSequence;)V
    ALOAD 9
    SWAP
    INVOKEINTERFACE net/sf/saxon/om/Item.getStringValueCS ()Ljava/lang/CharSequence;
    INVOKEVIRTUAL net/sf/saxon/tree/util/FastStringBuffer.append (Ljava/lang/CharSequence;)V
   L50
    SIPUSH 421
    INVOKESTATIC com/saxonica/ee/bytecode/util/ByteCodeTrace.trace (I)V
    ALOAD 7
    INVOKEINTERFACE net/sf/saxon/om/SequenceIterator.next ()Lnet/sf/saxon/om/Item;
    DUP
    IFNULL L51
    ALOAD 9
    ALOAD 12
    INVOKEVIRTUAL net/sf/saxon/tree/util/FastStringBuffer.append (Ljava/lang/CharSequence;)V
    ALOAD 9
    SWAP
    INVOKEINTERFACE net/sf/saxon/om/Item.getStringValueCS ()Ljava/lang/CharSequence;
    INVOKEVIRTUAL net/sf/saxon/tree/util/FastStringBuffer.append (Ljava/lang/CharSequence;)V
    GOTO L50
   L51
    SIPUSH 422
    INVOKESTATIC com/saxonica/ee/bytecode/util/ByteCodeTrace.trace (I)V
    POP
    ALOAD 9
    INVOKEVIRTUAL net/sf/saxon/tree/util/FastStringBuffer.condense ()Ljava/lang/CharSequence;
   L47
    SIPUSH 423
    INVOKESTATIC com/saxonica/ee/bytecode/util/ByteCodeTrace.trace (I)V
    INVOKEVIRTUAL net/sf/saxon/tree/util/FastStringBuffer.append (Ljava/lang/CharSequence;)V
    ALOAD 4
    INVOKEVIRTUAL net/sf/saxon/tree/util/FastStringBuffer.condense ()Ljava/lang/CharSequence;
    GETSTATIC EE__Slash__177280648321.nLiteralResultElement180 : Lnet/sf/saxon/style/LiteralResultElement;
    ICONST_0
    INVOKEINTERFACE net/sf/saxon/event/Receiver.attribute (Lnet/sf/saxon/om/NodeName;Lnet/sf/saxon/type/SimpleType;Ljava/lang/CharSequence;Lnet/sf/saxon/expr/parser/Location;I)V
    ALOAD 2
    INVOKEINTERFACE net/sf/saxon/event/Receiver.endElement ()V
    RETURN
    MAXSTACK = 0
    MAXLOCALS = 0
}

  // access flags 0x9
  public static Lnet/sf/saxon/om/FingerprintedQName; nFingerprintedQName182

  // access flags 0x9
  public static Lnet/sf/saxon/style/LiteralResultElement; nLiteralResultElement180

  // access flags 0x9
  public static Lnet/sf/saxon/om/NoNamespaceName; nNoNamespaceName178

  // access flags 0x9
  public static Lnet/sf/saxon/om/NamespaceBinding; nNamespaceBinding181

  // access flags 0x9
  public static Lnet/sf/saxon/type/Untyped; nUntyped179

  // access flags 0x9
  public static Lnet/sf/saxon/expr/UserFunctionCall; nUserFunctionCall184

  // access flags 0x9
  public static Lnet/sf/saxon/expr/UserFunctionCall; nUserFunctionCall185

  // access flags 0x9
  public static Lnet/sf/saxon/expr/UserFunctionCall; nUserFunctionCall183
}
