// class version 49.0 (49)
// access flags 0x1
public class EE__Slash_doc_40517978947 extends com/saxonica/ee/bytecode/GeneratedCode  {


  // access flags 0x1
  public <init>()V
    LINENUMBER 18 L0
    ALOAD 0
    INVOKESPECIAL com/saxonica/ee/bytecode/GeneratedCode.<init> ()V
    RETURN
    MAXSTACK = 0
    MAXLOCALS = 0

  // access flags 0x1
  public process(Lnet/sf/saxon/expr/XPathContext;)V throws net/sf/saxon/trans/XPathException 
    ALOAD 1
    INVOKEINTERFACE net/sf/saxon/expr/XPathContext.getReceiver ()Lnet/sf/saxon/event/SequenceReceiver;
    ASTORE 2
    LINENUMBER 18 L0
   L1
    LDC "FixedElement-out"
    INVOKESTATIC com/saxonica/ee/bytecode/util/ByteCodeTrace.showMessage (Ljava/lang/String;)V
   L2
    LDC "ElementCreator-push"
    INVOKESTATIC com/saxonica/ee/bytecode/util/ByteCodeTrace.showMessage (Ljava/lang/String;)V
    ALOAD 2
    DUP
    LDC "Receiver: "
    SWAP
    DUP
    IFNULL L3
    INVOKEVIRTUAL java/lang/Object.toString ()Ljava/lang/String;
    INVOKESTATIC com/saxonica/ee/bytecode/util/ByteCodeTrace.showObjectVariable (Ljava/lang/String;Ljava/lang/String;)V
    GOTO L4
   L3
    BIPUSH 74
    INVOKESTATIC com/saxonica/ee/bytecode/util/ByteCodeTrace.trace (I)V
    POP
    LDC "null"
    INVOKESTATIC com/saxonica/ee/bytecode/util/ByteCodeTrace.showObjectVariable (Ljava/lang/String;Ljava/lang/String;)V
   L4
    BIPUSH 75
    INVOKESTATIC com/saxonica/ee/bytecode/util/ByteCodeTrace.trace (I)V
    INVOKEINTERFACE net/sf/saxon/event/Receiver.getSystemId ()Ljava/lang/String;
    IFNONNULL L5
    ALOAD 2
    LDC "file:/Users/mike/w3c/xslt30-test-B/tests/attr/avt/avt-0303.xsl"
    INVOKEINTERFACE net/sf/saxon/event/Receiver.setSystemId (Ljava/lang/String;)V
   L5
    BIPUSH 76
    INVOKESTATIC com/saxonica/ee/bytecode/util/ByteCodeTrace.trace (I)V
    ALOAD 2
    GETSTATIC EE__Slash_doc_40517978947.nNoNamespaceName41 : Lnet/sf/saxon/om/NoNamespaceName;
    GETSTATIC EE__Slash_doc_40517978947.nUntyped42 : Lnet/sf/saxon/type/Untyped;
    GETSTATIC EE__Slash_doc_40517978947.nAttributeLocation43 : Lnet/sf/saxon/style/ExpressionContext$AttributeLocation;
    ICONST_0
    INVOKEINTERFACE net/sf/saxon/event/Receiver.startElement (Lnet/sf/saxon/om/NodeName;Lnet/sf/saxon/type/SchemaType;Lnet/sf/saxon/expr/parser/Location;I)V
   L6
    LDC "BlockCompiler-Push"
    INVOKESTATIC com/saxonica/ee/bytecode/util/ByteCodeTrace.showMessage (Ljava/lang/String;)V
   L7
    LDC "SimpleNodeConstructorCompiler-Push"
    INVOKESTATIC com/saxonica/ee/bytecode/util/ByteCodeTrace.showMessage (Ljava/lang/String;)V
    ALOAD 2
   L8
    LDC "LiteralCompiler-Primitive"
    INVOKESTATIC com/saxonica/ee/bytecode/util/ByteCodeTrace.showMessage (Ljava/lang/String;)V
    LDC "\n"
    GETSTATIC EE__Slash_doc_40517978947.nAttributeLocation43 : Lnet/sf/saxon/style/ExpressionContext$AttributeLocation;
    ICONST_0
    INVOKEINTERFACE net/sf/saxon/event/Receiver.characters (Ljava/lang/CharSequence;Lnet/sf/saxon/expr/parser/Location;I)V
   L9
    LDC "FixedElement-elem"
    INVOKESTATIC com/saxonica/ee/bytecode/util/ByteCodeTrace.showMessage (Ljava/lang/String;)V
   L10
    LDC "ElementCreator-push"
    INVOKESTATIC com/saxonica/ee/bytecode/util/ByteCodeTrace.showMessage (Ljava/lang/String;)V
    ALOAD 2
    DUP
    LDC "Receiver: "
    SWAP
    DUP
    IFNULL L11
    INVOKEVIRTUAL java/lang/Object.toString ()Ljava/lang/String;
    INVOKESTATIC com/saxonica/ee/bytecode/util/ByteCodeTrace.showObjectVariable (Ljava/lang/String;Ljava/lang/String;)V
    GOTO L12
   L11
    BIPUSH 77
    INVOKESTATIC com/saxonica/ee/bytecode/util/ByteCodeTrace.trace (I)V
    POP
    LDC "null"
    INVOKESTATIC com/saxonica/ee/bytecode/util/ByteCodeTrace.showObjectVariable (Ljava/lang/String;Ljava/lang/String;)V
   L12
    BIPUSH 78
    INVOKESTATIC com/saxonica/ee/bytecode/util/ByteCodeTrace.trace (I)V
    INVOKEINTERFACE net/sf/saxon/event/Receiver.getSystemId ()Ljava/lang/String;
    IFNONNULL L13
    ALOAD 2
    LDC "file:/Users/mike/w3c/xslt30-test-B/tests/attr/avt/avt-0303.xsl"
    INVOKEINTERFACE net/sf/saxon/event/Receiver.setSystemId (Ljava/lang/String;)V
   L13
    BIPUSH 79
    INVOKESTATIC com/saxonica/ee/bytecode/util/ByteCodeTrace.trace (I)V
    ALOAD 2
    GETSTATIC EE__Slash_doc_40517978947.nFingerprintedQName44 : Lnet/sf/saxon/om/FingerprintedQName;
    GETSTATIC EE__Slash_doc_40517978947.nUntyped42 : Lnet/sf/saxon/type/Untyped;
    GETSTATIC EE__Slash_doc_40517978947.nAttributeLocation43 : Lnet/sf/saxon/style/ExpressionContext$AttributeLocation;
    ICONST_0
    INVOKEINTERFACE net/sf/saxon/event/Receiver.startElement (Lnet/sf/saxon/om/NodeName;Lnet/sf/saxon/type/SchemaType;Lnet/sf/saxon/expr/parser/Location;I)V
   L14
    LDC "BlockCompiler-Push"
    INVOKESTATIC com/saxonica/ee/bytecode/util/ByteCodeTrace.showMessage (Ljava/lang/String;)V
   L15
    LDC "SimpleNodeConstructorCompiler-Push"
    INVOKESTATIC com/saxonica/ee/bytecode/util/ByteCodeTrace.showMessage (Ljava/lang/String;)V
    ALOAD 2
   L16
    LDC "StringFn-str"
    INVOKESTATIC com/saxonica/ee/bytecode/util/ByteCodeTrace.showMessage (Ljava/lang/String;)V
    TRYCATCHBLOCK L17 L18 L19 java/lang/UnsupportedOperationException
   L17
    BIPUSH 80
    INVOKESTATIC com/saxonica/ee/bytecode/util/ByteCodeTrace.trace (I)V
   L20
    LDC "AtomicSequenceConverterCompiler-Item"
    INVOKESTATIC com/saxonica/ee/bytecode/util/ByteCodeTrace.showMessage (Ljava/lang/String;)V
   L21
    LDC "AtomizerCompiler-Item"
    INVOKESTATIC com/saxonica/ee/bytecode/util/ByteCodeTrace.showMessage (Ljava/lang/String;)V
   L22
    LDC "FirstItemExpression"
    INVOKESTATIC com/saxonica/ee/bytecode/util/ByteCodeTrace.showMessage (Ljava/lang/String;)V
   L23
    LDC "AxisExpressionCompiler - iterate"
    INVOKESTATIC com/saxonica/ee/bytecode/util/ByteCodeTrace.showMessage (Ljava/lang/String;)V
    ALOAD 1
    INVOKEINTERFACE net/sf/saxon/expr/XPathContext.getContextItem ()Lnet/sf/saxon/om/Item;
    CHECKCAST net/sf/saxon/om/NodeInfo
   L24
    LDC "AxisExpressionCompiler - static method: iterate"
    INVOKESTATIC com/saxonica/ee/bytecode/util/ByteCodeTrace.showMessage (Ljava/lang/String;)V
    ICONST_3
    GETSTATIC EE__Slash_doc_40517978947.nNameTest45 : Lnet/sf/saxon/pattern/NameTest;
    LDC "calling iterateAxis"
    INVOKESTATIC com/saxonica/ee/bytecode/util/ByteCodeTrace.showMessage (Ljava/lang/String;)V
    INVOKEINTERFACE net/sf/saxon/om/NodeInfo.iterateAxis (BLnet/sf/saxon/pattern/NodeTest;)Lnet/sf/saxon/tree/iter/AxisIterator;
    LDC "returning axis iterator"
    INVOKESTATIC com/saxonica/ee/bytecode/util/ByteCodeTrace.showMessage (Ljava/lang/String;)V
    DUP
    INVOKEINTERFACE net/sf/saxon/om/SequenceIterator.next ()Lnet/sf/saxon/om/Item;
    SWAP
    INVOKEINTERFACE net/sf/saxon/om/SequenceIterator.close ()V
    DUP
    IFNULL L25
    INVOKEINTERFACE net/sf/saxon/om/Item.atomize ()Lnet/sf/saxon/om/AtomicSequence;
    INVOKEINTERFACE net/sf/saxon/om/AtomicSequence.head ()Lnet/sf/saxon/value/AtomicValue;
   L25
    BIPUSH 81
    INVOKESTATIC com/saxonica/ee/bytecode/util/ByteCodeTrace.trace (I)V
   L26
    LDC "AtomicSequenceConverterCompiler-Item-Returned"
    INVOKESTATIC com/saxonica/ee/bytecode/util/ByteCodeTrace.showMessage (Ljava/lang/String;)V
    DUP
    IFNONNULL L27
    POP
    ACONST_NULL
    GOTO L28
   L27
    BIPUSH 82
    INVOKESTATIC com/saxonica/ee/bytecode/util/ByteCodeTrace.trace (I)V
    INVOKEINTERFACE net/sf/saxon/om/Item.getStringValueCS ()Ljava/lang/CharSequence;
    INVOKESTATIC net/sf/saxon/value/StringValue.makeStringValue (Ljava/lang/CharSequence;)Lnet/sf/saxon/value/StringValue;
   L28
    BIPUSH 83
    INVOKESTATIC com/saxonica/ee/bytecode/util/ByteCodeTrace.trace (I)V
    DUP
    IFNONNULL L29
    POP
    LDC ""
    GOTO L30
   L29
    BIPUSH 84
    INVOKESTATIC com/saxonica/ee/bytecode/util/ByteCodeTrace.trace (I)V
    INVOKEINTERFACE net/sf/saxon/om/Item.getStringValueCS ()Ljava/lang/CharSequence;
   L30
    BIPUSH 85
    INVOKESTATIC com/saxonica/ee/bytecode/util/ByteCodeTrace.trace (I)V
   L18
    BIPUSH 86
    INVOKESTATIC com/saxonica/ee/bytecode/util/ByteCodeTrace.trace (I)V
    GOTO L31
   L19
    BIPUSH 87
    INVOKESTATIC com/saxonica/ee/bytecode/util/ByteCodeTrace.trace (I)V
   L32
    LDC "CatchStringFn"
    INVOKESTATIC com/saxonica/ee/bytecode/util/ByteCodeTrace.showMessage (Ljava/lang/String;)V
    INVOKEVIRTUAL java/lang/UnsupportedOperationException.getMessage ()Ljava/lang/String;
    LDC "FOTY0014"
    LDC "file:/Users/mike/w3c/xslt30-test-B/tests/attr/avt/avt-0303.xsl"
    BIPUSH 18
    ICONST_0
    INVOKESTATIC com/saxonica/ee/bytecode/util/Callback.makeXPathException (Ljava/lang/String;Ljava/lang/String;Ljava/lang/String;IZ)Lnet/sf/saxon/trans/XPathException;
    ATHROW
   L31
    BIPUSH 88
    INVOKESTATIC com/saxonica/ee/bytecode/util/ByteCodeTrace.trace (I)V
    INVOKESTATIC net/sf/saxon/value/Whitespace.trim (Ljava/lang/CharSequence;)Ljava/lang/String;
    INVOKEVIRTUAL java/lang/Object.toString ()Ljava/lang/String;
    DUP
    INVOKEINTERFACE java/lang/CharSequence.length ()I
    IFEQ L33
    DUP
    INVOKESTATIC net/sf/saxon/om/NameChecker.isValidNCName (Ljava/lang/CharSequence;)Z
    IFNE L34
    LDC "Namespace prefix is invalid"
    LDC "XTDE0920"
    LDC "file:/Users/mike/w3c/xslt30-test-B/tests/attr/avt/avt-0303.xsl"
    BIPUSH 18
    ICONST_0
    INVOKESTATIC com/saxonica/ee/bytecode/util/Callback.makeXPathException (Ljava/lang/String;Ljava/lang/String;Ljava/lang/String;IZ)Lnet/sf/saxon/trans/XPathException;
    ATHROW
   L34
    BIPUSH 89
    INVOKESTATIC com/saxonica/ee/bytecode/util/ByteCodeTrace.trace (I)V
    DUP
    LDC "xmlns"
    INVOKEVIRTUAL java/lang/Object.equals (Ljava/lang/Object;)Z
    IFEQ L33
    LDC "Namespace prefix must not be 'xmlns'"
    LDC "XTDE0920"
    LDC "file:/Users/mike/w3c/xslt30-test-B/tests/attr/avt/avt-0303.xsl"
    BIPUSH 18
    ICONST_0
    INVOKESTATIC com/saxonica/ee/bytecode/util/Callback.makeXPathException (Ljava/lang/String;Ljava/lang/String;Ljava/lang/String;IZ)Lnet/sf/saxon/trans/XPathException;
    ATHROW
   L33
    BIPUSH 90
    INVOKESTATIC com/saxonica/ee/bytecode/util/ByteCodeTrace.trace (I)V
   L35
    LDC "LiteralCompiler-Primitive"
    INVOKESTATIC com/saxonica/ee/bytecode/util/ByteCodeTrace.showMessage (Ljava/lang/String;)V
    LDC "http://www.test.org/"
    DUP2
    DUP
    INVOKEINTERFACE java/lang/CharSequence.length ()I
    IFNE L36
    LDC "Namespace URI must not be zero-length"
    LDC "XTDE0930"
    LDC "file:/Users/mike/w3c/xslt30-test-B/tests/attr/avt/avt-0303.xsl"
    BIPUSH 18
    ICONST_0
    INVOKESTATIC com/saxonica/ee/bytecode/util/Callback.makeXPathException (Ljava/lang/String;Ljava/lang/String;Ljava/lang/String;IZ)Lnet/sf/saxon/trans/XPathException;
    ATHROW
   L36
    BIPUSH 91
    INVOKESTATIC com/saxonica/ee/bytecode/util/ByteCodeTrace.trace (I)V
    LDC "http://www.w3.org/XML/1998/namespace"
    INVOKEVIRTUAL java/lang/Object.equals (Ljava/lang/Object;)Z
    SWAP
    LDC "xml"
    INVOKEVIRTUAL java/lang/Object.equals (Ljava/lang/Object;)Z
    IF_ICMPEQ L37
    LDC "Namespace prefix 'xml' and namespace uri http://www.w3.org/XML/1998/namespace must only be used together"
    LDC "XTDE0925"
    LDC "file:/Users/mike/w3c/xslt30-test-B/tests/attr/avt/avt-0303.xsl"
    BIPUSH 18
    ICONST_0
    INVOKESTATIC com/saxonica/ee/bytecode/util/Callback.makeXPathException (Ljava/lang/String;Ljava/lang/String;Ljava/lang/String;IZ)Lnet/sf/saxon/trans/XPathException;
    ATHROW
   L37
    BIPUSH 92
    INVOKESTATIC com/saxonica/ee/bytecode/util/ByteCodeTrace.trace (I)V
    DUP
    LDC "http://www.w3.org/2000/xmlns/"
    INVOKEVIRTUAL java/lang/Object.equals (Ljava/lang/Object;)Z
    IFEQ L38
    LDC "Namespace URI must not be http://www.w3.org/2000/xmlns/"
    LDC "XTDE0905"
    LDC "file:/Users/mike/w3c/xslt30-test-B/tests/attr/avt/avt-0303.xsl"
    BIPUSH 18
    ICONST_0
    INVOKESTATIC com/saxonica/ee/bytecode/util/Callback.makeXPathException (Ljava/lang/String;Ljava/lang/String;Ljava/lang/String;IZ)Lnet/sf/saxon/trans/XPathException;
    ATHROW
   L38
    BIPUSH 93
    INVOKESTATIC com/saxonica/ee/bytecode/util/ByteCodeTrace.trace (I)V
    DUP
    INVOKESTATIC net/sf/saxon/lib/StandardURIChecker.getInstance ()Lnet/sf/saxon/lib/StandardURIChecker;
    SWAP
    INVOKEVIRTUAL net/sf/saxon/lib/StandardURIChecker.isValidURI (Ljava/lang/CharSequence;)Z
    IFNE L39
    LDC "The string value of the constructed namespace node must be a valid URI"
    LDC "XTDE0905"
    LDC "file:/Users/mike/w3c/xslt30-test-B/tests/attr/avt/avt-0303.xsl"
    BIPUSH 18
    ICONST_0
    INVOKESTATIC com/saxonica/ee/bytecode/util/Callback.makeXPathException (Ljava/lang/String;Ljava/lang/String;Ljava/lang/String;IZ)Lnet/sf/saxon/trans/XPathException;
    ATHROW
   L39
    BIPUSH 94
    INVOKESTATIC com/saxonica/ee/bytecode/util/ByteCodeTrace.trace (I)V
    INVOKESTATIC net/sf/saxon/om/NamespaceBinding.makeNamespaceBinding (Ljava/lang/CharSequence;Ljava/lang/CharSequence;)Lnet/sf/saxon/om/NamespaceBinding;
    BIPUSH 32
    INVOKEINTERFACE net/sf/saxon/event/Receiver.namespace (Lnet/sf/saxon/om/NamespaceBinding;I)V
   L40
    LDC "SimpleNodeConstructorCompiler-Push"
    INVOKESTATIC com/saxonica/ee/bytecode/util/ByteCodeTrace.showMessage (Ljava/lang/String;)V
    ALOAD 2
   L41
    LDC "VariableReferenceCompiler-Item"
    INVOKESTATIC com/saxonica/ee/bytecode/util/ByteCodeTrace.showMessage (Ljava/lang/String;)V
    ALOAD 1
    DUP
    ICONST_0
    INVOKEINTERFACE net/sf/saxon/expr/XPathContext.getTargetComponent (I)Lnet/sf/saxon/expr/Component;
    DUP
    INVOKEVIRTUAL net/sf/saxon/expr/Component.getCode ()Lnet/sf/saxon/expr/instruct/ComponentCode;
    CHECKCAST net/sf/saxon/expr/instruct/GlobalVariable
    DUP_X2
    POP
    INVOKEVIRTUAL net/sf/saxon/expr/instruct/GlobalVariable.evaluateVariable (Lnet/sf/saxon/expr/XPathContext;Lnet/sf/saxon/expr/Component;)Lnet/sf/saxon/om/Sequence;
    DUP
    INSTANCEOF net/sf/saxon/om/Item
    IFEQ L42
    CHECKCAST net/sf/saxon/om/Item
    GOTO L43
   L42
    BIPUSH 95
    INVOKESTATIC com/saxonica/ee/bytecode/util/ByteCodeTrace.trace (I)V
    INVOKESTATIC net/sf/saxon/om/SequenceTool.asItem (Lnet/sf/saxon/om/Sequence;)Lnet/sf/saxon/om/Item;
   L43
    BIPUSH 96
    INVOKESTATIC com/saxonica/ee/bytecode/util/ByteCodeTrace.trace (I)V
    CHECKCAST net/sf/saxon/value/StringValue
    INVOKEVIRTUAL net/sf/saxon/value/StringValue.getStringValueCS ()Ljava/lang/CharSequence;
    INVOKESTATIC net/sf/saxon/value/Whitespace.trim (Ljava/lang/CharSequence;)Ljava/lang/String;
    INVOKEVIRTUAL java/lang/Object.toString ()Ljava/lang/String;
    DUP
    INVOKEINTERFACE java/lang/CharSequence.length ()I
    IFEQ L44
    DUP
    INVOKESTATIC net/sf/saxon/om/NameChecker.isValidNCName (Ljava/lang/CharSequence;)Z
    IFNE L45
    LDC "Namespace prefix is invalid"
    LDC "XTDE0920"
    LDC "file:/Users/mike/w3c/xslt30-test-B/tests/attr/avt/avt-0303.xsl"
    BIPUSH 19
    ICONST_0
    INVOKESTATIC com/saxonica/ee/bytecode/util/Callback.makeXPathException (Ljava/lang/String;Ljava/lang/String;Ljava/lang/String;IZ)Lnet/sf/saxon/trans/XPathException;
    ATHROW
   L45
    BIPUSH 97
    INVOKESTATIC com/saxonica/ee/bytecode/util/ByteCodeTrace.trace (I)V
    DUP
    LDC "xmlns"
    INVOKEVIRTUAL java/lang/Object.equals (Ljava/lang/Object;)Z
    IFEQ L44
    LDC "Namespace prefix must not be 'xmlns'"
    LDC "XTDE0920"
    LDC "file:/Users/mike/w3c/xslt30-test-B/tests/attr/avt/avt-0303.xsl"
    BIPUSH 19
    ICONST_0
    INVOKESTATIC com/saxonica/ee/bytecode/util/Callback.makeXPathException (Ljava/lang/String;Ljava/lang/String;Ljava/lang/String;IZ)Lnet/sf/saxon/trans/XPathException;
    ATHROW
   L44
    BIPUSH 98
    INVOKESTATIC com/saxonica/ee/bytecode/util/ByteCodeTrace.trace (I)V
   L46
    LDC "LiteralCompiler-Primitive"
    INVOKESTATIC com/saxonica/ee/bytecode/util/ByteCodeTrace.showMessage (Ljava/lang/String;)V
    LINENUMBER 19 L47
    LDC "http://www.example.org/"
    DUP2
    DUP
    INVOKEINTERFACE java/lang/CharSequence.length ()I
    IFNE L48
    LDC "Namespace URI must not be zero-length"
    LDC "XTDE0930"
    LDC "file:/Users/mike/w3c/xslt30-test-B/tests/attr/avt/avt-0303.xsl"
    BIPUSH 19
    ICONST_0
    INVOKESTATIC com/saxonica/ee/bytecode/util/Callback.makeXPathException (Ljava/lang/String;Ljava/lang/String;Ljava/lang/String;IZ)Lnet/sf/saxon/trans/XPathException;
    ATHROW
   L48
    BIPUSH 99
    INVOKESTATIC com/saxonica/ee/bytecode/util/ByteCodeTrace.trace (I)V
    LDC "http://www.w3.org/XML/1998/namespace"
    INVOKEVIRTUAL java/lang/Object.equals (Ljava/lang/Object;)Z
    SWAP
    LDC "xml"
    INVOKEVIRTUAL java/lang/Object.equals (Ljava/lang/Object;)Z
    IF_ICMPEQ L49
    LDC "Namespace prefix 'xml' and namespace uri http://www.w3.org/XML/1998/namespace must only be used together"
    LDC "XTDE0925"
    LDC "file:/Users/mike/w3c/xslt30-test-B/tests/attr/avt/avt-0303.xsl"
    BIPUSH 19
    ICONST_0
    INVOKESTATIC com/saxonica/ee/bytecode/util/Callback.makeXPathException (Ljava/lang/String;Ljava/lang/String;Ljava/lang/String;IZ)Lnet/sf/saxon/trans/XPathException;
    ATHROW
   L49
    BIPUSH 100
    INVOKESTATIC com/saxonica/ee/bytecode/util/ByteCodeTrace.trace (I)V
    DUP
    LDC "http://www.w3.org/2000/xmlns/"
    INVOKEVIRTUAL java/lang/Object.equals (Ljava/lang/Object;)Z
    IFEQ L50
    LDC "Namespace URI must not be http://www.w3.org/2000/xmlns/"
    LDC "XTDE0905"
    LDC "file:/Users/mike/w3c/xslt30-test-B/tests/attr/avt/avt-0303.xsl"
    BIPUSH 19
    ICONST_0
    INVOKESTATIC com/saxonica/ee/bytecode/util/Callback.makeXPathException (Ljava/lang/String;Ljava/lang/String;Ljava/lang/String;IZ)Lnet/sf/saxon/trans/XPathException;
    ATHROW
   L50
    BIPUSH 101
    INVOKESTATIC com/saxonica/ee/bytecode/util/ByteCodeTrace.trace (I)V
    DUP
    INVOKESTATIC net/sf/saxon/lib/StandardURIChecker.getInstance ()Lnet/sf/saxon/lib/StandardURIChecker;
    SWAP
    INVOKEVIRTUAL net/sf/saxon/lib/StandardURIChecker.isValidURI (Ljava/lang/CharSequence;)Z
    IFNE L51
    LDC "The string value of the constructed namespace node must be a valid URI"
    LDC "XTDE0905"
    LDC "file:/Users/mike/w3c/xslt30-test-B/tests/attr/avt/avt-0303.xsl"
    BIPUSH 19
    ICONST_0
    INVOKESTATIC com/saxonica/ee/bytecode/util/Callback.makeXPathException (Ljava/lang/String;Ljava/lang/String;Ljava/lang/String;IZ)Lnet/sf/saxon/trans/XPathException;
    ATHROW
   L51
    BIPUSH 102
    INVOKESTATIC com/saxonica/ee/bytecode/util/ByteCodeTrace.trace (I)V
    INVOKESTATIC net/sf/saxon/om/NamespaceBinding.makeNamespaceBinding (Ljava/lang/CharSequence;Ljava/lang/CharSequence;)Lnet/sf/saxon/om/NamespaceBinding;
    BIPUSH 32
    INVOKEINTERFACE net/sf/saxon/event/Receiver.namespace (Lnet/sf/saxon/om/NamespaceBinding;I)V
    ALOAD 2
    INVOKEINTERFACE net/sf/saxon/event/Receiver.endElement ()V
   L52
    LDC "SimpleNodeConstructorCompiler-Push"
    INVOKESTATIC com/saxonica/ee/bytecode/util/ByteCodeTrace.showMessage (Ljava/lang/String;)V
    ALOAD 2
   L53
    LDC "LiteralCompiler-Primitive"
    INVOKESTATIC com/saxonica/ee/bytecode/util/ByteCodeTrace.showMessage (Ljava/lang/String;)V
    LINENUMBER 18 L54
    LDC "\n"
    GETSTATIC EE__Slash_doc_40517978947.nAttributeLocation43 : Lnet/sf/saxon/style/ExpressionContext$AttributeLocation;
    ICONST_0
    INVOKEINTERFACE net/sf/saxon/event/Receiver.characters (Ljava/lang/CharSequence;Lnet/sf/saxon/expr/parser/Location;I)V
   L55
    LDC "FixedElement-elem"
    INVOKESTATIC com/saxonica/ee/bytecode/util/ByteCodeTrace.showMessage (Ljava/lang/String;)V
   L56
    LDC "ElementCreator-push"
    INVOKESTATIC com/saxonica/ee/bytecode/util/ByteCodeTrace.showMessage (Ljava/lang/String;)V
    LINENUMBER 24 L57
    ALOAD 2
    DUP
    LDC "Receiver: "
    SWAP
    DUP
    IFNULL L58
    INVOKEVIRTUAL java/lang/Object.toString ()Ljava/lang/String;
    INVOKESTATIC com/saxonica/ee/bytecode/util/ByteCodeTrace.showObjectVariable (Ljava/lang/String;Ljava/lang/String;)V
    GOTO L59
   L58
    BIPUSH 103
    INVOKESTATIC com/saxonica/ee/bytecode/util/ByteCodeTrace.trace (I)V
    POP
    LDC "null"
    INVOKESTATIC com/saxonica/ee/bytecode/util/ByteCodeTrace.showObjectVariable (Ljava/lang/String;Ljava/lang/String;)V
   L59
    BIPUSH 104
    INVOKESTATIC com/saxonica/ee/bytecode/util/ByteCodeTrace.trace (I)V
    INVOKEINTERFACE net/sf/saxon/event/Receiver.getSystemId ()Ljava/lang/String;
    IFNONNULL L60
    ALOAD 2
    LDC "file:/Users/mike/w3c/xslt30-test-B/tests/attr/avt/avt-0303.xsl"
    INVOKEINTERFACE net/sf/saxon/event/Receiver.setSystemId (Ljava/lang/String;)V
   L60
    BIPUSH 105
    INVOKESTATIC com/saxonica/ee/bytecode/util/ByteCodeTrace.trace (I)V
    ALOAD 2
    GETSTATIC EE__Slash_doc_40517978947.nFingerprintedQName44 : Lnet/sf/saxon/om/FingerprintedQName;
    GETSTATIC EE__Slash_doc_40517978947.nUntyped42 : Lnet/sf/saxon/type/Untyped;
    GETSTATIC EE__Slash_doc_40517978947.nAttributeLocation46 : Lnet/sf/saxon/style/ExpressionContext$AttributeLocation;
    ICONST_0
    INVOKEINTERFACE net/sf/saxon/event/Receiver.startElement (Lnet/sf/saxon/om/NodeName;Lnet/sf/saxon/type/SchemaType;Lnet/sf/saxon/expr/parser/Location;I)V
   L61
    LDC "BlockCompiler-Push"
    INVOKESTATIC com/saxonica/ee/bytecode/util/ByteCodeTrace.showMessage (Ljava/lang/String;)V
   L62
    LDC "SimpleNodeConstructorCompiler-Push"
    INVOKESTATIC com/saxonica/ee/bytecode/util/ByteCodeTrace.showMessage (Ljava/lang/String;)V
    ALOAD 2
   L63
    LDC "Concat-item"
    INVOKESTATIC com/saxonica/ee/bytecode/util/ByteCodeTrace.showMessage (Ljava/lang/String;)V
    NEW net/sf/saxon/tree/util/FastStringBuffer
    DUP
    BIPUSH 64
    INVOKESPECIAL net/sf/saxon/tree/util/FastStringBuffer.<init> (I)V
    ASTORE 4
    ALOAD 4
   L64
    LDC "StringFn-str"
    INVOKESTATIC com/saxonica/ee/bytecode/util/ByteCodeTrace.showMessage (Ljava/lang/String;)V
    TRYCATCHBLOCK L65 L66 L67 java/lang/UnsupportedOperationException
   L65
    BIPUSH 106
    INVOKESTATIC com/saxonica/ee/bytecode/util/ByteCodeTrace.trace (I)V
   L68
    LDC "AtomicSequenceConverterCompiler-Item"
    INVOKESTATIC com/saxonica/ee/bytecode/util/ByteCodeTrace.showMessage (Ljava/lang/String;)V
   L69
    LDC "AtomizerCompiler-Item"
    INVOKESTATIC com/saxonica/ee/bytecode/util/ByteCodeTrace.showMessage (Ljava/lang/String;)V
   L70
    LDC "FirstItemExpression"
    INVOKESTATIC com/saxonica/ee/bytecode/util/ByteCodeTrace.showMessage (Ljava/lang/String;)V
   L71
    LDC "AxisExpressionCompiler - iterate"
    INVOKESTATIC com/saxonica/ee/bytecode/util/ByteCodeTrace.showMessage (Ljava/lang/String;)V
    ALOAD 1
    INVOKEINTERFACE net/sf/saxon/expr/XPathContext.getContextItem ()Lnet/sf/saxon/om/Item;
    CHECKCAST net/sf/saxon/om/NodeInfo
   L72
    LDC "AxisExpressionCompiler - static method: iterate"
    INVOKESTATIC com/saxonica/ee/bytecode/util/ByteCodeTrace.showMessage (Ljava/lang/String;)V
    ICONST_3
    GETSTATIC EE__Slash_doc_40517978947.nNameTest45 : Lnet/sf/saxon/pattern/NameTest;
    LDC "calling iterateAxis"
    INVOKESTATIC com/saxonica/ee/bytecode/util/ByteCodeTrace.showMessage (Ljava/lang/String;)V
    INVOKEINTERFACE net/sf/saxon/om/NodeInfo.iterateAxis (BLnet/sf/saxon/pattern/NodeTest;)Lnet/sf/saxon/tree/iter/AxisIterator;
    LDC "returning axis iterator"
    INVOKESTATIC com/saxonica/ee/bytecode/util/ByteCodeTrace.showMessage (Ljava/lang/String;)V
    DUP
    INVOKEINTERFACE net/sf/saxon/om/SequenceIterator.next ()Lnet/sf/saxon/om/Item;
    SWAP
    INVOKEINTERFACE net/sf/saxon/om/SequenceIterator.close ()V
    DUP
    IFNULL L73
    INVOKEINTERFACE net/sf/saxon/om/Item.atomize ()Lnet/sf/saxon/om/AtomicSequence;
    INVOKEINTERFACE net/sf/saxon/om/AtomicSequence.head ()Lnet/sf/saxon/value/AtomicValue;
   L73
    BIPUSH 107
    INVOKESTATIC com/saxonica/ee/bytecode/util/ByteCodeTrace.trace (I)V
   L74
    LDC "AtomicSequenceConverterCompiler-Item-Returned"
    INVOKESTATIC com/saxonica/ee/bytecode/util/ByteCodeTrace.showMessage (Ljava/lang/String;)V
    DUP
    IFNONNULL L75
    POP
    ACONST_NULL
    GOTO L76
   L75
    BIPUSH 108
    INVOKESTATIC com/saxonica/ee/bytecode/util/ByteCodeTrace.trace (I)V
    INVOKEINTERFACE net/sf/saxon/om/Item.getStringValueCS ()Ljava/lang/CharSequence;
    INVOKESTATIC net/sf/saxon/value/StringValue.makeStringValue (Ljava/lang/CharSequence;)Lnet/sf/saxon/value/StringValue;
   L76
    BIPUSH 109
    INVOKESTATIC com/saxonica/ee/bytecode/util/ByteCodeTrace.trace (I)V
    DUP
    IFNONNULL L77
    POP
    LDC ""
    GOTO L78
   L77
    BIPUSH 110
    INVOKESTATIC com/saxonica/ee/bytecode/util/ByteCodeTrace.trace (I)V
    INVOKEINTERFACE net/sf/saxon/om/Item.getStringValueCS ()Ljava/lang/CharSequence;
   L78
    BIPUSH 111
    INVOKESTATIC com/saxonica/ee/bytecode/util/ByteCodeTrace.trace (I)V
   L66
    BIPUSH 112
    INVOKESTATIC com/saxonica/ee/bytecode/util/ByteCodeTrace.trace (I)V
    GOTO L79
   L67
    BIPUSH 113
    INVOKESTATIC com/saxonica/ee/bytecode/util/ByteCodeTrace.trace (I)V
   L80
    LDC "CatchStringFn"
    INVOKESTATIC com/saxonica/ee/bytecode/util/ByteCodeTrace.showMessage (Ljava/lang/String;)V
    INVOKEVIRTUAL java/lang/UnsupportedOperationException.getMessage ()Ljava/lang/String;
    LDC "FOTY0014"
    LDC "file:/Users/mike/w3c/xslt30-test-B/tests/attr/avt/avt-0303.xsl"
    BIPUSH 24
    ICONST_0
    INVOKESTATIC com/saxonica/ee/bytecode/util/Callback.makeXPathException (Ljava/lang/String;Ljava/lang/String;Ljava/lang/String;IZ)Lnet/sf/saxon/trans/XPathException;
    ATHROW
   L79
    BIPUSH 114
    INVOKESTATIC com/saxonica/ee/bytecode/util/ByteCodeTrace.trace (I)V
    INVOKEVIRTUAL net/sf/saxon/tree/util/FastStringBuffer.append (Ljava/lang/CharSequence;)V
    ALOAD 4
   L81
    LDC "LiteralCompiler-Primitive"
    INVOKESTATIC com/saxonica/ee/bytecode/util/ByteCodeTrace.showMessage (Ljava/lang/String;)V
    LDC "bc"
    INVOKEVIRTUAL net/sf/saxon/tree/util/FastStringBuffer.append (Ljava/lang/CharSequence;)V
    ALOAD 4
    INVOKEVIRTUAL net/sf/saxon/tree/util/FastStringBuffer.condense ()Ljava/lang/CharSequence;
    INVOKESTATIC net/sf/saxon/value/Whitespace.trim (Ljava/lang/CharSequence;)Ljava/lang/String;
    INVOKEVIRTUAL java/lang/Object.toString ()Ljava/lang/String;
    DUP
    INVOKEINTERFACE java/lang/CharSequence.length ()I
    IFEQ L82
    DUP
    INVOKESTATIC net/sf/saxon/om/NameChecker.isValidNCName (Ljava/lang/CharSequence;)Z
    IFNE L83
    LDC "Namespace prefix is invalid"
    LDC "XTDE0920"
    LDC "file:/Users/mike/w3c/xslt30-test-B/tests/attr/avt/avt-0303.xsl"
    BIPUSH 24
    ICONST_0
    INVOKESTATIC com/saxonica/ee/bytecode/util/Callback.makeXPathException (Ljava/lang/String;Ljava/lang/String;Ljava/lang/String;IZ)Lnet/sf/saxon/trans/XPathException;
    ATHROW
   L83
    BIPUSH 115
    INVOKESTATIC com/saxonica/ee/bytecode/util/ByteCodeTrace.trace (I)V
    DUP
    LDC "xmlns"
    INVOKEVIRTUAL java/lang/Object.equals (Ljava/lang/Object;)Z
    IFEQ L82
    LDC "Namespace prefix must not be 'xmlns'"
    LDC "XTDE0920"
    LDC "file:/Users/mike/w3c/xslt30-test-B/tests/attr/avt/avt-0303.xsl"
    BIPUSH 24
    ICONST_0
    INVOKESTATIC com/saxonica/ee/bytecode/util/Callback.makeXPathException (Ljava/lang/String;Ljava/lang/String;Ljava/lang/String;IZ)Lnet/sf/saxon/trans/XPathException;
    ATHROW
   L82
    BIPUSH 116
    INVOKESTATIC com/saxonica/ee/bytecode/util/ByteCodeTrace.trace (I)V
   L84
    LDC "LiteralCompiler-Primitive"
    INVOKESTATIC com/saxonica/ee/bytecode/util/ByteCodeTrace.showMessage (Ljava/lang/String;)V
    LDC "http://www.test.org/"
    DUP2
    DUP
    INVOKEINTERFACE java/lang/CharSequence.length ()I
    IFNE L85
    LDC "Namespace URI must not be zero-length"
    LDC "XTDE0930"
    LDC "file:/Users/mike/w3c/xslt30-test-B/tests/attr/avt/avt-0303.xsl"
    BIPUSH 24
    ICONST_0
    INVOKESTATIC com/saxonica/ee/bytecode/util/Callback.makeXPathException (Ljava/lang/String;Ljava/lang/String;Ljava/lang/String;IZ)Lnet/sf/saxon/trans/XPathException;
    ATHROW
   L85
    BIPUSH 117
    INVOKESTATIC com/saxonica/ee/bytecode/util/ByteCodeTrace.trace (I)V
    LDC "http://www.w3.org/XML/1998/namespace"
    INVOKEVIRTUAL java/lang/Object.equals (Ljava/lang/Object;)Z
    SWAP
    LDC "xml"
    INVOKEVIRTUAL java/lang/Object.equals (Ljava/lang/Object;)Z
    IF_ICMPEQ L86
    LDC "Namespace prefix 'xml' and namespace uri http://www.w3.org/XML/1998/namespace must only be used together"
    LDC "XTDE0925"
    LDC "file:/Users/mike/w3c/xslt30-test-B/tests/attr/avt/avt-0303.xsl"
    BIPUSH 24
    ICONST_0
    INVOKESTATIC com/saxonica/ee/bytecode/util/Callback.makeXPathException (Ljava/lang/String;Ljava/lang/String;Ljava/lang/String;IZ)Lnet/sf/saxon/trans/XPathException;
    ATHROW
   L86
    BIPUSH 118
    INVOKESTATIC com/saxonica/ee/bytecode/util/ByteCodeTrace.trace (I)V
    DUP
    LDC "http://www.w3.org/2000/xmlns/"
    INVOKEVIRTUAL java/lang/Object.equals (Ljava/lang/Object;)Z
    IFEQ L87
    LDC "Namespace URI must not be http://www.w3.org/2000/xmlns/"
    LDC "XTDE0905"
    LDC "file:/Users/mike/w3c/xslt30-test-B/tests/attr/avt/avt-0303.xsl"
    BIPUSH 24
    ICONST_0
    INVOKESTATIC com/saxonica/ee/bytecode/util/Callback.makeXPathException (Ljava/lang/String;Ljava/lang/String;Ljava/lang/String;IZ)Lnet/sf/saxon/trans/XPathException;
    ATHROW
   L87
    BIPUSH 119
    INVOKESTATIC com/saxonica/ee/bytecode/util/ByteCodeTrace.trace (I)V
    DUP
    INVOKESTATIC net/sf/saxon/lib/StandardURIChecker.getInstance ()Lnet/sf/saxon/lib/StandardURIChecker;
    SWAP
    INVOKEVIRTUAL net/sf/saxon/lib/StandardURIChecker.isValidURI (Ljava/lang/CharSequence;)Z
    IFNE L88
    LDC "The string value of the constructed namespace node must be a valid URI"
    LDC "XTDE0905"
    LDC "file:/Users/mike/w3c/xslt30-test-B/tests/attr/avt/avt-0303.xsl"
    BIPUSH 24
    ICONST_0
    INVOKESTATIC com/saxonica/ee/bytecode/util/Callback.makeXPathException (Ljava/lang/String;Ljava/lang/String;Ljava/lang/String;IZ)Lnet/sf/saxon/trans/XPathException;
    ATHROW
   L88
    BIPUSH 120
    INVOKESTATIC com/saxonica/ee/bytecode/util/ByteCodeTrace.trace (I)V
    INVOKESTATIC net/sf/saxon/om/NamespaceBinding.makeNamespaceBinding (Ljava/lang/CharSequence;Ljava/lang/CharSequence;)Lnet/sf/saxon/om/NamespaceBinding;
    BIPUSH 32
    INVOKEINTERFACE net/sf/saxon/event/Receiver.namespace (Lnet/sf/saxon/om/NamespaceBinding;I)V
   L89
    LDC "SimpleNodeConstructorCompiler-Push"
    INVOKESTATIC com/saxonica/ee/bytecode/util/ByteCodeTrace.showMessage (Ljava/lang/String;)V
    ALOAD 2
   L90
    LDC "VariableReferenceCompiler-Item"
    INVOKESTATIC com/saxonica/ee/bytecode/util/ByteCodeTrace.showMessage (Ljava/lang/String;)V
    ALOAD 1
    DUP
    ICONST_1
    INVOKEINTERFACE net/sf/saxon/expr/XPathContext.getTargetComponent (I)Lnet/sf/saxon/expr/Component;
    DUP
    INVOKEVIRTUAL net/sf/saxon/expr/Component.getCode ()Lnet/sf/saxon/expr/instruct/ComponentCode;
    CHECKCAST net/sf/saxon/expr/instruct/GlobalVariable
    DUP_X2
    POP
    INVOKEVIRTUAL net/sf/saxon/expr/instruct/GlobalVariable.evaluateVariable (Lnet/sf/saxon/expr/XPathContext;Lnet/sf/saxon/expr/Component;)Lnet/sf/saxon/om/Sequence;
    DUP
    INSTANCEOF net/sf/saxon/om/Item
    IFEQ L91
    CHECKCAST net/sf/saxon/om/Item
    GOTO L92
   L91
    BIPUSH 121
    INVOKESTATIC com/saxonica/ee/bytecode/util/ByteCodeTrace.trace (I)V
    INVOKESTATIC net/sf/saxon/om/SequenceTool.asItem (Lnet/sf/saxon/om/Sequence;)Lnet/sf/saxon/om/Item;
   L92
    BIPUSH 122
    INVOKESTATIC com/saxonica/ee/bytecode/util/ByteCodeTrace.trace (I)V
    CHECKCAST net/sf/saxon/value/StringValue
    INVOKEVIRTUAL net/sf/saxon/value/StringValue.getStringValueCS ()Ljava/lang/CharSequence;
    INVOKESTATIC net/sf/saxon/value/Whitespace.trim (Ljava/lang/CharSequence;)Ljava/lang/String;
    INVOKEVIRTUAL java/lang/Object.toString ()Ljava/lang/String;
    DUP
    INVOKEINTERFACE java/lang/CharSequence.length ()I
    IFEQ L93
    DUP
    INVOKESTATIC net/sf/saxon/om/NameChecker.isValidNCName (Ljava/lang/CharSequence;)Z
    IFNE L94
    LDC "Namespace prefix is invalid"
    LDC "XTDE0920"
    LDC "file:/Users/mike/w3c/xslt30-test-B/tests/attr/avt/avt-0303.xsl"
    BIPUSH 25
    ICONST_0
    INVOKESTATIC com/saxonica/ee/bytecode/util/Callback.makeXPathException (Ljava/lang/String;Ljava/lang/String;Ljava/lang/String;IZ)Lnet/sf/saxon/trans/XPathException;
    ATHROW
   L94
    BIPUSH 123
    INVOKESTATIC com/saxonica/ee/bytecode/util/ByteCodeTrace.trace (I)V
    DUP
    LDC "xmlns"
    INVOKEVIRTUAL java/lang/Object.equals (Ljava/lang/Object;)Z
    IFEQ L93
    LDC "Namespace prefix must not be 'xmlns'"
    LDC "XTDE0920"
    LDC "file:/Users/mike/w3c/xslt30-test-B/tests/attr/avt/avt-0303.xsl"
    BIPUSH 25
    ICONST_0
    INVOKESTATIC com/saxonica/ee/bytecode/util/Callback.makeXPathException (Ljava/lang/String;Ljava/lang/String;Ljava/lang/String;IZ)Lnet/sf/saxon/trans/XPathException;
    ATHROW
   L93
    BIPUSH 124
    INVOKESTATIC com/saxonica/ee/bytecode/util/ByteCodeTrace.trace (I)V
   L95
    LDC "LiteralCompiler-Primitive"
    INVOKESTATIC com/saxonica/ee/bytecode/util/ByteCodeTrace.showMessage (Ljava/lang/String;)V
    LINENUMBER 25 L96
    LDC "http://www.example.org/"
    DUP2
    DUP
    INVOKEINTERFACE java/lang/CharSequence.length ()I
    IFNE L97
    LDC "Namespace URI must not be zero-length"
    LDC "XTDE0930"
    LDC "file:/Users/mike/w3c/xslt30-test-B/tests/attr/avt/avt-0303.xsl"
    BIPUSH 25
    ICONST_0
    INVOKESTATIC com/saxonica/ee/bytecode/util/Callback.makeXPathException (Ljava/lang/String;Ljava/lang/String;Ljava/lang/String;IZ)Lnet/sf/saxon/trans/XPathException;
    ATHROW
   L97
    BIPUSH 125
    INVOKESTATIC com/saxonica/ee/bytecode/util/ByteCodeTrace.trace (I)V
    LDC "http://www.w3.org/XML/1998/namespace"
    INVOKEVIRTUAL java/lang/Object.equals (Ljava/lang/Object;)Z
    SWAP
    LDC "xml"
    INVOKEVIRTUAL java/lang/Object.equals (Ljava/lang/Object;)Z
    IF_ICMPEQ L98
    LDC "Namespace prefix 'xml' and namespace uri http://www.w3.org/XML/1998/namespace must only be used together"
    LDC "XTDE0925"
    LDC "file:/Users/mike/w3c/xslt30-test-B/tests/attr/avt/avt-0303.xsl"
    BIPUSH 25
    ICONST_0
    INVOKESTATIC com/saxonica/ee/bytecode/util/Callback.makeXPathException (Ljava/lang/String;Ljava/lang/String;Ljava/lang/String;IZ)Lnet/sf/saxon/trans/XPathException;
    ATHROW
   L98
    BIPUSH 126
    INVOKESTATIC com/saxonica/ee/bytecode/util/ByteCodeTrace.trace (I)V
    DUP
    LDC "http://www.w3.org/2000/xmlns/"
    INVOKEVIRTUAL java/lang/Object.equals (Ljava/lang/Object;)Z
    IFEQ L99
    LDC "Namespace URI must not be http://www.w3.org/2000/xmlns/"
    LDC "XTDE0905"
    LDC "file:/Users/mike/w3c/xslt30-test-B/tests/attr/avt/avt-0303.xsl"
    BIPUSH 25
    ICONST_0
    INVOKESTATIC com/saxonica/ee/bytecode/util/Callback.makeXPathException (Ljava/lang/String;Ljava/lang/String;Ljava/lang/String;IZ)Lnet/sf/saxon/trans/XPathException;
    ATHROW
   L99
    BIPUSH 127
    INVOKESTATIC com/saxonica/ee/bytecode/util/ByteCodeTrace.trace (I)V
    DUP
    INVOKESTATIC net/sf/saxon/lib/StandardURIChecker.getInstance ()Lnet/sf/saxon/lib/StandardURIChecker;
    SWAP
    INVOKEVIRTUAL net/sf/saxon/lib/StandardURIChecker.isValidURI (Ljava/lang/CharSequence;)Z
    IFNE L100
    LDC "The string value of the constructed namespace node must be a valid URI"
    LDC "XTDE0905"
    LDC "file:/Users/mike/w3c/xslt30-test-B/tests/attr/avt/avt-0303.xsl"
    BIPUSH 25
    ICONST_0
    INVOKESTATIC com/saxonica/ee/bytecode/util/Callback.makeXPathException (Ljava/lang/String;Ljava/lang/String;Ljava/lang/String;IZ)Lnet/sf/saxon/trans/XPathException;
    ATHROW
   L100
    SIPUSH 128
    INVOKESTATIC com/saxonica/ee/bytecode/util/ByteCodeTrace.trace (I)V
    INVOKESTATIC net/sf/saxon/om/NamespaceBinding.makeNamespaceBinding (Ljava/lang/CharSequence;Ljava/lang/CharSequence;)Lnet/sf/saxon/om/NamespaceBinding;
    BIPUSH 32
    INVOKEINTERFACE net/sf/saxon/event/Receiver.namespace (Lnet/sf/saxon/om/NamespaceBinding;I)V
    ALOAD 2
    INVOKEINTERFACE net/sf/saxon/event/Receiver.endElement ()V
   L101
    LDC "SimpleNodeConstructorCompiler-Push"
    INVOKESTATIC com/saxonica/ee/bytecode/util/ByteCodeTrace.showMessage (Ljava/lang/String;)V
    ALOAD 2
   L102
    LDC "LiteralCompiler-Primitive"
    INVOKESTATIC com/saxonica/ee/bytecode/util/ByteCodeTrace.showMessage (Ljava/lang/String;)V
    LINENUMBER 18 L103
    LDC "\n"
    GETSTATIC EE__Slash_doc_40517978947.nAttributeLocation43 : Lnet/sf/saxon/style/ExpressionContext$AttributeLocation;
    ICONST_0
    INVOKEINTERFACE net/sf/saxon/event/Receiver.characters (Ljava/lang/CharSequence;Lnet/sf/saxon/expr/parser/Location;I)V
   L104
    LDC "FixedElement-elem"
    INVOKESTATIC com/saxonica/ee/bytecode/util/ByteCodeTrace.showMessage (Ljava/lang/String;)V
   L105
    LDC "ElementCreator-push"
    INVOKESTATIC com/saxonica/ee/bytecode/util/ByteCodeTrace.showMessage (Ljava/lang/String;)V
    LINENUMBER 30 L106
    ALOAD 2
    DUP
    LDC "Receiver: "
    SWAP
    DUP
    IFNULL L107
    INVOKEVIRTUAL java/lang/Object.toString ()Ljava/lang/String;
    INVOKESTATIC com/saxonica/ee/bytecode/util/ByteCodeTrace.showObjectVariable (Ljava/lang/String;Ljava/lang/String;)V
    GOTO L108
   L107
    SIPUSH 129
    INVOKESTATIC com/saxonica/ee/bytecode/util/ByteCodeTrace.trace (I)V
    POP
    LDC "null"
    INVOKESTATIC com/saxonica/ee/bytecode/util/ByteCodeTrace.showObjectVariable (Ljava/lang/String;Ljava/lang/String;)V
   L108
    SIPUSH 130
    INVOKESTATIC com/saxonica/ee/bytecode/util/ByteCodeTrace.trace (I)V
    INVOKEINTERFACE net/sf/saxon/event/Receiver.getSystemId ()Ljava/lang/String;
    IFNONNULL L109
    ALOAD 2
    LDC "file:/Users/mike/w3c/xslt30-test-B/tests/attr/avt/avt-0303.xsl"
    INVOKEINTERFACE net/sf/saxon/event/Receiver.setSystemId (Ljava/lang/String;)V
   L109
    SIPUSH 131
    INVOKESTATIC com/saxonica/ee/bytecode/util/ByteCodeTrace.trace (I)V
    ALOAD 2
    GETSTATIC EE__Slash_doc_40517978947.nFingerprintedQName44 : Lnet/sf/saxon/om/FingerprintedQName;
    GETSTATIC EE__Slash_doc_40517978947.nUntyped42 : Lnet/sf/saxon/type/Untyped;
    GETSTATIC EE__Slash_doc_40517978947.nAttributeLocation47 : Lnet/sf/saxon/style/ExpressionContext$AttributeLocation;
    ICONST_0
    INVOKEINTERFACE net/sf/saxon/event/Receiver.startElement (Lnet/sf/saxon/om/NodeName;Lnet/sf/saxon/type/SchemaType;Lnet/sf/saxon/expr/parser/Location;I)V
   L110
    LDC "BlockCompiler-Push"
    INVOKESTATIC com/saxonica/ee/bytecode/util/ByteCodeTrace.showMessage (Ljava/lang/String;)V
   L111
    LDC "SimpleNodeConstructorCompiler-Push"
    INVOKESTATIC com/saxonica/ee/bytecode/util/ByteCodeTrace.showMessage (Ljava/lang/String;)V
    ALOAD 2
   L112
    LDC "Concat-item"
    INVOKESTATIC com/saxonica/ee/bytecode/util/ByteCodeTrace.showMessage (Ljava/lang/String;)V
    NEW net/sf/saxon/tree/util/FastStringBuffer
    DUP
    BIPUSH 64
    INVOKESPECIAL net/sf/saxon/tree/util/FastStringBuffer.<init> (I)V
    ASTORE 4
    ALOAD 4
   L113
    LDC "LiteralCompiler-Primitive"
    INVOKESTATIC com/saxonica/ee/bytecode/util/ByteCodeTrace.showMessage (Ljava/lang/String;)V
    LDC "a"
    INVOKEVIRTUAL net/sf/saxon/tree/util/FastStringBuffer.append (Ljava/lang/CharSequence;)V
    ALOAD 4
   L114
    LDC "StringFn-str"
    INVOKESTATIC com/saxonica/ee/bytecode/util/ByteCodeTrace.showMessage (Ljava/lang/String;)V
    TRYCATCHBLOCK L115 L116 L117 java/lang/UnsupportedOperationException
   L115
    SIPUSH 132
    INVOKESTATIC com/saxonica/ee/bytecode/util/ByteCodeTrace.trace (I)V
   L118
    LDC "AtomicSequenceConverterCompiler-Item"
    INVOKESTATIC com/saxonica/ee/bytecode/util/ByteCodeTrace.showMessage (Ljava/lang/String;)V
   L119
    LDC "AtomizerCompiler-Item"
    INVOKESTATIC com/saxonica/ee/bytecode/util/ByteCodeTrace.showMessage (Ljava/lang/String;)V
   L120
    LDC "FirstItemExpression"
    INVOKESTATIC com/saxonica/ee/bytecode/util/ByteCodeTrace.showMessage (Ljava/lang/String;)V
   L121
    LDC "AxisExpressionCompiler - iterate"
    INVOKESTATIC com/saxonica/ee/bytecode/util/ByteCodeTrace.showMessage (Ljava/lang/String;)V
    ALOAD 1
    INVOKEINTERFACE net/sf/saxon/expr/XPathContext.getContextItem ()Lnet/sf/saxon/om/Item;
    CHECKCAST net/sf/saxon/om/NodeInfo
   L122
    LDC "AxisExpressionCompiler - static method: iterate"
    INVOKESTATIC com/saxonica/ee/bytecode/util/ByteCodeTrace.showMessage (Ljava/lang/String;)V
    ICONST_3
    GETSTATIC EE__Slash_doc_40517978947.nNameTest45 : Lnet/sf/saxon/pattern/NameTest;
    LDC "calling iterateAxis"
    INVOKESTATIC com/saxonica/ee/bytecode/util/ByteCodeTrace.showMessage (Ljava/lang/String;)V
    INVOKEINTERFACE net/sf/saxon/om/NodeInfo.iterateAxis (BLnet/sf/saxon/pattern/NodeTest;)Lnet/sf/saxon/tree/iter/AxisIterator;
    LDC "returning axis iterator"
    INVOKESTATIC com/saxonica/ee/bytecode/util/ByteCodeTrace.showMessage (Ljava/lang/String;)V
    DUP
    INVOKEINTERFACE net/sf/saxon/om/SequenceIterator.next ()Lnet/sf/saxon/om/Item;
    SWAP
    INVOKEINTERFACE net/sf/saxon/om/SequenceIterator.close ()V
    DUP
    IFNULL L123
    INVOKEINTERFACE net/sf/saxon/om/Item.atomize ()Lnet/sf/saxon/om/AtomicSequence;
    INVOKEINTERFACE net/sf/saxon/om/AtomicSequence.head ()Lnet/sf/saxon/value/AtomicValue;
   L123
    SIPUSH 133
    INVOKESTATIC com/saxonica/ee/bytecode/util/ByteCodeTrace.trace (I)V
   L124
    LDC "AtomicSequenceConverterCompiler-Item-Returned"
    INVOKESTATIC com/saxonica/ee/bytecode/util/ByteCodeTrace.showMessage (Ljava/lang/String;)V
    DUP
    IFNONNULL L125
    POP
    ACONST_NULL
    GOTO L126
   L125
    SIPUSH 134
    INVOKESTATIC com/saxonica/ee/bytecode/util/ByteCodeTrace.trace (I)V
    INVOKEINTERFACE net/sf/saxon/om/Item.getStringValueCS ()Ljava/lang/CharSequence;
    INVOKESTATIC net/sf/saxon/value/StringValue.makeStringValue (Ljava/lang/CharSequence;)Lnet/sf/saxon/value/StringValue;
   L126
    SIPUSH 135
    INVOKESTATIC com/saxonica/ee/bytecode/util/ByteCodeTrace.trace (I)V
    DUP
    IFNONNULL L127
    POP
    LDC ""
    GOTO L128
   L127
    SIPUSH 136
    INVOKESTATIC com/saxonica/ee/bytecode/util/ByteCodeTrace.trace (I)V
    INVOKEINTERFACE net/sf/saxon/om/Item.getStringValueCS ()Ljava/lang/CharSequence;
   L128
    SIPUSH 137
    INVOKESTATIC com/saxonica/ee/bytecode/util/ByteCodeTrace.trace (I)V
   L116
    SIPUSH 138
    INVOKESTATIC com/saxonica/ee/bytecode/util/ByteCodeTrace.trace (I)V
    GOTO L129
   L117
    SIPUSH 139
    INVOKESTATIC com/saxonica/ee/bytecode/util/ByteCodeTrace.trace (I)V
   L130
    LDC "CatchStringFn"
    INVOKESTATIC com/saxonica/ee/bytecode/util/ByteCodeTrace.showMessage (Ljava/lang/String;)V
    INVOKEVIRTUAL java/lang/UnsupportedOperationException.getMessage ()Ljava/lang/String;
    LDC "FOTY0014"
    LDC "file:/Users/mike/w3c/xslt30-test-B/tests/attr/avt/avt-0303.xsl"
    BIPUSH 30
    ICONST_0
    INVOKESTATIC com/saxonica/ee/bytecode/util/Callback.makeXPathException (Ljava/lang/String;Ljava/lang/String;Ljava/lang/String;IZ)Lnet/sf/saxon/trans/XPathException;
    ATHROW
   L129
    SIPUSH 140
    INVOKESTATIC com/saxonica/ee/bytecode/util/ByteCodeTrace.trace (I)V
    INVOKEVIRTUAL net/sf/saxon/tree/util/FastStringBuffer.append (Ljava/lang/CharSequence;)V
    ALOAD 4
    INVOKEVIRTUAL net/sf/saxon/tree/util/FastStringBuffer.condense ()Ljava/lang/CharSequence;
    INVOKESTATIC net/sf/saxon/value/Whitespace.trim (Ljava/lang/CharSequence;)Ljava/lang/String;
    INVOKEVIRTUAL java/lang/Object.toString ()Ljava/lang/String;
    DUP
    INVOKEINTERFACE java/lang/CharSequence.length ()I
    IFEQ L131
    DUP
    INVOKESTATIC net/sf/saxon/om/NameChecker.isValidNCName (Ljava/lang/CharSequence;)Z
    IFNE L132
    LDC "Namespace prefix is invalid"
    LDC "XTDE0920"
    LDC "file:/Users/mike/w3c/xslt30-test-B/tests/attr/avt/avt-0303.xsl"
    BIPUSH 30
    ICONST_0
    INVOKESTATIC com/saxonica/ee/bytecode/util/Callback.makeXPathException (Ljava/lang/String;Ljava/lang/String;Ljava/lang/String;IZ)Lnet/sf/saxon/trans/XPathException;
    ATHROW
   L132
    SIPUSH 141
    INVOKESTATIC com/saxonica/ee/bytecode/util/ByteCodeTrace.trace (I)V
    DUP
    LDC "xmlns"
    INVOKEVIRTUAL java/lang/Object.equals (Ljava/lang/Object;)Z
    IFEQ L131
    LDC "Namespace prefix must not be 'xmlns'"
    LDC "XTDE0920"
    LDC "file:/Users/mike/w3c/xslt30-test-B/tests/attr/avt/avt-0303.xsl"
    BIPUSH 30
    ICONST_0
    INVOKESTATIC com/saxonica/ee/bytecode/util/Callback.makeXPathException (Ljava/lang/String;Ljava/lang/String;Ljava/lang/String;IZ)Lnet/sf/saxon/trans/XPathException;
    ATHROW
   L131
    SIPUSH 142
    INVOKESTATIC com/saxonica/ee/bytecode/util/ByteCodeTrace.trace (I)V
   L133
    LDC "LiteralCompiler-Primitive"
    INVOKESTATIC com/saxonica/ee/bytecode/util/ByteCodeTrace.showMessage (Ljava/lang/String;)V
    LDC "http://www.test.org/"
    DUP2
    DUP
    INVOKEINTERFACE java/lang/CharSequence.length ()I
    IFNE L134
    LDC "Namespace URI must not be zero-length"
    LDC "XTDE0930"
    LDC "file:/Users/mike/w3c/xslt30-test-B/tests/attr/avt/avt-0303.xsl"
    BIPUSH 30
    ICONST_0
    INVOKESTATIC com/saxonica/ee/bytecode/util/Callback.makeXPathException (Ljava/lang/String;Ljava/lang/String;Ljava/lang/String;IZ)Lnet/sf/saxon/trans/XPathException;
    ATHROW
   L134
    SIPUSH 143
    INVOKESTATIC com/saxonica/ee/bytecode/util/ByteCodeTrace.trace (I)V
    LDC "http://www.w3.org/XML/1998/namespace"
    INVOKEVIRTUAL java/lang/Object.equals (Ljava/lang/Object;)Z
    SWAP
    LDC "xml"
    INVOKEVIRTUAL java/lang/Object.equals (Ljava/lang/Object;)Z
    IF_ICMPEQ L135
    LDC "Namespace prefix 'xml' and namespace uri http://www.w3.org/XML/1998/namespace must only be used together"
    LDC "XTDE0925"
    LDC "file:/Users/mike/w3c/xslt30-test-B/tests/attr/avt/avt-0303.xsl"
    BIPUSH 30
    ICONST_0
    INVOKESTATIC com/saxonica/ee/bytecode/util/Callback.makeXPathException (Ljava/lang/String;Ljava/lang/String;Ljava/lang/String;IZ)Lnet/sf/saxon/trans/XPathException;
    ATHROW
   L135
    SIPUSH 144
    INVOKESTATIC com/saxonica/ee/bytecode/util/ByteCodeTrace.trace (I)V
    DUP
    LDC "http://www.w3.org/2000/xmlns/"
    INVOKEVIRTUAL java/lang/Object.equals (Ljava/lang/Object;)Z
    IFEQ L136
    LDC "Namespace URI must not be http://www.w3.org/2000/xmlns/"
    LDC "XTDE0905"
    LDC "file:/Users/mike/w3c/xslt30-test-B/tests/attr/avt/avt-0303.xsl"
    BIPUSH 30
    ICONST_0
    INVOKESTATIC com/saxonica/ee/bytecode/util/Callback.makeXPathException (Ljava/lang/String;Ljava/lang/String;Ljava/lang/String;IZ)Lnet/sf/saxon/trans/XPathException;
    ATHROW
   L136
    SIPUSH 145
    INVOKESTATIC com/saxonica/ee/bytecode/util/ByteCodeTrace.trace (I)V
    DUP
    INVOKESTATIC net/sf/saxon/lib/StandardURIChecker.getInstance ()Lnet/sf/saxon/lib/StandardURIChecker;
    SWAP
    INVOKEVIRTUAL net/sf/saxon/lib/StandardURIChecker.isValidURI (Ljava/lang/CharSequence;)Z
    IFNE L137
    LDC "The string value of the constructed namespace node must be a valid URI"
    LDC "XTDE0905"
    LDC "file:/Users/mike/w3c/xslt30-test-B/tests/attr/avt/avt-0303.xsl"
    BIPUSH 30
    ICONST_0
    INVOKESTATIC com/saxonica/ee/bytecode/util/Callback.makeXPathException (Ljava/lang/String;Ljava/lang/String;Ljava/lang/String;IZ)Lnet/sf/saxon/trans/XPathException;
    ATHROW
   L137
    SIPUSH 146
    INVOKESTATIC com/saxonica/ee/bytecode/util/ByteCodeTrace.trace (I)V
    INVOKESTATIC net/sf/saxon/om/NamespaceBinding.makeNamespaceBinding (Ljava/lang/CharSequence;Ljava/lang/CharSequence;)Lnet/sf/saxon/om/NamespaceBinding;
    BIPUSH 32
    INVOKEINTERFACE net/sf/saxon/event/Receiver.namespace (Lnet/sf/saxon/om/NamespaceBinding;I)V
   L138
    LDC "SimpleNodeConstructorCompiler-Push"
    INVOKESTATIC com/saxonica/ee/bytecode/util/ByteCodeTrace.showMessage (Ljava/lang/String;)V
    ALOAD 2
   L139
    LDC "VariableReferenceCompiler-Item"
    INVOKESTATIC com/saxonica/ee/bytecode/util/ByteCodeTrace.showMessage (Ljava/lang/String;)V
    ALOAD 1
    DUP
    ICONST_2
    INVOKEINTERFACE net/sf/saxon/expr/XPathContext.getTargetComponent (I)Lnet/sf/saxon/expr/Component;
    DUP
    INVOKEVIRTUAL net/sf/saxon/expr/Component.getCode ()Lnet/sf/saxon/expr/instruct/ComponentCode;
    CHECKCAST net/sf/saxon/expr/instruct/GlobalVariable
    DUP_X2
    POP
    INVOKEVIRTUAL net/sf/saxon/expr/instruct/GlobalVariable.evaluateVariable (Lnet/sf/saxon/expr/XPathContext;Lnet/sf/saxon/expr/Component;)Lnet/sf/saxon/om/Sequence;
    DUP
    INSTANCEOF net/sf/saxon/om/Item
    IFEQ L140
    CHECKCAST net/sf/saxon/om/Item
    GOTO L141
   L140
    SIPUSH 147
    INVOKESTATIC com/saxonica/ee/bytecode/util/ByteCodeTrace.trace (I)V
    INVOKESTATIC net/sf/saxon/om/SequenceTool.asItem (Lnet/sf/saxon/om/Sequence;)Lnet/sf/saxon/om/Item;
   L141
    SIPUSH 148
    INVOKESTATIC com/saxonica/ee/bytecode/util/ByteCodeTrace.trace (I)V
    CHECKCAST net/sf/saxon/value/StringValue
    INVOKEVIRTUAL net/sf/saxon/value/StringValue.getStringValueCS ()Ljava/lang/CharSequence;
    INVOKESTATIC net/sf/saxon/value/Whitespace.trim (Ljava/lang/CharSequence;)Ljava/lang/String;
    INVOKEVIRTUAL java/lang/Object.toString ()Ljava/lang/String;
    DUP
    INVOKEINTERFACE java/lang/CharSequence.length ()I
    IFEQ L142
    DUP
    INVOKESTATIC net/sf/saxon/om/NameChecker.isValidNCName (Ljava/lang/CharSequence;)Z
    IFNE L143
    LDC "Namespace prefix is invalid"
    LDC "XTDE0920"
    LDC "file:/Users/mike/w3c/xslt30-test-B/tests/attr/avt/avt-0303.xsl"
    BIPUSH 31
    ICONST_0
    INVOKESTATIC com/saxonica/ee/bytecode/util/Callback.makeXPathException (Ljava/lang/String;Ljava/lang/String;Ljava/lang/String;IZ)Lnet/sf/saxon/trans/XPathException;
    ATHROW
   L143
    SIPUSH 149
    INVOKESTATIC com/saxonica/ee/bytecode/util/ByteCodeTrace.trace (I)V
    DUP
    LDC "xmlns"
    INVOKEVIRTUAL java/lang/Object.equals (Ljava/lang/Object;)Z
    IFEQ L142
    LDC "Namespace prefix must not be 'xmlns'"
    LDC "XTDE0920"
    LDC "file:/Users/mike/w3c/xslt30-test-B/tests/attr/avt/avt-0303.xsl"
    BIPUSH 31
    ICONST_0
    INVOKESTATIC com/saxonica/ee/bytecode/util/Callback.makeXPathException (Ljava/lang/String;Ljava/lang/String;Ljava/lang/String;IZ)Lnet/sf/saxon/trans/XPathException;
    ATHROW
   L142
    SIPUSH 150
    INVOKESTATIC com/saxonica/ee/bytecode/util/ByteCodeTrace.trace (I)V
   L144
    LDC "LiteralCompiler-Primitive"
    INVOKESTATIC com/saxonica/ee/bytecode/util/ByteCodeTrace.showMessage (Ljava/lang/String;)V
    LINENUMBER 31 L145
    LDC "http://www.example.org/"
    DUP2
    DUP
    INVOKEINTERFACE java/lang/CharSequence.length ()I
    IFNE L146
    LDC "Namespace URI must not be zero-length"
    LDC "XTDE0930"
    LDC "file:/Users/mike/w3c/xslt30-test-B/tests/attr/avt/avt-0303.xsl"
    BIPUSH 31
    ICONST_0
    INVOKESTATIC com/saxonica/ee/bytecode/util/Callback.makeXPathException (Ljava/lang/String;Ljava/lang/String;Ljava/lang/String;IZ)Lnet/sf/saxon/trans/XPathException;
    ATHROW
   L146
    SIPUSH 151
    INVOKESTATIC com/saxonica/ee/bytecode/util/ByteCodeTrace.trace (I)V
    LDC "http://www.w3.org/XML/1998/namespace"
    INVOKEVIRTUAL java/lang/Object.equals (Ljava/lang/Object;)Z
    SWAP
    LDC "xml"
    INVOKEVIRTUAL java/lang/Object.equals (Ljava/lang/Object;)Z
    IF_ICMPEQ L147
    LDC "Namespace prefix 'xml' and namespace uri http://www.w3.org/XML/1998/namespace must only be used together"
    LDC "XTDE0925"
    LDC "file:/Users/mike/w3c/xslt30-test-B/tests/attr/avt/avt-0303.xsl"
    BIPUSH 31
    ICONST_0
    INVOKESTATIC com/saxonica/ee/bytecode/util/Callback.makeXPathException (Ljava/lang/String;Ljava/lang/String;Ljava/lang/String;IZ)Lnet/sf/saxon/trans/XPathException;
    ATHROW
   L147
    SIPUSH 152
    INVOKESTATIC com/saxonica/ee/bytecode/util/ByteCodeTrace.trace (I)V
    DUP
    LDC "http://www.w3.org/2000/xmlns/"
    INVOKEVIRTUAL java/lang/Object.equals (Ljava/lang/Object;)Z
    IFEQ L148
    LDC "Namespace URI must not be http://www.w3.org/2000/xmlns/"
    LDC "XTDE0905"
    LDC "file:/Users/mike/w3c/xslt30-test-B/tests/attr/avt/avt-0303.xsl"
    BIPUSH 31
    ICONST_0
    INVOKESTATIC com/saxonica/ee/bytecode/util/Callback.makeXPathException (Ljava/lang/String;Ljava/lang/String;Ljava/lang/String;IZ)Lnet/sf/saxon/trans/XPathException;
    ATHROW
   L148
    SIPUSH 153
    INVOKESTATIC com/saxonica/ee/bytecode/util/ByteCodeTrace.trace (I)V
    DUP
    INVOKESTATIC net/sf/saxon/lib/StandardURIChecker.getInstance ()Lnet/sf/saxon/lib/StandardURIChecker;
    SWAP
    INVOKEVIRTUAL net/sf/saxon/lib/StandardURIChecker.isValidURI (Ljava/lang/CharSequence;)Z
    IFNE L149
    LDC "The string value of the constructed namespace node must be a valid URI"
    LDC "XTDE0905"
    LDC "file:/Users/mike/w3c/xslt30-test-B/tests/attr/avt/avt-0303.xsl"
    BIPUSH 31
    ICONST_0
    INVOKESTATIC com/saxonica/ee/bytecode/util/Callback.makeXPathException (Ljava/lang/String;Ljava/lang/String;Ljava/lang/String;IZ)Lnet/sf/saxon/trans/XPathException;
    ATHROW
   L149
    SIPUSH 154
    INVOKESTATIC com/saxonica/ee/bytecode/util/ByteCodeTrace.trace (I)V
    INVOKESTATIC net/sf/saxon/om/NamespaceBinding.makeNamespaceBinding (Ljava/lang/CharSequence;Ljava/lang/CharSequence;)Lnet/sf/saxon/om/NamespaceBinding;
    BIPUSH 32
    INVOKEINTERFACE net/sf/saxon/event/Receiver.namespace (Lnet/sf/saxon/om/NamespaceBinding;I)V
    ALOAD 2
    INVOKEINTERFACE net/sf/saxon/event/Receiver.endElement ()V
   L150
    LDC "SimpleNodeConstructorCompiler-Push"
    INVOKESTATIC com/saxonica/ee/bytecode/util/ByteCodeTrace.showMessage (Ljava/lang/String;)V
    ALOAD 2
   L151
    LDC "LiteralCompiler-Primitive"
    INVOKESTATIC com/saxonica/ee/bytecode/util/ByteCodeTrace.showMessage (Ljava/lang/String;)V
    LINENUMBER 18 L152
    LDC "\n"
    GETSTATIC EE__Slash_doc_40517978947.nAttributeLocation43 : Lnet/sf/saxon/style/ExpressionContext$AttributeLocation;
    ICONST_0
    INVOKEINTERFACE net/sf/saxon/event/Receiver.characters (Ljava/lang/CharSequence;Lnet/sf/saxon/expr/parser/Location;I)V
   L153
    LDC "FixedElement-elem"
    INVOKESTATIC com/saxonica/ee/bytecode/util/ByteCodeTrace.showMessage (Ljava/lang/String;)V
   L154
    LDC "ElementCreator-push"
    INVOKESTATIC com/saxonica/ee/bytecode/util/ByteCodeTrace.showMessage (Ljava/lang/String;)V
    LINENUMBER 36 L155
    ALOAD 2
    DUP
    LDC "Receiver: "
    SWAP
    DUP
    IFNULL L156
    INVOKEVIRTUAL java/lang/Object.toString ()Ljava/lang/String;
    INVOKESTATIC com/saxonica/ee/bytecode/util/ByteCodeTrace.showObjectVariable (Ljava/lang/String;Ljava/lang/String;)V
    GOTO L157
   L156
    SIPUSH 155
    INVOKESTATIC com/saxonica/ee/bytecode/util/ByteCodeTrace.trace (I)V
    POP
    LDC "null"
    INVOKESTATIC com/saxonica/ee/bytecode/util/ByteCodeTrace.showObjectVariable (Ljava/lang/String;Ljava/lang/String;)V
   L157
    SIPUSH 156
    INVOKESTATIC com/saxonica/ee/bytecode/util/ByteCodeTrace.trace (I)V
    INVOKEINTERFACE net/sf/saxon/event/Receiver.getSystemId ()Ljava/lang/String;
    IFNONNULL L158
    ALOAD 2
    LDC "file:/Users/mike/w3c/xslt30-test-B/tests/attr/avt/avt-0303.xsl"
    INVOKEINTERFACE net/sf/saxon/event/Receiver.setSystemId (Ljava/lang/String;)V
   L158
    SIPUSH 157
    INVOKESTATIC com/saxonica/ee/bytecode/util/ByteCodeTrace.trace (I)V
    ALOAD 2
    GETSTATIC EE__Slash_doc_40517978947.nFingerprintedQName44 : Lnet/sf/saxon/om/FingerprintedQName;
    GETSTATIC EE__Slash_doc_40517978947.nUntyped42 : Lnet/sf/saxon/type/Untyped;
    GETSTATIC EE__Slash_doc_40517978947.nAttributeLocation48 : Lnet/sf/saxon/style/ExpressionContext$AttributeLocation;
    ICONST_0
    INVOKEINTERFACE net/sf/saxon/event/Receiver.startElement (Lnet/sf/saxon/om/NodeName;Lnet/sf/saxon/type/SchemaType;Lnet/sf/saxon/expr/parser/Location;I)V
   L159
    LDC "SimpleNodeConstructorCompiler-Push"
    INVOKESTATIC com/saxonica/ee/bytecode/util/ByteCodeTrace.showMessage (Ljava/lang/String;)V
    ALOAD 2
   L160
    LDC "Concat-item"
    INVOKESTATIC com/saxonica/ee/bytecode/util/ByteCodeTrace.showMessage (Ljava/lang/String;)V
    NEW net/sf/saxon/tree/util/FastStringBuffer
    DUP
    BIPUSH 64
    INVOKESPECIAL net/sf/saxon/tree/util/FastStringBuffer.<init> (I)V
    ASTORE 4
    ALOAD 4
   L161
    LDC "LiteralCompiler-Primitive"
    INVOKESTATIC com/saxonica/ee/bytecode/util/ByteCodeTrace.showMessage (Ljava/lang/String;)V
    LDC "a"
    INVOKEVIRTUAL net/sf/saxon/tree/util/FastStringBuffer.append (Ljava/lang/CharSequence;)V
    ALOAD 4
   L162
    LDC "StringFn-str"
    INVOKESTATIC com/saxonica/ee/bytecode/util/ByteCodeTrace.showMessage (Ljava/lang/String;)V
    TRYCATCHBLOCK L163 L164 L165 java/lang/UnsupportedOperationException
   L163
    SIPUSH 158
    INVOKESTATIC com/saxonica/ee/bytecode/util/ByteCodeTrace.trace (I)V
   L166
    LDC "AtomicSequenceConverterCompiler-Item"
    INVOKESTATIC com/saxonica/ee/bytecode/util/ByteCodeTrace.showMessage (Ljava/lang/String;)V
   L167
    LDC "AtomizerCompiler-Item"
    INVOKESTATIC com/saxonica/ee/bytecode/util/ByteCodeTrace.showMessage (Ljava/lang/String;)V
   L168
    LDC "itemAt"
    INVOKESTATIC com/saxonica/ee/bytecode/util/ByteCodeTrace.showMessage (Ljava/lang/String;)V
   L169
    LDC "AxisExpressionCompiler - iterate"
    INVOKESTATIC com/saxonica/ee/bytecode/util/ByteCodeTrace.showMessage (Ljava/lang/String;)V
    ALOAD 1
    INVOKEINTERFACE net/sf/saxon/expr/XPathContext.getContextItem ()Lnet/sf/saxon/om/Item;
    CHECKCAST net/sf/saxon/om/NodeInfo
   L170
    LDC "AxisExpressionCompiler - static method: iterate"
    INVOKESTATIC com/saxonica/ee/bytecode/util/ByteCodeTrace.showMessage (Ljava/lang/String;)V
    ICONST_3
    GETSTATIC EE__Slash_doc_40517978947.nNameTest45 : Lnet/sf/saxon/pattern/NameTest;
    LDC "calling iterateAxis"
    INVOKESTATIC com/saxonica/ee/bytecode/util/ByteCodeTrace.showMessage (Ljava/lang/String;)V
    INVOKEINTERFACE net/sf/saxon/om/NodeInfo.iterateAxis (BLnet/sf/saxon/pattern/NodeTest;)Lnet/sf/saxon/tree/iter/AxisIterator;
    LDC "returning axis iterator"
    INVOKESTATIC com/saxonica/ee/bytecode/util/ByteCodeTrace.showMessage (Ljava/lang/String;)V
    DUP
    INSTANCEOF net/sf/saxon/value/MemoClosure$ProgressiveIterator
    IFNE L171
    DUP
    INVOKEINTERFACE net/sf/saxon/om/SequenceIterator.getProperties ()I
    ICONST_1
    IAND
    IFNE L172
    ICONST_4
    INVOKESTATIC net/sf/saxon/expr/TailIterator.make (Lnet/sf/saxon/om/SequenceIterator;I)Lnet/sf/saxon/om/SequenceIterator;
    DUP
    INVOKEINTERFACE net/sf/saxon/om/SequenceIterator.next ()Lnet/sf/saxon/om/Item;
    SWAP
    INVOKEINTERFACE net/sf/saxon/om/SequenceIterator.close ()V
    GOTO L173
   L171
    SIPUSH 159
    INVOKESTATIC com/saxonica/ee/bytecode/util/ByteCodeTrace.trace (I)V
    CHECKCAST net/sf/saxon/value/MemoClosure$ProgressiveIterator
    INVOKEVIRTUAL net/sf/saxon/value/MemoClosure$ProgressiveIterator.getMemoClosure ()Lnet/sf/saxon/value/MemoClosure;
    ICONST_3
    INVOKEVIRTUAL net/sf/saxon/value/MemoClosure.itemAt (I)Lnet/sf/saxon/om/Item;
    GOTO L173
   L172
    SIPUSH 160
    INVOKESTATIC com/saxonica/ee/bytecode/util/ByteCodeTrace.trace (I)V
    CHECKCAST net/sf/saxon/tree/iter/GroundedIterator
    INVOKEINTERFACE net/sf/saxon/tree/iter/GroundedIterator.materialize ()Lnet/sf/saxon/om/GroundedValue;
    ICONST_3
    INVOKEINTERFACE net/sf/saxon/om/GroundedValue.itemAt (I)Lnet/sf/saxon/om/Item;
   L173
    SIPUSH 161
    INVOKESTATIC com/saxonica/ee/bytecode/util/ByteCodeTrace.trace (I)V
    DUP
    IFNULL L174
    INVOKEINTERFACE net/sf/saxon/om/Item.atomize ()Lnet/sf/saxon/om/AtomicSequence;
    INVOKEINTERFACE net/sf/saxon/om/AtomicSequence.head ()Lnet/sf/saxon/value/AtomicValue;
   L174
    SIPUSH 162
    INVOKESTATIC com/saxonica/ee/bytecode/util/ByteCodeTrace.trace (I)V
   L175
    LDC "AtomicSequenceConverterCompiler-Item-Returned"
    INVOKESTATIC com/saxonica/ee/bytecode/util/ByteCodeTrace.showMessage (Ljava/lang/String;)V
    DUP
    IFNONNULL L176
    POP
    ACONST_NULL
    GOTO L177
   L176
    SIPUSH 163
    INVOKESTATIC com/saxonica/ee/bytecode/util/ByteCodeTrace.trace (I)V
    INVOKEINTERFACE net/sf/saxon/om/Item.getStringValueCS ()Ljava/lang/CharSequence;
    INVOKESTATIC net/sf/saxon/value/StringValue.makeStringValue (Ljava/lang/CharSequence;)Lnet/sf/saxon/value/StringValue;
   L177
    SIPUSH 164
    INVOKESTATIC com/saxonica/ee/bytecode/util/ByteCodeTrace.trace (I)V
    DUP
    IFNONNULL L178
    POP
    LDC ""
    GOTO L179
   L178
    SIPUSH 165
    INVOKESTATIC com/saxonica/ee/bytecode/util/ByteCodeTrace.trace (I)V
    INVOKEINTERFACE net/sf/saxon/om/Item.getStringValueCS ()Ljava/lang/CharSequence;
   L179
    SIPUSH 166
    INVOKESTATIC com/saxonica/ee/bytecode/util/ByteCodeTrace.trace (I)V
   L164
    SIPUSH 167
    INVOKESTATIC com/saxonica/ee/bytecode/util/ByteCodeTrace.trace (I)V
    GOTO L180
   L165
    SIPUSH 168
    INVOKESTATIC com/saxonica/ee/bytecode/util/ByteCodeTrace.trace (I)V
   L181
    LDC "CatchStringFn"
    INVOKESTATIC com/saxonica/ee/bytecode/util/ByteCodeTrace.showMessage (Ljava/lang/String;)V
    INVOKEVIRTUAL java/lang/UnsupportedOperationException.getMessage ()Ljava/lang/String;
    LDC "FOTY0014"
    LDC "file:/Users/mike/w3c/xslt30-test-B/tests/attr/avt/avt-0303.xsl"
    BIPUSH 36
    ICONST_0
    INVOKESTATIC com/saxonica/ee/bytecode/util/Callback.makeXPathException (Ljava/lang/String;Ljava/lang/String;Ljava/lang/String;IZ)Lnet/sf/saxon/trans/XPathException;
    ATHROW
   L180
    SIPUSH 169
    INVOKESTATIC com/saxonica/ee/bytecode/util/ByteCodeTrace.trace (I)V
    INVOKEVIRTUAL net/sf/saxon/tree/util/FastStringBuffer.append (Ljava/lang/CharSequence;)V
    ALOAD 4
    INVOKEVIRTUAL net/sf/saxon/tree/util/FastStringBuffer.condense ()Ljava/lang/CharSequence;
    INVOKESTATIC net/sf/saxon/value/Whitespace.trim (Ljava/lang/CharSequence;)Ljava/lang/String;
    INVOKEVIRTUAL java/lang/Object.toString ()Ljava/lang/String;
    DUP
    INVOKEINTERFACE java/lang/CharSequence.length ()I
    IFEQ L182
    DUP
    INVOKESTATIC net/sf/saxon/om/NameChecker.isValidNCName (Ljava/lang/CharSequence;)Z
    IFNE L183
    LDC "Namespace prefix is invalid"
    LDC "XTDE0920"
    LDC "file:/Users/mike/w3c/xslt30-test-B/tests/attr/avt/avt-0303.xsl"
    BIPUSH 36
    ICONST_0
    INVOKESTATIC com/saxonica/ee/bytecode/util/Callback.makeXPathException (Ljava/lang/String;Ljava/lang/String;Ljava/lang/String;IZ)Lnet/sf/saxon/trans/XPathException;
    ATHROW
   L183
    SIPUSH 170
    INVOKESTATIC com/saxonica/ee/bytecode/util/ByteCodeTrace.trace (I)V
    DUP
    LDC "xmlns"
    INVOKEVIRTUAL java/lang/Object.equals (Ljava/lang/Object;)Z
    IFEQ L182
    LDC "Namespace prefix must not be 'xmlns'"
    LDC "XTDE0920"
    LDC "file:/Users/mike/w3c/xslt30-test-B/tests/attr/avt/avt-0303.xsl"
    BIPUSH 36
    ICONST_0
    INVOKESTATIC com/saxonica/ee/bytecode/util/Callback.makeXPathException (Ljava/lang/String;Ljava/lang/String;Ljava/lang/String;IZ)Lnet/sf/saxon/trans/XPathException;
    ATHROW
   L182
    SIPUSH 171
    INVOKESTATIC com/saxonica/ee/bytecode/util/ByteCodeTrace.trace (I)V
   L184
    LDC "LiteralCompiler-Primitive"
    INVOKESTATIC com/saxonica/ee/bytecode/util/ByteCodeTrace.showMessage (Ljava/lang/String;)V
    LDC "http://www.test.org/"
    DUP2
    DUP
    INVOKEINTERFACE java/lang/CharSequence.length ()I
    IFNE L185
    LDC "Namespace URI must not be zero-length"
    LDC "XTDE0930"
    LDC "file:/Users/mike/w3c/xslt30-test-B/tests/attr/avt/avt-0303.xsl"
    BIPUSH 36
    ICONST_0
    INVOKESTATIC com/saxonica/ee/bytecode/util/Callback.makeXPathException (Ljava/lang/String;Ljava/lang/String;Ljava/lang/String;IZ)Lnet/sf/saxon/trans/XPathException;
    ATHROW
   L185
    SIPUSH 172
    INVOKESTATIC com/saxonica/ee/bytecode/util/ByteCodeTrace.trace (I)V
    LDC "http://www.w3.org/XML/1998/namespace"
    INVOKEVIRTUAL java/lang/Object.equals (Ljava/lang/Object;)Z
    SWAP
    LDC "xml"
    INVOKEVIRTUAL java/lang/Object.equals (Ljava/lang/Object;)Z
    IF_ICMPEQ L186
    LDC "Namespace prefix 'xml' and namespace uri http://www.w3.org/XML/1998/namespace must only be used together"
    LDC "XTDE0925"
    LDC "file:/Users/mike/w3c/xslt30-test-B/tests/attr/avt/avt-0303.xsl"
    BIPUSH 36
    ICONST_0
    INVOKESTATIC com/saxonica/ee/bytecode/util/Callback.makeXPathException (Ljava/lang/String;Ljava/lang/String;Ljava/lang/String;IZ)Lnet/sf/saxon/trans/XPathException;
    ATHROW
   L186
    SIPUSH 173
    INVOKESTATIC com/saxonica/ee/bytecode/util/ByteCodeTrace.trace (I)V
    DUP
    LDC "http://www.w3.org/2000/xmlns/"
    INVOKEVIRTUAL java/lang/Object.equals (Ljava/lang/Object;)Z
    IFEQ L187
    LDC "Namespace URI must not be http://www.w3.org/2000/xmlns/"
    LDC "XTDE0905"
    LDC "file:/Users/mike/w3c/xslt30-test-B/tests/attr/avt/avt-0303.xsl"
    BIPUSH 36
    ICONST_0
    INVOKESTATIC com/saxonica/ee/bytecode/util/Callback.makeXPathException (Ljava/lang/String;Ljava/lang/String;Ljava/lang/String;IZ)Lnet/sf/saxon/trans/XPathException;
    ATHROW
   L187
    SIPUSH 174
    INVOKESTATIC com/saxonica/ee/bytecode/util/ByteCodeTrace.trace (I)V
    DUP
    INVOKESTATIC net/sf/saxon/lib/StandardURIChecker.getInstance ()Lnet/sf/saxon/lib/StandardURIChecker;
    SWAP
    INVOKEVIRTUAL net/sf/saxon/lib/StandardURIChecker.isValidURI (Ljava/lang/CharSequence;)Z
    IFNE L188
    LDC "The string value of the constructed namespace node must be a valid URI"
    LDC "XTDE0905"
    LDC "file:/Users/mike/w3c/xslt30-test-B/tests/attr/avt/avt-0303.xsl"
    BIPUSH 36
    ICONST_0
    INVOKESTATIC com/saxonica/ee/bytecode/util/Callback.makeXPathException (Ljava/lang/String;Ljava/lang/String;Ljava/lang/String;IZ)Lnet/sf/saxon/trans/XPathException;
    ATHROW
   L188
    SIPUSH 175
    INVOKESTATIC com/saxonica/ee/bytecode/util/ByteCodeTrace.trace (I)V
    INVOKESTATIC net/sf/saxon/om/NamespaceBinding.makeNamespaceBinding (Ljava/lang/CharSequence;Ljava/lang/CharSequence;)Lnet/sf/saxon/om/NamespaceBinding;
    BIPUSH 32
    INVOKEINTERFACE net/sf/saxon/event/Receiver.namespace (Lnet/sf/saxon/om/NamespaceBinding;I)V
    ALOAD 2
    INVOKEINTERFACE net/sf/saxon/event/Receiver.endElement ()V
    ALOAD 2
    INVOKEINTERFACE net/sf/saxon/event/Receiver.endElement ()V
    RETURN
    MAXSTACK = 0
    MAXLOCALS = 0
}

  // access flags 0x9
  public static Lnet/sf/saxon/om/FingerprintedQName; nFingerprintedQName44

  // access flags 0x9
  public static Lnet/sf/saxon/om/NoNamespaceName; nNoNamespaceName41

  // access flags 0x9
  public static Lnet/sf/saxon/style/ExpressionContext$AttributeLocation; nAttributeLocation46

  // access flags 0x9
  public static Lnet/sf/saxon/type/Untyped; nUntyped42

  // access flags 0x9
  public static Lnet/sf/saxon/pattern/NameTest; nNameTest45

  // access flags 0x9
  public static Lnet/sf/saxon/style/ExpressionContext$AttributeLocation; nAttributeLocation43

  // access flags 0x9
  public static Lnet/sf/saxon/style/ExpressionContext$AttributeLocation; nAttributeLocation48

  // access flags 0x9
  public static Lnet/sf/saxon/style/ExpressionContext$AttributeLocation; nAttributeLocation47
}
