// class version 49.0 (49)
// access flags 0x1
public class EE__Slash_doc_81855459426 extends com/saxonica/ee/bytecode/GeneratedCode  {


  // access flags 0x1
  public <init>()V
    LINENUMBER 18 L0
    ALOAD 0
    INVOKESPECIAL com/saxonica/ee/bytecode/GeneratedCode.<init> ()V
    RETURN
    MAXSTACK = 0
    MAXLOCALS = 0

  // access flags 0x1
  public process(Lnet/sf/saxon/expr/XPathContext;)V throws net/sf/saxon/trans/XPathException 
    ALOAD 1
    INVOKEINTERFACE net/sf/saxon/expr/XPathContext.getReceiver ()Lnet/sf/saxon/event/SequenceReceiver;
    ASTORE 2
    LINENUMBER 18 L0
   L1
    LDC "FixedElement-out"
    INVOKESTATIC com/saxonica/ee/bytecode/util/ByteCodeTrace.showMessage (Ljava/lang/String;)V
   L2
    LDC "ElementCreator-push"
    INVOKESTATIC com/saxonica/ee/bytecode/util/ByteCodeTrace.showMessage (Ljava/lang/String;)V
    ALOAD 2
    DUP
    LDC "Receiver: "
    SWAP
    DUP
    IFNULL L3
    INVOKEVIRTUAL java/lang/Object.toString ()Ljava/lang/String;
    INVOKESTATIC com/saxonica/ee/bytecode/util/ByteCodeTrace.showObjectVariable (Ljava/lang/String;Ljava/lang/String;)V
    GOTO L4
   L3
    SIPUSH 238
    INVOKESTATIC com/saxonica/ee/bytecode/util/ByteCodeTrace.trace (I)V
    POP
    LDC "null"
    INVOKESTATIC com/saxonica/ee/bytecode/util/ByteCodeTrace.showObjectVariable (Ljava/lang/String;Ljava/lang/String;)V
   L4
    SIPUSH 239
    INVOKESTATIC com/saxonica/ee/bytecode/util/ByteCodeTrace.trace (I)V
    INVOKEINTERFACE net/sf/saxon/event/Receiver.getSystemId ()Ljava/lang/String;
    IFNONNULL L5
    ALOAD 2
    LDC "file:/Users/mike/w3c/xslt30-test-B/tests/attr/avt/avt-0601.xsl"
    INVOKEINTERFACE net/sf/saxon/event/Receiver.setSystemId (Ljava/lang/String;)V
   L5
    SIPUSH 240
    INVOKESTATIC com/saxonica/ee/bytecode/util/ByteCodeTrace.trace (I)V
    ALOAD 2
    GETSTATIC EE__Slash_doc_81855459426.nNoNamespaceName82 : Lnet/sf/saxon/om/NoNamespaceName;
    GETSTATIC EE__Slash_doc_81855459426.nUntyped83 : Lnet/sf/saxon/type/Untyped;
    GETSTATIC EE__Slash_doc_81855459426.nNestedLocation84 : Lnet/sf/saxon/expr/parser/XPathParser$NestedLocation;
    ICONST_0
    INVOKEINTERFACE net/sf/saxon/event/Receiver.startElement (Lnet/sf/saxon/om/NodeName;Lnet/sf/saxon/type/SchemaType;Lnet/sf/saxon/expr/parser/Location;I)V
   L6
    LDC "BlockCompiler-Push"
    INVOKESTATIC com/saxonica/ee/bytecode/util/ByteCodeTrace.showMessage (Ljava/lang/String;)V
   L7
    LDC "FixedElement-E1"
    INVOKESTATIC com/saxonica/ee/bytecode/util/ByteCodeTrace.showMessage (Ljava/lang/String;)V
   L8
    LDC "ElementCreator-push"
    INVOKESTATIC com/saxonica/ee/bytecode/util/ByteCodeTrace.showMessage (Ljava/lang/String;)V
    ALOAD 2
    DUP
    LDC "Receiver: "
    SWAP
    DUP
    IFNULL L9
    INVOKEVIRTUAL java/lang/Object.toString ()Ljava/lang/String;
    INVOKESTATIC com/saxonica/ee/bytecode/util/ByteCodeTrace.showObjectVariable (Ljava/lang/String;Ljava/lang/String;)V
    GOTO L10
   L9
    SIPUSH 241
    INVOKESTATIC com/saxonica/ee/bytecode/util/ByteCodeTrace.trace (I)V
    POP
    LDC "null"
    INVOKESTATIC com/saxonica/ee/bytecode/util/ByteCodeTrace.showObjectVariable (Ljava/lang/String;Ljava/lang/String;)V
   L10
    SIPUSH 242
    INVOKESTATIC com/saxonica/ee/bytecode/util/ByteCodeTrace.trace (I)V
    INVOKEINTERFACE net/sf/saxon/event/Receiver.getSystemId ()Ljava/lang/String;
    IFNONNULL L11
    ALOAD 2
    LDC "file:/Users/mike/w3c/xslt30-test-B/tests/attr/avt/avt-0601.xsl"
    INVOKEINTERFACE net/sf/saxon/event/Receiver.setSystemId (Ljava/lang/String;)V
   L11
    SIPUSH 243
    INVOKESTATIC com/saxonica/ee/bytecode/util/ByteCodeTrace.trace (I)V
    ALOAD 2
    GETSTATIC EE__Slash_doc_81855459426.nNoNamespaceName85 : Lnet/sf/saxon/om/NoNamespaceName;
    GETSTATIC EE__Slash_doc_81855459426.nUntyped83 : Lnet/sf/saxon/type/Untyped;
    GETSTATIC EE__Slash_doc_81855459426.nNestedLocation84 : Lnet/sf/saxon/expr/parser/XPathParser$NestedLocation;
    ICONST_0
    INVOKEINTERFACE net/sf/saxon/event/Receiver.startElement (Lnet/sf/saxon/om/NodeName;Lnet/sf/saxon/type/SchemaType;Lnet/sf/saxon/expr/parser/Location;I)V
    GETSTATIC EE__Slash_doc_81855459426.nJavaPlatformPE86 : Lcom/saxonica/config/JavaPlatformPE;
   L12
    LDC "Concat-item"
    INVOKESTATIC com/saxonica/ee/bytecode/util/ByteCodeTrace.showMessage (Ljava/lang/String;)V
    NEW net/sf/saxon/tree/util/FastStringBuffer
    DUP
    BIPUSH 64
    INVOKESPECIAL net/sf/saxon/tree/util/FastStringBuffer.<init> (I)V
    ASTORE 4
    ALOAD 4
   L13
    LDC "LiteralCompiler-Primitive"
    INVOKESTATIC com/saxonica/ee/bytecode/util/ByteCodeTrace.showMessage (Ljava/lang/String;)V
    LDC "("
    INVOKEVIRTUAL net/sf/saxon/tree/util/FastStringBuffer.append (Ljava/lang/CharSequence;)V
    ALOAD 4
   L14
    LDC "StringJoin-Item"
    INVOKESTATIC com/saxonica/ee/bytecode/util/ByteCodeTrace.showMessage (Ljava/lang/String;)V
   L15
    LDC "AtomicSequenceConverterCompiler-Itr"
    INVOKESTATIC com/saxonica/ee/bytecode/util/ByteCodeTrace.showMessage (Ljava/lang/String;)V
   L16
    LDC "AtomicSequenceConverterCompiler-string"
    INVOKESTATIC com/saxonica/ee/bytecode/util/ByteCodeTrace.showMessage (Ljava/lang/String;)V
    NEW net/sf/saxon/expr/ItemMappingIterator
    DUP
   L17
    LDC "AtomizerCompiler-Itr"
    INVOKESTATIC com/saxonica/ee/bytecode/util/ByteCodeTrace.showMessage (Ljava/lang/String;)V
   L18
    LDC "AxisExpressionCompiler - iterate"
    INVOKESTATIC com/saxonica/ee/bytecode/util/ByteCodeTrace.showMessage (Ljava/lang/String;)V
    ALOAD 1
    INVOKEINTERFACE net/sf/saxon/expr/XPathContext.getContextItem ()Lnet/sf/saxon/om/Item;
    CHECKCAST net/sf/saxon/om/NodeInfo
   L19
    LDC "AxisExpressionCompiler - static method: iterate"
    INVOKESTATIC com/saxonica/ee/bytecode/util/ByteCodeTrace.showMessage (Ljava/lang/String;)V
    ICONST_3
    GETSTATIC EE__Slash_doc_81855459426.nNameTest87 : Lnet/sf/saxon/pattern/NameTest;
    LDC "calling iterateAxis"
    INVOKESTATIC com/saxonica/ee/bytecode/util/ByteCodeTrace.showMessage (Ljava/lang/String;)V
    INVOKEINTERFACE net/sf/saxon/om/NodeInfo.iterateAxis (BLnet/sf/saxon/pattern/NodeTest;)Lnet/sf/saxon/tree/iter/AxisIterator;
    LDC "returning axis iterator"
    INVOKESTATIC com/saxonica/ee/bytecode/util/ByteCodeTrace.showMessage (Ljava/lang/String;)V
    ICONST_1
    INVOKESTATIC net/sf/saxon/expr/Atomizer.getAtomizingIterator (Lnet/sf/saxon/om/SequenceIterator;Z)Lnet/sf/saxon/om/SequenceIterator;
    GETSTATIC net/sf/saxon/expr/AtomicSequenceConverter.TO_STRING_MAPPER : Lnet/sf/saxon/expr/AtomicSequenceConverter$ToStringMappingFunction;
    ICONST_1
    INVOKESPECIAL net/sf/saxon/expr/ItemMappingIterator.<init> (Lnet/sf/saxon/om/SequenceIterator;Lnet/sf/saxon/expr/ItemMappingFunction;Z)V
   L20
    LDC "StringJoin-Item-1"
    INVOKESTATIC com/saxonica/ee/bytecode/util/ByteCodeTrace.showMessage (Ljava/lang/String;)V
    ASTORE 5
    ALOAD 5
    INVOKEINTERFACE net/sf/saxon/om/SequenceIterator.next ()Lnet/sf/saxon/om/Item;
    DUP
    IFNONNULL L21
    POP
    LDC ""
    GOTO L22
   L21
    SIPUSH 244
    INVOKESTATIC com/saxonica/ee/bytecode/util/ByteCodeTrace.trace (I)V
    INVOKEINTERFACE net/sf/saxon/om/Item.getStringValueCS ()Ljava/lang/CharSequence;
    ASTORE 6
    ALOAD 5
    INVOKEINTERFACE net/sf/saxon/om/SequenceIterator.next ()Lnet/sf/saxon/om/Item;
    DUP
    IFNONNULL L23
    POP
    ALOAD 6
    GOTO L22
   L23
    SIPUSH 245
    INVOKESTATIC com/saxonica/ee/bytecode/util/ByteCodeTrace.trace (I)V
    NEW net/sf/saxon/tree/util/FastStringBuffer
    DUP
    BIPUSH 64
    INVOKESPECIAL net/sf/saxon/tree/util/FastStringBuffer.<init> (I)V
    ASTORE 7
    ALOAD 7
    ALOAD 6
    INVOKEVIRTUAL net/sf/saxon/tree/util/FastStringBuffer.append (Ljava/lang/CharSequence;)V
   L24
    LDC "LiteralCompiler-Primitive"
    INVOKESTATIC com/saxonica/ee/bytecode/util/ByteCodeTrace.showMessage (Ljava/lang/String;)V
    LDC " "
    ASTORE 8
    ALOAD 7
    ALOAD 8
    INVOKEVIRTUAL net/sf/saxon/tree/util/FastStringBuffer.append (Ljava/lang/CharSequence;)V
    ALOAD 7
    SWAP
    INVOKEINTERFACE net/sf/saxon/om/Item.getStringValueCS ()Ljava/lang/CharSequence;
    INVOKEVIRTUAL net/sf/saxon/tree/util/FastStringBuffer.append (Ljava/lang/CharSequence;)V
   L25
    SIPUSH 246
    INVOKESTATIC com/saxonica/ee/bytecode/util/ByteCodeTrace.trace (I)V
    ALOAD 5
    INVOKEINTERFACE net/sf/saxon/om/SequenceIterator.next ()Lnet/sf/saxon/om/Item;
    DUP
    IFNULL L26
    ALOAD 7
    ALOAD 8
    INVOKEVIRTUAL net/sf/saxon/tree/util/FastStringBuffer.append (Ljava/lang/CharSequence;)V
    ALOAD 7
    SWAP
    INVOKEINTERFACE net/sf/saxon/om/Item.getStringValueCS ()Ljava/lang/CharSequence;
    INVOKEVIRTUAL net/sf/saxon/tree/util/FastStringBuffer.append (Ljava/lang/CharSequence;)V
    GOTO L25
   L26
    SIPUSH 247
    INVOKESTATIC com/saxonica/ee/bytecode/util/ByteCodeTrace.trace (I)V
    POP
    ALOAD 7
    INVOKEVIRTUAL net/sf/saxon/tree/util/FastStringBuffer.condense ()Ljava/lang/CharSequence;
   L22
    SIPUSH 248
    INVOKESTATIC com/saxonica/ee/bytecode/util/ByteCodeTrace.trace (I)V
    INVOKEVIRTUAL net/sf/saxon/tree/util/FastStringBuffer.append (Ljava/lang/CharSequence;)V
    ALOAD 4
   L27
    LDC "LiteralCompiler-Primitive"
    INVOKESTATIC com/saxonica/ee/bytecode/util/ByteCodeTrace.showMessage (Ljava/lang/String;)V
    LDC ")              (.*)               (gesehen,)$"
    INVOKEVIRTUAL net/sf/saxon/tree/util/FastStringBuffer.append (Ljava/lang/CharSequence;)V
    ALOAD 4
    INVOKEVIRTUAL net/sf/saxon/tree/util/FastStringBuffer.condense ()Ljava/lang/CharSequence;
   L28
    LDC "Concat-item"
    INVOKESTATIC com/saxonica/ee/bytecode/util/ByteCodeTrace.showMessage (Ljava/lang/String;)V
    NEW net/sf/saxon/tree/util/FastStringBuffer
    DUP
    BIPUSH 64
    INVOKESPECIAL net/sf/saxon/tree/util/FastStringBuffer.<init> (I)V
    ASTORE 4
    ALOAD 4
   L29
    LDC "StringFn-str"
    INVOKESTATIC com/saxonica/ee/bytecode/util/ByteCodeTrace.showMessage (Ljava/lang/String;)V
    TRYCATCHBLOCK L30 L31 L32 java/lang/UnsupportedOperationException
   L30
    SIPUSH 249
    INVOKESTATIC com/saxonica/ee/bytecode/util/ByteCodeTrace.trace (I)V
   L33
    LDC "AtomicSequenceConverterCompiler-Item"
    INVOKESTATIC com/saxonica/ee/bytecode/util/ByteCodeTrace.showMessage (Ljava/lang/String;)V
   L34
    LDC "AtomizerCompiler-Item"
    INVOKESTATIC com/saxonica/ee/bytecode/util/ByteCodeTrace.showMessage (Ljava/lang/String;)V
   L35
    LDC "FirstItemExpression"
    INVOKESTATIC com/saxonica/ee/bytecode/util/ByteCodeTrace.showMessage (Ljava/lang/String;)V
   L36
    LDC "AxisExpressionCompiler - iterate"
    INVOKESTATIC com/saxonica/ee/bytecode/util/ByteCodeTrace.showMessage (Ljava/lang/String;)V
    ALOAD 1
    INVOKEINTERFACE net/sf/saxon/expr/XPathContext.getContextItem ()Lnet/sf/saxon/om/Item;
    CHECKCAST net/sf/saxon/om/NodeInfo
   L37
    LDC "AxisExpressionCompiler - static method: iterate"
    INVOKESTATIC com/saxonica/ee/bytecode/util/ByteCodeTrace.showMessage (Ljava/lang/String;)V
    ICONST_3
    GETSTATIC EE__Slash_doc_81855459426.nNameTest88 : Lnet/sf/saxon/pattern/NameTest;
    LDC "calling iterateAxis"
    INVOKESTATIC com/saxonica/ee/bytecode/util/ByteCodeTrace.showMessage (Ljava/lang/String;)V
    INVOKEINTERFACE net/sf/saxon/om/NodeInfo.iterateAxis (BLnet/sf/saxon/pattern/NodeTest;)Lnet/sf/saxon/tree/iter/AxisIterator;
    LDC "returning axis iterator"
    INVOKESTATIC com/saxonica/ee/bytecode/util/ByteCodeTrace.showMessage (Ljava/lang/String;)V
    DUP
    INVOKEINTERFACE net/sf/saxon/om/SequenceIterator.next ()Lnet/sf/saxon/om/Item;
    SWAP
    INVOKEINTERFACE net/sf/saxon/om/SequenceIterator.close ()V
    DUP
    IFNULL L38
    INVOKEINTERFACE net/sf/saxon/om/Item.atomize ()Lnet/sf/saxon/om/AtomicSequence;
    INVOKEINTERFACE net/sf/saxon/om/AtomicSequence.head ()Lnet/sf/saxon/value/AtomicValue;
   L38
    SIPUSH 250
    INVOKESTATIC com/saxonica/ee/bytecode/util/ByteCodeTrace.trace (I)V
   L39
    LDC "AtomicSequenceConverterCompiler-Item-Returned"
    INVOKESTATIC com/saxonica/ee/bytecode/util/ByteCodeTrace.showMessage (Ljava/lang/String;)V
    DUP
    IFNONNULL L40
    POP
    ACONST_NULL
    GOTO L41
   L40
    SIPUSH 251
    INVOKESTATIC com/saxonica/ee/bytecode/util/ByteCodeTrace.trace (I)V
    INVOKEINTERFACE net/sf/saxon/om/Item.getStringValueCS ()Ljava/lang/CharSequence;
    INVOKESTATIC net/sf/saxon/value/StringValue.makeStringValue (Ljava/lang/CharSequence;)Lnet/sf/saxon/value/StringValue;
   L41
    SIPUSH 252
    INVOKESTATIC com/saxonica/ee/bytecode/util/ByteCodeTrace.trace (I)V
    DUP
    IFNONNULL L42
    POP
    LDC ""
    GOTO L43
   L42
    SIPUSH 253
    INVOKESTATIC com/saxonica/ee/bytecode/util/ByteCodeTrace.trace (I)V
    INVOKEINTERFACE net/sf/saxon/om/Item.getStringValueCS ()Ljava/lang/CharSequence;
   L43
    SIPUSH 254
    INVOKESTATIC com/saxonica/ee/bytecode/util/ByteCodeTrace.trace (I)V
   L31
    SIPUSH 255
    INVOKESTATIC com/saxonica/ee/bytecode/util/ByteCodeTrace.trace (I)V
    GOTO L44
   L32
    SIPUSH 256
    INVOKESTATIC com/saxonica/ee/bytecode/util/ByteCodeTrace.trace (I)V
   L45
    LDC "CatchStringFn"
    INVOKESTATIC com/saxonica/ee/bytecode/util/ByteCodeTrace.showMessage (Ljava/lang/String;)V
    INVOKEVIRTUAL java/lang/UnsupportedOperationException.getMessage ()Ljava/lang/String;
    LDC "FOTY0014"
    LDC "file:/Users/mike/w3c/xslt30-test-B/tests/attr/avt/avt-0601.xsl"
    BIPUSH 18
    ICONST_0
    INVOKESTATIC com/saxonica/ee/bytecode/util/Callback.makeXPathException (Ljava/lang/String;Ljava/lang/String;Ljava/lang/String;IZ)Lnet/sf/saxon/trans/XPathException;
    ATHROW
   L44
    SIPUSH 257
    INVOKESTATIC com/saxonica/ee/bytecode/util/ByteCodeTrace.trace (I)V
    INVOKEVIRTUAL net/sf/saxon/tree/util/FastStringBuffer.append (Ljava/lang/CharSequence;)V
    ALOAD 4
   L46
    LDC "LiteralCompiler-Primitive"
    INVOKESTATIC com/saxonica/ee/bytecode/util/ByteCodeTrace.showMessage (Ljava/lang/String;)V
    LDC "i"
    INVOKEVIRTUAL net/sf/saxon/tree/util/FastStringBuffer.append (Ljava/lang/CharSequence;)V
    ALOAD 4
   L47
    LDC "StringFn-str"
    INVOKESTATIC com/saxonica/ee/bytecode/util/ByteCodeTrace.showMessage (Ljava/lang/String;)V
    TRYCATCHBLOCK L48 L49 L50 java/lang/UnsupportedOperationException
   L48
    SIPUSH 258
    INVOKESTATIC com/saxonica/ee/bytecode/util/ByteCodeTrace.trace (I)V
   L51
    LDC "AtomicSequenceConverterCompiler-Item"
    INVOKESTATIC com/saxonica/ee/bytecode/util/ByteCodeTrace.showMessage (Ljava/lang/String;)V
   L52
    LDC "AtomizerCompiler-Item"
    INVOKESTATIC com/saxonica/ee/bytecode/util/ByteCodeTrace.showMessage (Ljava/lang/String;)V
   L53
    LDC "itemAt"
    INVOKESTATIC com/saxonica/ee/bytecode/util/ByteCodeTrace.showMessage (Ljava/lang/String;)V
   L54
    LDC "AxisExpressionCompiler - iterate"
    INVOKESTATIC com/saxonica/ee/bytecode/util/ByteCodeTrace.showMessage (Ljava/lang/String;)V
    ALOAD 1
    INVOKEINTERFACE net/sf/saxon/expr/XPathContext.getContextItem ()Lnet/sf/saxon/om/Item;
    CHECKCAST net/sf/saxon/om/NodeInfo
   L55
    LDC "AxisExpressionCompiler - static method: iterate"
    INVOKESTATIC com/saxonica/ee/bytecode/util/ByteCodeTrace.showMessage (Ljava/lang/String;)V
    ICONST_3
    GETSTATIC EE__Slash_doc_81855459426.nNameTest88 : Lnet/sf/saxon/pattern/NameTest;
    LDC "calling iterateAxis"
    INVOKESTATIC com/saxonica/ee/bytecode/util/ByteCodeTrace.showMessage (Ljava/lang/String;)V
    INVOKEINTERFACE net/sf/saxon/om/NodeInfo.iterateAxis (BLnet/sf/saxon/pattern/NodeTest;)Lnet/sf/saxon/tree/iter/AxisIterator;
    LDC "returning axis iterator"
    INVOKESTATIC com/saxonica/ee/bytecode/util/ByteCodeTrace.showMessage (Ljava/lang/String;)V
    DUP
    INSTANCEOF net/sf/saxon/value/MemoClosure$ProgressiveIterator
    IFNE L56
    DUP
    INVOKEINTERFACE net/sf/saxon/om/SequenceIterator.getProperties ()I
    ICONST_1
    IAND
    IFNE L57
    ICONST_2
    INVOKESTATIC net/sf/saxon/expr/TailIterator.make (Lnet/sf/saxon/om/SequenceIterator;I)Lnet/sf/saxon/om/SequenceIterator;
    DUP
    INVOKEINTERFACE net/sf/saxon/om/SequenceIterator.next ()Lnet/sf/saxon/om/Item;
    SWAP
    INVOKEINTERFACE net/sf/saxon/om/SequenceIterator.close ()V
    GOTO L58
   L56
    SIPUSH 259
    INVOKESTATIC com/saxonica/ee/bytecode/util/ByteCodeTrace.trace (I)V
    CHECKCAST net/sf/saxon/value/MemoClosure$ProgressiveIterator
    INVOKEVIRTUAL net/sf/saxon/value/MemoClosure$ProgressiveIterator.getMemoClosure ()Lnet/sf/saxon/value/MemoClosure;
    ICONST_1
    INVOKEVIRTUAL net/sf/saxon/value/MemoClosure.itemAt (I)Lnet/sf/saxon/om/Item;
    GOTO L58
   L57
    SIPUSH 260
    INVOKESTATIC com/saxonica/ee/bytecode/util/ByteCodeTrace.trace (I)V
    CHECKCAST net/sf/saxon/tree/iter/GroundedIterator
    INVOKEINTERFACE net/sf/saxon/tree/iter/GroundedIterator.materialize ()Lnet/sf/saxon/om/GroundedValue;
    ICONST_1
    INVOKEINTERFACE net/sf/saxon/om/GroundedValue.itemAt (I)Lnet/sf/saxon/om/Item;
   L58
    SIPUSH 261
    INVOKESTATIC com/saxonica/ee/bytecode/util/ByteCodeTrace.trace (I)V
    DUP
    IFNULL L59
    INVOKEINTERFACE net/sf/saxon/om/Item.atomize ()Lnet/sf/saxon/om/AtomicSequence;
    INVOKEINTERFACE net/sf/saxon/om/AtomicSequence.head ()Lnet/sf/saxon/value/AtomicValue;
   L59
    SIPUSH 262
    INVOKESTATIC com/saxonica/ee/bytecode/util/ByteCodeTrace.trace (I)V
   L60
    LDC "AtomicSequenceConverterCompiler-Item-Returned"
    INVOKESTATIC com/saxonica/ee/bytecode/util/ByteCodeTrace.showMessage (Ljava/lang/String;)V
    DUP
    IFNONNULL L61
    POP
    ACONST_NULL
    GOTO L62
   L61
    SIPUSH 263
    INVOKESTATIC com/saxonica/ee/bytecode/util/ByteCodeTrace.trace (I)V
    INVOKEINTERFACE net/sf/saxon/om/Item.getStringValueCS ()Ljava/lang/CharSequence;
    INVOKESTATIC net/sf/saxon/value/StringValue.makeStringValue (Ljava/lang/CharSequence;)Lnet/sf/saxon/value/StringValue;
   L62
    SIPUSH 264
    INVOKESTATIC com/saxonica/ee/bytecode/util/ByteCodeTrace.trace (I)V
    DUP
    IFNONNULL L63
    POP
    LDC ""
    GOTO L64
   L63
    SIPUSH 265
    INVOKESTATIC com/saxonica/ee/bytecode/util/ByteCodeTrace.trace (I)V
    INVOKEINTERFACE net/sf/saxon/om/Item.getStringValueCS ()Ljava/lang/CharSequence;
   L64
    SIPUSH 266
    INVOKESTATIC com/saxonica/ee/bytecode/util/ByteCodeTrace.trace (I)V
   L49
    SIPUSH 267
    INVOKESTATIC com/saxonica/ee/bytecode/util/ByteCodeTrace.trace (I)V
    GOTO L65
   L50
    SIPUSH 268
    INVOKESTATIC com/saxonica/ee/bytecode/util/ByteCodeTrace.trace (I)V
   L66
    LDC "CatchStringFn"
    INVOKESTATIC com/saxonica/ee/bytecode/util/ByteCodeTrace.showMessage (Ljava/lang/String;)V
    INVOKEVIRTUAL java/lang/UnsupportedOperationException.getMessage ()Ljava/lang/String;
    LDC "FOTY0014"
    LDC "file:/Users/mike/w3c/xslt30-test-B/tests/attr/avt/avt-0601.xsl"
    BIPUSH 18
    ICONST_0
    INVOKESTATIC com/saxonica/ee/bytecode/util/Callback.makeXPathException (Ljava/lang/String;Ljava/lang/String;Ljava/lang/String;IZ)Lnet/sf/saxon/trans/XPathException;
    ATHROW
   L65
    SIPUSH 269
    INVOKESTATIC com/saxonica/ee/bytecode/util/ByteCodeTrace.trace (I)V
    INVOKEVIRTUAL net/sf/saxon/tree/util/FastStringBuffer.append (Ljava/lang/CharSequence;)V
    ALOAD 4
    INVOKEVIRTUAL net/sf/saxon/tree/util/FastStringBuffer.condense ()Ljava/lang/CharSequence;
    INVOKEVIRTUAL java/lang/Object.toString ()Ljava/lang/String;
    LDC "XP30"
    ACONST_NULL
    INVOKEINTERFACE net/sf/saxon/Platform.compileRegularExpression (Ljava/lang/CharSequence;Ljava/lang/String;Ljava/lang/String;Ljava/util/List;)Lnet/sf/saxon/regex/RegularExpression;
    DUP
    LDC ""
    INVOKEINTERFACE net/sf/saxon/regex/RegularExpression.matches (Ljava/lang/CharSequence;)Z
    IFEQ L67
    LDC "The regular expression must not be one that matches a zero-length string"
    LDC "XTDE1150"
    LDC "file:/Users/mike/w3c/xslt30-test-B/tests/attr/avt/avt-0601.xsl"
    BIPUSH 18
    ICONST_0
    INVOKESTATIC com/saxonica/ee/bytecode/util/Callback.makeXPathException (Ljava/lang/String;Ljava/lang/String;Ljava/lang/String;IZ)Lnet/sf/saxon/trans/XPathException;
    ATHROW
   L67
    SIPUSH 270
    INVOKESTATIC com/saxonica/ee/bytecode/util/ByteCodeTrace.trace (I)V
   L68
    LDC "CardinalityCheckerCompiler-Item"
    INVOKESTATIC com/saxonica/ee/bytecode/util/ByteCodeTrace.showMessage (Ljava/lang/String;)V
   L69
    LDC "AtomicSequenceConverterCompiler-Itr"
    INVOKESTATIC com/saxonica/ee/bytecode/util/ByteCodeTrace.showMessage (Ljava/lang/String;)V
   L70
    LDC "AtomicSequenceConverterCompiler-1"
    INVOKESTATIC com/saxonica/ee/bytecode/util/ByteCodeTrace.showMessage (Ljava/lang/String;)V
    NEW net/sf/saxon/expr/ItemMappingIterator
    DUP
   L71
    LDC "AtomizerCompiler-Itr"
    INVOKESTATIC com/saxonica/ee/bytecode/util/ByteCodeTrace.showMessage (Ljava/lang/String;)V
   L72
    LDC "AxisExpressionCompiler - iterate"
    INVOKESTATIC com/saxonica/ee/bytecode/util/ByteCodeTrace.showMessage (Ljava/lang/String;)V
    ALOAD 1
    INVOKEINTERFACE net/sf/saxon/expr/XPathContext.getContextItem ()Lnet/sf/saxon/om/Item;
    CHECKCAST net/sf/saxon/om/NodeInfo
   L73
    LDC "AxisExpressionCompiler - static method: iterate"
    INVOKESTATIC com/saxonica/ee/bytecode/util/ByteCodeTrace.showMessage (Ljava/lang/String;)V
    ICONST_3
    GETSTATIC EE__Slash_doc_81855459426.nNameTest89 : Lnet/sf/saxon/pattern/NameTest;
    LDC "calling iterateAxis"
    INVOKESTATIC com/saxonica/ee/bytecode/util/ByteCodeTrace.showMessage (Ljava/lang/String;)V
    INVOKEINTERFACE net/sf/saxon/om/NodeInfo.iterateAxis (BLnet/sf/saxon/pattern/NodeTest;)Lnet/sf/saxon/tree/iter/AxisIterator;
    LDC "returning axis iterator"
    INVOKESTATIC com/saxonica/ee/bytecode/util/ByteCodeTrace.showMessage (Ljava/lang/String;)V
    ICONST_1
    INVOKESTATIC net/sf/saxon/expr/Atomizer.getAtomizingIterator (Lnet/sf/saxon/om/SequenceIterator;Z)Lnet/sf/saxon/om/SequenceIterator;
    GETSTATIC EE__Slash_doc_81855459426.nAtomicSequenceMappingFunction90 : Lnet/sf/saxon/expr/AtomicSequenceConverter$AtomicSequenceMappingFunction;
    ICONST_1
    INVOKESPECIAL net/sf/saxon/expr/ItemMappingIterator.<init> (Lnet/sf/saxon/om/SequenceIterator;Lnet/sf/saxon/expr/ItemMappingFunction;Z)V
    CHECKCAST net/sf/saxon/om/SequenceIterator
    DUP
    INVOKEINTERFACE net/sf/saxon/om/SequenceIterator.next ()Lnet/sf/saxon/om/Item;
    SWAP
    INVOKEINTERFACE net/sf/saxon/om/SequenceIterator.next ()Lnet/sf/saxon/om/Item;
    IFNULL L74
    GETSTATIC EE__Slash_doc_81855459426.nCardinalityChecker91 : Lnet/sf/saxon/expr/CardinalityChecker;
    ALOAD 1
    INVOKESTATIC com/saxonica/ee/bytecode/util/Callback.makeMultipleItemsException (Lnet/sf/saxon/expr/CardinalityChecker;Lnet/sf/saxon/expr/XPathContext;)Lnet/sf/saxon/trans/XPathException;
    ATHROW
   L74
    SIPUSH 271
    INVOKESTATIC com/saxonica/ee/bytecode/util/ByteCodeTrace.trace (I)V
    DUP
    IFNONNULL L75
    POP
    LDC ""
    GOTO L76
   L75
    SIPUSH 272
    INVOKESTATIC com/saxonica/ee/bytecode/util/ByteCodeTrace.trace (I)V
    CHECKCAST net/sf/saxon/value/StringValue
    INVOKEVIRTUAL net/sf/saxon/value/StringValue.getStringValueCS ()Ljava/lang/CharSequence;
   L76
    SIPUSH 273
    INVOKESTATIC com/saxonica/ee/bytecode/util/ByteCodeTrace.trace (I)V
    INVOKEINTERFACE net/sf/saxon/regex/RegularExpression.analyze (Ljava/lang/CharSequence;)Lnet/sf/saxon/regex/RegexIterator;
    ASTORE 9
    ALOAD 1
    INVOKEINTERFACE net/sf/saxon/expr/XPathContext.newContext ()Lnet/sf/saxon/expr/XPathContextMajor;
    ASTORE 10
    ALOAD 10
    GETSTATIC EE__Slash_doc_81855459426.nAnalyzeString92 : Lnet/sf/saxon/expr/instruct/AnalyzeString;
    INVOKEVIRTUAL net/sf/saxon/expr/XPathContextMajor.setOrigin (Lnet/sf/saxon/expr/ContextOriginator;)V
    ALOAD 10
    NEW net/sf/saxon/om/FocusTrackingIterator
    DUP
    ALOAD 9
    INVOKESPECIAL net/sf/saxon/om/FocusTrackingIterator.<init> (Lnet/sf/saxon/om/SequenceIterator;)V
    DUP
    ASTORE 11
    INVOKEINTERFACE net/sf/saxon/expr/XPathContext.setCurrentIterator (Lnet/sf/saxon/om/FocusIterator;)V
    ALOAD 10
    ALOAD 9
    INVOKEVIRTUAL net/sf/saxon/expr/XPathContextMajor.setCurrentRegexIterator (Lnet/sf/saxon/regex/RegexIterator;)V
   L77
    SIPUSH 274
    INVOKESTATIC com/saxonica/ee/bytecode/util/ByteCodeTrace.trace (I)V
    ALOAD 11
    INVOKEINTERFACE net/sf/saxon/om/SequenceIterator.next ()Lnet/sf/saxon/om/Item;
    IFNULL L78
    ALOAD 9
    INVOKEINTERFACE net/sf/saxon/regex/RegexIterator.isMatching ()Z
    IFEQ L79
   L80
    LDC "SimpleNodeConstructorCompiler-Push"
    INVOKESTATIC com/saxonica/ee/bytecode/util/ByteCodeTrace.showMessage (Ljava/lang/String;)V
    ALOAD 2
   L81
    LDC "LiteralCompiler-Primitive"
    INVOKESTATIC com/saxonica/ee/bytecode/util/ByteCodeTrace.showMessage (Ljava/lang/String;)V
    LINENUMBER 20 L82
    LDC "*"
    GETSTATIC EE__Slash_doc_81855459426.nNestedLocation93 : Lnet/sf/saxon/expr/parser/XPathParser$NestedLocation;
    ICONST_4
    INVOKEINTERFACE net/sf/saxon/event/Receiver.characters (Ljava/lang/CharSequence;Lnet/sf/saxon/expr/parser/Location;I)V
    GOTO L77
   L79
    SIPUSH 275
    INVOKESTATIC com/saxonica/ee/bytecode/util/ByteCodeTrace.trace (I)V
   L83
    LDC "SimpleNodeConstructorCompiler-Push"
    INVOKESTATIC com/saxonica/ee/bytecode/util/ByteCodeTrace.showMessage (Ljava/lang/String;)V
    ALOAD 2
    LINENUMBER 23 L84
    ALOAD 10
    INVOKEINTERFACE net/sf/saxon/expr/XPathContext.getContextItem ()Lnet/sf/saxon/om/Item;
    CHECKCAST net/sf/saxon/value/StringValue
    INVOKEVIRTUAL net/sf/saxon/value/StringValue.getStringValueCS ()Ljava/lang/CharSequence;
    GETSTATIC EE__Slash_doc_81855459426.nNestedLocation94 : Lnet/sf/saxon/expr/parser/XPathParser$NestedLocation;
    ICONST_0
    INVOKEINTERFACE net/sf/saxon/event/Receiver.characters (Ljava/lang/CharSequence;Lnet/sf/saxon/expr/parser/Location;I)V
    GOTO L77
   L78
    SIPUSH 276
    INVOKESTATIC com/saxonica/ee/bytecode/util/ByteCodeTrace.trace (I)V
    ALOAD 2
    INVOKEINTERFACE net/sf/saxon/event/Receiver.endElement ()V
   L85
    LDC "FixedElement-E2"
    INVOKESTATIC com/saxonica/ee/bytecode/util/ByteCodeTrace.showMessage (Ljava/lang/String;)V
   L86
    LDC "ElementCreator-push"
    INVOKESTATIC com/saxonica/ee/bytecode/util/ByteCodeTrace.showMessage (Ljava/lang/String;)V
    LINENUMBER 30 L87
    ALOAD 2
    DUP
    LDC "Receiver: "
    SWAP
    DUP
    IFNULL L88
    INVOKEVIRTUAL java/lang/Object.toString ()Ljava/lang/String;
    INVOKESTATIC com/saxonica/ee/bytecode/util/ByteCodeTrace.showObjectVariable (Ljava/lang/String;Ljava/lang/String;)V
    GOTO L89
   L88
    SIPUSH 277
    INVOKESTATIC com/saxonica/ee/bytecode/util/ByteCodeTrace.trace (I)V
    POP
    LDC "null"
    INVOKESTATIC com/saxonica/ee/bytecode/util/ByteCodeTrace.showObjectVariable (Ljava/lang/String;Ljava/lang/String;)V
   L89
    SIPUSH 278
    INVOKESTATIC com/saxonica/ee/bytecode/util/ByteCodeTrace.trace (I)V
    INVOKEINTERFACE net/sf/saxon/event/Receiver.getSystemId ()Ljava/lang/String;
    IFNONNULL L90
    ALOAD 2
    LDC "file:/Users/mike/w3c/xslt30-test-B/tests/attr/avt/avt-0601.xsl"
    INVOKEINTERFACE net/sf/saxon/event/Receiver.setSystemId (Ljava/lang/String;)V
   L90
    SIPUSH 279
    INVOKESTATIC com/saxonica/ee/bytecode/util/ByteCodeTrace.trace (I)V
    ALOAD 2
    GETSTATIC EE__Slash_doc_81855459426.nNoNamespaceName95 : Lnet/sf/saxon/om/NoNamespaceName;
    GETSTATIC EE__Slash_doc_81855459426.nUntyped83 : Lnet/sf/saxon/type/Untyped;
    GETSTATIC EE__Slash_doc_81855459426.nNestedLocation96 : Lnet/sf/saxon/expr/parser/XPathParser$NestedLocation;
    ICONST_0
    INVOKEINTERFACE net/sf/saxon/event/Receiver.startElement (Lnet/sf/saxon/om/NodeName;Lnet/sf/saxon/type/SchemaType;Lnet/sf/saxon/expr/parser/Location;I)V
    GETSTATIC EE__Slash_doc_81855459426.nJavaPlatformPE86 : Lcom/saxonica/config/JavaPlatformPE;
   L91
    LDC "Concat-item"
    INVOKESTATIC com/saxonica/ee/bytecode/util/ByteCodeTrace.showMessage (Ljava/lang/String;)V
    NEW net/sf/saxon/tree/util/FastStringBuffer
    DUP
    BIPUSH 64
    INVOKESPECIAL net/sf/saxon/tree/util/FastStringBuffer.<init> (I)V
    ASTORE 4
    ALOAD 4
   L92
    LDC "LiteralCompiler-Primitive"
    INVOKESTATIC com/saxonica/ee/bytecode/util/ByteCodeTrace.showMessage (Ljava/lang/String;)V
    LDC "("
    INVOKEVIRTUAL net/sf/saxon/tree/util/FastStringBuffer.append (Ljava/lang/CharSequence;)V
    ALOAD 4
   L93
    LDC "StringJoin-Item"
    INVOKESTATIC com/saxonica/ee/bytecode/util/ByteCodeTrace.showMessage (Ljava/lang/String;)V
   L94
    LDC "AtomicSequenceConverterCompiler-Itr"
    INVOKESTATIC com/saxonica/ee/bytecode/util/ByteCodeTrace.showMessage (Ljava/lang/String;)V
   L95
    LDC "AtomicSequenceConverterCompiler-string"
    INVOKESTATIC com/saxonica/ee/bytecode/util/ByteCodeTrace.showMessage (Ljava/lang/String;)V
    NEW net/sf/saxon/expr/ItemMappingIterator
    DUP
   L96
    LDC "AtomizerCompiler-Itr"
    INVOKESTATIC com/saxonica/ee/bytecode/util/ByteCodeTrace.showMessage (Ljava/lang/String;)V
   L97
    LDC "AxisExpressionCompiler - iterate"
    INVOKESTATIC com/saxonica/ee/bytecode/util/ByteCodeTrace.showMessage (Ljava/lang/String;)V
    ALOAD 1
    INVOKEINTERFACE net/sf/saxon/expr/XPathContext.getContextItem ()Lnet/sf/saxon/om/Item;
    CHECKCAST net/sf/saxon/om/NodeInfo
   L98
    LDC "AxisExpressionCompiler - static method: iterate"
    INVOKESTATIC com/saxonica/ee/bytecode/util/ByteCodeTrace.showMessage (Ljava/lang/String;)V
    ICONST_3
    GETSTATIC EE__Slash_doc_81855459426.nNameTest87 : Lnet/sf/saxon/pattern/NameTest;
    LDC "calling iterateAxis"
    INVOKESTATIC com/saxonica/ee/bytecode/util/ByteCodeTrace.showMessage (Ljava/lang/String;)V
    INVOKEINTERFACE net/sf/saxon/om/NodeInfo.iterateAxis (BLnet/sf/saxon/pattern/NodeTest;)Lnet/sf/saxon/tree/iter/AxisIterator;
    LDC "returning axis iterator"
    INVOKESTATIC com/saxonica/ee/bytecode/util/ByteCodeTrace.showMessage (Ljava/lang/String;)V
    ICONST_1
    INVOKESTATIC net/sf/saxon/expr/Atomizer.getAtomizingIterator (Lnet/sf/saxon/om/SequenceIterator;Z)Lnet/sf/saxon/om/SequenceIterator;
    GETSTATIC net/sf/saxon/expr/AtomicSequenceConverter.TO_STRING_MAPPER : Lnet/sf/saxon/expr/AtomicSequenceConverter$ToStringMappingFunction;
    ICONST_1
    INVOKESPECIAL net/sf/saxon/expr/ItemMappingIterator.<init> (Lnet/sf/saxon/om/SequenceIterator;Lnet/sf/saxon/expr/ItemMappingFunction;Z)V
   L99
    LDC "StringJoin-Item-1"
    INVOKESTATIC com/saxonica/ee/bytecode/util/ByteCodeTrace.showMessage (Ljava/lang/String;)V
    ASTORE 5
    ALOAD 5
    INVOKEINTERFACE net/sf/saxon/om/SequenceIterator.next ()Lnet/sf/saxon/om/Item;
    DUP
    IFNONNULL L100
    POP
    LDC ""
    GOTO L101
   L100
    SIPUSH 280
    INVOKESTATIC com/saxonica/ee/bytecode/util/ByteCodeTrace.trace (I)V
    INVOKEINTERFACE net/sf/saxon/om/Item.getStringValueCS ()Ljava/lang/CharSequence;
    ASTORE 8
    ALOAD 5
    INVOKEINTERFACE net/sf/saxon/om/SequenceIterator.next ()Lnet/sf/saxon/om/Item;
    DUP
    IFNONNULL L102
    POP
    ALOAD 8
    GOTO L101
   L102
    SIPUSH 281
    INVOKESTATIC com/saxonica/ee/bytecode/util/ByteCodeTrace.trace (I)V
    NEW net/sf/saxon/tree/util/FastStringBuffer
    DUP
    BIPUSH 64
    INVOKESPECIAL net/sf/saxon/tree/util/FastStringBuffer.<init> (I)V
    ASTORE 7
    ALOAD 7
    ALOAD 8
    INVOKEVIRTUAL net/sf/saxon/tree/util/FastStringBuffer.append (Ljava/lang/CharSequence;)V
   L103
    LDC "LiteralCompiler-Primitive"
    INVOKESTATIC com/saxonica/ee/bytecode/util/ByteCodeTrace.showMessage (Ljava/lang/String;)V
    LDC " "
    ASTORE 12
    ALOAD 7
    ALOAD 12
    INVOKEVIRTUAL net/sf/saxon/tree/util/FastStringBuffer.append (Ljava/lang/CharSequence;)V
    ALOAD 7
    SWAP
    INVOKEINTERFACE net/sf/saxon/om/Item.getStringValueCS ()Ljava/lang/CharSequence;
    INVOKEVIRTUAL net/sf/saxon/tree/util/FastStringBuffer.append (Ljava/lang/CharSequence;)V
   L104
    SIPUSH 282
    INVOKESTATIC com/saxonica/ee/bytecode/util/ByteCodeTrace.trace (I)V
    ALOAD 5
    INVOKEINTERFACE net/sf/saxon/om/SequenceIterator.next ()Lnet/sf/saxon/om/Item;
    DUP
    IFNULL L105
    ALOAD 7
    ALOAD 12
    INVOKEVIRTUAL net/sf/saxon/tree/util/FastStringBuffer.append (Ljava/lang/CharSequence;)V
    ALOAD 7
    SWAP
    INVOKEINTERFACE net/sf/saxon/om/Item.getStringValueCS ()Ljava/lang/CharSequence;
    INVOKEVIRTUAL net/sf/saxon/tree/util/FastStringBuffer.append (Ljava/lang/CharSequence;)V
    GOTO L104
   L105
    SIPUSH 283
    INVOKESTATIC com/saxonica/ee/bytecode/util/ByteCodeTrace.trace (I)V
    POP
    ALOAD 7
    INVOKEVIRTUAL net/sf/saxon/tree/util/FastStringBuffer.condense ()Ljava/lang/CharSequence;
   L101
    SIPUSH 284
    INVOKESTATIC com/saxonica/ee/bytecode/util/ByteCodeTrace.trace (I)V
    INVOKEVIRTUAL net/sf/saxon/tree/util/FastStringBuffer.append (Ljava/lang/CharSequence;)V
    ALOAD 4
   L106
    LDC "LiteralCompiler-Primitive"
    INVOKESTATIC com/saxonica/ee/bytecode/util/ByteCodeTrace.showMessage (Ljava/lang/String;)V
    LDC ")(.*) (krahen)"
    INVOKEVIRTUAL net/sf/saxon/tree/util/FastStringBuffer.append (Ljava/lang/CharSequence;)V
    ALOAD 4
    INVOKEVIRTUAL net/sf/saxon/tree/util/FastStringBuffer.condense ()Ljava/lang/CharSequence;
   L107
    LDC "Concat-item"
    INVOKESTATIC com/saxonica/ee/bytecode/util/ByteCodeTrace.showMessage (Ljava/lang/String;)V
    NEW net/sf/saxon/tree/util/FastStringBuffer
    DUP
    BIPUSH 64
    INVOKESPECIAL net/sf/saxon/tree/util/FastStringBuffer.<init> (I)V
    ASTORE 4
    ALOAD 4
   L108
    LDC "LiteralCompiler-Primitive"
    INVOKESTATIC com/saxonica/ee/bytecode/util/ByteCodeTrace.showMessage (Ljava/lang/String;)V
    LDC "ss"
    INVOKEVIRTUAL net/sf/saxon/tree/util/FastStringBuffer.append (Ljava/lang/CharSequence;)V
    ALOAD 4
   L109
    LDC "StringFn-str"
    INVOKESTATIC com/saxonica/ee/bytecode/util/ByteCodeTrace.showMessage (Ljava/lang/String;)V
    TRYCATCHBLOCK L110 L111 L112 java/lang/UnsupportedOperationException
   L110
    SIPUSH 285
    INVOKESTATIC com/saxonica/ee/bytecode/util/ByteCodeTrace.trace (I)V
   L113
    LDC "AtomicSequenceConverterCompiler-Item"
    INVOKESTATIC com/saxonica/ee/bytecode/util/ByteCodeTrace.showMessage (Ljava/lang/String;)V
   L114
    LDC "AtomizerCompiler-Item"
    INVOKESTATIC com/saxonica/ee/bytecode/util/ByteCodeTrace.showMessage (Ljava/lang/String;)V
   L115
    LDC "FirstItemExpression"
    INVOKESTATIC com/saxonica/ee/bytecode/util/ByteCodeTrace.showMessage (Ljava/lang/String;)V
   L116
    LDC "AxisExpressionCompiler - iterate"
    INVOKESTATIC com/saxonica/ee/bytecode/util/ByteCodeTrace.showMessage (Ljava/lang/String;)V
    ALOAD 1
    INVOKEINTERFACE net/sf/saxon/expr/XPathContext.getContextItem ()Lnet/sf/saxon/om/Item;
    CHECKCAST net/sf/saxon/om/NodeInfo
   L117
    LDC "AxisExpressionCompiler - static method: iterate"
    INVOKESTATIC com/saxonica/ee/bytecode/util/ByteCodeTrace.showMessage (Ljava/lang/String;)V
    ICONST_3
    GETSTATIC EE__Slash_doc_81855459426.nNameTest88 : Lnet/sf/saxon/pattern/NameTest;
    LDC "calling iterateAxis"
    INVOKESTATIC com/saxonica/ee/bytecode/util/ByteCodeTrace.showMessage (Ljava/lang/String;)V
    INVOKEINTERFACE net/sf/saxon/om/NodeInfo.iterateAxis (BLnet/sf/saxon/pattern/NodeTest;)Lnet/sf/saxon/tree/iter/AxisIterator;
    LDC "returning axis iterator"
    INVOKESTATIC com/saxonica/ee/bytecode/util/ByteCodeTrace.showMessage (Ljava/lang/String;)V
    DUP
    INVOKEINTERFACE net/sf/saxon/om/SequenceIterator.next ()Lnet/sf/saxon/om/Item;
    SWAP
    INVOKEINTERFACE net/sf/saxon/om/SequenceIterator.close ()V
    DUP
    IFNULL L118
    INVOKEINTERFACE net/sf/saxon/om/Item.atomize ()Lnet/sf/saxon/om/AtomicSequence;
    INVOKEINTERFACE net/sf/saxon/om/AtomicSequence.head ()Lnet/sf/saxon/value/AtomicValue;
   L118
    SIPUSH 286
    INVOKESTATIC com/saxonica/ee/bytecode/util/ByteCodeTrace.trace (I)V
   L119
    LDC "AtomicSequenceConverterCompiler-Item-Returned"
    INVOKESTATIC com/saxonica/ee/bytecode/util/ByteCodeTrace.showMessage (Ljava/lang/String;)V
    DUP
    IFNONNULL L120
    POP
    ACONST_NULL
    GOTO L121
   L120
    SIPUSH 287
    INVOKESTATIC com/saxonica/ee/bytecode/util/ByteCodeTrace.trace (I)V
    INVOKEINTERFACE net/sf/saxon/om/Item.getStringValueCS ()Ljava/lang/CharSequence;
    INVOKESTATIC net/sf/saxon/value/StringValue.makeStringValue (Ljava/lang/CharSequence;)Lnet/sf/saxon/value/StringValue;
   L121
    SIPUSH 288
    INVOKESTATIC com/saxonica/ee/bytecode/util/ByteCodeTrace.trace (I)V
    DUP
    IFNONNULL L122
    POP
    LDC ""
    GOTO L123
   L122
    SIPUSH 289
    INVOKESTATIC com/saxonica/ee/bytecode/util/ByteCodeTrace.trace (I)V
    INVOKEINTERFACE net/sf/saxon/om/Item.getStringValueCS ()Ljava/lang/CharSequence;
   L123
    SIPUSH 290
    INVOKESTATIC com/saxonica/ee/bytecode/util/ByteCodeTrace.trace (I)V
   L111
    SIPUSH 291
    INVOKESTATIC com/saxonica/ee/bytecode/util/ByteCodeTrace.trace (I)V
    GOTO L124
   L112
    SIPUSH 292
    INVOKESTATIC com/saxonica/ee/bytecode/util/ByteCodeTrace.trace (I)V
   L125
    LDC "CatchStringFn"
    INVOKESTATIC com/saxonica/ee/bytecode/util/ByteCodeTrace.showMessage (Ljava/lang/String;)V
    INVOKEVIRTUAL java/lang/UnsupportedOperationException.getMessage ()Ljava/lang/String;
    LDC "FOTY0014"
    LDC "file:/Users/mike/w3c/xslt30-test-B/tests/attr/avt/avt-0601.xsl"
    BIPUSH 30
    ICONST_0
    INVOKESTATIC com/saxonica/ee/bytecode/util/Callback.makeXPathException (Ljava/lang/String;Ljava/lang/String;Ljava/lang/String;IZ)Lnet/sf/saxon/trans/XPathException;
    ATHROW
   L124
    SIPUSH 293
    INVOKESTATIC com/saxonica/ee/bytecode/util/ByteCodeTrace.trace (I)V
    INVOKEVIRTUAL net/sf/saxon/tree/util/FastStringBuffer.append (Ljava/lang/CharSequence;)V
    ALOAD 4
   L126
    LDC "LiteralCompiler-Primitive"
    INVOKESTATIC com/saxonica/ee/bytecode/util/ByteCodeTrace.showMessage (Ljava/lang/String;)V
    LDC "i"
    INVOKEVIRTUAL net/sf/saxon/tree/util/FastStringBuffer.append (Ljava/lang/CharSequence;)V
    ALOAD 4
   L127
    LDC "StringFn-str"
    INVOKESTATIC com/saxonica/ee/bytecode/util/ByteCodeTrace.showMessage (Ljava/lang/String;)V
    TRYCATCHBLOCK L128 L129 L130 java/lang/UnsupportedOperationException
   L128
    SIPUSH 294
    INVOKESTATIC com/saxonica/ee/bytecode/util/ByteCodeTrace.trace (I)V
   L131
    LDC "AtomicSequenceConverterCompiler-Item"
    INVOKESTATIC com/saxonica/ee/bytecode/util/ByteCodeTrace.showMessage (Ljava/lang/String;)V
   L132
    LDC "AtomizerCompiler-Item"
    INVOKESTATIC com/saxonica/ee/bytecode/util/ByteCodeTrace.showMessage (Ljava/lang/String;)V
   L133
    LDC "itemAt"
    INVOKESTATIC com/saxonica/ee/bytecode/util/ByteCodeTrace.showMessage (Ljava/lang/String;)V
   L134
    LDC "AxisExpressionCompiler - iterate"
    INVOKESTATIC com/saxonica/ee/bytecode/util/ByteCodeTrace.showMessage (Ljava/lang/String;)V
    ALOAD 1
    INVOKEINTERFACE net/sf/saxon/expr/XPathContext.getContextItem ()Lnet/sf/saxon/om/Item;
    CHECKCAST net/sf/saxon/om/NodeInfo
   L135
    LDC "AxisExpressionCompiler - static method: iterate"
    INVOKESTATIC com/saxonica/ee/bytecode/util/ByteCodeTrace.showMessage (Ljava/lang/String;)V
    ICONST_3
    GETSTATIC EE__Slash_doc_81855459426.nNameTest88 : Lnet/sf/saxon/pattern/NameTest;
    LDC "calling iterateAxis"
    INVOKESTATIC com/saxonica/ee/bytecode/util/ByteCodeTrace.showMessage (Ljava/lang/String;)V
    INVOKEINTERFACE net/sf/saxon/om/NodeInfo.iterateAxis (BLnet/sf/saxon/pattern/NodeTest;)Lnet/sf/saxon/tree/iter/AxisIterator;
    LDC "returning axis iterator"
    INVOKESTATIC com/saxonica/ee/bytecode/util/ByteCodeTrace.showMessage (Ljava/lang/String;)V
    DUP
    INSTANCEOF net/sf/saxon/value/MemoClosure$ProgressiveIterator
    IFNE L136
    DUP
    INVOKEINTERFACE net/sf/saxon/om/SequenceIterator.getProperties ()I
    ICONST_1
    IAND
    IFNE L137
    ICONST_2
    INVOKESTATIC net/sf/saxon/expr/TailIterator.make (Lnet/sf/saxon/om/SequenceIterator;I)Lnet/sf/saxon/om/SequenceIterator;
    DUP
    INVOKEINTERFACE net/sf/saxon/om/SequenceIterator.next ()Lnet/sf/saxon/om/Item;
    SWAP
    INVOKEINTERFACE net/sf/saxon/om/SequenceIterator.close ()V
    GOTO L138
   L136
    SIPUSH 295
    INVOKESTATIC com/saxonica/ee/bytecode/util/ByteCodeTrace.trace (I)V
    CHECKCAST net/sf/saxon/value/MemoClosure$ProgressiveIterator
    INVOKEVIRTUAL net/sf/saxon/value/MemoClosure$ProgressiveIterator.getMemoClosure ()Lnet/sf/saxon/value/MemoClosure;
    ICONST_1
    INVOKEVIRTUAL net/sf/saxon/value/MemoClosure.itemAt (I)Lnet/sf/saxon/om/Item;
    GOTO L138
   L137
    SIPUSH 296
    INVOKESTATIC com/saxonica/ee/bytecode/util/ByteCodeTrace.trace (I)V
    CHECKCAST net/sf/saxon/tree/iter/GroundedIterator
    INVOKEINTERFACE net/sf/saxon/tree/iter/GroundedIterator.materialize ()Lnet/sf/saxon/om/GroundedValue;
    ICONST_1
    INVOKEINTERFACE net/sf/saxon/om/GroundedValue.itemAt (I)Lnet/sf/saxon/om/Item;
   L138
    SIPUSH 297
    INVOKESTATIC com/saxonica/ee/bytecode/util/ByteCodeTrace.trace (I)V
    DUP
    IFNULL L139
    INVOKEINTERFACE net/sf/saxon/om/Item.atomize ()Lnet/sf/saxon/om/AtomicSequence;
    INVOKEINTERFACE net/sf/saxon/om/AtomicSequence.head ()Lnet/sf/saxon/value/AtomicValue;
   L139
    SIPUSH 298
    INVOKESTATIC com/saxonica/ee/bytecode/util/ByteCodeTrace.trace (I)V
   L140
    LDC "AtomicSequenceConverterCompiler-Item-Returned"
    INVOKESTATIC com/saxonica/ee/bytecode/util/ByteCodeTrace.showMessage (Ljava/lang/String;)V
    DUP
    IFNONNULL L141
    POP
    ACONST_NULL
    GOTO L142
   L141
    SIPUSH 299
    INVOKESTATIC com/saxonica/ee/bytecode/util/ByteCodeTrace.trace (I)V
    INVOKEINTERFACE net/sf/saxon/om/Item.getStringValueCS ()Ljava/lang/CharSequence;
    INVOKESTATIC net/sf/saxon/value/StringValue.makeStringValue (Ljava/lang/CharSequence;)Lnet/sf/saxon/value/StringValue;
   L142
    SIPUSH 300
    INVOKESTATIC com/saxonica/ee/bytecode/util/ByteCodeTrace.trace (I)V
    DUP
    IFNONNULL L143
    POP
    LDC ""
    GOTO L144
   L143
    SIPUSH 301
    INVOKESTATIC com/saxonica/ee/bytecode/util/ByteCodeTrace.trace (I)V
    INVOKEINTERFACE net/sf/saxon/om/Item.getStringValueCS ()Ljava/lang/CharSequence;
   L144
    SIPUSH 302
    INVOKESTATIC com/saxonica/ee/bytecode/util/ByteCodeTrace.trace (I)V
   L129
    SIPUSH 303
    INVOKESTATIC com/saxonica/ee/bytecode/util/ByteCodeTrace.trace (I)V
    GOTO L145
   L130
    SIPUSH 304
    INVOKESTATIC com/saxonica/ee/bytecode/util/ByteCodeTrace.trace (I)V
   L146
    LDC "CatchStringFn"
    INVOKESTATIC com/saxonica/ee/bytecode/util/ByteCodeTrace.showMessage (Ljava/lang/String;)V
    INVOKEVIRTUAL java/lang/UnsupportedOperationException.getMessage ()Ljava/lang/String;
    LDC "FOTY0014"
    LDC "file:/Users/mike/w3c/xslt30-test-B/tests/attr/avt/avt-0601.xsl"
    BIPUSH 30
    ICONST_0
    INVOKESTATIC com/saxonica/ee/bytecode/util/Callback.makeXPathException (Ljava/lang/String;Ljava/lang/String;Ljava/lang/String;IZ)Lnet/sf/saxon/trans/XPathException;
    ATHROW
   L145
    SIPUSH 305
    INVOKESTATIC com/saxonica/ee/bytecode/util/ByteCodeTrace.trace (I)V
    INVOKEVIRTUAL net/sf/saxon/tree/util/FastStringBuffer.append (Ljava/lang/CharSequence;)V
    ALOAD 4
   L147
    LDC "LiteralCompiler-Primitive"
    INVOKESTATIC com/saxonica/ee/bytecode/util/ByteCodeTrace.showMessage (Ljava/lang/String;)V
    LDC "xxm"
    INVOKEVIRTUAL net/sf/saxon/tree/util/FastStringBuffer.append (Ljava/lang/CharSequence;)V
    ALOAD 4
    INVOKEVIRTUAL net/sf/saxon/tree/util/FastStringBuffer.condense ()Ljava/lang/CharSequence;
    INVOKEVIRTUAL java/lang/Object.toString ()Ljava/lang/String;
    LDC "XP30"
    ACONST_NULL
    INVOKEINTERFACE net/sf/saxon/Platform.compileRegularExpression (Ljava/lang/CharSequence;Ljava/lang/String;Ljava/lang/String;Ljava/util/List;)Lnet/sf/saxon/regex/RegularExpression;
    DUP
    LDC ""
    INVOKEINTERFACE net/sf/saxon/regex/RegularExpression.matches (Ljava/lang/CharSequence;)Z
    IFEQ L148
    LDC "The regular expression must not be one that matches a zero-length string"
    LDC "XTDE1150"
    LDC "file:/Users/mike/w3c/xslt30-test-B/tests/attr/avt/avt-0601.xsl"
    BIPUSH 30
    ICONST_0
    INVOKESTATIC com/saxonica/ee/bytecode/util/Callback.makeXPathException (Ljava/lang/String;Ljava/lang/String;Ljava/lang/String;IZ)Lnet/sf/saxon/trans/XPathException;
    ATHROW
   L148
    SIPUSH 306
    INVOKESTATIC com/saxonica/ee/bytecode/util/ByteCodeTrace.trace (I)V
   L149
    LDC "CardinalityCheckerCompiler-Item"
    INVOKESTATIC com/saxonica/ee/bytecode/util/ByteCodeTrace.showMessage (Ljava/lang/String;)V
   L150
    LDC "AtomicSequenceConverterCompiler-Itr"
    INVOKESTATIC com/saxonica/ee/bytecode/util/ByteCodeTrace.showMessage (Ljava/lang/String;)V
   L151
    LDC "AtomicSequenceConverterCompiler-1"
    INVOKESTATIC com/saxonica/ee/bytecode/util/ByteCodeTrace.showMessage (Ljava/lang/String;)V
    NEW net/sf/saxon/expr/ItemMappingIterator
    DUP
   L152
    LDC "AtomizerCompiler-Itr"
    INVOKESTATIC com/saxonica/ee/bytecode/util/ByteCodeTrace.showMessage (Ljava/lang/String;)V
   L153
    LDC "AxisExpressionCompiler - iterate"
    INVOKESTATIC com/saxonica/ee/bytecode/util/ByteCodeTrace.showMessage (Ljava/lang/String;)V
    ALOAD 1
    INVOKEINTERFACE net/sf/saxon/expr/XPathContext.getContextItem ()Lnet/sf/saxon/om/Item;
    CHECKCAST net/sf/saxon/om/NodeInfo
   L154
    LDC "AxisExpressionCompiler - static method: iterate"
    INVOKESTATIC com/saxonica/ee/bytecode/util/ByteCodeTrace.showMessage (Ljava/lang/String;)V
    ICONST_3
    GETSTATIC EE__Slash_doc_81855459426.nNameTest89 : Lnet/sf/saxon/pattern/NameTest;
    LDC "calling iterateAxis"
    INVOKESTATIC com/saxonica/ee/bytecode/util/ByteCodeTrace.showMessage (Ljava/lang/String;)V
    INVOKEINTERFACE net/sf/saxon/om/NodeInfo.iterateAxis (BLnet/sf/saxon/pattern/NodeTest;)Lnet/sf/saxon/tree/iter/AxisIterator;
    LDC "returning axis iterator"
    INVOKESTATIC com/saxonica/ee/bytecode/util/ByteCodeTrace.showMessage (Ljava/lang/String;)V
    ICONST_1
    INVOKESTATIC net/sf/saxon/expr/Atomizer.getAtomizingIterator (Lnet/sf/saxon/om/SequenceIterator;Z)Lnet/sf/saxon/om/SequenceIterator;
    GETSTATIC EE__Slash_doc_81855459426.nAtomicSequenceMappingFunction97 : Lnet/sf/saxon/expr/AtomicSequenceConverter$AtomicSequenceMappingFunction;
    ICONST_1
    INVOKESPECIAL net/sf/saxon/expr/ItemMappingIterator.<init> (Lnet/sf/saxon/om/SequenceIterator;Lnet/sf/saxon/expr/ItemMappingFunction;Z)V
    CHECKCAST net/sf/saxon/om/SequenceIterator
    DUP
    INVOKEINTERFACE net/sf/saxon/om/SequenceIterator.next ()Lnet/sf/saxon/om/Item;
    SWAP
    INVOKEINTERFACE net/sf/saxon/om/SequenceIterator.next ()Lnet/sf/saxon/om/Item;
    IFNULL L155
    GETSTATIC EE__Slash_doc_81855459426.nCardinalityChecker98 : Lnet/sf/saxon/expr/CardinalityChecker;
    ALOAD 1
    INVOKESTATIC com/saxonica/ee/bytecode/util/Callback.makeMultipleItemsException (Lnet/sf/saxon/expr/CardinalityChecker;Lnet/sf/saxon/expr/XPathContext;)Lnet/sf/saxon/trans/XPathException;
    ATHROW
   L155
    SIPUSH 307
    INVOKESTATIC com/saxonica/ee/bytecode/util/ByteCodeTrace.trace (I)V
    DUP
    IFNONNULL L156
    POP
    LDC ""
    GOTO L157
   L156
    SIPUSH 308
    INVOKESTATIC com/saxonica/ee/bytecode/util/ByteCodeTrace.trace (I)V
    CHECKCAST net/sf/saxon/value/StringValue
    INVOKEVIRTUAL net/sf/saxon/value/StringValue.getStringValueCS ()Ljava/lang/CharSequence;
   L157
    SIPUSH 309
    INVOKESTATIC com/saxonica/ee/bytecode/util/ByteCodeTrace.trace (I)V
    INVOKEINTERFACE net/sf/saxon/regex/RegularExpression.analyze (Ljava/lang/CharSequence;)Lnet/sf/saxon/regex/RegexIterator;
    ASTORE 13
    ALOAD 1
    INVOKEINTERFACE net/sf/saxon/expr/XPathContext.newContext ()Lnet/sf/saxon/expr/XPathContextMajor;
    ASTORE 14
    ALOAD 14
    GETSTATIC EE__Slash_doc_81855459426.nAnalyzeString99 : Lnet/sf/saxon/expr/instruct/AnalyzeString;
    INVOKEVIRTUAL net/sf/saxon/expr/XPathContextMajor.setOrigin (Lnet/sf/saxon/expr/ContextOriginator;)V
    ALOAD 14
    NEW net/sf/saxon/om/FocusTrackingIterator
    DUP
    ALOAD 13
    INVOKESPECIAL net/sf/saxon/om/FocusTrackingIterator.<init> (Lnet/sf/saxon/om/SequenceIterator;)V
    DUP
    ASTORE 15
    INVOKEINTERFACE net/sf/saxon/expr/XPathContext.setCurrentIterator (Lnet/sf/saxon/om/FocusIterator;)V
    ALOAD 14
    ALOAD 13
    INVOKEVIRTUAL net/sf/saxon/expr/XPathContextMajor.setCurrentRegexIterator (Lnet/sf/saxon/regex/RegexIterator;)V
   L158
    SIPUSH 310
    INVOKESTATIC com/saxonica/ee/bytecode/util/ByteCodeTrace.trace (I)V
    ALOAD 15
    INVOKEINTERFACE net/sf/saxon/om/SequenceIterator.next ()Lnet/sf/saxon/om/Item;
    IFNULL L159
    ALOAD 13
    INVOKEINTERFACE net/sf/saxon/regex/RegexIterator.isMatching ()Z
    IFEQ L160
   L161
    LDC "SimpleNodeConstructorCompiler-Push"
    INVOKESTATIC com/saxonica/ee/bytecode/util/ByteCodeTrace.showMessage (Ljava/lang/String;)V
    ALOAD 2
   L162
    LDC "LiteralCompiler-Primitive"
    INVOKESTATIC com/saxonica/ee/bytecode/util/ByteCodeTrace.showMessage (Ljava/lang/String;)V
    LINENUMBER 32 L163
    LDC "*"
    GETSTATIC EE__Slash_doc_81855459426.nNestedLocation100 : Lnet/sf/saxon/expr/parser/XPathParser$NestedLocation;
    ICONST_4
    INVOKEINTERFACE net/sf/saxon/event/Receiver.characters (Ljava/lang/CharSequence;Lnet/sf/saxon/expr/parser/Location;I)V
    GOTO L158
   L160
    SIPUSH 311
    INVOKESTATIC com/saxonica/ee/bytecode/util/ByteCodeTrace.trace (I)V
   L164
    LDC "SimpleNodeConstructorCompiler-Push"
    INVOKESTATIC com/saxonica/ee/bytecode/util/ByteCodeTrace.showMessage (Ljava/lang/String;)V
    ALOAD 2
    LINENUMBER 35 L165
    ALOAD 14
    INVOKEINTERFACE net/sf/saxon/expr/XPathContext.getContextItem ()Lnet/sf/saxon/om/Item;
    CHECKCAST net/sf/saxon/value/StringValue
    INVOKEVIRTUAL net/sf/saxon/value/StringValue.getStringValueCS ()Ljava/lang/CharSequence;
    GETSTATIC EE__Slash_doc_81855459426.nNestedLocation101 : Lnet/sf/saxon/expr/parser/XPathParser$NestedLocation;
    ICONST_0
    INVOKEINTERFACE net/sf/saxon/event/Receiver.characters (Ljava/lang/CharSequence;Lnet/sf/saxon/expr/parser/Location;I)V
    GOTO L158
   L159
    SIPUSH 312
    INVOKESTATIC com/saxonica/ee/bytecode/util/ByteCodeTrace.trace (I)V
    ALOAD 2
    INVOKEINTERFACE net/sf/saxon/event/Receiver.endElement ()V
   L166
    LDC "FixedElement-E3"
    INVOKESTATIC com/saxonica/ee/bytecode/util/ByteCodeTrace.showMessage (Ljava/lang/String;)V
   L167
    LDC "ElementCreator-push"
    INVOKESTATIC com/saxonica/ee/bytecode/util/ByteCodeTrace.showMessage (Ljava/lang/String;)V
    LINENUMBER 42 L168
    ALOAD 2
    DUP
    LDC "Receiver: "
    SWAP
    DUP
    IFNULL L169
    INVOKEVIRTUAL java/lang/Object.toString ()Ljava/lang/String;
    INVOKESTATIC com/saxonica/ee/bytecode/util/ByteCodeTrace.showObjectVariable (Ljava/lang/String;Ljava/lang/String;)V
    GOTO L170
   L169
    SIPUSH 313
    INVOKESTATIC com/saxonica/ee/bytecode/util/ByteCodeTrace.trace (I)V
    POP
    LDC "null"
    INVOKESTATIC com/saxonica/ee/bytecode/util/ByteCodeTrace.showObjectVariable (Ljava/lang/String;Ljava/lang/String;)V
   L170
    SIPUSH 314
    INVOKESTATIC com/saxonica/ee/bytecode/util/ByteCodeTrace.trace (I)V
    INVOKEINTERFACE net/sf/saxon/event/Receiver.getSystemId ()Ljava/lang/String;
    IFNONNULL L171
    ALOAD 2
    LDC "file:/Users/mike/w3c/xslt30-test-B/tests/attr/avt/avt-0601.xsl"
    INVOKEINTERFACE net/sf/saxon/event/Receiver.setSystemId (Ljava/lang/String;)V
   L171
    SIPUSH 315
    INVOKESTATIC com/saxonica/ee/bytecode/util/ByteCodeTrace.trace (I)V
    ALOAD 2
    GETSTATIC EE__Slash_doc_81855459426.nNoNamespaceName102 : Lnet/sf/saxon/om/NoNamespaceName;
    GETSTATIC EE__Slash_doc_81855459426.nUntyped83 : Lnet/sf/saxon/type/Untyped;
    GETSTATIC EE__Slash_doc_81855459426.nNestedLocation103 : Lnet/sf/saxon/expr/parser/XPathParser$NestedLocation;
    ICONST_0
    INVOKEINTERFACE net/sf/saxon/event/Receiver.startElement (Lnet/sf/saxon/om/NodeName;Lnet/sf/saxon/type/SchemaType;Lnet/sf/saxon/expr/parser/Location;I)V
    GETSTATIC EE__Slash_doc_81855459426.nJavaPlatformPE86 : Lcom/saxonica/config/JavaPlatformPE;
   L172
    LDC "Concat-item"
    INVOKESTATIC com/saxonica/ee/bytecode/util/ByteCodeTrace.showMessage (Ljava/lang/String;)V
    NEW net/sf/saxon/tree/util/FastStringBuffer
    DUP
    BIPUSH 64
    INVOKESPECIAL net/sf/saxon/tree/util/FastStringBuffer.<init> (I)V
    ASTORE 4
    ALOAD 4
   L173
    LDC "LiteralCompiler-Primitive"
    INVOKESTATIC com/saxonica/ee/bytecode/util/ByteCodeTrace.showMessage (Ljava/lang/String;)V
    LDC "("
    INVOKEVIRTUAL net/sf/saxon/tree/util/FastStringBuffer.append (Ljava/lang/CharSequence;)V
    ALOAD 4
   L174
    LDC "StringJoin-Item"
    INVOKESTATIC com/saxonica/ee/bytecode/util/ByteCodeTrace.showMessage (Ljava/lang/String;)V
   L175
    LDC "AtomicSequenceConverterCompiler-Itr"
    INVOKESTATIC com/saxonica/ee/bytecode/util/ByteCodeTrace.showMessage (Ljava/lang/String;)V
   L176
    LDC "AtomicSequenceConverterCompiler-string"
    INVOKESTATIC com/saxonica/ee/bytecode/util/ByteCodeTrace.showMessage (Ljava/lang/String;)V
    NEW net/sf/saxon/expr/ItemMappingIterator
    DUP
   L177
    LDC "AtomizerCompiler-Itr"
    INVOKESTATIC com/saxonica/ee/bytecode/util/ByteCodeTrace.showMessage (Ljava/lang/String;)V
   L178
    LDC "AxisExpressionCompiler - iterate"
    INVOKESTATIC com/saxonica/ee/bytecode/util/ByteCodeTrace.showMessage (Ljava/lang/String;)V
    ALOAD 1
    INVOKEINTERFACE net/sf/saxon/expr/XPathContext.getContextItem ()Lnet/sf/saxon/om/Item;
    CHECKCAST net/sf/saxon/om/NodeInfo
   L179
    LDC "AxisExpressionCompiler - static method: iterate"
    INVOKESTATIC com/saxonica/ee/bytecode/util/ByteCodeTrace.showMessage (Ljava/lang/String;)V
    ICONST_3
    GETSTATIC EE__Slash_doc_81855459426.nNameTest87 : Lnet/sf/saxon/pattern/NameTest;
    LDC "calling iterateAxis"
    INVOKESTATIC com/saxonica/ee/bytecode/util/ByteCodeTrace.showMessage (Ljava/lang/String;)V
    INVOKEINTERFACE net/sf/saxon/om/NodeInfo.iterateAxis (BLnet/sf/saxon/pattern/NodeTest;)Lnet/sf/saxon/tree/iter/AxisIterator;
    LDC "returning axis iterator"
    INVOKESTATIC com/saxonica/ee/bytecode/util/ByteCodeTrace.showMessage (Ljava/lang/String;)V
    ICONST_1
    INVOKESTATIC net/sf/saxon/expr/Atomizer.getAtomizingIterator (Lnet/sf/saxon/om/SequenceIterator;Z)Lnet/sf/saxon/om/SequenceIterator;
    GETSTATIC net/sf/saxon/expr/AtomicSequenceConverter.TO_STRING_MAPPER : Lnet/sf/saxon/expr/AtomicSequenceConverter$ToStringMappingFunction;
    ICONST_1
    INVOKESPECIAL net/sf/saxon/expr/ItemMappingIterator.<init> (Lnet/sf/saxon/om/SequenceIterator;Lnet/sf/saxon/expr/ItemMappingFunction;Z)V
   L180
    LDC "StringJoin-Item-1"
    INVOKESTATIC com/saxonica/ee/bytecode/util/ByteCodeTrace.showMessage (Ljava/lang/String;)V
    ASTORE 5
    ALOAD 5
    INVOKEINTERFACE net/sf/saxon/om/SequenceIterator.next ()Lnet/sf/saxon/om/Item;
    DUP
    IFNONNULL L181
    POP
    LDC ""
    GOTO L182
   L181
    SIPUSH 316
    INVOKESTATIC com/saxonica/ee/bytecode/util/ByteCodeTrace.trace (I)V
    INVOKEINTERFACE net/sf/saxon/om/Item.getStringValueCS ()Ljava/lang/CharSequence;
    ASTORE 12
    ALOAD 5
    INVOKEINTERFACE net/sf/saxon/om/SequenceIterator.next ()Lnet/sf/saxon/om/Item;
    DUP
    IFNONNULL L183
    POP
    ALOAD 12
    GOTO L182
   L183
    SIPUSH 317
    INVOKESTATIC com/saxonica/ee/bytecode/util/ByteCodeTrace.trace (I)V
    NEW net/sf/saxon/tree/util/FastStringBuffer
    DUP
    BIPUSH 64
    INVOKESPECIAL net/sf/saxon/tree/util/FastStringBuffer.<init> (I)V
    ASTORE 7
    ALOAD 7
    ALOAD 12
    INVOKEVIRTUAL net/sf/saxon/tree/util/FastStringBuffer.append (Ljava/lang/CharSequence;)V
   L184
    LDC "LiteralCompiler-Primitive"
    INVOKESTATIC com/saxonica/ee/bytecode/util/ByteCodeTrace.showMessage (Ljava/lang/String;)V
    LDC " "
    ASTORE 16
    ALOAD 7
    ALOAD 16
    INVOKEVIRTUAL net/sf/saxon/tree/util/FastStringBuffer.append (Ljava/lang/CharSequence;)V
    ALOAD 7
    SWAP
    INVOKEINTERFACE net/sf/saxon/om/Item.getStringValueCS ()Ljava/lang/CharSequence;
    INVOKEVIRTUAL net/sf/saxon/tree/util/FastStringBuffer.append (Ljava/lang/CharSequence;)V
   L185
    SIPUSH 318
    INVOKESTATIC com/saxonica/ee/bytecode/util/ByteCodeTrace.trace (I)V
    ALOAD 5
    INVOKEINTERFACE net/sf/saxon/om/SequenceIterator.next ()Lnet/sf/saxon/om/Item;
    DUP
    IFNULL L186
    ALOAD 7
    ALOAD 16
    INVOKEVIRTUAL net/sf/saxon/tree/util/FastStringBuffer.append (Ljava/lang/CharSequence;)V
    ALOAD 7
    SWAP
    INVOKEINTERFACE net/sf/saxon/om/Item.getStringValueCS ()Ljava/lang/CharSequence;
    INVOKEVIRTUAL net/sf/saxon/tree/util/FastStringBuffer.append (Ljava/lang/CharSequence;)V
    GOTO L185
   L186
    SIPUSH 319
    INVOKESTATIC com/saxonica/ee/bytecode/util/ByteCodeTrace.trace (I)V
    POP
    ALOAD 7
    INVOKEVIRTUAL net/sf/saxon/tree/util/FastStringBuffer.condense ()Ljava/lang/CharSequence;
   L182
    SIPUSH 320
    INVOKESTATIC com/saxonica/ee/bytecode/util/ByteCodeTrace.trace (I)V
    INVOKEVIRTUAL net/sf/saxon/tree/util/FastStringBuffer.append (Ljava/lang/CharSequence;)V
    ALOAD 4
   L187
    LDC "LiteralCompiler-Primitive"
    INVOKESTATIC com/saxonica/ee/bytecode/util/ByteCodeTrace.showMessage (Ljava/lang/String;)V
    LDC ")              (.*)               (gesehen,)$"
    INVOKEVIRTUAL net/sf/saxon/tree/util/FastStringBuffer.append (Ljava/lang/CharSequence;)V
    ALOAD 4
    INVOKEVIRTUAL net/sf/saxon/tree/util/FastStringBuffer.condense ()Ljava/lang/CharSequence;
   L188
    LDC "VariableReferenceCompiler-Item"
    INVOKESTATIC com/saxonica/ee/bytecode/util/ByteCodeTrace.showMessage (Ljava/lang/String;)V
    ALOAD 1
    DUP
    ICONST_0
    INVOKEINTERFACE net/sf/saxon/expr/XPathContext.getTargetComponent (I)Lnet/sf/saxon/expr/Component;
    DUP
    INVOKEVIRTUAL net/sf/saxon/expr/Component.getCode ()Lnet/sf/saxon/expr/instruct/ComponentCode;
    CHECKCAST net/sf/saxon/expr/instruct/GlobalVariable
    DUP_X2
    POP
    INVOKEVIRTUAL net/sf/saxon/expr/instruct/GlobalVariable.evaluateVariable (Lnet/sf/saxon/expr/XPathContext;Lnet/sf/saxon/expr/Component;)Lnet/sf/saxon/om/Sequence;
    DUP
    INSTANCEOF net/sf/saxon/om/Item
    IFEQ L189
    CHECKCAST net/sf/saxon/om/Item
    GOTO L190
   L189
    SIPUSH 321
    INVOKESTATIC com/saxonica/ee/bytecode/util/ByteCodeTrace.trace (I)V
    INVOKESTATIC net/sf/saxon/om/SequenceTool.asItem (Lnet/sf/saxon/om/Sequence;)Lnet/sf/saxon/om/Item;
   L190
    SIPUSH 322
    INVOKESTATIC com/saxonica/ee/bytecode/util/ByteCodeTrace.trace (I)V
    CHECKCAST net/sf/saxon/value/StringValue
    INVOKEVIRTUAL net/sf/saxon/value/StringValue.getStringValueCS ()Ljava/lang/CharSequence;
    INVOKEVIRTUAL java/lang/Object.toString ()Ljava/lang/String;
    LDC "XP30"
    ACONST_NULL
    INVOKEINTERFACE net/sf/saxon/Platform.compileRegularExpression (Ljava/lang/CharSequence;Ljava/lang/String;Ljava/lang/String;Ljava/util/List;)Lnet/sf/saxon/regex/RegularExpression;
    DUP
    LDC ""
    INVOKEINTERFACE net/sf/saxon/regex/RegularExpression.matches (Ljava/lang/CharSequence;)Z
    IFEQ L191
    LDC "The regular expression must not be one that matches a zero-length string"
    LDC "XTDE1150"
    LDC "file:/Users/mike/w3c/xslt30-test-B/tests/attr/avt/avt-0601.xsl"
    BIPUSH 42
    ICONST_0
    INVOKESTATIC com/saxonica/ee/bytecode/util/Callback.makeXPathException (Ljava/lang/String;Ljava/lang/String;Ljava/lang/String;IZ)Lnet/sf/saxon/trans/XPathException;
    ATHROW
   L191
    SIPUSH 323
    INVOKESTATIC com/saxonica/ee/bytecode/util/ByteCodeTrace.trace (I)V
   L192
    LDC "CardinalityCheckerCompiler-Item"
    INVOKESTATIC com/saxonica/ee/bytecode/util/ByteCodeTrace.showMessage (Ljava/lang/String;)V
   L193
    LDC "AtomicSequenceConverterCompiler-Itr"
    INVOKESTATIC com/saxonica/ee/bytecode/util/ByteCodeTrace.showMessage (Ljava/lang/String;)V
   L194
    LDC "AtomicSequenceConverterCompiler-1"
    INVOKESTATIC com/saxonica/ee/bytecode/util/ByteCodeTrace.showMessage (Ljava/lang/String;)V
    NEW net/sf/saxon/expr/ItemMappingIterator
    DUP
   L195
    LDC "AtomizerCompiler-Itr"
    INVOKESTATIC com/saxonica/ee/bytecode/util/ByteCodeTrace.showMessage (Ljava/lang/String;)V
   L196
    LDC "AxisExpressionCompiler - iterate"
    INVOKESTATIC com/saxonica/ee/bytecode/util/ByteCodeTrace.showMessage (Ljava/lang/String;)V
    ALOAD 1
    INVOKEINTERFACE net/sf/saxon/expr/XPathContext.getContextItem ()Lnet/sf/saxon/om/Item;
    CHECKCAST net/sf/saxon/om/NodeInfo
   L197
    LDC "AxisExpressionCompiler - static method: iterate"
    INVOKESTATIC com/saxonica/ee/bytecode/util/ByteCodeTrace.showMessage (Ljava/lang/String;)V
    ICONST_3
    GETSTATIC EE__Slash_doc_81855459426.nNameTest89 : Lnet/sf/saxon/pattern/NameTest;
    LDC "calling iterateAxis"
    INVOKESTATIC com/saxonica/ee/bytecode/util/ByteCodeTrace.showMessage (Ljava/lang/String;)V
    INVOKEINTERFACE net/sf/saxon/om/NodeInfo.iterateAxis (BLnet/sf/saxon/pattern/NodeTest;)Lnet/sf/saxon/tree/iter/AxisIterator;
    LDC "returning axis iterator"
    INVOKESTATIC com/saxonica/ee/bytecode/util/ByteCodeTrace.showMessage (Ljava/lang/String;)V
    ICONST_1
    INVOKESTATIC net/sf/saxon/expr/Atomizer.getAtomizingIterator (Lnet/sf/saxon/om/SequenceIterator;Z)Lnet/sf/saxon/om/SequenceIterator;
    GETSTATIC EE__Slash_doc_81855459426.nAtomicSequenceMappingFunction104 : Lnet/sf/saxon/expr/AtomicSequenceConverter$AtomicSequenceMappingFunction;
    ICONST_1
    INVOKESPECIAL net/sf/saxon/expr/ItemMappingIterator.<init> (Lnet/sf/saxon/om/SequenceIterator;Lnet/sf/saxon/expr/ItemMappingFunction;Z)V
    CHECKCAST net/sf/saxon/om/SequenceIterator
    DUP
    INVOKEINTERFACE net/sf/saxon/om/SequenceIterator.next ()Lnet/sf/saxon/om/Item;
    SWAP
    INVOKEINTERFACE net/sf/saxon/om/SequenceIterator.next ()Lnet/sf/saxon/om/Item;
    IFNULL L198
    GETSTATIC EE__Slash_doc_81855459426.nCardinalityChecker105 : Lnet/sf/saxon/expr/CardinalityChecker;
    ALOAD 1
    INVOKESTATIC com/saxonica/ee/bytecode/util/Callback.makeMultipleItemsException (Lnet/sf/saxon/expr/CardinalityChecker;Lnet/sf/saxon/expr/XPathContext;)Lnet/sf/saxon/trans/XPathException;
    ATHROW
   L198
    SIPUSH 324
    INVOKESTATIC com/saxonica/ee/bytecode/util/ByteCodeTrace.trace (I)V
    DUP
    IFNONNULL L199
    POP
    LDC ""
    GOTO L200
   L199
    SIPUSH 325
    INVOKESTATIC com/saxonica/ee/bytecode/util/ByteCodeTrace.trace (I)V
    CHECKCAST net/sf/saxon/value/StringValue
    INVOKEVIRTUAL net/sf/saxon/value/StringValue.getStringValueCS ()Ljava/lang/CharSequence;
   L200
    SIPUSH 326
    INVOKESTATIC com/saxonica/ee/bytecode/util/ByteCodeTrace.trace (I)V
    INVOKEINTERFACE net/sf/saxon/regex/RegularExpression.analyze (Ljava/lang/CharSequence;)Lnet/sf/saxon/regex/RegexIterator;
    ASTORE 17
    ALOAD 1
    INVOKEINTERFACE net/sf/saxon/expr/XPathContext.newContext ()Lnet/sf/saxon/expr/XPathContextMajor;
    ASTORE 18
    ALOAD 18
    GETSTATIC EE__Slash_doc_81855459426.nAnalyzeString106 : Lnet/sf/saxon/expr/instruct/AnalyzeString;
    INVOKEVIRTUAL net/sf/saxon/expr/XPathContextMajor.setOrigin (Lnet/sf/saxon/expr/ContextOriginator;)V
    ALOAD 18
    NEW net/sf/saxon/om/FocusTrackingIterator
    DUP
    ALOAD 17
    INVOKESPECIAL net/sf/saxon/om/FocusTrackingIterator.<init> (Lnet/sf/saxon/om/SequenceIterator;)V
    DUP
    ASTORE 19
    INVOKEINTERFACE net/sf/saxon/expr/XPathContext.setCurrentIterator (Lnet/sf/saxon/om/FocusIterator;)V
    ALOAD 18
    ALOAD 17
    INVOKEVIRTUAL net/sf/saxon/expr/XPathContextMajor.setCurrentRegexIterator (Lnet/sf/saxon/regex/RegexIterator;)V
   L201
    SIPUSH 327
    INVOKESTATIC com/saxonica/ee/bytecode/util/ByteCodeTrace.trace (I)V
    ALOAD 19
    INVOKEINTERFACE net/sf/saxon/om/SequenceIterator.next ()Lnet/sf/saxon/om/Item;
    IFNULL L202
    ALOAD 17
    INVOKEINTERFACE net/sf/saxon/regex/RegexIterator.isMatching ()Z
    IFEQ L203
   L204
    LDC "SimpleNodeConstructorCompiler-Push"
    INVOKESTATIC com/saxonica/ee/bytecode/util/ByteCodeTrace.showMessage (Ljava/lang/String;)V
    ALOAD 2
   L205
    LDC "LiteralCompiler-Primitive"
    INVOKESTATIC com/saxonica/ee/bytecode/util/ByteCodeTrace.showMessage (Ljava/lang/String;)V
    LINENUMBER 44 L206
    LDC "*"
    GETSTATIC EE__Slash_doc_81855459426.nNestedLocation107 : Lnet/sf/saxon/expr/parser/XPathParser$NestedLocation;
    ICONST_4
    INVOKEINTERFACE net/sf/saxon/event/Receiver.characters (Ljava/lang/CharSequence;Lnet/sf/saxon/expr/parser/Location;I)V
    GOTO L201
   L203
    SIPUSH 328
    INVOKESTATIC com/saxonica/ee/bytecode/util/ByteCodeTrace.trace (I)V
   L207
    LDC "SimpleNodeConstructorCompiler-Push"
    INVOKESTATIC com/saxonica/ee/bytecode/util/ByteCodeTrace.showMessage (Ljava/lang/String;)V
    ALOAD 2
    LINENUMBER 47 L208
    ALOAD 18
    INVOKEINTERFACE net/sf/saxon/expr/XPathContext.getContextItem ()Lnet/sf/saxon/om/Item;
    CHECKCAST net/sf/saxon/value/StringValue
    INVOKEVIRTUAL net/sf/saxon/value/StringValue.getStringValueCS ()Ljava/lang/CharSequence;
    GETSTATIC EE__Slash_doc_81855459426.nNestedLocation108 : Lnet/sf/saxon/expr/parser/XPathParser$NestedLocation;
    ICONST_0
    INVOKEINTERFACE net/sf/saxon/event/Receiver.characters (Ljava/lang/CharSequence;Lnet/sf/saxon/expr/parser/Location;I)V
    GOTO L201
   L202
    SIPUSH 329
    INVOKESTATIC com/saxonica/ee/bytecode/util/ByteCodeTrace.trace (I)V
    ALOAD 2
    INVOKEINTERFACE net/sf/saxon/event/Receiver.endElement ()V
   L209
    LDC "FixedElement-E4"
    INVOKESTATIC com/saxonica/ee/bytecode/util/ByteCodeTrace.showMessage (Ljava/lang/String;)V
   L210
    LDC "ElementCreator-push"
    INVOKESTATIC com/saxonica/ee/bytecode/util/ByteCodeTrace.showMessage (Ljava/lang/String;)V
    LINENUMBER 54 L211
    ALOAD 2
    DUP
    LDC "Receiver: "
    SWAP
    DUP
    IFNULL L212
    INVOKEVIRTUAL java/lang/Object.toString ()Ljava/lang/String;
    INVOKESTATIC com/saxonica/ee/bytecode/util/ByteCodeTrace.showObjectVariable (Ljava/lang/String;Ljava/lang/String;)V
    GOTO L213
   L212
    SIPUSH 330
    INVOKESTATIC com/saxonica/ee/bytecode/util/ByteCodeTrace.trace (I)V
    POP
    LDC "null"
    INVOKESTATIC com/saxonica/ee/bytecode/util/ByteCodeTrace.showObjectVariable (Ljava/lang/String;Ljava/lang/String;)V
   L213
    SIPUSH 331
    INVOKESTATIC com/saxonica/ee/bytecode/util/ByteCodeTrace.trace (I)V
    INVOKEINTERFACE net/sf/saxon/event/Receiver.getSystemId ()Ljava/lang/String;
    IFNONNULL L214
    ALOAD 2
    LDC "file:/Users/mike/w3c/xslt30-test-B/tests/attr/avt/avt-0601.xsl"
    INVOKEINTERFACE net/sf/saxon/event/Receiver.setSystemId (Ljava/lang/String;)V
   L214
    SIPUSH 332
    INVOKESTATIC com/saxonica/ee/bytecode/util/ByteCodeTrace.trace (I)V
    ALOAD 2
    GETSTATIC EE__Slash_doc_81855459426.nNoNamespaceName109 : Lnet/sf/saxon/om/NoNamespaceName;
    GETSTATIC EE__Slash_doc_81855459426.nUntyped83 : Lnet/sf/saxon/type/Untyped;
    GETSTATIC EE__Slash_doc_81855459426.nNestedLocation110 : Lnet/sf/saxon/expr/parser/XPathParser$NestedLocation;
    ICONST_0
    INVOKEINTERFACE net/sf/saxon/event/Receiver.startElement (Lnet/sf/saxon/om/NodeName;Lnet/sf/saxon/type/SchemaType;Lnet/sf/saxon/expr/parser/Location;I)V
    GETSTATIC EE__Slash_doc_81855459426.nJavaPlatformPE86 : Lcom/saxonica/config/JavaPlatformPE;
   L215
    LDC "Concat-item"
    INVOKESTATIC com/saxonica/ee/bytecode/util/ByteCodeTrace.showMessage (Ljava/lang/String;)V
    NEW net/sf/saxon/tree/util/FastStringBuffer
    DUP
    BIPUSH 64
    INVOKESPECIAL net/sf/saxon/tree/util/FastStringBuffer.<init> (I)V
    ASTORE 4
    ALOAD 4
   L216
    LDC "LiteralCompiler-Primitive"
    INVOKESTATIC com/saxonica/ee/bytecode/util/ByteCodeTrace.showMessage (Ljava/lang/String;)V
    LDC "("
    INVOKEVIRTUAL net/sf/saxon/tree/util/FastStringBuffer.append (Ljava/lang/CharSequence;)V
    ALOAD 4
   L217
    LDC "StringJoin-Item"
    INVOKESTATIC com/saxonica/ee/bytecode/util/ByteCodeTrace.showMessage (Ljava/lang/String;)V
   L218
    LDC "AtomicSequenceConverterCompiler-Itr"
    INVOKESTATIC com/saxonica/ee/bytecode/util/ByteCodeTrace.showMessage (Ljava/lang/String;)V
   L219
    LDC "AtomicSequenceConverterCompiler-string"
    INVOKESTATIC com/saxonica/ee/bytecode/util/ByteCodeTrace.showMessage (Ljava/lang/String;)V
    NEW net/sf/saxon/expr/ItemMappingIterator
    DUP
   L220
    LDC "AtomizerCompiler-Itr"
    INVOKESTATIC com/saxonica/ee/bytecode/util/ByteCodeTrace.showMessage (Ljava/lang/String;)V
   L221
    LDC "AxisExpressionCompiler - iterate"
    INVOKESTATIC com/saxonica/ee/bytecode/util/ByteCodeTrace.showMessage (Ljava/lang/String;)V
    ALOAD 1
    INVOKEINTERFACE net/sf/saxon/expr/XPathContext.getContextItem ()Lnet/sf/saxon/om/Item;
    CHECKCAST net/sf/saxon/om/NodeInfo
   L222
    LDC "AxisExpressionCompiler - static method: iterate"
    INVOKESTATIC com/saxonica/ee/bytecode/util/ByteCodeTrace.showMessage (Ljava/lang/String;)V
    ICONST_3
    GETSTATIC EE__Slash_doc_81855459426.nNameTest87 : Lnet/sf/saxon/pattern/NameTest;
    LDC "calling iterateAxis"
    INVOKESTATIC com/saxonica/ee/bytecode/util/ByteCodeTrace.showMessage (Ljava/lang/String;)V
    INVOKEINTERFACE net/sf/saxon/om/NodeInfo.iterateAxis (BLnet/sf/saxon/pattern/NodeTest;)Lnet/sf/saxon/tree/iter/AxisIterator;
    LDC "returning axis iterator"
    INVOKESTATIC com/saxonica/ee/bytecode/util/ByteCodeTrace.showMessage (Ljava/lang/String;)V
    ICONST_1
    INVOKESTATIC net/sf/saxon/expr/Atomizer.getAtomizingIterator (Lnet/sf/saxon/om/SequenceIterator;Z)Lnet/sf/saxon/om/SequenceIterator;
    GETSTATIC net/sf/saxon/expr/AtomicSequenceConverter.TO_STRING_MAPPER : Lnet/sf/saxon/expr/AtomicSequenceConverter$ToStringMappingFunction;
    ICONST_1
    INVOKESPECIAL net/sf/saxon/expr/ItemMappingIterator.<init> (Lnet/sf/saxon/om/SequenceIterator;Lnet/sf/saxon/expr/ItemMappingFunction;Z)V
   L223
    LDC "StringJoin-Item-1"
    INVOKESTATIC com/saxonica/ee/bytecode/util/ByteCodeTrace.showMessage (Ljava/lang/String;)V
    ASTORE 5
    ALOAD 5
    INVOKEINTERFACE net/sf/saxon/om/SequenceIterator.next ()Lnet/sf/saxon/om/Item;
    DUP
    IFNONNULL L224
    POP
    LDC ""
    GOTO L225
   L224
    SIPUSH 333
    INVOKESTATIC com/saxonica/ee/bytecode/util/ByteCodeTrace.trace (I)V
    INVOKEINTERFACE net/sf/saxon/om/Item.getStringValueCS ()Ljava/lang/CharSequence;
    ASTORE 16
    ALOAD 5
    INVOKEINTERFACE net/sf/saxon/om/SequenceIterator.next ()Lnet/sf/saxon/om/Item;
    DUP
    IFNONNULL L226
    POP
    ALOAD 16
    GOTO L225
   L226
    SIPUSH 334
    INVOKESTATIC com/saxonica/ee/bytecode/util/ByteCodeTrace.trace (I)V
    NEW net/sf/saxon/tree/util/FastStringBuffer
    DUP
    BIPUSH 64
    INVOKESPECIAL net/sf/saxon/tree/util/FastStringBuffer.<init> (I)V
    ASTORE 7
    ALOAD 7
    ALOAD 16
    INVOKEVIRTUAL net/sf/saxon/tree/util/FastStringBuffer.append (Ljava/lang/CharSequence;)V
   L227
    LDC "LiteralCompiler-Primitive"
    INVOKESTATIC com/saxonica/ee/bytecode/util/ByteCodeTrace.showMessage (Ljava/lang/String;)V
    LDC " "
    ASTORE 20
    ALOAD 7
    ALOAD 20
    INVOKEVIRTUAL net/sf/saxon/tree/util/FastStringBuffer.append (Ljava/lang/CharSequence;)V
    ALOAD 7
    SWAP
    INVOKEINTERFACE net/sf/saxon/om/Item.getStringValueCS ()Ljava/lang/CharSequence;
    INVOKEVIRTUAL net/sf/saxon/tree/util/FastStringBuffer.append (Ljava/lang/CharSequence;)V
   L228
    SIPUSH 335
    INVOKESTATIC com/saxonica/ee/bytecode/util/ByteCodeTrace.trace (I)V
    ALOAD 5
    INVOKEINTERFACE net/sf/saxon/om/SequenceIterator.next ()Lnet/sf/saxon/om/Item;
    DUP
    IFNULL L229
    ALOAD 7
    ALOAD 20
    INVOKEVIRTUAL net/sf/saxon/tree/util/FastStringBuffer.append (Ljava/lang/CharSequence;)V
    ALOAD 7
    SWAP
    INVOKEINTERFACE net/sf/saxon/om/Item.getStringValueCS ()Ljava/lang/CharSequence;
    INVOKEVIRTUAL net/sf/saxon/tree/util/FastStringBuffer.append (Ljava/lang/CharSequence;)V
    GOTO L228
   L229
    SIPUSH 336
    INVOKESTATIC com/saxonica/ee/bytecode/util/ByteCodeTrace.trace (I)V
    POP
    ALOAD 7
    INVOKEVIRTUAL net/sf/saxon/tree/util/FastStringBuffer.condense ()Ljava/lang/CharSequence;
   L225
    SIPUSH 337
    INVOKESTATIC com/saxonica/ee/bytecode/util/ByteCodeTrace.trace (I)V
    INVOKEVIRTUAL net/sf/saxon/tree/util/FastStringBuffer.append (Ljava/lang/CharSequence;)V
    ALOAD 4
   L230
    LDC "LiteralCompiler-Primitive"
    INVOKESTATIC com/saxonica/ee/bytecode/util/ByteCodeTrace.showMessage (Ljava/lang/String;)V
    LDC ")(.*) (krahen)"
    INVOKEVIRTUAL net/sf/saxon/tree/util/FastStringBuffer.append (Ljava/lang/CharSequence;)V
    ALOAD 4
    INVOKEVIRTUAL net/sf/saxon/tree/util/FastStringBuffer.condense ()Ljava/lang/CharSequence;
   L231
    LDC "VariableReferenceCompiler-Item"
    INVOKESTATIC com/saxonica/ee/bytecode/util/ByteCodeTrace.showMessage (Ljava/lang/String;)V
    ALOAD 1
    DUP
    ICONST_1
    INVOKEINTERFACE net/sf/saxon/expr/XPathContext.getTargetComponent (I)Lnet/sf/saxon/expr/Component;
    DUP
    INVOKEVIRTUAL net/sf/saxon/expr/Component.getCode ()Lnet/sf/saxon/expr/instruct/ComponentCode;
    CHECKCAST net/sf/saxon/expr/instruct/GlobalVariable
    DUP_X2
    POP
    INVOKEVIRTUAL net/sf/saxon/expr/instruct/GlobalVariable.evaluateVariable (Lnet/sf/saxon/expr/XPathContext;Lnet/sf/saxon/expr/Component;)Lnet/sf/saxon/om/Sequence;
    DUP
    INSTANCEOF net/sf/saxon/om/Item
    IFEQ L232
    CHECKCAST net/sf/saxon/om/Item
    GOTO L233
   L232
    SIPUSH 338
    INVOKESTATIC com/saxonica/ee/bytecode/util/ByteCodeTrace.trace (I)V
    INVOKESTATIC net/sf/saxon/om/SequenceTool.asItem (Lnet/sf/saxon/om/Sequence;)Lnet/sf/saxon/om/Item;
   L233
    SIPUSH 339
    INVOKESTATIC com/saxonica/ee/bytecode/util/ByteCodeTrace.trace (I)V
    CHECKCAST net/sf/saxon/value/StringValue
    INVOKEVIRTUAL net/sf/saxon/value/StringValue.getStringValueCS ()Ljava/lang/CharSequence;
    INVOKEVIRTUAL java/lang/Object.toString ()Ljava/lang/String;
    LDC "XP30"
    ACONST_NULL
    INVOKEINTERFACE net/sf/saxon/Platform.compileRegularExpression (Ljava/lang/CharSequence;Ljava/lang/String;Ljava/lang/String;Ljava/util/List;)Lnet/sf/saxon/regex/RegularExpression;
    DUP
    LDC ""
    INVOKEINTERFACE net/sf/saxon/regex/RegularExpression.matches (Ljava/lang/CharSequence;)Z
    IFEQ L234
    LDC "The regular expression must not be one that matches a zero-length string"
    LDC "XTDE1150"
    LDC "file:/Users/mike/w3c/xslt30-test-B/tests/attr/avt/avt-0601.xsl"
    BIPUSH 54
    ICONST_0
    INVOKESTATIC com/saxonica/ee/bytecode/util/Callback.makeXPathException (Ljava/lang/String;Ljava/lang/String;Ljava/lang/String;IZ)Lnet/sf/saxon/trans/XPathException;
    ATHROW
   L234
    SIPUSH 340
    INVOKESTATIC com/saxonica/ee/bytecode/util/ByteCodeTrace.trace (I)V
   L235
    LDC "CardinalityCheckerCompiler-Item"
    INVOKESTATIC com/saxonica/ee/bytecode/util/ByteCodeTrace.showMessage (Ljava/lang/String;)V
   L236
    LDC "AtomicSequenceConverterCompiler-Itr"
    INVOKESTATIC com/saxonica/ee/bytecode/util/ByteCodeTrace.showMessage (Ljava/lang/String;)V
   L237
    LDC "AtomicSequenceConverterCompiler-1"
    INVOKESTATIC com/saxonica/ee/bytecode/util/ByteCodeTrace.showMessage (Ljava/lang/String;)V
    NEW net/sf/saxon/expr/ItemMappingIterator
    DUP
   L238
    LDC "AtomizerCompiler-Itr"
    INVOKESTATIC com/saxonica/ee/bytecode/util/ByteCodeTrace.showMessage (Ljava/lang/String;)V
   L239
    LDC "AxisExpressionCompiler - iterate"
    INVOKESTATIC com/saxonica/ee/bytecode/util/ByteCodeTrace.showMessage (Ljava/lang/String;)V
    ALOAD 1
    INVOKEINTERFACE net/sf/saxon/expr/XPathContext.getContextItem ()Lnet/sf/saxon/om/Item;
    CHECKCAST net/sf/saxon/om/NodeInfo
   L240
    LDC "AxisExpressionCompiler - static method: iterate"
    INVOKESTATIC com/saxonica/ee/bytecode/util/ByteCodeTrace.showMessage (Ljava/lang/String;)V
    ICONST_3
    GETSTATIC EE__Slash_doc_81855459426.nNameTest89 : Lnet/sf/saxon/pattern/NameTest;
    LDC "calling iterateAxis"
    INVOKESTATIC com/saxonica/ee/bytecode/util/ByteCodeTrace.showMessage (Ljava/lang/String;)V
    INVOKEINTERFACE net/sf/saxon/om/NodeInfo.iterateAxis (BLnet/sf/saxon/pattern/NodeTest;)Lnet/sf/saxon/tree/iter/AxisIterator;
    LDC "returning axis iterator"
    INVOKESTATIC com/saxonica/ee/bytecode/util/ByteCodeTrace.showMessage (Ljava/lang/String;)V
    ICONST_1
    INVOKESTATIC net/sf/saxon/expr/Atomizer.getAtomizingIterator (Lnet/sf/saxon/om/SequenceIterator;Z)Lnet/sf/saxon/om/SequenceIterator;
    GETSTATIC EE__Slash_doc_81855459426.nAtomicSequenceMappingFunction111 : Lnet/sf/saxon/expr/AtomicSequenceConverter$AtomicSequenceMappingFunction;
    ICONST_1
    INVOKESPECIAL net/sf/saxon/expr/ItemMappingIterator.<init> (Lnet/sf/saxon/om/SequenceIterator;Lnet/sf/saxon/expr/ItemMappingFunction;Z)V
    CHECKCAST net/sf/saxon/om/SequenceIterator
    DUP
    INVOKEINTERFACE net/sf/saxon/om/SequenceIterator.next ()Lnet/sf/saxon/om/Item;
    SWAP
    INVOKEINTERFACE net/sf/saxon/om/SequenceIterator.next ()Lnet/sf/saxon/om/Item;
    IFNULL L241
    GETSTATIC EE__Slash_doc_81855459426.nCardinalityChecker112 : Lnet/sf/saxon/expr/CardinalityChecker;
    ALOAD 1
    INVOKESTATIC com/saxonica/ee/bytecode/util/Callback.makeMultipleItemsException (Lnet/sf/saxon/expr/CardinalityChecker;Lnet/sf/saxon/expr/XPathContext;)Lnet/sf/saxon/trans/XPathException;
    ATHROW
   L241
    SIPUSH 341
    INVOKESTATIC com/saxonica/ee/bytecode/util/ByteCodeTrace.trace (I)V
    DUP
    IFNONNULL L242
    POP
    LDC ""
    GOTO L243
   L242
    SIPUSH 342
    INVOKESTATIC com/saxonica/ee/bytecode/util/ByteCodeTrace.trace (I)V
    CHECKCAST net/sf/saxon/value/StringValue
    INVOKEVIRTUAL net/sf/saxon/value/StringValue.getStringValueCS ()Ljava/lang/CharSequence;
   L243
    SIPUSH 343
    INVOKESTATIC com/saxonica/ee/bytecode/util/ByteCodeTrace.trace (I)V
    INVOKEINTERFACE net/sf/saxon/regex/RegularExpression.analyze (Ljava/lang/CharSequence;)Lnet/sf/saxon/regex/RegexIterator;
    ASTORE 21
    ALOAD 1
    INVOKEINTERFACE net/sf/saxon/expr/XPathContext.newContext ()Lnet/sf/saxon/expr/XPathContextMajor;
    ASTORE 22
    ALOAD 22
    GETSTATIC EE__Slash_doc_81855459426.nAnalyzeString113 : Lnet/sf/saxon/expr/instruct/AnalyzeString;
    INVOKEVIRTUAL net/sf/saxon/expr/XPathContextMajor.setOrigin (Lnet/sf/saxon/expr/ContextOriginator;)V
    ALOAD 22
    NEW net/sf/saxon/om/FocusTrackingIterator
    DUP
    ALOAD 21
    INVOKESPECIAL net/sf/saxon/om/FocusTrackingIterator.<init> (Lnet/sf/saxon/om/SequenceIterator;)V
    DUP
    ASTORE 23
    INVOKEINTERFACE net/sf/saxon/expr/XPathContext.setCurrentIterator (Lnet/sf/saxon/om/FocusIterator;)V
    ALOAD 22
    ALOAD 21
    INVOKEVIRTUAL net/sf/saxon/expr/XPathContextMajor.setCurrentRegexIterator (Lnet/sf/saxon/regex/RegexIterator;)V
   L244
    SIPUSH 344
    INVOKESTATIC com/saxonica/ee/bytecode/util/ByteCodeTrace.trace (I)V
    ALOAD 23
    INVOKEINTERFACE net/sf/saxon/om/SequenceIterator.next ()Lnet/sf/saxon/om/Item;
    IFNULL L245
    ALOAD 21
    INVOKEINTERFACE net/sf/saxon/regex/RegexIterator.isMatching ()Z
    IFEQ L246
   L247
    LDC "SimpleNodeConstructorCompiler-Push"
    INVOKESTATIC com/saxonica/ee/bytecode/util/ByteCodeTrace.showMessage (Ljava/lang/String;)V
    ALOAD 2
   L248
    LDC "LiteralCompiler-Primitive"
    INVOKESTATIC com/saxonica/ee/bytecode/util/ByteCodeTrace.showMessage (Ljava/lang/String;)V
    LINENUMBER 56 L249
    LDC "*"
    GETSTATIC EE__Slash_doc_81855459426.nNestedLocation114 : Lnet/sf/saxon/expr/parser/XPathParser$NestedLocation;
    ICONST_4
    INVOKEINTERFACE net/sf/saxon/event/Receiver.characters (Ljava/lang/CharSequence;Lnet/sf/saxon/expr/parser/Location;I)V
    GOTO L244
   L246
    SIPUSH 345
    INVOKESTATIC com/saxonica/ee/bytecode/util/ByteCodeTrace.trace (I)V
   L250
    LDC "SimpleNodeConstructorCompiler-Push"
    INVOKESTATIC com/saxonica/ee/bytecode/util/ByteCodeTrace.showMessage (Ljava/lang/String;)V
    ALOAD 2
    LINENUMBER 59 L251
    ALOAD 22
    INVOKEINTERFACE net/sf/saxon/expr/XPathContext.getContextItem ()Lnet/sf/saxon/om/Item;
    CHECKCAST net/sf/saxon/value/StringValue
    INVOKEVIRTUAL net/sf/saxon/value/StringValue.getStringValueCS ()Ljava/lang/CharSequence;
    GETSTATIC EE__Slash_doc_81855459426.nNestedLocation115 : Lnet/sf/saxon/expr/parser/XPathParser$NestedLocation;
    ICONST_0
    INVOKEINTERFACE net/sf/saxon/event/Receiver.characters (Ljava/lang/CharSequence;Lnet/sf/saxon/expr/parser/Location;I)V
    GOTO L244
   L245
    SIPUSH 346
    INVOKESTATIC com/saxonica/ee/bytecode/util/ByteCodeTrace.trace (I)V
    ALOAD 2
    INVOKEINTERFACE net/sf/saxon/event/Receiver.endElement ()V
    ALOAD 2
    INVOKEINTERFACE net/sf/saxon/event/Receiver.endElement ()V
    RETURN
    MAXSTACK = 0
    MAXLOCALS = 0
}

  // access flags 0x9
  public static Lnet/sf/saxon/expr/parser/XPathParser$NestedLocation; nNestedLocation108

  // access flags 0x9
  public static Lnet/sf/saxon/expr/AtomicSequenceConverter$AtomicSequenceMappingFunction; nAtomicSequenceMappingFunction111

  // access flags 0x9
  public static Lnet/sf/saxon/expr/AtomicSequenceConverter$AtomicSequenceMappingFunction; nAtomicSequenceMappingFunction104

  // access flags 0x9
  public static Lnet/sf/saxon/expr/parser/XPathParser$NestedLocation; nNestedLocation101

  // access flags 0x9
  public static Lnet/sf/saxon/expr/parser/XPathParser$NestedLocation; nNestedLocation93

  // access flags 0x9
  public static Lnet/sf/saxon/expr/instruct/AnalyzeString; nAnalyzeString92

  // access flags 0x9
  public static Lnet/sf/saxon/expr/CardinalityChecker; nCardinalityChecker91

  // access flags 0x9
  public static Lnet/sf/saxon/expr/parser/XPathParser$NestedLocation; nNestedLocation84

  // access flags 0x9
  public static Lnet/sf/saxon/expr/parser/XPathParser$NestedLocation; nNestedLocation100

  // access flags 0x9
  public static Lnet/sf/saxon/om/NoNamespaceName; nNoNamespaceName82

  // access flags 0x9
  public static Lnet/sf/saxon/pattern/NameTest; nNameTest87

  // access flags 0x9
  public static Lnet/sf/saxon/expr/instruct/AnalyzeString; nAnalyzeString113

  // access flags 0x9
  public static Lnet/sf/saxon/expr/CardinalityChecker; nCardinalityChecker112

  // access flags 0x9
  public static Lnet/sf/saxon/expr/parser/XPathParser$NestedLocation; nNestedLocation110

  // access flags 0x9
  public static Lnet/sf/saxon/pattern/NameTest; nNameTest89

  // access flags 0x9
  public static Lnet/sf/saxon/pattern/NameTest; nNameTest88

  // access flags 0x9
  public static Lcom/saxonica/config/JavaPlatformPE; nJavaPlatformPE86

  // access flags 0x9
  public static Lnet/sf/saxon/expr/parser/XPathParser$NestedLocation; nNestedLocation103

  // access flags 0x9
  public static Lnet/sf/saxon/expr/CardinalityChecker; nCardinalityChecker105

  // access flags 0x9
  public static Lnet/sf/saxon/expr/instruct/AnalyzeString; nAnalyzeString106

  // access flags 0x9
  public static Lnet/sf/saxon/expr/AtomicSequenceConverter$AtomicSequenceMappingFunction; nAtomicSequenceMappingFunction97

  // access flags 0x9
  public static Lnet/sf/saxon/expr/parser/XPathParser$NestedLocation; nNestedLocation94

  // access flags 0x9
  public static Lnet/sf/saxon/om/NoNamespaceName; nNoNamespaceName85

  // access flags 0x9
  public static Lnet/sf/saxon/expr/parser/XPathParser$NestedLocation; nNestedLocation115

  // access flags 0x9
  public static Lnet/sf/saxon/expr/parser/XPathParser$NestedLocation; nNestedLocation114

  // access flags 0x9
  public static Lnet/sf/saxon/expr/parser/XPathParser$NestedLocation; nNestedLocation107

  // access flags 0x9
  public static Lnet/sf/saxon/expr/AtomicSequenceConverter$AtomicSequenceMappingFunction; nAtomicSequenceMappingFunction90

  // access flags 0x9
  public static Lnet/sf/saxon/om/NoNamespaceName; nNoNamespaceName95

  // access flags 0x9
  public static Lnet/sf/saxon/om/NoNamespaceName; nNoNamespaceName102

  // access flags 0x9
  public static Lnet/sf/saxon/type/Untyped; nUntyped83

  // access flags 0x9
  public static Lnet/sf/saxon/om/NoNamespaceName; nNoNamespaceName109

  // access flags 0x9
  public static Lnet/sf/saxon/expr/parser/XPathParser$NestedLocation; nNestedLocation96

  // access flags 0x9
  public static Lnet/sf/saxon/expr/CardinalityChecker; nCardinalityChecker98

  // access flags 0x9
  public static Lnet/sf/saxon/expr/instruct/AnalyzeString; nAnalyzeString99
}
