// class version 49.0 (49)
// access flags 0x1
public class EE__Slash__267119518863 extends com/saxonica/ee/bytecode/GeneratedCode  {


  // access flags 0x1
  public <init>()V
    LINENUMBER 21 L0
    ALOAD 0
    INVOKESPECIAL com/saxonica/ee/bytecode/GeneratedCode.<init> ()V
    RETURN
    MAXSTACK = 0
    MAXLOCALS = 0

  // access flags 0x1
  public process(Lnet/sf/saxon/expr/XPathContext;)V throws net/sf/saxon/trans/XPathException 
    ALOAD 1
    INVOKEINTERFACE net/sf/saxon/expr/XPathContext.getReceiver ()Lnet/sf/saxon/event/SequenceReceiver;
    ASTORE 2
    LINENUMBER 21 L0
   L1
    LDC "FixedElement-erg"
    INVOKESTATIC com/saxonica/ee/bytecode/util/ByteCodeTrace.showMessage (Ljava/lang/String;)V
   L2
    LDC "ElementCreator-push"
    INVOKESTATIC com/saxonica/ee/bytecode/util/ByteCodeTrace.showMessage (Ljava/lang/String;)V
    ALOAD 2
    DUP
    LDC "Receiver: "
    SWAP
    DUP
    IFNULL L3
    INVOKEVIRTUAL java/lang/Object.toString ()Ljava/lang/String;
    INVOKESTATIC com/saxonica/ee/bytecode/util/ByteCodeTrace.showObjectVariable (Ljava/lang/String;Ljava/lang/String;)V
    GOTO L4
   L3
    SIPUSH 527
    INVOKESTATIC com/saxonica/ee/bytecode/util/ByteCodeTrace.trace (I)V
    POP
    LDC "null"
    INVOKESTATIC com/saxonica/ee/bytecode/util/ByteCodeTrace.showObjectVariable (Ljava/lang/String;Ljava/lang/String;)V
   L4
    SIPUSH 528
    INVOKESTATIC com/saxonica/ee/bytecode/util/ByteCodeTrace.trace (I)V
    INVOKEINTERFACE net/sf/saxon/event/Receiver.getSystemId ()Ljava/lang/String;
    IFNONNULL L5
    ALOAD 2
    LDC "file:/Users/mike/w3c/xslt30-test-B/tests/attr/avt/avt-2201.xsl"
    INVOKEINTERFACE net/sf/saxon/event/Receiver.setSystemId (Ljava/lang/String;)V
   L5
    SIPUSH 529
    INVOKESTATIC com/saxonica/ee/bytecode/util/ByteCodeTrace.trace (I)V
    ALOAD 2
    GETSTATIC EE__Slash__267119518863.nNoNamespaceName268 : Lnet/sf/saxon/om/NoNamespaceName;
    GETSTATIC EE__Slash__267119518863.nUntyped269 : Lnet/sf/saxon/type/Untyped;
    GETSTATIC EE__Slash__267119518863.nLiteralResultElement270 : Lnet/sf/saxon/style/LiteralResultElement;
    ICONST_0
    INVOKEINTERFACE net/sf/saxon/event/Receiver.startElement (Lnet/sf/saxon/om/NodeName;Lnet/sf/saxon/type/SchemaType;Lnet/sf/saxon/expr/parser/Location;I)V
   L6
    LDC "BlockCompiler-Push"
    INVOKESTATIC com/saxonica/ee/bytecode/util/ByteCodeTrace.showMessage (Ljava/lang/String;)V
   L7
    LDC "FixedElement-aa"
    INVOKESTATIC com/saxonica/ee/bytecode/util/ByteCodeTrace.showMessage (Ljava/lang/String;)V
   L8
    LDC "ElementCreator-push"
    INVOKESTATIC com/saxonica/ee/bytecode/util/ByteCodeTrace.showMessage (Ljava/lang/String;)V
    ALOAD 2
    DUP
    LDC "Receiver: "
    SWAP
    DUP
    IFNULL L9
    INVOKEVIRTUAL java/lang/Object.toString ()Ljava/lang/String;
    INVOKESTATIC com/saxonica/ee/bytecode/util/ByteCodeTrace.showObjectVariable (Ljava/lang/String;Ljava/lang/String;)V
    GOTO L10
   L9
    SIPUSH 530
    INVOKESTATIC com/saxonica/ee/bytecode/util/ByteCodeTrace.trace (I)V
    POP
    LDC "null"
    INVOKESTATIC com/saxonica/ee/bytecode/util/ByteCodeTrace.showObjectVariable (Ljava/lang/String;Ljava/lang/String;)V
   L10
    SIPUSH 531
    INVOKESTATIC com/saxonica/ee/bytecode/util/ByteCodeTrace.trace (I)V
    INVOKEINTERFACE net/sf/saxon/event/Receiver.getSystemId ()Ljava/lang/String;
    IFNONNULL L11
    ALOAD 2
    LDC "file:/Users/mike/w3c/xslt30-test-B/tests/attr/avt/avt-2201.xsl"
    INVOKEINTERFACE net/sf/saxon/event/Receiver.setSystemId (Ljava/lang/String;)V
   L11
    SIPUSH 532
    INVOKESTATIC com/saxonica/ee/bytecode/util/ByteCodeTrace.trace (I)V
    ALOAD 2
    GETSTATIC EE__Slash__267119518863.nNoNamespaceName271 : Lnet/sf/saxon/om/NoNamespaceName;
    GETSTATIC EE__Slash__267119518863.nUntyped269 : Lnet/sf/saxon/type/Untyped;
    GETSTATIC EE__Slash__267119518863.nLiteralResultElement270 : Lnet/sf/saxon/style/LiteralResultElement;
    ICONST_0
    INVOKEINTERFACE net/sf/saxon/event/Receiver.startElement (Lnet/sf/saxon/om/NodeName;Lnet/sf/saxon/type/SchemaType;Lnet/sf/saxon/expr/parser/Location;I)V
    ALOAD 2
    GETSTATIC EE__Slash__267119518863.nFingerprintedQName272 : Lnet/sf/saxon/om/FingerprintedQName;
    GETSTATIC net/sf/saxon/type/BuiltInAtomicType.UNTYPED_ATOMIC : Lnet/sf/saxon/type/BuiltInAtomicType;
   L12
    LDC "LiteralCompiler-Primitive"
    INVOKESTATIC com/saxonica/ee/bytecode/util/ByteCodeTrace.showMessage (Ljava/lang/String;)V
    LDC "str"
    GETSTATIC EE__Slash__267119518863.nLiteralResultElement270 : Lnet/sf/saxon/style/LiteralResultElement;
    ICONST_4
    INVOKEINTERFACE net/sf/saxon/event/Receiver.attribute (Lnet/sf/saxon/om/NodeName;Lnet/sf/saxon/type/SimpleType;Ljava/lang/CharSequence;Lnet/sf/saxon/expr/parser/Location;I)V
    ALOAD 2
    INVOKEINTERFACE net/sf/saxon/event/Receiver.endElement ()V
   L13
    LDC "FixedElement-bb"
    INVOKESTATIC com/saxonica/ee/bytecode/util/ByteCodeTrace.showMessage (Ljava/lang/String;)V
   L14
    LDC "ElementCreator-push"
    INVOKESTATIC com/saxonica/ee/bytecode/util/ByteCodeTrace.showMessage (Ljava/lang/String;)V
    LINENUMBER 25 L15
    ALOAD 2
    DUP
    LDC "Receiver: "
    SWAP
    DUP
    IFNULL L16
    INVOKEVIRTUAL java/lang/Object.toString ()Ljava/lang/String;
    INVOKESTATIC com/saxonica/ee/bytecode/util/ByteCodeTrace.showObjectVariable (Ljava/lang/String;Ljava/lang/String;)V
    GOTO L17
   L16
    SIPUSH 533
    INVOKESTATIC com/saxonica/ee/bytecode/util/ByteCodeTrace.trace (I)V
    POP
    LDC "null"
    INVOKESTATIC com/saxonica/ee/bytecode/util/ByteCodeTrace.showObjectVariable (Ljava/lang/String;Ljava/lang/String;)V
   L17
    SIPUSH 534
    INVOKESTATIC com/saxonica/ee/bytecode/util/ByteCodeTrace.trace (I)V
    INVOKEINTERFACE net/sf/saxon/event/Receiver.getSystemId ()Ljava/lang/String;
    IFNONNULL L18
    ALOAD 2
    LDC "file:/Users/mike/w3c/xslt30-test-B/tests/attr/avt/avt-2201.xsl"
    INVOKEINTERFACE net/sf/saxon/event/Receiver.setSystemId (Ljava/lang/String;)V
   L18
    SIPUSH 535
    INVOKESTATIC com/saxonica/ee/bytecode/util/ByteCodeTrace.trace (I)V
    ALOAD 2
    GETSTATIC EE__Slash__267119518863.nNoNamespaceName273 : Lnet/sf/saxon/om/NoNamespaceName;
    GETSTATIC EE__Slash__267119518863.nUntyped269 : Lnet/sf/saxon/type/Untyped;
    GETSTATIC EE__Slash__267119518863.nAttributeLocation274 : Lnet/sf/saxon/style/ExpressionContext$AttributeLocation;
    ICONST_0
    INVOKEINTERFACE net/sf/saxon/event/Receiver.startElement (Lnet/sf/saxon/om/NodeName;Lnet/sf/saxon/type/SchemaType;Lnet/sf/saxon/expr/parser/Location;I)V
    ALOAD 2
    GETSTATIC EE__Slash__267119518863.nFingerprintedQName275 : Lnet/sf/saxon/om/FingerprintedQName;
    GETSTATIC net/sf/saxon/type/BuiltInAtomicType.UNTYPED_ATOMIC : Lnet/sf/saxon/type/BuiltInAtomicType;
   L19
    LDC "LiteralCompiler-Primitive"
    INVOKESTATIC com/saxonica/ee/bytecode/util/ByteCodeTrace.showMessage (Ljava/lang/String;)V
    LDC ""
    GETSTATIC EE__Slash__267119518863.nAttributeLocation274 : Lnet/sf/saxon/style/ExpressionContext$AttributeLocation;
    ICONST_0
    INVOKEINTERFACE net/sf/saxon/event/Receiver.attribute (Lnet/sf/saxon/om/NodeName;Lnet/sf/saxon/type/SimpleType;Ljava/lang/CharSequence;Lnet/sf/saxon/expr/parser/Location;I)V
    ALOAD 2
    INVOKEINTERFACE net/sf/saxon/event/Receiver.endElement ()V
   L20
    LDC "ComputedElement-push"
    INVOKESTATIC com/saxonica/ee/bytecode/util/ByteCodeTrace.showMessage (Ljava/lang/String;)V
   L21
    LDC "ElementCreator-push"
    INVOKESTATIC com/saxonica/ee/bytecode/util/ByteCodeTrace.showMessage (Ljava/lang/String;)V
    LINENUMBER 29 L22
    ALOAD 2
    DUP
    LDC "Receiver: "
    SWAP
    DUP
    IFNULL L23
    INVOKEVIRTUAL java/lang/Object.toString ()Ljava/lang/String;
    INVOKESTATIC com/saxonica/ee/bytecode/util/ByteCodeTrace.showObjectVariable (Ljava/lang/String;Ljava/lang/String;)V
    GOTO L24
   L23
    SIPUSH 536
    INVOKESTATIC com/saxonica/ee/bytecode/util/ByteCodeTrace.trace (I)V
    POP
    LDC "null"
    INVOKESTATIC com/saxonica/ee/bytecode/util/ByteCodeTrace.showObjectVariable (Ljava/lang/String;Ljava/lang/String;)V
   L24
    SIPUSH 537
    INVOKESTATIC com/saxonica/ee/bytecode/util/ByteCodeTrace.trace (I)V
    INVOKEINTERFACE net/sf/saxon/event/Receiver.getSystemId ()Ljava/lang/String;
    IFNONNULL L25
    ALOAD 2
    LDC "file:/Users/mike/w3c/xslt30-test-B/tests/attr/avt/avt-2201.xsl"
    INVOKEINTERFACE net/sf/saxon/event/Receiver.setSystemId (Ljava/lang/String;)V
   L25
    SIPUSH 538
    INVOKESTATIC com/saxonica/ee/bytecode/util/ByteCodeTrace.trace (I)V
    ALOAD 2
    ACONST_NULL
    ASTORE 4
   L26
    LDC "LiteralCompiler-item"
    INVOKESTATIC com/saxonica/ee/bytecode/util/ByteCodeTrace.showMessage (Ljava/lang/String;)V
    GETSTATIC EE__Slash__267119518863.nStringValue276 : Lnet/sf/saxon/value/StringValue;
    CHECKCAST net/sf/saxon/value/AtomicValue
    DUP
    IFNONNULL L27
    POP
    LDC "Invalid element name (empty sequence)"
    LDC "XTDE0820"
    LDC "file:/Users/mike/w3c/xslt30-test-B/tests/attr/avt/avt-2201.xsl"
    BIPUSH 29
    ICONST_0
    INVOKESTATIC com/saxonica/ee/bytecode/util/Callback.makeXPathException (Ljava/lang/String;Ljava/lang/String;Ljava/lang/String;IZ)Lnet/sf/saxon/trans/XPathException;
    ATHROW
    GOTO L28
   L27
    SIPUSH 539
    INVOKESTATIC com/saxonica/ee/bytecode/util/ByteCodeTrace.trace (I)V
    DUP
    INSTANCEOF net/sf/saxon/value/StringValue
    IFEQ L29
    INVOKEVIRTUAL net/sf/saxon/value/AtomicValue.getStringValueCS ()Ljava/lang/CharSequence;
    INVOKESTATIC net/sf/saxon/value/Whitespace.trimWhitespace (Ljava/lang/CharSequence;)Ljava/lang/CharSequence;
    ASTORE 6
    ALOAD 6
    TRYCATCHBLOCK L30 L31 L32 net/sf/saxon/om/QNameException
   L30
    SIPUSH 540
    INVOKESTATIC com/saxonica/ee/bytecode/util/ByteCodeTrace.trace (I)V
    INVOKESTATIC net/sf/saxon/om/NameChecker.getQNameParts (Ljava/lang/CharSequence;)[Ljava/lang/String;
   L31
    SIPUSH 541
    INVOKESTATIC com/saxonica/ee/bytecode/util/ByteCodeTrace.trace (I)V
    DUP
    ICONST_0
    AALOAD
    ASTORE 5
    ICONST_1
    AALOAD
    ASTORE 3
    GOTO L33
   L32
    SIPUSH 542
    INVOKESTATIC com/saxonica/ee/bytecode/util/ByteCodeTrace.trace (I)V
    LDC "Invalid element name: <{$1}>"
    ALOAD 6
    INVOKESTATIC com/saxonica/ee/bytecode/util/Callback.makeMessageFromTemplate (Ljava/lang/String;Ljava/lang/CharSequence;)Ljava/lang/String;
    LDC "XTDE0820"
    LDC "file:/Users/mike/w3c/xslt30-test-B/tests/attr/avt/avt-2201.xsl"
    BIPUSH 29
    ICONST_0
    INVOKESTATIC com/saxonica/ee/bytecode/util/Callback.makeXPathException (Ljava/lang/String;Ljava/lang/String;Ljava/lang/String;IZ)Lnet/sf/saxon/trans/XPathException;
    ATHROW
   L29
    SIPUSH 543
    INVOKESTATIC com/saxonica/ee/bytecode/util/ByteCodeTrace.trace (I)V
    LDC "Computed element name has incorrect type"
    LDC "XTDE0820"
    LDC "file:/Users/mike/w3c/xslt30-test-B/tests/attr/avt/avt-2201.xsl"
    BIPUSH 29
    ICONST_1
    INVOKESTATIC com/saxonica/ee/bytecode/util/Callback.makeXPathException (Ljava/lang/String;Ljava/lang/String;Ljava/lang/String;IZ)Lnet/sf/saxon/trans/XPathException;
    ATHROW
    GOTO L28
   L33
    SIPUSH 544
    INVOKESTATIC com/saxonica/ee/bytecode/util/ByteCodeTrace.trace (I)V
    ALOAD 4
    IFNONNULL L34
    LDC ""
    ASTORE 4
   L34
    SIPUSH 545
    INVOKESTATIC com/saxonica/ee/bytecode/util/ByteCodeTrace.trace (I)V
    ALOAD 4
    INVOKEVIRTUAL java/lang/String.length ()I
    ICONST_0
    IF_ICMPNE L35
    LDC ""
    ASTORE 5
   L35
    SIPUSH 546
    INVOKESTATIC com/saxonica/ee/bytecode/util/ByteCodeTrace.trace (I)V
    ALOAD 5
    LDC "xmlns"
    INVOKEVIRTUAL java/lang/String.equals (Ljava/lang/Object;)Z
    IFEQ L36
    LDC "x-xmlns"
    ASTORE 5
   L36
    SIPUSH 547
    INVOKESTATIC com/saxonica/ee/bytecode/util/ByteCodeTrace.trace (I)V
    ALOAD 4
    LDC "http://www.w3.org/2000/xmlns/"
    INVOKEVIRTUAL java/lang/String.equals (Ljava/lang/Object;)Z
    IFEQ L37
    LDC "Cannot create element in namespace {$1}"
    ALOAD 4
    INVOKESTATIC com/saxonica/ee/bytecode/util/Callback.makeMessageFromTemplate (Ljava/lang/String;Ljava/lang/CharSequence;)Ljava/lang/String;
    LDC "XTDE0835"
    LDC "file:/Users/mike/w3c/xslt30-test-B/tests/attr/avt/avt-2201.xsl"
    BIPUSH 29
    ICONST_0
    INVOKESTATIC com/saxonica/ee/bytecode/util/Callback.makeXPathException (Ljava/lang/String;Ljava/lang/String;Ljava/lang/String;IZ)Lnet/sf/saxon/trans/XPathException;
    ATHROW
    GOTO L28
   L37
    SIPUSH 548
    INVOKESTATIC com/saxonica/ee/bytecode/util/ByteCodeTrace.trace (I)V
    ALOAD 4
    LDC "http://www.w3.org/XML/1998/namespace"
    INVOKEVIRTUAL java/lang/String.equals (Ljava/lang/Object;)Z
    ALOAD 5
    LDC "xml"
    INVOKEVIRTUAL java/lang/String.equals (Ljava/lang/Object;)Z
    IF_ICMPEQ L38
    ALOAD 5
    ALOAD 4
    ICONST_1
    LDC "file:/Users/mike/w3c/xslt30-test-B/tests/attr/avt/avt-2201.xsl"
    BIPUSH 29
    INVOKESTATIC com/saxonica/ee/bytecode/util/Callback.makeXmlNamespaceException (Ljava/lang/String;Ljava/lang/String;ZLjava/lang/String;I)Lnet/sf/saxon/trans/XPathException;
    ATHROW
   L38
    SIPUSH 549
    INVOKESTATIC com/saxonica/ee/bytecode/util/ByteCodeTrace.trace (I)V
    NEW net/sf/saxon/om/FingerprintedQName
    DUP
    ALOAD 5
    ALOAD 4
    INVOKEVIRTUAL java/lang/Object.toString ()Ljava/lang/String;
    ALOAD 3
    INVOKESPECIAL net/sf/saxon/om/FingerprintedQName.<init> (Ljava/lang/String;Ljava/lang/String;Ljava/lang/String;)V
   L28
    SIPUSH 550
    INVOKESTATIC com/saxonica/ee/bytecode/util/ByteCodeTrace.trace (I)V
    GETSTATIC EE__Slash__267119518863.nUntyped269 : Lnet/sf/saxon/type/Untyped;
    GETSTATIC EE__Slash__267119518863.nAttributeLocation277 : Lnet/sf/saxon/style/ExpressionContext$AttributeLocation;
    ICONST_0
    INVOKEINTERFACE net/sf/saxon/event/Receiver.startElement (Lnet/sf/saxon/om/NodeName;Lnet/sf/saxon/type/SchemaType;Lnet/sf/saxon/expr/parser/Location;I)V
    ALOAD 2
    INVOKEINTERFACE net/sf/saxon/event/Receiver.endElement ()V
   L39
    LDC "ComputedElement-push"
    INVOKESTATIC com/saxonica/ee/bytecode/util/ByteCodeTrace.showMessage (Ljava/lang/String;)V
   L40
    LDC "ElementCreator-push"
    INVOKESTATIC com/saxonica/ee/bytecode/util/ByteCodeTrace.showMessage (Ljava/lang/String;)V
    LINENUMBER 33 L41
    ALOAD 2
    DUP
    LDC "Receiver: "
    SWAP
    DUP
    IFNULL L42
    INVOKEVIRTUAL java/lang/Object.toString ()Ljava/lang/String;
    INVOKESTATIC com/saxonica/ee/bytecode/util/ByteCodeTrace.showObjectVariable (Ljava/lang/String;Ljava/lang/String;)V
    GOTO L43
   L42
    SIPUSH 551
    INVOKESTATIC com/saxonica/ee/bytecode/util/ByteCodeTrace.trace (I)V
    POP
    LDC "null"
    INVOKESTATIC com/saxonica/ee/bytecode/util/ByteCodeTrace.showObjectVariable (Ljava/lang/String;Ljava/lang/String;)V
   L43
    SIPUSH 552
    INVOKESTATIC com/saxonica/ee/bytecode/util/ByteCodeTrace.trace (I)V
    INVOKEINTERFACE net/sf/saxon/event/Receiver.getSystemId ()Ljava/lang/String;
    IFNONNULL L44
    ALOAD 2
    LDC "file:/Users/mike/w3c/xslt30-test-B/tests/attr/avt/avt-2201.xsl"
    INVOKEINTERFACE net/sf/saxon/event/Receiver.setSystemId (Ljava/lang/String;)V
   L44
    SIPUSH 553
    INVOKESTATIC com/saxonica/ee/bytecode/util/ByteCodeTrace.trace (I)V
    ALOAD 2
    ACONST_NULL
    ASTORE 4
   L45
    LDC "LiteralCompiler-item"
    INVOKESTATIC com/saxonica/ee/bytecode/util/ByteCodeTrace.showMessage (Ljava/lang/String;)V
    GETSTATIC EE__Slash__267119518863.nStringValue278 : Lnet/sf/saxon/value/StringValue;
    CHECKCAST net/sf/saxon/value/AtomicValue
    DUP
    IFNONNULL L46
    POP
    LDC "Invalid element name (empty sequence)"
    LDC "XTDE0820"
    LDC "file:/Users/mike/w3c/xslt30-test-B/tests/attr/avt/avt-2201.xsl"
    BIPUSH 33
    ICONST_0
    INVOKESTATIC com/saxonica/ee/bytecode/util/Callback.makeXPathException (Ljava/lang/String;Ljava/lang/String;Ljava/lang/String;IZ)Lnet/sf/saxon/trans/XPathException;
    ATHROW
    GOTO L47
   L46
    SIPUSH 554
    INVOKESTATIC com/saxonica/ee/bytecode/util/ByteCodeTrace.trace (I)V
    DUP
    INSTANCEOF net/sf/saxon/value/StringValue
    IFEQ L48
    INVOKEVIRTUAL net/sf/saxon/value/AtomicValue.getStringValueCS ()Ljava/lang/CharSequence;
    INVOKESTATIC net/sf/saxon/value/Whitespace.trimWhitespace (Ljava/lang/CharSequence;)Ljava/lang/CharSequence;
    ASTORE 7
    ALOAD 7
    TRYCATCHBLOCK L49 L50 L51 net/sf/saxon/om/QNameException
   L49
    SIPUSH 555
    INVOKESTATIC com/saxonica/ee/bytecode/util/ByteCodeTrace.trace (I)V
    INVOKESTATIC net/sf/saxon/om/NameChecker.getQNameParts (Ljava/lang/CharSequence;)[Ljava/lang/String;
   L50
    SIPUSH 556
    INVOKESTATIC com/saxonica/ee/bytecode/util/ByteCodeTrace.trace (I)V
    DUP
    ICONST_0
    AALOAD
    ASTORE 5
    ICONST_1
    AALOAD
    ASTORE 3
    GOTO L52
   L51
    SIPUSH 557
    INVOKESTATIC com/saxonica/ee/bytecode/util/ByteCodeTrace.trace (I)V
    LDC "Invalid element name: <{$1}>"
    ALOAD 7
    INVOKESTATIC com/saxonica/ee/bytecode/util/Callback.makeMessageFromTemplate (Ljava/lang/String;Ljava/lang/CharSequence;)Ljava/lang/String;
    LDC "XTDE0820"
    LDC "file:/Users/mike/w3c/xslt30-test-B/tests/attr/avt/avt-2201.xsl"
    BIPUSH 33
    ICONST_0
    INVOKESTATIC com/saxonica/ee/bytecode/util/Callback.makeXPathException (Ljava/lang/String;Ljava/lang/String;Ljava/lang/String;IZ)Lnet/sf/saxon/trans/XPathException;
    ATHROW
   L48
    SIPUSH 558
    INVOKESTATIC com/saxonica/ee/bytecode/util/ByteCodeTrace.trace (I)V
    LDC "Computed element name has incorrect type"
    LDC "XTDE0820"
    LDC "file:/Users/mike/w3c/xslt30-test-B/tests/attr/avt/avt-2201.xsl"
    BIPUSH 33
    ICONST_1
    INVOKESTATIC com/saxonica/ee/bytecode/util/Callback.makeXPathException (Ljava/lang/String;Ljava/lang/String;Ljava/lang/String;IZ)Lnet/sf/saxon/trans/XPathException;
    ATHROW
    GOTO L47
   L52
    SIPUSH 559
    INVOKESTATIC com/saxonica/ee/bytecode/util/ByteCodeTrace.trace (I)V
    ALOAD 4
    IFNONNULL L53
    LDC ""
    ASTORE 4
   L53
    SIPUSH 560
    INVOKESTATIC com/saxonica/ee/bytecode/util/ByteCodeTrace.trace (I)V
    ALOAD 4
    INVOKEVIRTUAL java/lang/String.length ()I
    ICONST_0
    IF_ICMPNE L54
    LDC ""
    ASTORE 5
   L54
    SIPUSH 561
    INVOKESTATIC com/saxonica/ee/bytecode/util/ByteCodeTrace.trace (I)V
    ALOAD 5
    LDC "xmlns"
    INVOKEVIRTUAL java/lang/String.equals (Ljava/lang/Object;)Z
    IFEQ L55
    LDC "x-xmlns"
    ASTORE 5
   L55
    SIPUSH 562
    INVOKESTATIC com/saxonica/ee/bytecode/util/ByteCodeTrace.trace (I)V
    ALOAD 4
    LDC "http://www.w3.org/2000/xmlns/"
    INVOKEVIRTUAL java/lang/String.equals (Ljava/lang/Object;)Z
    IFEQ L56
    LDC "Cannot create element in namespace {$1}"
    ALOAD 4
    INVOKESTATIC com/saxonica/ee/bytecode/util/Callback.makeMessageFromTemplate (Ljava/lang/String;Ljava/lang/CharSequence;)Ljava/lang/String;
    LDC "XTDE0835"
    LDC "file:/Users/mike/w3c/xslt30-test-B/tests/attr/avt/avt-2201.xsl"
    BIPUSH 33
    ICONST_0
    INVOKESTATIC com/saxonica/ee/bytecode/util/Callback.makeXPathException (Ljava/lang/String;Ljava/lang/String;Ljava/lang/String;IZ)Lnet/sf/saxon/trans/XPathException;
    ATHROW
    GOTO L47
   L56
    SIPUSH 563
    INVOKESTATIC com/saxonica/ee/bytecode/util/ByteCodeTrace.trace (I)V
    ALOAD 4
    LDC "http://www.w3.org/XML/1998/namespace"
    INVOKEVIRTUAL java/lang/String.equals (Ljava/lang/Object;)Z
    ALOAD 5
    LDC "xml"
    INVOKEVIRTUAL java/lang/String.equals (Ljava/lang/Object;)Z
    IF_ICMPEQ L57
    ALOAD 5
    ALOAD 4
    ICONST_1
    LDC "file:/Users/mike/w3c/xslt30-test-B/tests/attr/avt/avt-2201.xsl"
    BIPUSH 33
    INVOKESTATIC com/saxonica/ee/bytecode/util/Callback.makeXmlNamespaceException (Ljava/lang/String;Ljava/lang/String;ZLjava/lang/String;I)Lnet/sf/saxon/trans/XPathException;
    ATHROW
   L57
    SIPUSH 564
    INVOKESTATIC com/saxonica/ee/bytecode/util/ByteCodeTrace.trace (I)V
    NEW net/sf/saxon/om/FingerprintedQName
    DUP
    ALOAD 5
    ALOAD 4
    INVOKEVIRTUAL java/lang/Object.toString ()Ljava/lang/String;
    ALOAD 3
    INVOKESPECIAL net/sf/saxon/om/FingerprintedQName.<init> (Ljava/lang/String;Ljava/lang/String;Ljava/lang/String;)V
   L47
    SIPUSH 565
    INVOKESTATIC com/saxonica/ee/bytecode/util/ByteCodeTrace.trace (I)V
    GETSTATIC EE__Slash__267119518863.nUntyped269 : Lnet/sf/saxon/type/Untyped;
    GETSTATIC EE__Slash__267119518863.nAttributeLocation279 : Lnet/sf/saxon/style/ExpressionContext$AttributeLocation;
    ICONST_0
    INVOKEINTERFACE net/sf/saxon/event/Receiver.startElement (Lnet/sf/saxon/om/NodeName;Lnet/sf/saxon/type/SchemaType;Lnet/sf/saxon/expr/parser/Location;I)V
    ALOAD 2
    INVOKEINTERFACE net/sf/saxon/event/Receiver.endElement ()V
   L58
    LDC "FixedElement-aa"
    INVOKESTATIC com/saxonica/ee/bytecode/util/ByteCodeTrace.showMessage (Ljava/lang/String;)V
   L59
    LDC "ElementCreator-push"
    INVOKESTATIC com/saxonica/ee/bytecode/util/ByteCodeTrace.showMessage (Ljava/lang/String;)V
    LINENUMBER 40 L60
    ALOAD 2
    DUP
    LDC "Receiver: "
    SWAP
    DUP
    IFNULL L61
    INVOKEVIRTUAL java/lang/Object.toString ()Ljava/lang/String;
    INVOKESTATIC com/saxonica/ee/bytecode/util/ByteCodeTrace.showObjectVariable (Ljava/lang/String;Ljava/lang/String;)V
    GOTO L62
   L61
    SIPUSH 566
    INVOKESTATIC com/saxonica/ee/bytecode/util/ByteCodeTrace.trace (I)V
    POP
    LDC "null"
    INVOKESTATIC com/saxonica/ee/bytecode/util/ByteCodeTrace.showObjectVariable (Ljava/lang/String;Ljava/lang/String;)V
   L62
    SIPUSH 567
    INVOKESTATIC com/saxonica/ee/bytecode/util/ByteCodeTrace.trace (I)V
    INVOKEINTERFACE net/sf/saxon/event/Receiver.getSystemId ()Ljava/lang/String;
    IFNONNULL L63
    ALOAD 2
    LDC "file:/Users/mike/w3c/xslt30-test-B/tests/attr/avt/avt-2201.xsl"
    INVOKEINTERFACE net/sf/saxon/event/Receiver.setSystemId (Ljava/lang/String;)V
   L63
    SIPUSH 568
    INVOKESTATIC com/saxonica/ee/bytecode/util/ByteCodeTrace.trace (I)V
    ALOAD 2
    GETSTATIC EE__Slash__267119518863.nNoNamespaceName271 : Lnet/sf/saxon/om/NoNamespaceName;
    GETSTATIC EE__Slash__267119518863.nUntyped269 : Lnet/sf/saxon/type/Untyped;
    GETSTATIC EE__Slash__267119518863.nLiteralResultElement280 : Lnet/sf/saxon/style/LiteralResultElement;
    ICONST_0
    INVOKEINTERFACE net/sf/saxon/event/Receiver.startElement (Lnet/sf/saxon/om/NodeName;Lnet/sf/saxon/type/SchemaType;Lnet/sf/saxon/expr/parser/Location;I)V
    ALOAD 2
    GETSTATIC EE__Slash__267119518863.nFingerprintedQName272 : Lnet/sf/saxon/om/FingerprintedQName;
    GETSTATIC net/sf/saxon/type/BuiltInAtomicType.UNTYPED_ATOMIC : Lnet/sf/saxon/type/BuiltInAtomicType;
   L64
    LDC "LiteralCompiler-Primitive"
    INVOKESTATIC com/saxonica/ee/bytecode/util/ByteCodeTrace.showMessage (Ljava/lang/String;)V
    LDC "rtf"
    GETSTATIC EE__Slash__267119518863.nLiteralResultElement280 : Lnet/sf/saxon/style/LiteralResultElement;
    ICONST_0
    INVOKEINTERFACE net/sf/saxon/event/Receiver.attribute (Lnet/sf/saxon/om/NodeName;Lnet/sf/saxon/type/SimpleType;Ljava/lang/CharSequence;Lnet/sf/saxon/expr/parser/Location;I)V
    ALOAD 2
    INVOKEINTERFACE net/sf/saxon/event/Receiver.endElement ()V
   L65
    LDC "FixedElement-bb"
    INVOKESTATIC com/saxonica/ee/bytecode/util/ByteCodeTrace.showMessage (Ljava/lang/String;)V
   L66
    LDC "ElementCreator-push"
    INVOKESTATIC com/saxonica/ee/bytecode/util/ByteCodeTrace.showMessage (Ljava/lang/String;)V
    LINENUMBER 44 L67
    ALOAD 2
    DUP
    LDC "Receiver: "
    SWAP
    DUP
    IFNULL L68
    INVOKEVIRTUAL java/lang/Object.toString ()Ljava/lang/String;
    INVOKESTATIC com/saxonica/ee/bytecode/util/ByteCodeTrace.showObjectVariable (Ljava/lang/String;Ljava/lang/String;)V
    GOTO L69
   L68
    SIPUSH 569
    INVOKESTATIC com/saxonica/ee/bytecode/util/ByteCodeTrace.trace (I)V
    POP
    LDC "null"
    INVOKESTATIC com/saxonica/ee/bytecode/util/ByteCodeTrace.showObjectVariable (Ljava/lang/String;Ljava/lang/String;)V
   L69
    SIPUSH 570
    INVOKESTATIC com/saxonica/ee/bytecode/util/ByteCodeTrace.trace (I)V
    INVOKEINTERFACE net/sf/saxon/event/Receiver.getSystemId ()Ljava/lang/String;
    IFNONNULL L70
    ALOAD 2
    LDC "file:/Users/mike/w3c/xslt30-test-B/tests/attr/avt/avt-2201.xsl"
    INVOKEINTERFACE net/sf/saxon/event/Receiver.setSystemId (Ljava/lang/String;)V
   L70
    SIPUSH 571
    INVOKESTATIC com/saxonica/ee/bytecode/util/ByteCodeTrace.trace (I)V
    ALOAD 2
    GETSTATIC EE__Slash__267119518863.nNoNamespaceName273 : Lnet/sf/saxon/om/NoNamespaceName;
    GETSTATIC EE__Slash__267119518863.nUntyped269 : Lnet/sf/saxon/type/Untyped;
    GETSTATIC EE__Slash__267119518863.nAttributeLocation281 : Lnet/sf/saxon/style/ExpressionContext$AttributeLocation;
    ICONST_0
    INVOKEINTERFACE net/sf/saxon/event/Receiver.startElement (Lnet/sf/saxon/om/NodeName;Lnet/sf/saxon/type/SchemaType;Lnet/sf/saxon/expr/parser/Location;I)V
    ALOAD 2
    GETSTATIC EE__Slash__267119518863.nFingerprintedQName282 : Lnet/sf/saxon/om/FingerprintedQName;
    GETSTATIC net/sf/saxon/type/BuiltInAtomicType.UNTYPED_ATOMIC : Lnet/sf/saxon/type/BuiltInAtomicType;
   L71
    LDC "LiteralCompiler-Primitive"
    INVOKESTATIC com/saxonica/ee/bytecode/util/ByteCodeTrace.showMessage (Ljava/lang/String;)V
    LDC ""
    GETSTATIC EE__Slash__267119518863.nAttributeLocation281 : Lnet/sf/saxon/style/ExpressionContext$AttributeLocation;
    ICONST_0
    INVOKEINTERFACE net/sf/saxon/event/Receiver.attribute (Lnet/sf/saxon/om/NodeName;Lnet/sf/saxon/type/SimpleType;Ljava/lang/CharSequence;Lnet/sf/saxon/expr/parser/Location;I)V
    ALOAD 2
    INVOKEINTERFACE net/sf/saxon/event/Receiver.endElement ()V
   L72
    LDC "ComputedElement-push"
    INVOKESTATIC com/saxonica/ee/bytecode/util/ByteCodeTrace.showMessage (Ljava/lang/String;)V
   L73
    LDC "ElementCreator-push"
    INVOKESTATIC com/saxonica/ee/bytecode/util/ByteCodeTrace.showMessage (Ljava/lang/String;)V
    LINENUMBER 48 L74
    ALOAD 2
    DUP
    LDC "Receiver: "
    SWAP
    DUP
    IFNULL L75
    INVOKEVIRTUAL java/lang/Object.toString ()Ljava/lang/String;
    INVOKESTATIC com/saxonica/ee/bytecode/util/ByteCodeTrace.showObjectVariable (Ljava/lang/String;Ljava/lang/String;)V
    GOTO L76
   L75
    SIPUSH 572
    INVOKESTATIC com/saxonica/ee/bytecode/util/ByteCodeTrace.trace (I)V
    POP
    LDC "null"
    INVOKESTATIC com/saxonica/ee/bytecode/util/ByteCodeTrace.showObjectVariable (Ljava/lang/String;Ljava/lang/String;)V
   L76
    SIPUSH 573
    INVOKESTATIC com/saxonica/ee/bytecode/util/ByteCodeTrace.trace (I)V
    INVOKEINTERFACE net/sf/saxon/event/Receiver.getSystemId ()Ljava/lang/String;
    IFNONNULL L77
    ALOAD 2
    LDC "file:/Users/mike/w3c/xslt30-test-B/tests/attr/avt/avt-2201.xsl"
    INVOKEINTERFACE net/sf/saxon/event/Receiver.setSystemId (Ljava/lang/String;)V
   L77
    SIPUSH 574
    INVOKESTATIC com/saxonica/ee/bytecode/util/ByteCodeTrace.trace (I)V
    ALOAD 2
    ACONST_NULL
    ASTORE 4
   L78
    LDC "LiteralCompiler-item"
    INVOKESTATIC com/saxonica/ee/bytecode/util/ByteCodeTrace.showMessage (Ljava/lang/String;)V
    GETSTATIC EE__Slash__267119518863.nStringValue283 : Lnet/sf/saxon/value/StringValue;
    CHECKCAST net/sf/saxon/value/AtomicValue
    DUP
    IFNONNULL L79
    POP
    LDC "Invalid element name (empty sequence)"
    LDC "XTDE0820"
    LDC "file:/Users/mike/w3c/xslt30-test-B/tests/attr/avt/avt-2201.xsl"
    BIPUSH 48
    ICONST_0
    INVOKESTATIC com/saxonica/ee/bytecode/util/Callback.makeXPathException (Ljava/lang/String;Ljava/lang/String;Ljava/lang/String;IZ)Lnet/sf/saxon/trans/XPathException;
    ATHROW
    GOTO L80
   L79
    SIPUSH 575
    INVOKESTATIC com/saxonica/ee/bytecode/util/ByteCodeTrace.trace (I)V
    DUP
    INSTANCEOF net/sf/saxon/value/StringValue
    IFEQ L81
    INVOKEVIRTUAL net/sf/saxon/value/AtomicValue.getStringValueCS ()Ljava/lang/CharSequence;
    INVOKESTATIC net/sf/saxon/value/Whitespace.trimWhitespace (Ljava/lang/CharSequence;)Ljava/lang/CharSequence;
    ASTORE 8
    ALOAD 8
    TRYCATCHBLOCK L82 L83 L84 net/sf/saxon/om/QNameException
   L82
    SIPUSH 576
    INVOKESTATIC com/saxonica/ee/bytecode/util/ByteCodeTrace.trace (I)V
    INVOKESTATIC net/sf/saxon/om/NameChecker.getQNameParts (Ljava/lang/CharSequence;)[Ljava/lang/String;
   L83
    SIPUSH 577
    INVOKESTATIC com/saxonica/ee/bytecode/util/ByteCodeTrace.trace (I)V
    DUP
    ICONST_0
    AALOAD
    ASTORE 5
    ICONST_1
    AALOAD
    ASTORE 3
    GOTO L85
   L84
    SIPUSH 578
    INVOKESTATIC com/saxonica/ee/bytecode/util/ByteCodeTrace.trace (I)V
    LDC "Invalid element name: <{$1}>"
    ALOAD 8
    INVOKESTATIC com/saxonica/ee/bytecode/util/Callback.makeMessageFromTemplate (Ljava/lang/String;Ljava/lang/CharSequence;)Ljava/lang/String;
    LDC "XTDE0820"
    LDC "file:/Users/mike/w3c/xslt30-test-B/tests/attr/avt/avt-2201.xsl"
    BIPUSH 48
    ICONST_0
    INVOKESTATIC com/saxonica/ee/bytecode/util/Callback.makeXPathException (Ljava/lang/String;Ljava/lang/String;Ljava/lang/String;IZ)Lnet/sf/saxon/trans/XPathException;
    ATHROW
   L81
    SIPUSH 579
    INVOKESTATIC com/saxonica/ee/bytecode/util/ByteCodeTrace.trace (I)V
    LDC "Computed element name has incorrect type"
    LDC "XTDE0820"
    LDC "file:/Users/mike/w3c/xslt30-test-B/tests/attr/avt/avt-2201.xsl"
    BIPUSH 48
    ICONST_1
    INVOKESTATIC com/saxonica/ee/bytecode/util/Callback.makeXPathException (Ljava/lang/String;Ljava/lang/String;Ljava/lang/String;IZ)Lnet/sf/saxon/trans/XPathException;
    ATHROW
    GOTO L80
   L85
    SIPUSH 580
    INVOKESTATIC com/saxonica/ee/bytecode/util/ByteCodeTrace.trace (I)V
    ALOAD 4
    IFNONNULL L86
    GETSTATIC EE__Slash__267119518863.nRetainedStaticContext284 : Lnet/sf/saxon/expr/parser/RetainedStaticContext;
    ALOAD 5
    ICONST_1
    INVOKEINTERFACE net/sf/saxon/om/NamespaceResolver.getURIForPrefix (Ljava/lang/String;Z)Ljava/lang/String;
    DUP
    IFNONNULL L87
    POP
    LDC "Undeclared prefix in element name: {$1}"
    ALOAD 5
    INVOKESTATIC com/saxonica/ee/bytecode/util/Callback.makeMessageFromTemplate (Ljava/lang/String;Ljava/lang/CharSequence;)Ljava/lang/String;
    LDC "XTDE0830"
    LDC "file:/Users/mike/w3c/xslt30-test-B/tests/attr/avt/avt-2201.xsl"
    BIPUSH 48
    ICONST_0
    INVOKESTATIC com/saxonica/ee/bytecode/util/Callback.makeXPathException (Ljava/lang/String;Ljava/lang/String;Ljava/lang/String;IZ)Lnet/sf/saxon/trans/XPathException;
    ATHROW
    GOTO L80
   L87
    SIPUSH 581
    INVOKESTATIC com/saxonica/ee/bytecode/util/ByteCodeTrace.trace (I)V
    ASTORE 4
   L86
    SIPUSH 582
    INVOKESTATIC com/saxonica/ee/bytecode/util/ByteCodeTrace.trace (I)V
   L88
    SIPUSH 583
    INVOKESTATIC com/saxonica/ee/bytecode/util/ByteCodeTrace.trace (I)V
    ALOAD 4
    LDC "http://www.w3.org/2000/xmlns/"
    INVOKEVIRTUAL java/lang/String.equals (Ljava/lang/Object;)Z
    IFEQ L89
    LDC "Cannot create element in namespace {$1}"
    ALOAD 4
    INVOKESTATIC com/saxonica/ee/bytecode/util/Callback.makeMessageFromTemplate (Ljava/lang/String;Ljava/lang/CharSequence;)Ljava/lang/String;
    LDC "XTDE0835"
    LDC "file:/Users/mike/w3c/xslt30-test-B/tests/attr/avt/avt-2201.xsl"
    BIPUSH 48
    ICONST_0
    INVOKESTATIC com/saxonica/ee/bytecode/util/Callback.makeXPathException (Ljava/lang/String;Ljava/lang/String;Ljava/lang/String;IZ)Lnet/sf/saxon/trans/XPathException;
    ATHROW
    GOTO L80
   L89
    SIPUSH 584
    INVOKESTATIC com/saxonica/ee/bytecode/util/ByteCodeTrace.trace (I)V
    ALOAD 4
    LDC "http://www.w3.org/XML/1998/namespace"
    INVOKEVIRTUAL java/lang/String.equals (Ljava/lang/Object;)Z
    ALOAD 5
    LDC "xml"
    INVOKEVIRTUAL java/lang/String.equals (Ljava/lang/Object;)Z
    IF_ICMPEQ L90
    ALOAD 5
    ALOAD 4
    ICONST_1
    LDC "file:/Users/mike/w3c/xslt30-test-B/tests/attr/avt/avt-2201.xsl"
    BIPUSH 48
    INVOKESTATIC com/saxonica/ee/bytecode/util/Callback.makeXmlNamespaceException (Ljava/lang/String;Ljava/lang/String;ZLjava/lang/String;I)Lnet/sf/saxon/trans/XPathException;
    ATHROW
   L90
    SIPUSH 585
    INVOKESTATIC com/saxonica/ee/bytecode/util/ByteCodeTrace.trace (I)V
    NEW net/sf/saxon/om/FingerprintedQName
    DUP
    ALOAD 5
    ALOAD 4
    INVOKEVIRTUAL java/lang/Object.toString ()Ljava/lang/String;
    ALOAD 3
    INVOKESPECIAL net/sf/saxon/om/FingerprintedQName.<init> (Ljava/lang/String;Ljava/lang/String;Ljava/lang/String;)V
   L80
    SIPUSH 586
    INVOKESTATIC com/saxonica/ee/bytecode/util/ByteCodeTrace.trace (I)V
    GETSTATIC EE__Slash__267119518863.nUntyped269 : Lnet/sf/saxon/type/Untyped;
    GETSTATIC EE__Slash__267119518863.nAttributeLocation285 : Lnet/sf/saxon/style/ExpressionContext$AttributeLocation;
    ICONST_0
    INVOKEINTERFACE net/sf/saxon/event/Receiver.startElement (Lnet/sf/saxon/om/NodeName;Lnet/sf/saxon/type/SchemaType;Lnet/sf/saxon/expr/parser/Location;I)V
    ALOAD 2
    INVOKEINTERFACE net/sf/saxon/event/Receiver.endElement ()V
    ALOAD 2
    INVOKEINTERFACE net/sf/saxon/event/Receiver.endElement ()V
    RETURN
    MAXSTACK = 0
    MAXLOCALS = 0
}

  // access flags 0x9
  public static Lnet/sf/saxon/om/FingerprintedQName; nFingerprintedQName282

  // access flags 0x9
  public static Lnet/sf/saxon/om/FingerprintedQName; nFingerprintedQName272

  // access flags 0x9
  public static Lnet/sf/saxon/om/FingerprintedQName; nFingerprintedQName275

  // access flags 0x9
  public static Lnet/sf/saxon/style/ExpressionContext$AttributeLocation; nAttributeLocation274

  // access flags 0x9
  public static Lnet/sf/saxon/style/ExpressionContext$AttributeLocation; nAttributeLocation277

  // access flags 0x9
  public static Lnet/sf/saxon/value/StringValue; nStringValue278

  // access flags 0x9
  public static Lnet/sf/saxon/style/ExpressionContext$AttributeLocation; nAttributeLocation285

  // access flags 0x9
  public static Lnet/sf/saxon/value/StringValue; nStringValue283

  // access flags 0x9
  public static Lnet/sf/saxon/style/ExpressionContext$AttributeLocation; nAttributeLocation281

  // access flags 0x9
  public static Lnet/sf/saxon/style/ExpressionContext$AttributeLocation; nAttributeLocation279

  // access flags 0x9
  public static Lnet/sf/saxon/value/StringValue; nStringValue276

  // access flags 0x9
  public static Lnet/sf/saxon/style/LiteralResultElement; nLiteralResultElement270

  // access flags 0x9
  public static Lnet/sf/saxon/type/Untyped; nUntyped269

  // access flags 0x9
  public static Lnet/sf/saxon/expr/parser/RetainedStaticContext; nRetainedStaticContext284

  // access flags 0x9
  public static Lnet/sf/saxon/om/NoNamespaceName; nNoNamespaceName268

  // access flags 0x9
  public static Lnet/sf/saxon/om/NoNamespaceName; nNoNamespaceName273

  // access flags 0x9
  public static Lnet/sf/saxon/style/LiteralResultElement; nLiteralResultElement280

  // access flags 0x9
  public static Lnet/sf/saxon/om/NoNamespaceName; nNoNamespaceName271
}
