// class version 49.0 (49)
// access flags 0x1
public class EE_doc_1061582593918 extends com/saxonica/ee/bytecode/GeneratedCode  {


  // access flags 0x1
  public <init>()V
    LINENUMBER 8 L0
    ALOAD 0
    INVOKESPECIAL com/saxonica/ee/bytecode/GeneratedCode.<init> ()V
    RETURN
    MAXSTACK = 0
    MAXLOCALS = 0

  // access flags 0x1
  public process(Lnet/sf/saxon/expr/XPathContext;)V throws net/sf/saxon/trans/XPathException 
    ALOAD 1
    INVOKEINTERFACE net/sf/saxon/expr/XPathContext.getReceiver ()Lnet/sf/saxon/event/SequenceReceiver;
    ASTORE 2
    LINENUMBER 8 L0
   L1
    LDC "CopyOf - Push"
    INVOKESTATIC com/saxonica/ee/bytecode/util/ByteCodeTrace.showMessage (Ljava/lang/String;)V
    ALOAD 1
    INVOKEINTERFACE net/sf/saxon/expr/XPathContext.getContextItem ()Lnet/sf/saxon/om/Item;
    ASTORE 3
   L2
    LDC "CopyOf - Element"
    INVOKESTATIC com/saxonica/ee/bytecode/util/ByteCodeTrace.showMessage (Ljava/lang/String;)V
    ALOAD 1
    INVOKEINTERFACE net/sf/saxon/expr/XPathContext.getConfiguration ()Lnet/sf/saxon/Configuration;
    ALOAD 2
    NEW net/sf/saxon/lib/ParseOptions
    DUP
    INVOKESPECIAL net/sf/saxon/lib/ParseOptions.<init> ()V
    DUP
    ICONST_4
    INVOKEVIRTUAL net/sf/saxon/lib/ParseOptions.setSchemaValidationMode (I)V
    DUP
    NEW net/sf/saxon/om/NameOfNode
    DUP
    ALOAD 3
    CHECKCAST net/sf/saxon/om/NodeInfo
    INVOKESPECIAL net/sf/saxon/om/NameOfNode.<init> (Lnet/sf/saxon/om/NodeInfo;)V
    INVOKEINTERFACE net/sf/saxon/om/NodeName.getStructuredQName ()Lnet/sf/saxon/om/StructuredQName;
    INVOKEVIRTUAL net/sf/saxon/lib/ParseOptions.setTopLevelElement (Lnet/sf/saxon/om/StructuredQName;)V
    GETSTATIC EE_doc_1061582593918.nNestedLocation107 : Lnet/sf/saxon/expr/parser/XPathParser$NestedLocation;
    INVOKEVIRTUAL net/sf/saxon/Configuration.getElementValidator (Lnet/sf/saxon/event/SequenceReceiver;Lnet/sf/saxon/lib/ParseOptions;Lnet/sf/saxon/expr/parser/Location;)Lnet/sf/saxon/event/SequenceReceiver;
    ASTORE 4
    ALOAD 3
    CHECKCAST net/sf/saxon/om/NodeInfo
    ALOAD 4
    BIPUSH 6
    GETSTATIC EE_doc_1061582593918.nNestedLocation107 : Lnet/sf/saxon/expr/parser/XPathParser$NestedLocation;
    INVOKEINTERFACE net/sf/saxon/om/NodeInfo.copy (Lnet/sf/saxon/event/Receiver;ILnet/sf/saxon/expr/parser/Location;)V
    RETURN
    MAXSTACK = 0
    MAXLOCALS = 0
}

  // access flags 0x9
  public static Lnet/sf/saxon/expr/parser/XPathParser$NestedLocation; nNestedLocation107
}
