// class version 49.0 (49)
// access flags 0x1
public class EE_doc_9947590721 extends com/saxonica/ee/bytecode/GeneratedCode  {


  // access flags 0x1
  public <init>()V
    LINENUMBER 16 L0
    ALOAD 0
    INVOKESPECIAL com/saxonica/ee/bytecode/GeneratedCode.<init> ()V
    RETURN
    MAXSTACK = 0
    MAXLOCALS = 0

  // access flags 0x1
  public process(Lnet/sf/saxon/expr/XPathContext;)V throws net/sf/saxon/trans/XPathException 
    ALOAD 1
    INVOKEINTERFACE net/sf/saxon/expr/XPathContext.getReceiver ()Lnet/sf/saxon/event/SequenceReceiver;
    ASTORE 2
    LINENUMBER 16 L0
   L1
    LDC "FixedElement-output"
    INVOKESTATIC com/saxonica/ee/bytecode/util/ByteCodeTrace.showMessage (Ljava/lang/String;)V
   L2
    LDC "ElementCreator-push"
    INVOKESTATIC com/saxonica/ee/bytecode/util/ByteCodeTrace.showMessage (Ljava/lang/String;)V
    ALOAD 2
    DUP
    LDC "Receiver: "
    SWAP
    DUP
    IFNULL L3
    INVOKEVIRTUAL java/lang/Object.toString ()Ljava/lang/String;
    INVOKESTATIC com/saxonica/ee/bytecode/util/ByteCodeTrace.showObjectVariable (Ljava/lang/String;Ljava/lang/String;)V
    GOTO L4
   L3
    BIPUSH 13
    INVOKESTATIC com/saxonica/ee/bytecode/util/ByteCodeTrace.trace (I)V
    POP
    LDC "null"
    INVOKESTATIC com/saxonica/ee/bytecode/util/ByteCodeTrace.showObjectVariable (Ljava/lang/String;Ljava/lang/String;)V
   L4
    BIPUSH 14
    INVOKESTATIC com/saxonica/ee/bytecode/util/ByteCodeTrace.trace (I)V
    INVOKEINTERFACE net/sf/saxon/event/Receiver.getSystemId ()Ljava/lang/String;
    IFNONNULL L5
    ALOAD 2
    LDC "file:/Users/mike/w3c/xslt30-test-B/tests/attr/avt/avt-0201.xsl"
    INVOKEINTERFACE net/sf/saxon/event/Receiver.setSystemId (Ljava/lang/String;)V
   L5
    BIPUSH 15
    INVOKESTATIC com/saxonica/ee/bytecode/util/ByteCodeTrace.trace (I)V
    ALOAD 2
    GETSTATIC EE_doc_9947590721.nNoNamespaceName10 : Lnet/sf/saxon/om/NoNamespaceName;
    GETSTATIC EE_doc_9947590721.nUntyped11 : Lnet/sf/saxon/type/Untyped;
    GETSTATIC EE_doc_9947590721.nLiteralResultElement12 : Lnet/sf/saxon/style/LiteralResultElement;
    ICONST_0
    INVOKEINTERFACE net/sf/saxon/event/Receiver.startElement (Lnet/sf/saxon/om/NodeName;Lnet/sf/saxon/type/SchemaType;Lnet/sf/saxon/expr/parser/Location;I)V
   L6
    LDC "BlockCompiler-Push"
    INVOKESTATIC com/saxonica/ee/bytecode/util/ByteCodeTrace.showMessage (Ljava/lang/String;)V
   L7
    LDC "FixedElement-out"
    INVOKESTATIC com/saxonica/ee/bytecode/util/ByteCodeTrace.showMessage (Ljava/lang/String;)V
   L8
    LDC "ElementCreator-push"
    INVOKESTATIC com/saxonica/ee/bytecode/util/ByteCodeTrace.showMessage (Ljava/lang/String;)V
    ALOAD 2
    DUP
    LDC "Receiver: "
    SWAP
    DUP
    IFNULL L9
    INVOKEVIRTUAL java/lang/Object.toString ()Ljava/lang/String;
    INVOKESTATIC com/saxonica/ee/bytecode/util/ByteCodeTrace.showObjectVariable (Ljava/lang/String;Ljava/lang/String;)V
    GOTO L10
   L9
    BIPUSH 16
    INVOKESTATIC com/saxonica/ee/bytecode/util/ByteCodeTrace.trace (I)V
    POP
    LDC "null"
    INVOKESTATIC com/saxonica/ee/bytecode/util/ByteCodeTrace.showObjectVariable (Ljava/lang/String;Ljava/lang/String;)V
   L10
    BIPUSH 17
    INVOKESTATIC com/saxonica/ee/bytecode/util/ByteCodeTrace.trace (I)V
    INVOKEINTERFACE net/sf/saxon/event/Receiver.getSystemId ()Ljava/lang/String;
    IFNONNULL L11
    ALOAD 2
    LDC "file:/Users/mike/w3c/xslt30-test-B/tests/attr/avt/avt-0201.xsl"
    INVOKEINTERFACE net/sf/saxon/event/Receiver.setSystemId (Ljava/lang/String;)V
   L11
    BIPUSH 18
    INVOKESTATIC com/saxonica/ee/bytecode/util/ByteCodeTrace.trace (I)V
    ALOAD 2
    GETSTATIC EE_doc_9947590721.nNoNamespaceName13 : Lnet/sf/saxon/om/NoNamespaceName;
    GETSTATIC EE_doc_9947590721.nUntyped11 : Lnet/sf/saxon/type/Untyped;
    GETSTATIC EE_doc_9947590721.nLiteralResultElement12 : Lnet/sf/saxon/style/LiteralResultElement;
    ICONST_0
    INVOKEINTERFACE net/sf/saxon/event/Receiver.startElement (Lnet/sf/saxon/om/NodeName;Lnet/sf/saxon/type/SchemaType;Lnet/sf/saxon/expr/parser/Location;I)V
    ALOAD 2
    GETSTATIC EE_doc_9947590721.nFingerprintedQName14 : Lnet/sf/saxon/om/FingerprintedQName;
    GETSTATIC net/sf/saxon/type/BuiltInAtomicType.UNTYPED_ATOMIC : Lnet/sf/saxon/type/BuiltInAtomicType;
   L12
    LDC "VariableReferenceCompiler-Item"
    INVOKESTATIC com/saxonica/ee/bytecode/util/ByteCodeTrace.showMessage (Ljava/lang/String;)V
    ALOAD 1
    DUP
    ICONST_0
    INVOKEINTERFACE net/sf/saxon/expr/XPathContext.getTargetComponent (I)Lnet/sf/saxon/expr/Component;
    DUP
    INVOKEVIRTUAL net/sf/saxon/expr/Component.getCode ()Lnet/sf/saxon/expr/instruct/ComponentCode;
    CHECKCAST net/sf/saxon/expr/instruct/GlobalVariable
    DUP_X2
    POP
    INVOKEVIRTUAL net/sf/saxon/expr/instruct/GlobalVariable.evaluateVariable (Lnet/sf/saxon/expr/XPathContext;Lnet/sf/saxon/expr/Component;)Lnet/sf/saxon/om/Sequence;
    DUP
    INSTANCEOF net/sf/saxon/om/Item
    IFEQ L13
    CHECKCAST net/sf/saxon/om/Item
    GOTO L14
   L13
    BIPUSH 19
    INVOKESTATIC com/saxonica/ee/bytecode/util/ByteCodeTrace.trace (I)V
    INVOKESTATIC net/sf/saxon/om/SequenceTool.asItem (Lnet/sf/saxon/om/Sequence;)Lnet/sf/saxon/om/Item;
   L14
    BIPUSH 20
    INVOKESTATIC com/saxonica/ee/bytecode/util/ByteCodeTrace.trace (I)V
    CHECKCAST net/sf/saxon/value/StringValue
    INVOKEVIRTUAL net/sf/saxon/value/StringValue.getStringValueCS ()Ljava/lang/CharSequence;
    GETSTATIC EE_doc_9947590721.nLiteralResultElement12 : Lnet/sf/saxon/style/LiteralResultElement;
    ICONST_0
    INVOKEINTERFACE net/sf/saxon/event/Receiver.attribute (Lnet/sf/saxon/om/NodeName;Lnet/sf/saxon/type/SimpleType;Ljava/lang/CharSequence;Lnet/sf/saxon/expr/parser/Location;I)V
    ALOAD 2
    INVOKEINTERFACE net/sf/saxon/event/Receiver.endElement ()V
   L15
    LDC "FixedElement-out"
    INVOKESTATIC com/saxonica/ee/bytecode/util/ByteCodeTrace.showMessage (Ljava/lang/String;)V
   L16
    LDC "ElementCreator-push"
    INVOKESTATIC com/saxonica/ee/bytecode/util/ByteCodeTrace.showMessage (Ljava/lang/String;)V
    LINENUMBER 17 L17
    ALOAD 2
    DUP
    LDC "Receiver: "
    SWAP
    DUP
    IFNULL L18
    INVOKEVIRTUAL java/lang/Object.toString ()Ljava/lang/String;
    INVOKESTATIC com/saxonica/ee/bytecode/util/ByteCodeTrace.showObjectVariable (Ljava/lang/String;Ljava/lang/String;)V
    GOTO L19
   L18
    BIPUSH 21
    INVOKESTATIC com/saxonica/ee/bytecode/util/ByteCodeTrace.trace (I)V
    POP
    LDC "null"
    INVOKESTATIC com/saxonica/ee/bytecode/util/ByteCodeTrace.showObjectVariable (Ljava/lang/String;Ljava/lang/String;)V
   L19
    BIPUSH 22
    INVOKESTATIC com/saxonica/ee/bytecode/util/ByteCodeTrace.trace (I)V
    INVOKEINTERFACE net/sf/saxon/event/Receiver.getSystemId ()Ljava/lang/String;
    IFNONNULL L20
    ALOAD 2
    LDC "file:/Users/mike/w3c/xslt30-test-B/tests/attr/avt/avt-0201.xsl"
    INVOKEINTERFACE net/sf/saxon/event/Receiver.setSystemId (Ljava/lang/String;)V
   L20
    BIPUSH 23
    INVOKESTATIC com/saxonica/ee/bytecode/util/ByteCodeTrace.trace (I)V
    ALOAD 2
    GETSTATIC EE_doc_9947590721.nNoNamespaceName13 : Lnet/sf/saxon/om/NoNamespaceName;
    GETSTATIC EE_doc_9947590721.nUntyped11 : Lnet/sf/saxon/type/Untyped;
    GETSTATIC EE_doc_9947590721.nLiteralResultElement15 : Lnet/sf/saxon/style/LiteralResultElement;
    ICONST_0
    INVOKEINTERFACE net/sf/saxon/event/Receiver.startElement (Lnet/sf/saxon/om/NodeName;Lnet/sf/saxon/type/SchemaType;Lnet/sf/saxon/expr/parser/Location;I)V
    ALOAD 2
    GETSTATIC EE_doc_9947590721.nFingerprintedQName14 : Lnet/sf/saxon/om/FingerprintedQName;
    GETSTATIC net/sf/saxon/type/BuiltInAtomicType.UNTYPED_ATOMIC : Lnet/sf/saxon/type/BuiltInAtomicType;
   L21
    LDC "VariableReferenceCompiler-Item"
    INVOKESTATIC com/saxonica/ee/bytecode/util/ByteCodeTrace.showMessage (Ljava/lang/String;)V
    ALOAD 1
    DUP
    ICONST_1
    INVOKEINTERFACE net/sf/saxon/expr/XPathContext.getTargetComponent (I)Lnet/sf/saxon/expr/Component;
    DUP
    INVOKEVIRTUAL net/sf/saxon/expr/Component.getCode ()Lnet/sf/saxon/expr/instruct/ComponentCode;
    CHECKCAST net/sf/saxon/expr/instruct/GlobalVariable
    DUP_X2
    POP
    INVOKEVIRTUAL net/sf/saxon/expr/instruct/GlobalVariable.evaluateVariable (Lnet/sf/saxon/expr/XPathContext;Lnet/sf/saxon/expr/Component;)Lnet/sf/saxon/om/Sequence;
    DUP
    INSTANCEOF net/sf/saxon/om/Item
    IFEQ L22
    CHECKCAST net/sf/saxon/om/Item
    GOTO L23
   L22
    BIPUSH 24
    INVOKESTATIC com/saxonica/ee/bytecode/util/ByteCodeTrace.trace (I)V
    INVOKESTATIC net/sf/saxon/om/SequenceTool.asItem (Lnet/sf/saxon/om/Sequence;)Lnet/sf/saxon/om/Item;
   L23
    BIPUSH 25
    INVOKESTATIC com/saxonica/ee/bytecode/util/ByteCodeTrace.trace (I)V
    CHECKCAST net/sf/saxon/value/StringValue
    INVOKEVIRTUAL net/sf/saxon/value/StringValue.getStringValueCS ()Ljava/lang/CharSequence;
    GETSTATIC EE_doc_9947590721.nLiteralResultElement15 : Lnet/sf/saxon/style/LiteralResultElement;
    ICONST_0
    INVOKEINTERFACE net/sf/saxon/event/Receiver.attribute (Lnet/sf/saxon/om/NodeName;Lnet/sf/saxon/type/SimpleType;Ljava/lang/CharSequence;Lnet/sf/saxon/expr/parser/Location;I)V
    ALOAD 2
    INVOKEINTERFACE net/sf/saxon/event/Receiver.endElement ()V
    ALOAD 2
    INVOKEINTERFACE net/sf/saxon/event/Receiver.endElement ()V
    RETURN
    MAXSTACK = 0
    MAXLOCALS = 0
}

  // access flags 0x9
  public static Lnet/sf/saxon/om/FingerprintedQName; nFingerprintedQName14

  // access flags 0x9
  public static Lnet/sf/saxon/om/NoNamespaceName; nNoNamespaceName10

  // access flags 0x9
  public static Lnet/sf/saxon/om/NoNamespaceName; nNoNamespaceName13

  // access flags 0x9
  public static Lnet/sf/saxon/type/Untyped; nUntyped11

  // access flags 0x9
  public static Lnet/sf/saxon/style/LiteralResultElement; nLiteralResultElement15

  // access flags 0x9
  public static Lnet/sf/saxon/style/LiteralResultElement; nLiteralResultElement12
}
