// class version 49.0 (49)
// access flags 0x1
public class EE_doc_2141191031827 extends com/saxonica/ee/bytecode/GeneratedCode  {


  // access flags 0x1
  public <init>()V
    LINENUMBER 7 L0
    ALOAD 0
    INVOKESPECIAL com/saxonica/ee/bytecode/GeneratedCode.<init> ()V
    RETURN
    MAXSTACK = 0
    MAXLOCALS = 0

  // access flags 0x1
  public process(Lnet/sf/saxon/expr/XPathContext;)V throws net/sf/saxon/trans/XPathException 
    ALOAD 1
    INVOKEINTERFACE net/sf/saxon/expr/XPathContext.getReceiver ()Lnet/sf/saxon/event/SequenceReceiver;
    ASTORE 2
    LINENUMBER 7 L0
   L1
    LDC "FixedElement-doc"
    INVOKESTATIC com/saxonica/ee/bytecode/util/ByteCodeTrace.showMessage (Ljava/lang/String;)V
   L2
    LDC "ElementCreator-push"
    INVOKESTATIC com/saxonica/ee/bytecode/util/ByteCodeTrace.showMessage (Ljava/lang/String;)V
    ALOAD 2
    DUP
    LDC "Receiver: "
    SWAP
    DUP
    IFNULL L3
    INVOKEVIRTUAL java/lang/Object.toString ()Ljava/lang/String;
    INVOKESTATIC com/saxonica/ee/bytecode/util/ByteCodeTrace.showObjectVariable (Ljava/lang/String;Ljava/lang/String;)V
    GOTO L4
   L3
    SIPUSH 456
    INVOKESTATIC com/saxonica/ee/bytecode/util/ByteCodeTrace.trace (I)V
    POP
    LDC "null"
    INVOKESTATIC com/saxonica/ee/bytecode/util/ByteCodeTrace.showObjectVariable (Ljava/lang/String;Ljava/lang/String;)V
   L4
    SIPUSH 457
    INVOKESTATIC com/saxonica/ee/bytecode/util/ByteCodeTrace.trace (I)V
    INVOKEINTERFACE net/sf/saxon/event/Receiver.getSystemId ()Ljava/lang/String;
    IFNONNULL L5
    ALOAD 2
    LDC "file:/Users/mike/w3c/xslt30-test-B/tests/attr/avt/avt-1501.xsl"
    INVOKEINTERFACE net/sf/saxon/event/Receiver.setSystemId (Ljava/lang/String;)V
   L5
    SIPUSH 458
    INVOKESTATIC com/saxonica/ee/bytecode/util/ByteCodeTrace.trace (I)V
    ALOAD 2
    GETSTATIC EE_doc_2141191031827.nNoNamespaceName215 : Lnet/sf/saxon/om/NoNamespaceName;
    GETSTATIC EE_doc_2141191031827.nUntyped216 : Lnet/sf/saxon/type/Untyped;
    GETSTATIC EE_doc_2141191031827.nLiteralResultElement217 : Lnet/sf/saxon/style/LiteralResultElement;
    ICONST_0
    INVOKEINTERFACE net/sf/saxon/event/Receiver.startElement (Lnet/sf/saxon/om/NodeName;Lnet/sf/saxon/type/SchemaType;Lnet/sf/saxon/expr/parser/Location;I)V
   L6
    LDC "BlockCompiler-Push"
    INVOKESTATIC com/saxonica/ee/bytecode/util/ByteCodeTrace.showMessage (Ljava/lang/String;)V
   L7
    LDC "SimpleNodeConstructorCompiler-Push"
    INVOKESTATIC com/saxonica/ee/bytecode/util/ByteCodeTrace.showMessage (Ljava/lang/String;)V
    ALOAD 2
   L8
    LDC "LiteralCompiler-Primitive"
    INVOKESTATIC com/saxonica/ee/bytecode/util/ByteCodeTrace.showMessage (Ljava/lang/String;)V
    LDC ":\n    "
    GETSTATIC EE_doc_2141191031827.nLiteralResultElement217 : Lnet/sf/saxon/style/LiteralResultElement;
    ICONST_0
    INVOKEINTERFACE net/sf/saxon/event/Receiver.characters (Ljava/lang/CharSequence;Lnet/sf/saxon/expr/parser/Location;I)V
   L9
    LDC "SlashExpressionCompiler-Push"
    INVOKESTATIC com/saxonica/ee/bytecode/util/ByteCodeTrace.showMessage (Ljava/lang/String;)V
    LINENUMBER 8 L10
    ALOAD 1
    INVOKEINTERFACE net/sf/saxon/expr/XPathContext.newMinorContext ()Lnet/sf/saxon/expr/XPathContextMinor;
   L11
    LDC "SlashExpressionCompiler - newMinorContext"
    INVOKESTATIC com/saxonica/ee/bytecode/util/ByteCodeTrace.showMessage (Ljava/lang/String;)V
    ASTORE 3
    ALOAD 3
    NEW net/sf/saxon/om/FocusTrackingIterator
    DUP
   L12
    LDC "AxisExpressionCompiler - iterate"
    INVOKESTATIC com/saxonica/ee/bytecode/util/ByteCodeTrace.showMessage (Ljava/lang/String;)V
    ALOAD 1
    INVOKEINTERFACE net/sf/saxon/expr/XPathContext.getContextItem ()Lnet/sf/saxon/om/Item;
    CHECKCAST net/sf/saxon/om/NodeInfo
   L13
    LDC "AxisExpressionCompiler - static method: iterate"
    INVOKESTATIC com/saxonica/ee/bytecode/util/ByteCodeTrace.showMessage (Ljava/lang/String;)V
    ICONST_3
    GETSTATIC EE_doc_2141191031827.nNameTest218 : Lnet/sf/saxon/pattern/NameTest;
    LDC "calling iterateAxis"
    INVOKESTATIC com/saxonica/ee/bytecode/util/ByteCodeTrace.showMessage (Ljava/lang/String;)V
    INVOKEINTERFACE net/sf/saxon/om/NodeInfo.iterateAxis (BLnet/sf/saxon/pattern/NodeTest;)Lnet/sf/saxon/tree/iter/AxisIterator;
    LDC "returning axis iterator"
    INVOKESTATIC com/saxonica/ee/bytecode/util/ByteCodeTrace.showMessage (Ljava/lang/String;)V
    INVOKESPECIAL net/sf/saxon/om/FocusTrackingIterator.<init> (Lnet/sf/saxon/om/SequenceIterator;)V
    DUP
    ASTORE 4
    INVOKEINTERFACE net/sf/saxon/expr/XPathContext.setCurrentIterator (Lnet/sf/saxon/om/FocusIterator;)V
   L14
    SIPUSH 459
    INVOKESTATIC com/saxonica/ee/bytecode/util/ByteCodeTrace.trace (I)V
    ALOAD 4
    LDC "forEachSelectIterator"
    ALOAD 4
    INVOKEVIRTUAL java/lang/Object.toString ()Ljava/lang/String;
    INVOKESTATIC com/saxonica/ee/bytecode/util/ByteCodeTrace.showObjectVariable (Ljava/lang/String;Ljava/lang/String;)V
    INVOKEINTERFACE net/sf/saxon/om/SequenceIterator.next ()Lnet/sf/saxon/om/Item;
    IFNULL L15
   L16
    LDC "SlashExpressionCompiler - compileAction"
    INVOKESTATIC com/saxonica/ee/bytecode/util/ByteCodeTrace.showMessage (Ljava/lang/String;)V
   L17
    LDC "BlockCompiler-Push"
    INVOKESTATIC com/saxonica/ee/bytecode/util/ByteCodeTrace.showMessage (Ljava/lang/String;)V
   L18
    LDC "FixedElement-out"
    INVOKESTATIC com/saxonica/ee/bytecode/util/ByteCodeTrace.showMessage (Ljava/lang/String;)V
   L19
    LDC "ElementCreator-push"
    INVOKESTATIC com/saxonica/ee/bytecode/util/ByteCodeTrace.showMessage (Ljava/lang/String;)V
    LINENUMBER 9 L20
    ALOAD 2
    DUP
    LDC "Receiver: "
    SWAP
    DUP
    IFNULL L21
    INVOKEVIRTUAL java/lang/Object.toString ()Ljava/lang/String;
    INVOKESTATIC com/saxonica/ee/bytecode/util/ByteCodeTrace.showObjectVariable (Ljava/lang/String;Ljava/lang/String;)V
    GOTO L22
   L21
    SIPUSH 460
    INVOKESTATIC com/saxonica/ee/bytecode/util/ByteCodeTrace.trace (I)V
    POP
    LDC "null"
    INVOKESTATIC com/saxonica/ee/bytecode/util/ByteCodeTrace.showObjectVariable (Ljava/lang/String;Ljava/lang/String;)V
   L22
    SIPUSH 461
    INVOKESTATIC com/saxonica/ee/bytecode/util/ByteCodeTrace.trace (I)V
    INVOKEINTERFACE net/sf/saxon/event/Receiver.getSystemId ()Ljava/lang/String;
    IFNONNULL L23
    ALOAD 2
    LDC "file:/Users/mike/w3c/xslt30-test-B/tests/attr/avt/avt-1501.xsl"
    INVOKEINTERFACE net/sf/saxon/event/Receiver.setSystemId (Ljava/lang/String;)V
   L23
    SIPUSH 462
    INVOKESTATIC com/saxonica/ee/bytecode/util/ByteCodeTrace.trace (I)V
    ALOAD 2
    GETSTATIC EE_doc_2141191031827.nNoNamespaceName219 : Lnet/sf/saxon/om/NoNamespaceName;
    GETSTATIC EE_doc_2141191031827.nUntyped216 : Lnet/sf/saxon/type/Untyped;
    GETSTATIC EE_doc_2141191031827.nLiteralResultElement220 : Lnet/sf/saxon/style/LiteralResultElement;
    ICONST_0
    INVOKEINTERFACE net/sf/saxon/event/Receiver.startElement (Lnet/sf/saxon/om/NodeName;Lnet/sf/saxon/type/SchemaType;Lnet/sf/saxon/expr/parser/Location;I)V
    ALOAD 2
    GETSTATIC EE_doc_2141191031827.nFingerprintedQName221 : Lnet/sf/saxon/om/FingerprintedQName;
    GETSTATIC net/sf/saxon/type/BuiltInAtomicType.UNTYPED_ATOMIC : Lnet/sf/saxon/type/BuiltInAtomicType;
   L24
    LDC "Concat-item"
    INVOKESTATIC com/saxonica/ee/bytecode/util/ByteCodeTrace.showMessage (Ljava/lang/String;)V
    NEW net/sf/saxon/tree/util/FastStringBuffer
    DUP
    BIPUSH 64
    INVOKESPECIAL net/sf/saxon/tree/util/FastStringBuffer.<init> (I)V
    ASTORE 6
    ALOAD 6
   L25
    LDC "LiteralCompiler-Primitive"
    INVOKESTATIC com/saxonica/ee/bytecode/util/ByteCodeTrace.showMessage (Ljava/lang/String;)V
    LDC "position = "
    INVOKEVIRTUAL net/sf/saxon/tree/util/FastStringBuffer.append (Ljava/lang/CharSequence;)V
    ALOAD 6
   L26
    LDC "AtomicSequenceConverterCompiler-Item"
    INVOKESTATIC com/saxonica/ee/bytecode/util/ByteCodeTrace.showMessage (Ljava/lang/String;)V
   L27
    LDC "PositionCompiler-Int"
    INVOKESTATIC com/saxonica/ee/bytecode/util/ByteCodeTrace.showMessage (Ljava/lang/String;)V
    ALOAD 3
    INVOKEINTERFACE net/sf/saxon/expr/XPathContext.getCurrentIterator ()Lnet/sf/saxon/om/FocusIterator;
    INVOKEINTERFACE net/sf/saxon/om/FocusIterator.position ()I
    INVOKESTATIC java/lang/Integer.toString (I)Ljava/lang/String;
    INVOKEVIRTUAL net/sf/saxon/tree/util/FastStringBuffer.append (Ljava/lang/CharSequence;)V
    ALOAD 6
   L28
    LDC "LiteralCompiler-Primitive"
    INVOKESTATIC com/saxonica/ee/bytecode/util/ByteCodeTrace.showMessage (Ljava/lang/String;)V
    LDC ", last = "
    INVOKEVIRTUAL net/sf/saxon/tree/util/FastStringBuffer.append (Ljava/lang/CharSequence;)V
    ALOAD 6
   L29
    LDC "AtomicSequenceConverterCompiler-Item"
    INVOKESTATIC com/saxonica/ee/bytecode/util/ByteCodeTrace.showMessage (Ljava/lang/String;)V
   L30
    LDC "Last"
    INVOKESTATIC com/saxonica/ee/bytecode/util/ByteCodeTrace.showMessage (Ljava/lang/String;)V
    ALOAD 3
    INVOKEINTERFACE net/sf/saxon/expr/XPathContext.getLast ()I
    INVOKESTATIC java/lang/Integer.toString (I)Ljava/lang/String;
    INVOKEVIRTUAL net/sf/saxon/tree/util/FastStringBuffer.append (Ljava/lang/CharSequence;)V
    ALOAD 6
    INVOKEVIRTUAL net/sf/saxon/tree/util/FastStringBuffer.condense ()Ljava/lang/CharSequence;
    GETSTATIC EE_doc_2141191031827.nLiteralResultElement220 : Lnet/sf/saxon/style/LiteralResultElement;
    ICONST_0
    INVOKEINTERFACE net/sf/saxon/event/Receiver.attribute (Lnet/sf/saxon/om/NodeName;Lnet/sf/saxon/type/SimpleType;Ljava/lang/CharSequence;Lnet/sf/saxon/expr/parser/Location;I)V
    ALOAD 2
    INVOKEINTERFACE net/sf/saxon/event/Receiver.endElement ()V
   L31
    LDC "SimpleNodeConstructorCompiler-Push"
    INVOKESTATIC com/saxonica/ee/bytecode/util/ByteCodeTrace.showMessage (Ljava/lang/String;)V
    ALOAD 2
   L32
    LDC "LiteralCompiler-Primitive"
    INVOKESTATIC com/saxonica/ee/bytecode/util/ByteCodeTrace.showMessage (Ljava/lang/String;)V
    LINENUMBER 8 L33
    LDC ";\n    "
    GETSTATIC EE_doc_2141191031827.nXSLForEach222 : Lnet/sf/saxon/style/XSLForEach;
    ICONST_0
    INVOKEINTERFACE net/sf/saxon/event/Receiver.characters (Ljava/lang/CharSequence;Lnet/sf/saxon/expr/parser/Location;I)V
    GOTO L14
   L15
    SIPUSH 463
    INVOKESTATIC com/saxonica/ee/bytecode/util/ByteCodeTrace.trace (I)V
    ALOAD 2
    INVOKEINTERFACE net/sf/saxon/event/Receiver.endElement ()V
    RETURN
    MAXSTACK = 0
    MAXLOCALS = 0
}

  // access flags 0x9
  public static Lnet/sf/saxon/om/FingerprintedQName; nFingerprintedQName221

  // access flags 0x9
  public static Lnet/sf/saxon/om/NoNamespaceName; nNoNamespaceName215

  // access flags 0x9
  public static Lnet/sf/saxon/om/NoNamespaceName; nNoNamespaceName219

  // access flags 0x9
  public static Lnet/sf/saxon/type/Untyped; nUntyped216

  // access flags 0x9
  public static Lnet/sf/saxon/style/LiteralResultElement; nLiteralResultElement220

  // access flags 0x9
  public static Lnet/sf/saxon/style/XSLForEach; nXSLForEach222

  // access flags 0x9
  public static Lnet/sf/saxon/style/LiteralResultElement; nLiteralResultElement217

  // access flags 0x9
  public static Lnet/sf/saxon/pattern/NameTest; nNameTest218
}
