// class version 49.0 (49)
// access flags 0x1
public class EE_doc_1431443407612 extends com/saxonica/ee/bytecode/GeneratedCode  {


  // access flags 0x1
  public <init>()V
    ALOAD 0
    INVOKESPECIAL com/saxonica/ee/bytecode/GeneratedCode.<init> ()V
    RETURN
    MAXSTACK = 0
    MAXLOCALS = 0

  // access flags 0x1
  public process(Lnet/sf/saxon/expr/XPathContext;)V throws net/sf/saxon/trans/XPathException 
    ALOAD 1
    INVOKEINTERFACE net/sf/saxon/expr/XPathContext.getReceiver ()Lnet/sf/saxon/event/SequenceReceiver;
    ASTORE 2
   L0
    LDC "FixedElement-in"
    INVOKESTATIC com/saxonica/ee/bytecode/util/ByteCodeTrace.showMessage (Ljava/lang/String;)V
   L1
    LDC "ElementCreator-push"
    INVOKESTATIC com/saxonica/ee/bytecode/util/ByteCodeTrace.showMessage (Ljava/lang/String;)V
    ALOAD 2
    DUP
    LDC "Receiver: "
    SWAP
    DUP
    IFNULL L2
    INVOKEVIRTUAL java/lang/Object.toString ()Ljava/lang/String;
    INVOKESTATIC com/saxonica/ee/bytecode/util/ByteCodeTrace.showObjectVariable (Ljava/lang/String;Ljava/lang/String;)V
    GOTO L3
   L2
    SIPUSH 263
    INVOKESTATIC com/saxonica/ee/bytecode/util/ByteCodeTrace.trace (I)V
    POP
    LDC "null"
    INVOKESTATIC com/saxonica/ee/bytecode/util/ByteCodeTrace.showObjectVariable (Ljava/lang/String;Ljava/lang/String;)V
   L3
    SIPUSH 264
    INVOKESTATIC com/saxonica/ee/bytecode/util/ByteCodeTrace.trace (I)V
    INVOKEINTERFACE net/sf/saxon/event/Receiver.getSystemId ()Ljava/lang/String;
    IFNONNULL L4
    ALOAD 2
    LDC "file:/Users/mike/w3c/xslt30-test-B/tests/decl/context-item/context-item-018.xsl"
    INVOKEINTERFACE net/sf/saxon/event/Receiver.setSystemId (Ljava/lang/String;)V
   L4
    SIPUSH 265
    INVOKESTATIC com/saxonica/ee/bytecode/util/ByteCodeTrace.trace (I)V
    ALOAD 2
    GETSTATIC EE_doc_1431443407612.nNoNamespaceName144 : Lnet/sf/saxon/om/NoNamespaceName;
    GETSTATIC EE_doc_1431443407612.nUntyped145 : Lnet/sf/saxon/type/Untyped;
    GETSTATIC EE_doc_1431443407612.nExplicitLocation146 : Lnet/sf/saxon/expr/parser/ExplicitLocation;
    ICONST_0
    INVOKEINTERFACE net/sf/saxon/event/Receiver.startElement (Lnet/sf/saxon/om/NodeName;Lnet/sf/saxon/type/SchemaType;Lnet/sf/saxon/expr/parser/Location;I)V
   L5
    LDC "NextMatch-push"
    INVOKESTATIC com/saxonica/ee/bytecode/util/ByteCodeTrace.showMessage (Ljava/lang/String;)V
   L6
    LDC "compileParameterSet"
    INVOKESTATIC com/saxonica/ee/bytecode/util/ByteCodeTrace.showMessage (Ljava/lang/String;)V
    ACONST_NULL
    ASTORE 3
    ALOAD 1
    INVOKEINTERFACE net/sf/saxon/expr/XPathContext.getTunnelParameters ()Lnet/sf/saxon/expr/instruct/ParameterSet;
    ASTORE 5
    ALOAD 5
    IFNONNULL L7
   L8
    LDC "compileParameterSet"
    INVOKESTATIC com/saxonica/ee/bytecode/util/ByteCodeTrace.showMessage (Ljava/lang/String;)V
    ACONST_NULL
    GOTO L9
   L7
    SIPUSH 266
    INVOKESTATIC com/saxonica/ee/bytecode/util/ByteCodeTrace.trace (I)V
    NEW net/sf/saxon/expr/instruct/ParameterSet
    DUP
    ALOAD 5
    ICONST_0
    INVOKESPECIAL net/sf/saxon/expr/instruct/ParameterSet.<init> (Lnet/sf/saxon/expr/instruct/ParameterSet;I)V
   L9
    SIPUSH 267
    INVOKESTATIC com/saxonica/ee/bytecode/util/ByteCodeTrace.trace (I)V
    ASTORE 4
    ALOAD 1
    INVOKEINTERFACE net/sf/saxon/expr/XPathContext.getCurrentIterator ()Lnet/sf/saxon/om/FocusIterator;
    DUP
    IFNONNULL L10
    LDC "Cannot call xsl:next-match when there is no context item"
    LDC "XTDE0565"
    ACONST_NULL
    ICONST_M1
    ICONST_0
    INVOKESTATIC com/saxonica/ee/bytecode/util/Callback.makeXPathException (Ljava/lang/String;Ljava/lang/String;Ljava/lang/String;IZ)Lnet/sf/saxon/trans/XPathException;
    ATHROW
   L10
    SIPUSH 268
    INVOKESTATIC com/saxonica/ee/bytecode/util/ByteCodeTrace.trace (I)V
    INVOKEINTERFACE net/sf/saxon/om/FocusIterator.current ()Lnet/sf/saxon/om/Item;
    ASTORE 6
    ALOAD 1
    INVOKEINTERFACE net/sf/saxon/expr/XPathContext.getController ()Lnet/sf/saxon/Controller;
    INVOKEVIRTUAL net/sf/saxon/Controller.getRuleManager ()Lnet/sf/saxon/trans/RuleManager;
    ALOAD 6
    ALOAD 1
    INVOKEINTERFACE net/sf/saxon/expr/XPathContext.getCurrentTemplateRule ()Lnet/sf/saxon/trans/Rule;
    DUP
    IFNONNULL L11
    LDC "There is no current template rule"
    LDC "XTDE0560"
    ACONST_NULL
    ICONST_M1
    ICONST_0
    INVOKESTATIC com/saxonica/ee/bytecode/util/Callback.makeXPathException (Ljava/lang/String;Ljava/lang/String;Ljava/lang/String;IZ)Lnet/sf/saxon/trans/XPathException;
    ATHROW
   L11
    SIPUSH 269
    INVOKESTATIC com/saxonica/ee/bytecode/util/ByteCodeTrace.trace (I)V
    ALOAD 1
    INVOKEINTERFACE net/sf/saxon/expr/XPathContext.getCurrentMode ()Lnet/sf/saxon/expr/Component;
    DUP
    IFNONNULL L12
    POP
    ALOAD 1
    INVOKEINTERFACE net/sf/saxon/expr/XPathContext.getController ()Lnet/sf/saxon/Controller;
    INVOKEVIRTUAL net/sf/saxon/Controller.getRuleManager ()Lnet/sf/saxon/trans/RuleManager;
    INVOKEVIRTUAL net/sf/saxon/trans/RuleManager.getUnnamedMode ()Lnet/sf/saxon/trans/Mode;
    GOTO L13
   L12
    SIPUSH 270
    INVOKESTATIC com/saxonica/ee/bytecode/util/ByteCodeTrace.trace (I)V
    INVOKEVIRTUAL net/sf/saxon/expr/Component.getCode ()Lnet/sf/saxon/expr/instruct/ComponentCode;
    CHECKCAST net/sf/saxon/trans/Mode
   L13
    SIPUSH 271
    INVOKESTATIC com/saxonica/ee/bytecode/util/ByteCodeTrace.trace (I)V
    DUP
    ASTORE 7
    SWAP
    ALOAD 1
    INVOKEVIRTUAL net/sf/saxon/trans/RuleManager.getNextMatchHandler (Lnet/sf/saxon/om/Item;Lnet/sf/saxon/trans/Mode;Lnet/sf/saxon/trans/Rule;Lnet/sf/saxon/expr/XPathContext;)Lnet/sf/saxon/trans/Rule;
    DUP
    IFNONNULL L14
    POP
    ALOAD 7
    INVOKEVIRTUAL net/sf/saxon/trans/Mode.getBuiltInRuleSet ()Lnet/sf/saxon/trans/BuiltInRuleSet;
    ALOAD 6
    ALOAD 3
    ALOAD 4
    ALOAD 1
    GETSTATIC EE_doc_1431443407612.nExplicitLocation146 : Lnet/sf/saxon/expr/parser/ExplicitLocation;
    INVOKEINTERFACE net/sf/saxon/trans/BuiltInRuleSet.process (Lnet/sf/saxon/om/Item;Lnet/sf/saxon/expr/instruct/ParameterSet;Lnet/sf/saxon/expr/instruct/ParameterSet;Lnet/sf/saxon/expr/XPathContext;Lnet/sf/saxon/expr/parser/Location;)V
    GOTO L15
   L14
    SIPUSH 272
    INVOKESTATIC com/saxonica/ee/bytecode/util/ByteCodeTrace.trace (I)V
    ASTORE 8
    ALOAD 1
    INVOKEINTERFACE net/sf/saxon/expr/XPathContext.newContext ()Lnet/sf/saxon/expr/XPathContextMajor;
    DUP
    ALOAD 3
    INVOKEVIRTUAL net/sf/saxon/expr/XPathContextMajor.setLocalParameters (Lnet/sf/saxon/expr/instruct/ParameterSet;)V
    DUP
    ALOAD 4
    INVOKEVIRTUAL net/sf/saxon/expr/XPathContextMajor.setTunnelParameters (Lnet/sf/saxon/expr/instruct/ParameterSet;)V
    DUP
    ALOAD 8
    INVOKEVIRTUAL net/sf/saxon/expr/XPathContextMajor.setCurrentTemplateRule (Lnet/sf/saxon/trans/Rule;)V
    DUP
    GETSTATIC EE_doc_1431443407612.nNextMatch147 : Lnet/sf/saxon/expr/instruct/NextMatch;
    INVOKEVIRTUAL net/sf/saxon/expr/XPathContextMajor.setOrigin (Lnet/sf/saxon/expr/ContextOriginator;)V
    DUP
    ALOAD 8
    INVOKEVIRTUAL net/sf/saxon/trans/Rule.getAction ()Lnet/sf/saxon/trans/RuleTarget;
    CHECKCAST net/sf/saxon/expr/instruct/TemplateRule
    DUP
    ASTORE 9
    INVOKEVIRTUAL net/sf/saxon/expr/instruct/TemplateRule.getStackFrameMap ()Lnet/sf/saxon/expr/instruct/SlotManager;
    INVOKEVIRTUAL net/sf/saxon/expr/XPathContextMajor.openStackFrame (Lnet/sf/saxon/expr/instruct/SlotManager;)V
    ALOAD 9
    SWAP
    INVOKEVIRTUAL net/sf/saxon/expr/instruct/TemplateRule.apply (Lnet/sf/saxon/expr/XPathContextMajor;)V
   L15
    SIPUSH 273
    INVOKESTATIC com/saxonica/ee/bytecode/util/ByteCodeTrace.trace (I)V
    ALOAD 2
    INVOKEINTERFACE net/sf/saxon/event/Receiver.endElement ()V
    RETURN
    MAXSTACK = 0
    MAXLOCALS = 0
}

  // access flags 0x9
  public static Lnet/sf/saxon/type/Untyped; nUntyped145

  // access flags 0x9
  public static Lnet/sf/saxon/om/NoNamespaceName; nNoNamespaceName144

  // access flags 0x9
  public static Lnet/sf/saxon/expr/instruct/NextMatch; nNextMatch147

  // access flags 0x9
  public static Lnet/sf/saxon/expr/parser/ExplicitLocation; nExplicitLocation146
}
