// class version 49.0 (49)
// access flags 0x1
public class EE_f_t_1861236903224 extends com/saxonica/ee/bytecode/GeneratedCode  {


  // access flags 0x1
  public <init>()V
    LINENUMBER 11 L0
    ALOAD 0
    INVOKESPECIAL com/saxonica/ee/bytecode/GeneratedCode.<init> ()V
    RETURN
    MAXSTACK = 0
    MAXLOCALS = 0

  // access flags 0x1
  public iterate(Lnet/sf/saxon/expr/XPathContext;)Lnet/sf/saxon/om/SequenceIterator; throws net/sf/saxon/trans/XPathException 
    ALOAD 1
    INVOKEINTERFACE net/sf/saxon/expr/XPathContext.getReceiver ()Lnet/sf/saxon/event/SequenceReceiver;
    ASTORE 2
   L0
    LDC "BlockCompiler-Itr"
    INVOKESTATIC com/saxonica/ee/bytecode/util/ByteCodeTrace.showMessage (Ljava/lang/String;)V
    LINENUMBER 11 L1
   L2
    LDC "BlockCompiler - next"
    INVOKESTATIC com/saxonica/ee/bytecode/util/ByteCodeTrace.showMessage (Ljava/lang/String;)V
    GETSTATIC EE_f_t_1861236903224.nClass188 : Ljava/lang/Class;
    INVOKEVIRTUAL java/lang/Class.newInstance ()Ljava/lang/Object;
    ASTORE 3
    ALOAD 3
    CHECKCAST com/saxonica/ee/bytecode/iter/CompiledBlockIterator
    ALOAD 1
    INVOKEVIRTUAL com/saxonica/ee/bytecode/iter/CompiledBlockIterator.setContext (Lnet/sf/saxon/expr/XPathContext;)V
    ALOAD 3
    CHECKCAST com/saxonica/ee/bytecode/iter/CompiledBlockIterator
    ARETURN
    MAXSTACK = 0
    MAXLOCALS = 0

  // access flags 0x1
  public process(Lnet/sf/saxon/expr/XPathContext;)V throws net/sf/saxon/trans/XPathException 
    ALOAD 1
    INVOKEINTERFACE net/sf/saxon/expr/XPathContext.getReceiver ()Lnet/sf/saxon/event/SequenceReceiver;
    ASTORE 2
    LINENUMBER 11 L0
   L1
    LDC "BlockCompiler-Push"
    INVOKESTATIC com/saxonica/ee/bytecode/util/ByteCodeTrace.showMessage (Ljava/lang/String;)V
   L2
    LDC "SimpleNodeConstructorCompiler-Push"
    INVOKESTATIC com/saxonica/ee/bytecode/util/ByteCodeTrace.showMessage (Ljava/lang/String;)V
    ALOAD 2
   L3
    LDC "LiteralCompiler-Primitive"
    INVOKESTATIC com/saxonica/ee/bytecode/util/ByteCodeTrace.showMessage (Ljava/lang/String;)V
    LDC ""
    GETSTATIC EE_f_t_1861236903224.nXSLFunction189 : Lnet/sf/saxon/style/XSLFunction;
    ICONST_4
    INVOKEINTERFACE net/sf/saxon/event/Receiver.characters (Ljava/lang/CharSequence;Lnet/sf/saxon/expr/parser/Location;I)V
   L4
    LDC "SimpleNodeConstructorCompiler-Push"
    INVOKESTATIC com/saxonica/ee/bytecode/util/ByteCodeTrace.showMessage (Ljava/lang/String;)V
    ALOAD 2
   L5
    LDC "LiteralCompiler-Primitive"
    INVOKESTATIC com/saxonica/ee/bytecode/util/ByteCodeTrace.showMessage (Ljava/lang/String;)V
    LDC "["
    GETSTATIC EE_f_t_1861236903224.nXSLFunction189 : Lnet/sf/saxon/style/XSLFunction;
    ICONST_4
    INVOKEINTERFACE net/sf/saxon/event/Receiver.characters (Ljava/lang/CharSequence;Lnet/sf/saxon/expr/parser/Location;I)V
   L6
    LDC "SimpleNodeConstructorCompiler-Push"
    INVOKESTATIC com/saxonica/ee/bytecode/util/ByteCodeTrace.showMessage (Ljava/lang/String;)V
    ALOAD 2
   L7
    LDC "StringJoin-Item"
    INVOKESTATIC com/saxonica/ee/bytecode/util/ByteCodeTrace.showMessage (Ljava/lang/String;)V
   L8
    LDC "AtomicSequenceConverterCompiler-Itr"
    INVOKESTATIC com/saxonica/ee/bytecode/util/ByteCodeTrace.showMessage (Ljava/lang/String;)V
   L9
    LDC "AtomicSequenceConverterCompiler-string"
    INVOKESTATIC com/saxonica/ee/bytecode/util/ByteCodeTrace.showMessage (Ljava/lang/String;)V
    NEW net/sf/saxon/expr/ItemMappingIterator
    DUP
   L10
    LDC "AtomizerCompiler-Itr"
    INVOKESTATIC com/saxonica/ee/bytecode/util/ByteCodeTrace.showMessage (Ljava/lang/String;)V
    NEW net/sf/saxon/tree/iter/AdjacentTextNodeMergingIterator
    DUP
   L11
    LDC "LocalVariableReference-Itr - p"
    INVOKESTATIC com/saxonica/ee/bytecode/util/ByteCodeTrace.showMessage (Ljava/lang/String;)V
    LINENUMBER 13 L12
    ALOAD 1
    INVOKEINTERFACE net/sf/saxon/expr/XPathContext.getStackFrame ()Lnet/sf/saxon/expr/StackFrame;
    INVOKEVIRTUAL net/sf/saxon/expr/StackFrame.getStackFrameValues ()[Lnet/sf/saxon/om/Sequence;
    ICONST_0
    AALOAD
    INVOKEINTERFACE net/sf/saxon/om/Sequence.iterate ()Lnet/sf/saxon/om/SequenceIterator;
    INVOKESPECIAL net/sf/saxon/tree/iter/AdjacentTextNodeMergingIterator.<init> (Lnet/sf/saxon/om/SequenceIterator;)V
    ICONST_1
    INVOKESTATIC net/sf/saxon/expr/Atomizer.getAtomizingIterator (Lnet/sf/saxon/om/SequenceIterator;Z)Lnet/sf/saxon/om/SequenceIterator;
    GETSTATIC net/sf/saxon/expr/AtomicSequenceConverter.TO_STRING_MAPPER : Lnet/sf/saxon/expr/AtomicSequenceConverter$ToStringMappingFunction;
    ICONST_1
    INVOKESPECIAL net/sf/saxon/expr/ItemMappingIterator.<init> (Lnet/sf/saxon/om/SequenceIterator;Lnet/sf/saxon/expr/ItemMappingFunction;Z)V
   L13
    LDC "StringJoin-Item-1"
    INVOKESTATIC com/saxonica/ee/bytecode/util/ByteCodeTrace.showMessage (Ljava/lang/String;)V
    ASTORE 3
    ALOAD 3
    INVOKEINTERFACE net/sf/saxon/om/SequenceIterator.next ()Lnet/sf/saxon/om/Item;
    DUP
    IFNONNULL L14
    POP
    LDC ""
    GOTO L15
   L14
    SIPUSH 439
    INVOKESTATIC com/saxonica/ee/bytecode/util/ByteCodeTrace.trace (I)V
    INVOKEINTERFACE net/sf/saxon/om/Item.getStringValueCS ()Ljava/lang/CharSequence;
    ASTORE 4
    ALOAD 3
    INVOKEINTERFACE net/sf/saxon/om/SequenceIterator.next ()Lnet/sf/saxon/om/Item;
    DUP
    IFNONNULL L16
    POP
    ALOAD 4
    GOTO L15
   L16
    SIPUSH 440
    INVOKESTATIC com/saxonica/ee/bytecode/util/ByteCodeTrace.trace (I)V
    NEW net/sf/saxon/tree/util/FastStringBuffer
    DUP
    BIPUSH 64
    INVOKESPECIAL net/sf/saxon/tree/util/FastStringBuffer.<init> (I)V
    ASTORE 5
    ALOAD 5
    ALOAD 4
    INVOKEVIRTUAL net/sf/saxon/tree/util/FastStringBuffer.append (Ljava/lang/CharSequence;)V
   L17
    LDC "LiteralCompiler-Primitive"
    INVOKESTATIC com/saxonica/ee/bytecode/util/ByteCodeTrace.showMessage (Ljava/lang/String;)V
    LDC " "
    ASTORE 6
    ALOAD 5
    ALOAD 6
    INVOKEVIRTUAL net/sf/saxon/tree/util/FastStringBuffer.append (Ljava/lang/CharSequence;)V
    ALOAD 5
    SWAP
    INVOKEINTERFACE net/sf/saxon/om/Item.getStringValueCS ()Ljava/lang/CharSequence;
    INVOKEVIRTUAL net/sf/saxon/tree/util/FastStringBuffer.append (Ljava/lang/CharSequence;)V
   L18
    SIPUSH 441
    INVOKESTATIC com/saxonica/ee/bytecode/util/ByteCodeTrace.trace (I)V
    ALOAD 3
    INVOKEINTERFACE net/sf/saxon/om/SequenceIterator.next ()Lnet/sf/saxon/om/Item;
    DUP
    IFNULL L19
    ALOAD 5
    ALOAD 6
    INVOKEVIRTUAL net/sf/saxon/tree/util/FastStringBuffer.append (Ljava/lang/CharSequence;)V
    ALOAD 5
    SWAP
    INVOKEINTERFACE net/sf/saxon/om/Item.getStringValueCS ()Ljava/lang/CharSequence;
    INVOKEVIRTUAL net/sf/saxon/tree/util/FastStringBuffer.append (Ljava/lang/CharSequence;)V
    GOTO L18
   L19
    SIPUSH 442
    INVOKESTATIC com/saxonica/ee/bytecode/util/ByteCodeTrace.trace (I)V
    POP
    ALOAD 5
    INVOKEVIRTUAL net/sf/saxon/tree/util/FastStringBuffer.condense ()Ljava/lang/CharSequence;
   L15
    SIPUSH 443
    INVOKESTATIC com/saxonica/ee/bytecode/util/ByteCodeTrace.trace (I)V
    GETSTATIC EE_f_t_1861236903224.nNestedLocation190 : Lnet/sf/saxon/expr/parser/XPathParser$NestedLocation;
    ICONST_0
    INVOKEINTERFACE net/sf/saxon/event/Receiver.characters (Ljava/lang/CharSequence;Lnet/sf/saxon/expr/parser/Location;I)V
   L20
    LDC "SimpleNodeConstructorCompiler-Push"
    INVOKESTATIC com/saxonica/ee/bytecode/util/ByteCodeTrace.showMessage (Ljava/lang/String;)V
    ALOAD 2
   L21
    LDC "LiteralCompiler-Primitive"
    INVOKESTATIC com/saxonica/ee/bytecode/util/ByteCodeTrace.showMessage (Ljava/lang/String;)V
    LINENUMBER 11 L22
    LDC "]"
    GETSTATIC EE_f_t_1861236903224.nXSLFunction189 : Lnet/sf/saxon/style/XSLFunction;
    ICONST_4
    INVOKEINTERFACE net/sf/saxon/event/Receiver.characters (Ljava/lang/CharSequence;Lnet/sf/saxon/expr/parser/Location;I)V
   L23
    LDC "SimpleNodeConstructorCompiler-Push"
    INVOKESTATIC com/saxonica/ee/bytecode/util/ByteCodeTrace.showMessage (Ljava/lang/String;)V
    ALOAD 2
   L24
    LDC "LiteralCompiler-Primitive"
    INVOKESTATIC com/saxonica/ee/bytecode/util/ByteCodeTrace.showMessage (Ljava/lang/String;)V
    LDC ""
    GETSTATIC EE_f_t_1861236903224.nXSLFunction189 : Lnet/sf/saxon/style/XSLFunction;
    ICONST_4
    INVOKEINTERFACE net/sf/saxon/event/Receiver.characters (Ljava/lang/CharSequence;Lnet/sf/saxon/expr/parser/Location;I)V
    RETURN
    MAXSTACK = 0
    MAXLOCALS = 0
}

  // access flags 0x9
  public static Lnet/sf/saxon/expr/parser/XPathParser$NestedLocation; nNestedLocation190

  // access flags 0x9
  public static Ljava/lang/Class; nClass188

  // access flags 0x9
  public static Lnet/sf/saxon/style/XSLFunction; nXSLFunction189
}
