// class version 49.0 (49)
// access flags 0x1
public class EE_main_552118205382 extends com/saxonica/ee/bytecode/GeneratedCode  {


  // access flags 0x1
  public <init>()V
    LINENUMBER 14 L0
    ALOAD 0
    INVOKESPECIAL com/saxonica/ee/bytecode/GeneratedCode.<init> ()V
    RETURN
    MAXSTACK = 0
    MAXLOCALS = 0

  // access flags 0x1
  public process(Lnet/sf/saxon/expr/XPathContext;)V throws net/sf/saxon/trans/XPathException 
    ALOAD 1
    INVOKEINTERFACE net/sf/saxon/expr/XPathContext.getReceiver ()Lnet/sf/saxon/event/SequenceReceiver;
    ASTORE 2
    LINENUMBER 14 L0
   L1
    LDC "FixedElement-out"
    INVOKESTATIC com/saxonica/ee/bytecode/util/ByteCodeTrace.showMessage (Ljava/lang/String;)V
   L2
    LDC "ElementCreator-push"
    INVOKESTATIC com/saxonica/ee/bytecode/util/ByteCodeTrace.showMessage (Ljava/lang/String;)V
    ALOAD 2
    DUP
    LDC "Receiver: "
    SWAP
    DUP
    IFNULL L3
    INVOKEVIRTUAL java/lang/Object.toString ()Ljava/lang/String;
    INVOKESTATIC com/saxonica/ee/bytecode/util/ByteCodeTrace.showObjectVariable (Ljava/lang/String;Ljava/lang/String;)V
    GOTO L4
   L3
    BIPUSH 109
    INVOKESTATIC com/saxonica/ee/bytecode/util/ByteCodeTrace.trace (I)V
    POP
    LDC "null"
    INVOKESTATIC com/saxonica/ee/bytecode/util/ByteCodeTrace.showObjectVariable (Ljava/lang/String;Ljava/lang/String;)V
   L4
    BIPUSH 110
    INVOKESTATIC com/saxonica/ee/bytecode/util/ByteCodeTrace.trace (I)V
    INVOKEINTERFACE net/sf/saxon/event/Receiver.getSystemId ()Ljava/lang/String;
    IFNONNULL L5
    ALOAD 2
    LDC "file:/Users/mike/w3c/xslt30-test-B/tests/decl/context-item/context-item-008.xsl"
    INVOKEINTERFACE net/sf/saxon/event/Receiver.setSystemId (Ljava/lang/String;)V
   L5
    BIPUSH 111
    INVOKESTATIC com/saxonica/ee/bytecode/util/ByteCodeTrace.trace (I)V
    ALOAD 2
    GETSTATIC EE_main_552118205382.nNoNamespaceName56 : Lnet/sf/saxon/om/NoNamespaceName;
    GETSTATIC EE_main_552118205382.nUntyped57 : Lnet/sf/saxon/type/Untyped;
    GETSTATIC EE_main_552118205382.nNestedLocation58 : Lnet/sf/saxon/expr/parser/XPathParser$NestedLocation;
    ICONST_0
    INVOKEINTERFACE net/sf/saxon/event/Receiver.startElement (Lnet/sf/saxon/om/NodeName;Lnet/sf/saxon/type/SchemaType;Lnet/sf/saxon/expr/parser/Location;I)V
   L6
    LDC "BlockCompiler-Push"
    INVOKESTATIC com/saxonica/ee/bytecode/util/ByteCodeTrace.showMessage (Ljava/lang/String;)V
   L7
    LDC "SlashExpressionCompiler-Push"
    INVOKESTATIC com/saxonica/ee/bytecode/util/ByteCodeTrace.showMessage (Ljava/lang/String;)V
    ALOAD 1
    INVOKEINTERFACE net/sf/saxon/expr/XPathContext.newMinorContext ()Lnet/sf/saxon/expr/XPathContextMinor;
   L8
    LDC "SlashExpressionCompiler - newMinorContext"
    INVOKESTATIC com/saxonica/ee/bytecode/util/ByteCodeTrace.showMessage (Ljava/lang/String;)V
    ASTORE 3
    ALOAD 3
    NEW net/sf/saxon/om/FocusTrackingIterator
    DUP
   L9
    LDC "LiteralCompiler-itr"
    INVOKESTATIC com/saxonica/ee/bytecode/util/ByteCodeTrace.showMessage (Ljava/lang/String;)V
    GETSTATIC EE_main_552118205382.nIntegerRange59 : Lnet/sf/saxon/value/IntegerRange;
    INVOKEINTERFACE net/sf/saxon/om/Sequence.iterate ()Lnet/sf/saxon/om/SequenceIterator;
    INVOKESPECIAL net/sf/saxon/om/FocusTrackingIterator.<init> (Lnet/sf/saxon/om/SequenceIterator;)V
    DUP
    ASTORE 4
    INVOKEINTERFACE net/sf/saxon/expr/XPathContext.setCurrentIterator (Lnet/sf/saxon/om/FocusIterator;)V
   L10
    BIPUSH 112
    INVOKESTATIC com/saxonica/ee/bytecode/util/ByteCodeTrace.trace (I)V
    ALOAD 4
    LDC "forEachSelectIterator"
    ALOAD 4
    INVOKEVIRTUAL java/lang/Object.toString ()Ljava/lang/String;
    INVOKESTATIC com/saxonica/ee/bytecode/util/ByteCodeTrace.showObjectVariable (Ljava/lang/String;Ljava/lang/String;)V
    INVOKEINTERFACE net/sf/saxon/om/SequenceIterator.next ()Lnet/sf/saxon/om/Item;
    IFNULL L11
   L12
    LDC "SlashExpressionCompiler - compileAction"
    INVOKESTATIC com/saxonica/ee/bytecode/util/ByteCodeTrace.showMessage (Ljava/lang/String;)V
    ALOAD 3
    ICONST_0
    INVOKEINTERFACE net/sf/saxon/expr/XPathContext.getTargetComponent (I)Lnet/sf/saxon/expr/Component;
    DUP
    INVOKEVIRTUAL net/sf/saxon/expr/Component.getVisibility ()Lnet/sf/saxon/trans/Visibility;
    GETSTATIC net/sf/saxon/trans/Visibility.ABSTRACT : Lnet/sf/saxon/trans/Visibility;
    IF_ACMPNE L13
    LDC "Cannot call an abstract template rule"
    LDC "XTSE3080"
    LDC "file:/Users/mike/w3c/xslt30-test-B/tests/decl/context-item/context-item-008.xsl"
    BIPUSH 14
    ICONST_0
    INVOKESTATIC com/saxonica/ee/bytecode/util/Callback.makeXPathException (Ljava/lang/String;Ljava/lang/String;Ljava/lang/String;IZ)Lnet/sf/saxon/trans/XPathException;
    ATHROW
    ATHROW
   L13
    BIPUSH 113
    INVOKESTATIC com/saxonica/ee/bytecode/util/ByteCodeTrace.trace (I)V
    DUP
    ASTORE 5
    INVOKEVIRTUAL net/sf/saxon/expr/Component.getCode ()Lnet/sf/saxon/expr/instruct/ComponentCode;
    CHECKCAST net/sf/saxon/expr/instruct/NamedTemplate
    ASTORE 6
    ALOAD 3
    INVOKEINTERFACE net/sf/saxon/expr/XPathContext.newContext ()Lnet/sf/saxon/expr/XPathContextMajor;
   L14
    LDC "CallTemplateCompiler - newMajorContext"
    INVOKESTATIC com/saxonica/ee/bytecode/util/ByteCodeTrace.showMessage (Ljava/lang/String;)V
    ASTORE 7
    ALOAD 7
    ALOAD 5
    INVOKEVIRTUAL net/sf/saxon/expr/XPathContextMajor.setCurrentComponent (Lnet/sf/saxon/expr/Component;)V
    ALOAD 7
    ALOAD 6
    INVOKEVIRTUAL net/sf/saxon/expr/instruct/NamedTemplate.getStackFrameMap ()Lnet/sf/saxon/expr/instruct/SlotManager;
    INVOKEVIRTUAL net/sf/saxon/expr/XPathContextMajor.openStackFrame (Lnet/sf/saxon/expr/instruct/SlotManager;)V
    ALOAD 7
   L15
    LDC "compileParameterSet"
    INVOKESTATIC com/saxonica/ee/bytecode/util/ByteCodeTrace.showMessage (Ljava/lang/String;)V
    ACONST_NULL
    INVOKEVIRTUAL net/sf/saxon/expr/XPathContextMajor.setLocalParameters (Lnet/sf/saxon/expr/instruct/ParameterSet;)V
    ALOAD 7
    ALOAD 3
    INVOKEINTERFACE net/sf/saxon/expr/XPathContext.getTunnelParameters ()Lnet/sf/saxon/expr/instruct/ParameterSet;
    ASTORE 8
    ALOAD 8
    IFNONNULL L16
   L17
    LDC "compileParameterSet"
    INVOKESTATIC com/saxonica/ee/bytecode/util/ByteCodeTrace.showMessage (Ljava/lang/String;)V
    ACONST_NULL
    GOTO L18
   L16
    BIPUSH 114
    INVOKESTATIC com/saxonica/ee/bytecode/util/ByteCodeTrace.trace (I)V
    NEW net/sf/saxon/expr/instruct/ParameterSet
    DUP
    ALOAD 8
    ICONST_0
    INVOKESPECIAL net/sf/saxon/expr/instruct/ParameterSet.<init> (Lnet/sf/saxon/expr/instruct/ParameterSet;I)V
   L18
    BIPUSH 115
    INVOKESTATIC com/saxonica/ee/bytecode/util/ByteCodeTrace.trace (I)V
    INVOKEVIRTUAL net/sf/saxon/expr/XPathContextMajor.setTunnelParameters (Lnet/sf/saxon/expr/instruct/ParameterSet;)V
    ALOAD 7
    GETSTATIC EE_main_552118205382.nCallTemplate60 : Lnet/sf/saxon/expr/instruct/CallTemplate;
    INVOKEVIRTUAL net/sf/saxon/expr/XPathContextMajor.setOrigin (Lnet/sf/saxon/expr/ContextOriginator;)V
    ALOAD 6
    ALOAD 7
    INVOKEVIRTUAL net/sf/saxon/expr/instruct/NamedTemplate.expand (Lnet/sf/saxon/expr/XPathContext;)Lnet/sf/saxon/expr/instruct/TailCall;
   L19
    BIPUSH 116
    INVOKESTATIC com/saxonica/ee/bytecode/util/ByteCodeTrace.trace (I)V
    DUP
    IFNULL L20
    INVOKEINTERFACE net/sf/saxon/expr/instruct/TailCall.processLeavingTail ()Lnet/sf/saxon/expr/instruct/TailCall;
    GOTO L19
   L20
    BIPUSH 117
    INVOKESTATIC com/saxonica/ee/bytecode/util/ByteCodeTrace.trace (I)V
    POP
    GOTO L10
   L11
    BIPUSH 118
    INVOKESTATIC com/saxonica/ee/bytecode/util/ByteCodeTrace.trace (I)V
    LINENUMBER 18 L21
    ALOAD 1
    ICONST_1
    INVOKEINTERFACE net/sf/saxon/expr/XPathContext.getTargetComponent (I)Lnet/sf/saxon/expr/Component;
    DUP
    INVOKEVIRTUAL net/sf/saxon/expr/Component.getVisibility ()Lnet/sf/saxon/trans/Visibility;
    GETSTATIC net/sf/saxon/trans/Visibility.ABSTRACT : Lnet/sf/saxon/trans/Visibility;
    IF_ACMPNE L22
    LDC "Cannot call an abstract template rule"
    LDC "XTSE3080"
    LDC "file:/Users/mike/w3c/xslt30-test-B/tests/decl/context-item/context-item-008.xsl"
    BIPUSH 18
    ICONST_0
    INVOKESTATIC com/saxonica/ee/bytecode/util/Callback.makeXPathException (Ljava/lang/String;Ljava/lang/String;Ljava/lang/String;IZ)Lnet/sf/saxon/trans/XPathException;
    ATHROW
    ATHROW
   L22
    BIPUSH 119
    INVOKESTATIC com/saxonica/ee/bytecode/util/ByteCodeTrace.trace (I)V
    DUP
    ASTORE 6
    INVOKEVIRTUAL net/sf/saxon/expr/Component.getCode ()Lnet/sf/saxon/expr/instruct/ComponentCode;
    CHECKCAST net/sf/saxon/expr/instruct/NamedTemplate
    ASTORE 9
    ALOAD 1
    INVOKEINTERFACE net/sf/saxon/expr/XPathContext.newContext ()Lnet/sf/saxon/expr/XPathContextMajor;
   L23
    LDC "CallTemplateCompiler - newMajorContext"
    INVOKESTATIC com/saxonica/ee/bytecode/util/ByteCodeTrace.showMessage (Ljava/lang/String;)V
    ASTORE 7
    ALOAD 7
    ALOAD 6
    INVOKEVIRTUAL net/sf/saxon/expr/XPathContextMajor.setCurrentComponent (Lnet/sf/saxon/expr/Component;)V
    ALOAD 7
    ALOAD 9
    INVOKEVIRTUAL net/sf/saxon/expr/instruct/NamedTemplate.getStackFrameMap ()Lnet/sf/saxon/expr/instruct/SlotManager;
    INVOKEVIRTUAL net/sf/saxon/expr/XPathContextMajor.openStackFrame (Lnet/sf/saxon/expr/instruct/SlotManager;)V
    ALOAD 7
   L24
    LDC "compileParameterSet"
    INVOKESTATIC com/saxonica/ee/bytecode/util/ByteCodeTrace.showMessage (Ljava/lang/String;)V
    NEW net/sf/saxon/expr/instruct/ParameterSet
    DUP
    ICONST_1
    INVOKESPECIAL net/sf/saxon/expr/instruct/ParameterSet.<init> (I)V
    DUP
    ALOAD 1
    DUP
    INVOKEINTERFACE net/sf/saxon/expr/XPathContext.getTemporaryOutputState ()I
    ISTORE 10
    SIPUSH 208
    INVOKEINTERFACE net/sf/saxon/expr/XPathContext.setTemporaryOutputState (I)V
    GETSTATIC EE_main_552118205382.nStructuredQName61 : Lnet/sf/saxon/om/StructuredQName;
   L25
    LDC "LiteralCompiler-item"
    INVOKESTATIC com/saxonica/ee/bytecode/util/ByteCodeTrace.showMessage (Ljava/lang/String;)V
    LDC 6
    INVOKESTATIC net/sf/saxon/value/Int64Value.makeIntegerValue (J)Lnet/sf/saxon/value/Int64Value;
    ICONST_1
    INVOKEVIRTUAL net/sf/saxon/expr/instruct/ParameterSet.put (Lnet/sf/saxon/om/StructuredQName;Lnet/sf/saxon/om/Sequence;Z)V
    ALOAD 1
    ILOAD 10
    INVOKEINTERFACE net/sf/saxon/expr/XPathContext.setTemporaryOutputState (I)V
    INVOKEVIRTUAL net/sf/saxon/expr/XPathContextMajor.setLocalParameters (Lnet/sf/saxon/expr/instruct/ParameterSet;)V
    ALOAD 7
    ALOAD 1
    INVOKEINTERFACE net/sf/saxon/expr/XPathContext.getTunnelParameters ()Lnet/sf/saxon/expr/instruct/ParameterSet;
    ASTORE 8
    ALOAD 8
    IFNONNULL L26
   L27
    LDC "compileParameterSet"
    INVOKESTATIC com/saxonica/ee/bytecode/util/ByteCodeTrace.showMessage (Ljava/lang/String;)V
    ACONST_NULL
    GOTO L28
   L26
    BIPUSH 120
    INVOKESTATIC com/saxonica/ee/bytecode/util/ByteCodeTrace.trace (I)V
    NEW net/sf/saxon/expr/instruct/ParameterSet
    DUP
    ALOAD 8
    ICONST_0
    INVOKESPECIAL net/sf/saxon/expr/instruct/ParameterSet.<init> (Lnet/sf/saxon/expr/instruct/ParameterSet;I)V
   L28
    BIPUSH 121
    INVOKESTATIC com/saxonica/ee/bytecode/util/ByteCodeTrace.trace (I)V
    INVOKEVIRTUAL net/sf/saxon/expr/XPathContextMajor.setTunnelParameters (Lnet/sf/saxon/expr/instruct/ParameterSet;)V
    ALOAD 7
    GETSTATIC EE_main_552118205382.nCallTemplate62 : Lnet/sf/saxon/expr/instruct/CallTemplate;
    INVOKEVIRTUAL net/sf/saxon/expr/XPathContextMajor.setOrigin (Lnet/sf/saxon/expr/ContextOriginator;)V
    ALOAD 9
    ALOAD 7
    INVOKEVIRTUAL net/sf/saxon/expr/instruct/NamedTemplate.expand (Lnet/sf/saxon/expr/XPathContext;)Lnet/sf/saxon/expr/instruct/TailCall;
   L29
    BIPUSH 122
    INVOKESTATIC com/saxonica/ee/bytecode/util/ByteCodeTrace.trace (I)V
    DUP
    IFNULL L30
    INVOKEINTERFACE net/sf/saxon/expr/instruct/TailCall.processLeavingTail ()Lnet/sf/saxon/expr/instruct/TailCall;
    GOTO L29
   L30
    BIPUSH 123
    INVOKESTATIC com/saxonica/ee/bytecode/util/ByteCodeTrace.trace (I)V
    POP
    ALOAD 2
    INVOKEINTERFACE net/sf/saxon/event/Receiver.endElement ()V
    RETURN
    MAXSTACK = 0
    MAXLOCALS = 0
}

  // access flags 0x9
  public static Lnet/sf/saxon/type/Untyped; nUntyped57

  // access flags 0x9
  public static Lnet/sf/saxon/expr/instruct/CallTemplate; nCallTemplate60

  // access flags 0x9
  public static Lnet/sf/saxon/expr/parser/XPathParser$NestedLocation; nNestedLocation58

  // access flags 0x9
  public static Lnet/sf/saxon/om/StructuredQName; nStructuredQName61

  // access flags 0x9
  public static Lnet/sf/saxon/om/NoNamespaceName; nNoNamespaceName56

  // access flags 0x9
  public static Lnet/sf/saxon/value/IntegerRange; nIntegerRange59

  // access flags 0x9
  public static Lnet/sf/saxon/expr/instruct/CallTemplate; nCallTemplate62
}
