// class version 49.0 (49)
// access flags 0x1
public class EE_main_1001114329560 extends com/saxonica/ee/bytecode/GeneratedCode  {


  // access flags 0x1
  public <init>()V
    LINENUMBER 14 L0
    ALOAD 0
    INVOKESPECIAL com/saxonica/ee/bytecode/GeneratedCode.<init> ()V
    RETURN
    MAXSTACK = 0
    MAXLOCALS = 0

  // access flags 0x1
  public process(Lnet/sf/saxon/expr/XPathContext;)V throws net/sf/saxon/trans/XPathException 
    ALOAD 1
    INVOKEINTERFACE net/sf/saxon/expr/XPathContext.getReceiver ()Lnet/sf/saxon/event/SequenceReceiver;
    ASTORE 2
    LINENUMBER 14 L0
   L1
    LDC "FixedElement-out"
    INVOKESTATIC com/saxonica/ee/bytecode/util/ByteCodeTrace.showMessage (Ljava/lang/String;)V
   L2
    LDC "ElementCreator-push"
    INVOKESTATIC com/saxonica/ee/bytecode/util/ByteCodeTrace.showMessage (Ljava/lang/String;)V
    ALOAD 2
    DUP
    LDC "Receiver: "
    SWAP
    DUP
    IFNULL L3
    INVOKEVIRTUAL java/lang/Object.toString ()Ljava/lang/String;
    INVOKESTATIC com/saxonica/ee/bytecode/util/ByteCodeTrace.showObjectVariable (Ljava/lang/String;Ljava/lang/String;)V
    GOTO L4
   L3
    SIPUSH 198
    INVOKESTATIC com/saxonica/ee/bytecode/util/ByteCodeTrace.trace (I)V
    POP
    LDC "null"
    INVOKESTATIC com/saxonica/ee/bytecode/util/ByteCodeTrace.showObjectVariable (Ljava/lang/String;Ljava/lang/String;)V
   L4
    SIPUSH 199
    INVOKESTATIC com/saxonica/ee/bytecode/util/ByteCodeTrace.trace (I)V
    INVOKEINTERFACE net/sf/saxon/event/Receiver.getSystemId ()Ljava/lang/String;
    IFNONNULL L5
    ALOAD 2
    LDC "file:/Users/mike/w3c/xslt30-test-B/tests/decl/context-item/context-item-013.xsl"
    INVOKEINTERFACE net/sf/saxon/event/Receiver.setSystemId (Ljava/lang/String;)V
   L5
    SIPUSH 200
    INVOKESTATIC com/saxonica/ee/bytecode/util/ByteCodeTrace.trace (I)V
    ALOAD 2
    GETSTATIC EE_main_1001114329560.nNoNamespaceName101 : Lnet/sf/saxon/om/NoNamespaceName;
    GETSTATIC EE_main_1001114329560.nUntyped102 : Lnet/sf/saxon/type/Untyped;
    GETSTATIC EE_main_1001114329560.nNestedLocation103 : Lnet/sf/saxon/expr/parser/XPathParser$NestedLocation;
    ICONST_0
    INVOKEINTERFACE net/sf/saxon/event/Receiver.startElement (Lnet/sf/saxon/om/NodeName;Lnet/sf/saxon/type/SchemaType;Lnet/sf/saxon/expr/parser/Location;I)V
   L6
    LDC "ApplyTemplates-push"
    INVOKESTATIC com/saxonica/ee/bytecode/util/ByteCodeTrace.showMessage (Ljava/lang/String;)V
    ALOAD 1
    ICONST_0
    INVOKEINTERFACE net/sf/saxon/expr/XPathContext.getTargetComponent (I)Lnet/sf/saxon/expr/Component;
    ASTORE 3
    ALOAD 1
    INVOKEINTERFACE net/sf/saxon/expr/XPathContext.newContext ()Lnet/sf/saxon/expr/XPathContextMajor;
   L7
    LDC "ApplyTemplatesCompiler - newMajorContext"
    INVOKESTATIC com/saxonica/ee/bytecode/util/ByteCodeTrace.showMessage (Ljava/lang/String;)V
    ASTORE 4
    ALOAD 4
    NEW net/sf/saxon/om/FocusTrackingIterator
    DUP
   L8
    LDC "SimpleStepExpression-Itr"
    INVOKESTATIC com/saxonica/ee/bytecode/util/ByteCodeTrace.showMessage (Ljava/lang/String;)V
    ALOAD 1
    INVOKEINTERFACE net/sf/saxon/expr/XPathContext.getContextItem ()Lnet/sf/saxon/om/Item;
    DUP
    IFNONNULL L9
    LDC "There is no context item"
    LDC "XPDY0002"
    LDC "file:/Users/mike/w3c/xslt30-test-B/tests/decl/context-item/context-item-013.xsl"
    BIPUSH 14
    ICONST_0
    INVOKESTATIC com/saxonica/ee/bytecode/util/Callback.makeXPathException (Ljava/lang/String;Ljava/lang/String;Ljava/lang/String;IZ)Lnet/sf/saxon/trans/XPathException;
    ATHROW
   L9
    SIPUSH 201
    INVOKESTATIC com/saxonica/ee/bytecode/util/ByteCodeTrace.trace (I)V
    DUP
    INSTANCEOF net/sf/saxon/om/NodeInfo
    IFNE L10
    DUP
    INVOKESTATIC net/sf/saxon/type/Type.displayTypeName (Lnet/sf/saxon/om/Item;)Ljava/lang/String;
    LDC "Required item type of the context item for the child axis is node(); actual type is {$1}"
    SWAP
    INVOKESTATIC com/saxonica/ee/bytecode/util/Callback.makeMessageFromTemplate (Ljava/lang/String;Ljava/lang/CharSequence;)Ljava/lang/String;
    LDC "XPTY0020"
    LDC "file:/Users/mike/w3c/xslt30-test-B/tests/decl/context-item/context-item-013.xsl"
    BIPUSH 14
    ICONST_1
    INVOKESTATIC com/saxonica/ee/bytecode/util/Callback.makeXPathException (Ljava/lang/String;Ljava/lang/String;Ljava/lang/String;IZ)Lnet/sf/saxon/trans/XPathException;
    ATHROW
   L10
    SIPUSH 202
    INVOKESTATIC com/saxonica/ee/bytecode/util/ByteCodeTrace.trace (I)V
    CHECKCAST net/sf/saxon/om/NodeInfo
   L11
    LDC "AxisExpressionCompiler - static method: iterate"
    INVOKESTATIC com/saxonica/ee/bytecode/util/ByteCodeTrace.showMessage (Ljava/lang/String;)V
    ICONST_3
    GETSTATIC EE_main_1001114329560.nNameTest104 : Lnet/sf/saxon/pattern/NameTest;
    LDC "calling iterateAxis"
    INVOKESTATIC com/saxonica/ee/bytecode/util/ByteCodeTrace.showMessage (Ljava/lang/String;)V
    INVOKEINTERFACE net/sf/saxon/om/NodeInfo.iterateAxis (BLnet/sf/saxon/pattern/NodeTest;)Lnet/sf/saxon/tree/iter/AxisIterator;
    LDC "returning axis iterator"
    INVOKESTATIC com/saxonica/ee/bytecode/util/ByteCodeTrace.showMessage (Ljava/lang/String;)V
    INVOKESPECIAL net/sf/saxon/om/FocusTrackingIterator.<init> (Lnet/sf/saxon/om/SequenceIterator;)V
    INVOKEINTERFACE net/sf/saxon/expr/XPathContext.setCurrentIterator (Lnet/sf/saxon/om/FocusIterator;)V
   L12
    LDC "ApplyTemplatesCompiler - setCurrentIterator"
    INVOKESTATIC com/saxonica/ee/bytecode/util/ByteCodeTrace.showMessage (Ljava/lang/String;)V
    ALOAD 4
    CHECKCAST net/sf/saxon/expr/XPathContextMajor
    GETSTATIC EE_main_1001114329560.nApplyTemplates105 : Lnet/sf/saxon/expr/instruct/ApplyTemplates;
    INVOKEVIRTUAL net/sf/saxon/expr/XPathContextMajor.setOrigin (Lnet/sf/saxon/expr/ContextOriginator;)V
    ALOAD 4
    ALOAD 3
    INVOKEVIRTUAL net/sf/saxon/expr/XPathContextMajor.setCurrentMode (Lnet/sf/saxon/expr/Component;)V
   L13
    LDC "compileParameterSet"
    INVOKESTATIC com/saxonica/ee/bytecode/util/ByteCodeTrace.showMessage (Ljava/lang/String;)V
    ACONST_NULL
    ASTORE 5
    ALOAD 1
    INVOKEINTERFACE net/sf/saxon/expr/XPathContext.getTunnelParameters ()Lnet/sf/saxon/expr/instruct/ParameterSet;
    ASTORE 7
    ALOAD 7
    IFNONNULL L14
   L15
    LDC "compileParameterSet"
    INVOKESTATIC com/saxonica/ee/bytecode/util/ByteCodeTrace.showMessage (Ljava/lang/String;)V
    ACONST_NULL
    GOTO L16
   L14
    SIPUSH 203
    INVOKESTATIC com/saxonica/ee/bytecode/util/ByteCodeTrace.trace (I)V
    NEW net/sf/saxon/expr/instruct/ParameterSet
    DUP
    ALOAD 7
    ICONST_0
    INVOKESPECIAL net/sf/saxon/expr/instruct/ParameterSet.<init> (Lnet/sf/saxon/expr/instruct/ParameterSet;I)V
   L16
    SIPUSH 204
    INVOKESTATIC com/saxonica/ee/bytecode/util/ByteCodeTrace.trace (I)V
    ASTORE 6
    ALOAD 3
    INVOKEVIRTUAL net/sf/saxon/expr/Component.getCode ()Lnet/sf/saxon/expr/instruct/ComponentCode;
    CHECKCAST net/sf/saxon/trans/Mode
    ALOAD 5
    ALOAD 6
    ALOAD 4
    GETSTATIC EE_main_1001114329560.nNestedLocation103 : Lnet/sf/saxon/expr/parser/XPathParser$NestedLocation;
    INVOKEVIRTUAL net/sf/saxon/trans/Mode.applyTemplates (Lnet/sf/saxon/expr/instruct/ParameterSet;Lnet/sf/saxon/expr/instruct/ParameterSet;Lnet/sf/saxon/expr/XPathContextMajor;Lnet/sf/saxon/expr/parser/Location;)Lnet/sf/saxon/expr/instruct/TailCall;
   L17
    SIPUSH 205
    INVOKESTATIC com/saxonica/ee/bytecode/util/ByteCodeTrace.trace (I)V
    DUP
    IFNULL L18
    INVOKEINTERFACE net/sf/saxon/expr/instruct/TailCall.processLeavingTail ()Lnet/sf/saxon/expr/instruct/TailCall;
    GOTO L17
   L18
    SIPUSH 206
    INVOKESTATIC com/saxonica/ee/bytecode/util/ByteCodeTrace.trace (I)V
    POP
    ALOAD 2
    INVOKEINTERFACE net/sf/saxon/event/Receiver.endElement ()V
    RETURN
    MAXSTACK = 0
    MAXLOCALS = 0
}

  // access flags 0x9
  public static Lnet/sf/saxon/expr/instruct/ApplyTemplates; nApplyTemplates105

  // access flags 0x9
  public static Lnet/sf/saxon/expr/parser/XPathParser$NestedLocation; nNestedLocation103

  // access flags 0x9
  public static Lnet/sf/saxon/om/NoNamespaceName; nNoNamespaceName101

  // access flags 0x9
  public static Lnet/sf/saxon/type/Untyped; nUntyped102

  // access flags 0x9
  public static Lnet/sf/saxon/pattern/NameTest; nNameTest104
}
