// class version 49.0 (49)
// access flags 0x1
public class EE_str1_01332226643 extends com/saxonica/ee/bytecode/GeneratedCode  {


  // access flags 0x1
  public <init>()V
    LINENUMBER 15 L0
    ALOAD 0
    INVOKESPECIAL com/saxonica/ee/bytecode/GeneratedCode.<init> ()V
    RETURN
    MAXSTACK = 0
    MAXLOCALS = 0

  // access flags 0x1
  public process(Lnet/sf/saxon/expr/XPathContext;)V throws net/sf/saxon/trans/XPathException 
    ALOAD 1
    INVOKEINTERFACE net/sf/saxon/expr/XPathContext.getReceiver ()Lnet/sf/saxon/event/SequenceReceiver;
    ASTORE 2
    LINENUMBER 15 L0
   L1
    LDC "SimpleNodeConstructorCompiler-Push"
    INVOKESTATIC com/saxonica/ee/bytecode/util/ByteCodeTrace.showMessage (Ljava/lang/String;)V
    ALOAD 2
   L2
    LDC "StaticFunctionCallCompiler"
    INVOKESTATIC com/saxonica/ee/bytecode/util/ByteCodeTrace.showMessage (Ljava/lang/String;)V
    ICONST_1
    ANEWARRAY net/sf/saxon/om/Sequence
    ASTORE 3
   L3
    LDC "StaticFunctionCallCompiler-ArrayCreated"
    INVOKESTATIC com/saxonica/ee/bytecode/util/ByteCodeTrace.showMessage (Ljava/lang/String;)V
    ALOAD 3
    ICONST_0
   L4
    LDC "LiteralCompiler-item"
    INVOKESTATIC com/saxonica/ee/bytecode/util/ByteCodeTrace.showMessage (Ljava/lang/String;)V
    LCONST_1
    INVOKESTATIC net/sf/saxon/value/Int64Value.makeIntegerValue (J)Lnet/sf/saxon/value/Int64Value;
   L5
    LDC "StaticFunctionCallCompiler-SetArg0"
    INVOKESTATIC com/saxonica/ee/bytecode/util/ByteCodeTrace.showMessage (Ljava/lang/String;)V
    AASTORE
    GETSTATIC EE_str1_01332226643.nRegexGroup1 : Lnet/sf/saxon/functions/RegexGroup;
    ALOAD 1
    ALOAD 3
    INVOKEINTERFACE net/sf/saxon/om/Function.call (Lnet/sf/saxon/expr/XPathContext;[Lnet/sf/saxon/om/Sequence;)Lnet/sf/saxon/om/Sequence;
    INVOKEINTERFACE net/sf/saxon/om/Sequence.iterate ()Lnet/sf/saxon/om/SequenceIterator;
   L6
    LDC "StaticFunctionCallCompiler-Done1"
    INVOKESTATIC com/saxonica/ee/bytecode/util/ByteCodeTrace.showMessage (Ljava/lang/String;)V
    INVOKEINTERFACE net/sf/saxon/om/SequenceIterator.next ()Lnet/sf/saxon/om/Item;
    CHECKCAST net/sf/saxon/value/StringValue
    INVOKEVIRTUAL net/sf/saxon/value/StringValue.getStringValueCS ()Ljava/lang/CharSequence;
    GETSTATIC EE_str1_01332226643.nNestedLocation2 : Lnet/sf/saxon/expr/parser/XPathParser$NestedLocation;
    ICONST_0
    INVOKEINTERFACE net/sf/saxon/event/Receiver.characters (Ljava/lang/CharSequence;Lnet/sf/saxon/expr/parser/Location;I)V
    RETURN
    MAXSTACK = 0
    MAXLOCALS = 0
}

  // access flags 0x9
  public static Lnet/sf/saxon/functions/RegexGroup; nRegexGroup1

  // access flags 0x9
  public static Lnet/sf/saxon/expr/parser/XPathParser$NestedLocation; nNestedLocation2
}
