// class version 49.0 (49)
// access flags 0x1
public class EE_t_381263457655 extends com/saxonica/ee/bytecode/GeneratedCode  {


  // access flags 0x1
  public <init>()V
    LINENUMBER 6 L0
    ALOAD 0
    INVOKESPECIAL com/saxonica/ee/bytecode/GeneratedCode.<init> ()V
    RETURN
    MAXSTACK = 0
    MAXLOCALS = 0

  // access flags 0x1
  public process(Lnet/sf/saxon/expr/XPathContext;)V throws net/sf/saxon/trans/XPathException 
    ALOAD 1
    INVOKEINTERFACE net/sf/saxon/expr/XPathContext.getReceiver ()Lnet/sf/saxon/event/SequenceReceiver;
    ASTORE 2
    LINENUMBER 6 L0
   L1
    LDC "BlockCompiler-Push"
    INVOKESTATIC com/saxonica/ee/bytecode/util/ByteCodeTrace.showMessage (Ljava/lang/String;)V
   L2
    LDC "SimpleNodeConstructorCompiler-Push"
    INVOKESTATIC com/saxonica/ee/bytecode/util/ByteCodeTrace.showMessage (Ljava/lang/String;)V
    ALOAD 2
   L3
    LDC "LiteralCompiler-Primitive"
    INVOKESTATIC com/saxonica/ee/bytecode/util/ByteCodeTrace.showMessage (Ljava/lang/String;)V
    LDC "\n      "
    GETSTATIC EE_t_381263457655.nXSLTemplate39 : Lnet/sf/saxon/style/XSLTemplate;
    ICONST_0
    INVOKEINTERFACE net/sf/saxon/event/Receiver.characters (Ljava/lang/CharSequence;Lnet/sf/saxon/expr/parser/Location;I)V
   L4
    LDC "LocalParam-push"
    INVOKESTATIC com/saxonica/ee/bytecode/util/ByteCodeTrace.showMessage (Ljava/lang/String;)V
    ALOAD 1
    GETSTATIC EE_t_381263457655.nStructuredQName40 : Lnet/sf/saxon/om/StructuredQName;
    ICONST_0
    ICONST_0
    INVOKEINTERFACE net/sf/saxon/expr/XPathContext.useLocalParameter (Lnet/sf/saxon/om/StructuredQName;IZ)I
    DUP
    ICONST_1
    IF_ICMPNE L5
    POP
    ALOAD 1
    ICONST_0
    LINENUMBER 8 L6
   L7
    LDC "SuppliedParameterReference-Itr"
    INVOKESTATIC com/saxonica/ee/bytecode/util/ByteCodeTrace.showMessage (Ljava/lang/String;)V
    ALOAD 1
    ICONST_0
    INVOKEINTERFACE net/sf/saxon/expr/XPathContext.evaluateLocalVariable (I)Lnet/sf/saxon/om/Sequence;
    INVOKEINTERFACE net/sf/saxon/om/Sequence.iterate ()Lnet/sf/saxon/om/SequenceIterator;
    INVOKESTATIC net/sf/saxon/value/SequenceExtent.makeSequenceExtent (Lnet/sf/saxon/om/SequenceIterator;)Lnet/sf/saxon/om/GroundedValue;
    INVOKEINTERFACE net/sf/saxon/expr/XPathContext.setLocalVariable (ILnet/sf/saxon/om/Sequence;)V
    GOTO L8
   L5
    BIPUSH 58
    INVOKESTATIC com/saxonica/ee/bytecode/util/ByteCodeTrace.trace (I)V
    ICONST_0
    IF_ICMPNE L8
    ALOAD 1
    ICONST_0
    ALOAD 1
    DUP
    INVOKEINTERFACE net/sf/saxon/expr/XPathContext.getTemporaryOutputState ()I
    ISTORE 3
    SIPUSH 208
    INVOKEINTERFACE net/sf/saxon/expr/XPathContext.setTemporaryOutputState (I)V
   L9
    LDC "LiteralCompiler-item"
    INVOKESTATIC com/saxonica/ee/bytecode/util/ByteCodeTrace.showMessage (Ljava/lang/String;)V
    LDC 3
    INVOKESTATIC net/sf/saxon/value/Int64Value.makeIntegerValue (J)Lnet/sf/saxon/value/Int64Value;
    ALOAD 1
    ILOAD 3
    INVOKEINTERFACE net/sf/saxon/expr/XPathContext.setTemporaryOutputState (I)V
    INVOKEINTERFACE net/sf/saxon/expr/XPathContext.setLocalVariable (ILnet/sf/saxon/om/Sequence;)V
   L8
    BIPUSH 59
    INVOKESTATIC com/saxonica/ee/bytecode/util/ByteCodeTrace.trace (I)V
   L10
    LDC "SimpleNodeConstructorCompiler-Push"
    INVOKESTATIC com/saxonica/ee/bytecode/util/ByteCodeTrace.showMessage (Ljava/lang/String;)V
    ALOAD 2
   L11
    LDC "LiteralCompiler-Primitive"
    INVOKESTATIC com/saxonica/ee/bytecode/util/ByteCodeTrace.showMessage (Ljava/lang/String;)V
    LINENUMBER 6 L12
    LDC "\n      "
    GETSTATIC EE_t_381263457655.nXSLTemplate39 : Lnet/sf/saxon/style/XSLTemplate;
    ICONST_0
    INVOKEINTERFACE net/sf/saxon/event/Receiver.characters (Ljava/lang/CharSequence;Lnet/sf/saxon/expr/parser/Location;I)V
   L13
    LDC "ToItemCompilerPush"
    INVOKESTATIC com/saxonica/ee/bytecode/util/ByteCodeTrace.showMessage (Ljava/lang/String;)V
    ALOAD 2
   L14
    LDC "ArithmeticCompiler"
    INVOKESTATIC com/saxonica/ee/bytecode/util/ByteCodeTrace.showMessage (Ljava/lang/String;)V
   L15
    LDC "AtomicSequenceConverterCompiler-Item"
    INVOKESTATIC com/saxonica/ee/bytecode/util/ByteCodeTrace.showMessage (Ljava/lang/String;)V
    LINENUMBER 9 L16
   L17
    LDC "SingletonAtomizerCompilerS-fromSingleton"
    INVOKESTATIC com/saxonica/ee/bytecode/util/ByteCodeTrace.showMessage (Ljava/lang/String;)V
    ALOAD 1
    INVOKEINTERFACE net/sf/saxon/expr/XPathContext.getContextItem ()Lnet/sf/saxon/om/Item;
    DUP
    IFNONNULL L18
    LDC "There is no context item"
    LDC "XPDY0002"
    LDC "file:/Users/mike/w3c/xslt30-test-B/tests/decl/context-item/context-item-007.xsl"
    BIPUSH 9
    ICONST_0
    INVOKESTATIC com/saxonica/ee/bytecode/util/Callback.makeXPathException (Ljava/lang/String;Ljava/lang/String;Ljava/lang/String;IZ)Lnet/sf/saxon/trans/XPathException;
    ATHROW
   L18
    BIPUSH 60
    INVOKESTATIC com/saxonica/ee/bytecode/util/ByteCodeTrace.trace (I)V
    DUP
    IFNULL L19
    INVOKEINTERFACE net/sf/saxon/om/Item.atomize ()Lnet/sf/saxon/om/AtomicSequence;
    DUP
    INVOKEINTERFACE net/sf/saxon/om/AtomicSequence.getLength ()I
    ICONST_1
    IF_ICMPLE L20
    LDC "A sequence of more than one item is not allowed as the first operand of '+'"
    LDC "XPTY0004"
    LDC "file:/Users/mike/w3c/xslt30-test-B/tests/decl/context-item/context-item-007.xsl"
    BIPUSH 9
    ICONST_1
    INVOKESTATIC com/saxonica/ee/bytecode/util/Callback.makeXPathException (Ljava/lang/String;Ljava/lang/String;Ljava/lang/String;IZ)Lnet/sf/saxon/trans/XPathException;
    ATHROW
   L20
    BIPUSH 61
    INVOKESTATIC com/saxonica/ee/bytecode/util/ByteCodeTrace.trace (I)V
    INVOKEINTERFACE net/sf/saxon/om/AtomicSequence.head ()Lnet/sf/saxon/value/AtomicValue;
    GOTO L21
   L19
    BIPUSH 62
    INVOKESTATIC com/saxonica/ee/bytecode/util/ByteCodeTrace.trace (I)V
   L21
    BIPUSH 63
    INVOKESTATIC com/saxonica/ee/bytecode/util/ByteCodeTrace.trace (I)V
   L22
    LDC "AtomicSequenceConverterCompiler-Item-Returned"
    INVOKESTATIC com/saxonica/ee/bytecode/util/ByteCodeTrace.showMessage (Ljava/lang/String;)V
    DUP
    IFNONNULL L23
    POP
    ACONST_NULL
    GOTO L24
   L23
    BIPUSH 64
    INVOKESTATIC com/saxonica/ee/bytecode/util/ByteCodeTrace.trace (I)V
    GETSTATIC EE_t_381263457655.nUntypedConverter41 : Lnet/sf/saxon/expr/UntypedSequenceConverter$UntypedConverter;
    SWAP
    CHECKCAST net/sf/saxon/value/AtomicValue
    INVOKEVIRTUAL net/sf/saxon/type/Converter.convert (Lnet/sf/saxon/value/AtomicValue;)Lnet/sf/saxon/type/ConversionResult;
    INVOKEINTERFACE net/sf/saxon/type/ConversionResult.asAtomic ()Lnet/sf/saxon/value/AtomicValue;
   L24
    BIPUSH 65
    INVOKESTATIC com/saxonica/ee/bytecode/util/ByteCodeTrace.trace (I)V
    CHECKCAST net/sf/saxon/value/AtomicValue
    DUP
    IFNONNULL L25
    POP
    ACONST_NULL
    GOTO L26
   L25
    BIPUSH 66
    INVOKESTATIC com/saxonica/ee/bytecode/util/ByteCodeTrace.trace (I)V
   L27
    LDC "AtomicSequenceConverterCompiler-Item"
    INVOKESTATIC com/saxonica/ee/bytecode/util/ByteCodeTrace.showMessage (Ljava/lang/String;)V
   L28
    LDC "SingletonAtomizerCompiler"
    INVOKESTATIC com/saxonica/ee/bytecode/util/ByteCodeTrace.showMessage (Ljava/lang/String;)V
   L29
    LDC "LocalVariableReference-Itr - p"
    INVOKESTATIC com/saxonica/ee/bytecode/util/ByteCodeTrace.showMessage (Ljava/lang/String;)V
    ALOAD 1
    INVOKEINTERFACE net/sf/saxon/expr/XPathContext.getStackFrame ()Lnet/sf/saxon/expr/StackFrame;
    INVOKEVIRTUAL net/sf/saxon/expr/StackFrame.getStackFrameValues ()[Lnet/sf/saxon/om/Sequence;
    ICONST_0
    AALOAD
    INVOKEINTERFACE net/sf/saxon/om/Sequence.iterate ()Lnet/sf/saxon/om/SequenceIterator;
    ASTORE 4
    ICONST_0
    ISTORE 5
    ACONST_NULL
    ASTORE 6
   L30
    BIPUSH 67
    INVOKESTATIC com/saxonica/ee/bytecode/util/ByteCodeTrace.trace (I)V
    ALOAD 4
    INVOKEINTERFACE net/sf/saxon/om/SequenceIterator.next ()Lnet/sf/saxon/om/Item;
    ASTORE 7
    ALOAD 7
    IFNULL L31
   L32
    LDC " SingletonAtomizerCompiler-atomic"
    INVOKESTATIC com/saxonica/ee/bytecode/util/ByteCodeTrace.showMessage (Ljava/lang/String;)V
    ALOAD 7
    INSTANCEOF net/sf/saxon/value/AtomicValue
    IFEQ L33
    IINC 5 1
    ILOAD 5
    ICONST_1
    IF_ICMPGT L34
    ALOAD 7
    ASTORE 6
    GOTO L30
   L33
    BIPUSH 68
    INVOKESTATIC com/saxonica/ee/bytecode/util/ByteCodeTrace.trace (I)V
   L35
    LDC " SingletonAtomizerCompiler-external"
    INVOKESTATIC com/saxonica/ee/bytecode/util/ByteCodeTrace.showMessage (Ljava/lang/String;)V
    ALOAD 7
    INSTANCEOF net/sf/saxon/value/ObjectValue
    IFEQ L36
    IINC 5 1
    ILOAD 5
    ICONST_1
    IF_ICMPGT L34
    ALOAD 7
    INVOKEINTERFACE net/sf/saxon/om/Item.getStringValue ()Ljava/lang/String;
    INVOKESTATIC net/sf/saxon/value/StringValue.makeStringValue (Ljava/lang/CharSequence;)Lnet/sf/saxon/value/StringValue;
    ASTORE 6
    GOTO L30
   L36
    BIPUSH 69
    INVOKESTATIC com/saxonica/ee/bytecode/util/ByteCodeTrace.trace (I)V
   L37
    LDC " SingletonAtomizerCompiler-Function"
    INVOKESTATIC com/saxonica/ee/bytecode/util/ByteCodeTrace.showMessage (Ljava/lang/String;)V
    ALOAD 7
    INSTANCEOF net/sf/saxon/om/Function
    IFEQ L38
    LDC "A function item cannot appear as the second operand of '+'"
    LDC "XPTY0004"
    LDC "file:/Users/mike/w3c/xslt30-test-B/tests/decl/context-item/context-item-007.xsl"
    BIPUSH 9
    ICONST_1
    INVOKESTATIC com/saxonica/ee/bytecode/util/Callback.makeXPathException (Ljava/lang/String;Ljava/lang/String;Ljava/lang/String;IZ)Lnet/sf/saxon/trans/XPathException;
    ATHROW
   L38
    BIPUSH 70
    INVOKESTATIC com/saxonica/ee/bytecode/util/ByteCodeTrace.trace (I)V
   L39
    LDC " SingletonAtomizerCompiler-Node"
    INVOKESTATIC com/saxonica/ee/bytecode/util/ByteCodeTrace.showMessage (Ljava/lang/String;)V
    ALOAD 7
    INSTANCEOF net/sf/saxon/om/NodeInfo
    IFEQ L30
    ALOAD 7
    CHECKCAST net/sf/saxon/om/NodeInfo
    INVOKEINTERFACE net/sf/saxon/om/NodeInfo.atomize ()Lnet/sf/saxon/om/AtomicSequence;
    ASTORE 8
    ALOAD 8
    INVOKEINTERFACE net/sf/saxon/om/AtomicSequence.getLength ()I
    ILOAD 5
    IADD
    ISTORE 5
    ILOAD 5
    ICONST_1
    IF_ICMPGT L34
    ALOAD 8
    INVOKEINTERFACE net/sf/saxon/om/Sequence.head ()Lnet/sf/saxon/om/Item;
    ASTORE 6
    GOTO L30
   L34
    BIPUSH 71
    INVOKESTATIC com/saxonica/ee/bytecode/util/ByteCodeTrace.trace (I)V
    LDC "A sequence of more than one item is not allowed as the second operand of '+'"
    LDC "XPTY0004"
    LDC "file:/Users/mike/w3c/xslt30-test-B/tests/decl/context-item/context-item-007.xsl"
    BIPUSH 9
    ICONST_1
    INVOKESTATIC com/saxonica/ee/bytecode/util/Callback.makeXPathException (Ljava/lang/String;Ljava/lang/String;Ljava/lang/String;IZ)Lnet/sf/saxon/trans/XPathException;
    ATHROW
   L31
    BIPUSH 72
    INVOKESTATIC com/saxonica/ee/bytecode/util/ByteCodeTrace.trace (I)V
   L40
    BIPUSH 73
    INVOKESTATIC com/saxonica/ee/bytecode/util/ByteCodeTrace.trace (I)V
    ALOAD 6
   L41
    LDC "AtomicSequenceConverterCompiler-Item-Returned"
    INVOKESTATIC com/saxonica/ee/bytecode/util/ByteCodeTrace.showMessage (Ljava/lang/String;)V
    DUP
    IFNONNULL L42
    POP
    ACONST_NULL
    GOTO L43
   L42
    BIPUSH 74
    INVOKESTATIC com/saxonica/ee/bytecode/util/ByteCodeTrace.trace (I)V
    GETSTATIC EE_t_381263457655.nUntypedConverter42 : Lnet/sf/saxon/expr/UntypedSequenceConverter$UntypedConverter;
    SWAP
    CHECKCAST net/sf/saxon/value/AtomicValue
    INVOKEVIRTUAL net/sf/saxon/type/Converter.convert (Lnet/sf/saxon/value/AtomicValue;)Lnet/sf/saxon/type/ConversionResult;
    INVOKEINTERFACE net/sf/saxon/type/ConversionResult.asAtomic ()Lnet/sf/saxon/value/AtomicValue;
   L43
    BIPUSH 75
    INVOKESTATIC com/saxonica/ee/bytecode/util/ByteCodeTrace.trace (I)V
    CHECKCAST net/sf/saxon/value/AtomicValue
    DUP
    IFNONNULL L44
    POP2
    ACONST_NULL
    GOTO L26
   L44
    BIPUSH 76
    INVOKESTATIC com/saxonica/ee/bytecode/util/ByteCodeTrace.trace (I)V
   L45
    LDC "AnyPlusCalculator-0"
    INVOKESTATIC com/saxonica/ee/bytecode/util/ByteCodeTrace.showMessage (Ljava/lang/String;)V
    SWAP
    DUP2
    INVOKEVIRTUAL net/sf/saxon/value/AtomicValue.getItemType ()Lnet/sf/saxon/type/AtomicType;
    INVOKEINTERFACE net/sf/saxon/type/ItemType.getPrimitiveType ()I
    SWAP
    INVOKEVIRTUAL net/sf/saxon/value/AtomicValue.getItemType ()Lnet/sf/saxon/type/AtomicType;
    INVOKEINTERFACE net/sf/saxon/type/ItemType.getPrimitiveType ()I
    ICONST_0
    ICONST_1
    INVOKESTATIC net/sf/saxon/expr/Calculator.getCalculator (IIIZ)Lnet/sf/saxon/expr/Calculator;
    DUP_X2
    IFNONNULL L46
    LDC "Unsuitable types for plus (+) operation"
    LDC "XPTY0004"
    LDC "file:/Users/mike/w3c/xslt30-test-B/tests/decl/context-item/context-item-007.xsl"
    BIPUSH 9
    ICONST_1
    INVOKESTATIC com/saxonica/ee/bytecode/util/Callback.makeXPathException (Ljava/lang/String;Ljava/lang/String;Ljava/lang/String;IZ)Lnet/sf/saxon/trans/XPathException;
    ATHROW
   L46
    BIPUSH 77
    INVOKESTATIC com/saxonica/ee/bytecode/util/ByteCodeTrace.trace (I)V
    SWAP
    ALOAD 1
    INVOKEVIRTUAL net/sf/saxon/expr/Calculator.compute (Lnet/sf/saxon/value/AtomicValue;Lnet/sf/saxon/value/AtomicValue;Lnet/sf/saxon/expr/XPathContext;)Lnet/sf/saxon/value/AtomicValue;
   L26
    BIPUSH 78
    INVOKESTATIC com/saxonica/ee/bytecode/util/ByteCodeTrace.trace (I)V
    INVOKEVIRTUAL net/sf/saxon/event/SequenceReceiver.append (Lnet/sf/saxon/om/Item;)V
   L47
    LDC "SimpleNodeConstructorCompiler-Push"
    INVOKESTATIC com/saxonica/ee/bytecode/util/ByteCodeTrace.showMessage (Ljava/lang/String;)V
    ALOAD 2
   L48
    LDC "LiteralCompiler-Primitive"
    INVOKESTATIC com/saxonica/ee/bytecode/util/ByteCodeTrace.showMessage (Ljava/lang/String;)V
    LINENUMBER 6 L49
    LDC "\n    "
    GETSTATIC EE_t_381263457655.nXSLTemplate39 : Lnet/sf/saxon/style/XSLTemplate;
    ICONST_0
    INVOKEINTERFACE net/sf/saxon/event/Receiver.characters (Ljava/lang/CharSequence;Lnet/sf/saxon/expr/parser/Location;I)V
    RETURN
    MAXSTACK = 0
    MAXLOCALS = 0
}

  // access flags 0x9
  public static Lnet/sf/saxon/expr/UntypedSequenceConverter$UntypedConverter; nUntypedConverter42

  // access flags 0x9
  public static Lnet/sf/saxon/om/StructuredQName; nStructuredQName40

  // access flags 0x9
  public static Lnet/sf/saxon/style/XSLTemplate; nXSLTemplate39

  // access flags 0x9
  public static Lnet/sf/saxon/expr/UntypedSequenceConverter$UntypedConverter; nUntypedConverter41
}
