// class version 49.0 (49)
// access flags 0x1
public class EE_t_261765187962 extends com/saxonica/ee/bytecode/GeneratedCode  {


  // access flags 0x1
  public <init>()V
    LINENUMBER 8 L0
    ALOAD 0
    INVOKESPECIAL com/saxonica/ee/bytecode/GeneratedCode.<init> ()V
    RETURN
    MAXSTACK = 0
    MAXLOCALS = 0

  // access flags 0x1
  public process(Lnet/sf/saxon/expr/XPathContext;)V throws net/sf/saxon/trans/XPathException 
    ALOAD 1
    INVOKEINTERFACE net/sf/saxon/expr/XPathContext.getReceiver ()Lnet/sf/saxon/event/SequenceReceiver;
    ASTORE 2
    LINENUMBER 8 L0
   L1
    LDC "ToItemCompilerPush"
    INVOKESTATIC com/saxonica/ee/bytecode/util/ByteCodeTrace.showMessage (Ljava/lang/String;)V
    ALOAD 2
    ALOAD 1
    INVOKEINTERFACE net/sf/saxon/expr/XPathContext.getContextItem ()Lnet/sf/saxon/om/Item;
    DUP
    IFNONNULL L2
    LDC "There is no context item"
    LDC "XPDY0002"
    LDC "file:/Users/mike/w3c/xslt30-test-B/tests/decl/context-item/context-item-005.xsl"
    BIPUSH 8
    ICONST_0
    INVOKESTATIC com/saxonica/ee/bytecode/util/Callback.makeXPathException (Ljava/lang/String;Ljava/lang/String;Ljava/lang/String;IZ)Lnet/sf/saxon/trans/XPathException;
    ATHROW
   L2
    BIPUSH 40
    INVOKESTATIC com/saxonica/ee/bytecode/util/ByteCodeTrace.trace (I)V
    INVOKEVIRTUAL net/sf/saxon/event/SequenceReceiver.append (Lnet/sf/saxon/om/Item;)V
    RETURN
    MAXSTACK = 0
    MAXLOCALS = 0
}
}
// class version 49.0 (49)
// access flags 0x1
public class EE_t_261765187962 extends com/saxonica/ee/bytecode/GeneratedCode  {


  // access flags 0x1
  public <init>()V
    LINENUMBER 8 L0
    ALOAD 0
    INVOKESPECIAL com/saxonica/ee/bytecode/GeneratedCode.<init> ()V
    RETURN
    MAXSTACK = 0
    MAXLOCALS = 0

  // access flags 0x1
  public process(Lnet/sf/saxon/expr/XPathContext;)V throws net/sf/saxon/trans/XPathException 
    ALOAD 1
    INVOKEINTERFACE net/sf/saxon/expr/XPathContext.getReceiver ()Lnet/sf/saxon/event/SequenceReceiver;
    ASTORE 2
    LINENUMBER 8 L0
   L1
    LDC "ToItemCompilerPush"
    INVOKESTATIC com/saxonica/ee/bytecode/util/ByteCodeTrace.showMessage (Ljava/lang/String;)V
    ALOAD 2
    ALOAD 1
    INVOKEINTERFACE net/sf/saxon/expr/XPathContext.getContextItem ()Lnet/sf/saxon/om/Item;
    DUP
    IFNONNULL L2
    LDC "There is no context item"
    LDC "XPDY0002"
    LDC "file:/Users/mike/w3c/xslt30-test-B/tests/decl/context-item/context-item-005.xsl"
    BIPUSH 8
    ICONST_0
    INVOKESTATIC com/saxonica/ee/bytecode/util/Callback.makeXPathException (Ljava/lang/String;Ljava/lang/String;Ljava/lang/String;IZ)Lnet/sf/saxon/trans/XPathException;
    ATHROW
   L2
    BIPUSH 40
    INVOKESTATIC com/saxonica/ee/bytecode/util/ByteCodeTrace.trace (I)V
    INVOKEVIRTUAL net/sf/saxon/event/SequenceReceiver.append (Lnet/sf/saxon/om/Item;)V
    RETURN
    MAXSTACK = 0
    MAXLOCALS = 0
}
}
// class version 49.0 (49)
// access flags 0x1
public class EE_t_261765187962 extends com/saxonica/ee/bytecode/GeneratedCode  {


  // access flags 0x1
  public <init>()V
    LINENUMBER 8 L0
    ALOAD 0
    INVOKESPECIAL com/saxonica/ee/bytecode/GeneratedCode.<init> ()V
    RETURN
    MAXSTACK = 0
    MAXLOCALS = 0

  // access flags 0x1
  public process(Lnet/sf/saxon/expr/XPathContext;)V throws net/sf/saxon/trans/XPathException 
    ALOAD 1
    INVOKEINTERFACE net/sf/saxon/expr/XPathContext.getReceiver ()Lnet/sf/saxon/event/SequenceReceiver;
    ASTORE 2
    LINENUMBER 8 L0
   L1
    LDC "ToItemCompilerPush"
    INVOKESTATIC com/saxonica/ee/bytecode/util/ByteCodeTrace.showMessage (Ljava/lang/String;)V
    ALOAD 2
    ALOAD 1
    INVOKEINTERFACE net/sf/saxon/expr/XPathContext.getContextItem ()Lnet/sf/saxon/om/Item;
    DUP
    IFNONNULL L2
    LDC "There is no context item"
    LDC "XPDY0002"
    LDC "file:/Users/mike/w3c/xslt30-test-B/tests/decl/context-item/context-item-005.xsl"
    BIPUSH 8
    ICONST_0
    INVOKESTATIC com/saxonica/ee/bytecode/util/Callback.makeXPathException (Ljava/lang/String;Ljava/lang/String;Ljava/lang/String;IZ)Lnet/sf/saxon/trans/XPathException;
    ATHROW
   L2
    BIPUSH 40
    INVOKESTATIC com/saxonica/ee/bytecode/util/ByteCodeTrace.trace (I)V
    INVOKEVIRTUAL net/sf/saxon/event/SequenceReceiver.append (Lnet/sf/saxon/om/Item;)V
    RETURN
    MAXSTACK = 0
    MAXLOCALS = 0
}
}
