  // compiled from: file:/Users/mike/w3c/xslt30-test-B/tests/attr/avt/avt-1205.xsl
// class version 49.0 (49)
// access flags 0x1
public class gen_CompiledBlockIterator_187 extends com/saxonica/ee/bytecode/iter/CompiledBlockIterator  {


  // access flags 0x1
  public <init>()V
    ALOAD 0
    INVOKESPECIAL com/saxonica/ee/bytecode/iter/CompiledBlockIterator.<init> ()V
    RETURN
    MAXSTACK = 0
    MAXLOCALS = 0

  // access flags 0x1
  public next()Lnet/sf/saxon/om/Item; throws net/sf/saxon/trans/XPathException 
    LINENUMBER 11 L0
    ALOAD 0
    GETFIELD com/saxonica/ee/bytecode/iter/CompiledBlockIterator.context : Lnet/sf/saxon/expr/XPathContext;
    DUP
    ASTORE 1
    INVOKEINTERFACE net/sf/saxon/expr/XPathContext.getReceiver ()Lnet/sf/saxon/event/SequenceReceiver;
    ASTORE 3
    ACONST_NULL
    ASTORE 2
   L1
    SIPUSH 424
    INVOKESTATIC com/saxonica/ee/bytecode/util/ByteCodeTrace.trace (I)V
    ALOAD 0
    GETFIELD com/saxonica/ee/bytecode/iter/CompiledBlockIterator.currentIterator : Lnet/sf/saxon/om/SequenceIterator;
    DUP
    IFNONNULL L2
    POP
    GOTO L3
   L2
    SIPUSH 425
    INVOKESTATIC com/saxonica/ee/bytecode/util/ByteCodeTrace.trace (I)V
    INVOKEINTERFACE net/sf/saxon/om/SequenceIterator.next ()Lnet/sf/saxon/om/Item;
    DUP
    ASTORE 2
    IFNONNULL L4
    ALOAD 0
    ACONST_NULL
    PUTFIELD com/saxonica/ee/bytecode/iter/CompiledBlockIterator.currentIterator : Lnet/sf/saxon/om/SequenceIterator;
    GOTO L3
   L4
    SIPUSH 426
    INVOKESTATIC com/saxonica/ee/bytecode/util/ByteCodeTrace.trace (I)V
    GOTO L5
   L3
    SIPUSH 427
    INVOKESTATIC com/saxonica/ee/bytecode/util/ByteCodeTrace.trace (I)V
    ALOAD 0
    GETFIELD com/saxonica/ee/bytecode/iter/CompiledBlockIterator.state : I
    TABLESWITCH
      0: L6
      1: L7
      2: L8
      3: L9
      4: L10
      5: L11
      default: L12
   L6
   L13
    LDC "BlockCompiler - caseStatement"
    INVOKESTATIC com/saxonica/ee/bytecode/util/ByteCodeTrace.showMessage (Ljava/lang/String;)V
    ALOAD 0
    ICONST_1
    PUTFIELD com/saxonica/ee/bytecode/iter/CompiledBlockIterator.state : I
   L14
    LDC "BlockCompiler - caseStatement-asItem0"
    INVOKESTATIC com/saxonica/ee/bytecode/util/ByteCodeTrace.showMessage (Ljava/lang/String;)V
   L15
    LDC "ValueOfCompiler"
    INVOKESTATIC com/saxonica/ee/bytecode/util/ByteCodeTrace.showMessage (Ljava/lang/String;)V
   L16
    LDC "LiteralCompiler-Primitive"
    INVOKESTATIC com/saxonica/ee/bytecode/util/ByteCodeTrace.showMessage (Ljava/lang/String;)V
    LDC ""
    ASTORE 4
    NEW net/sf/saxon/tree/util/Orphan
    DUP
    ALOAD 1
    INVOKEINTERFACE net/sf/saxon/expr/XPathContext.getConfiguration ()Lnet/sf/saxon/Configuration;
    INVOKESPECIAL net/sf/saxon/tree/util/Orphan.<init> (Lnet/sf/saxon/Configuration;)V
    ASTORE 5
    ALOAD 5
    ICONST_3
    INVOKEVIRTUAL net/sf/saxon/tree/util/Orphan.setNodeKind (S)V
    ALOAD 5
    ALOAD 4
    INVOKEVIRTUAL net/sf/saxon/tree/util/Orphan.setStringValue (Ljava/lang/CharSequence;)V
    ALOAD 5
   L17
    SIPUSH 428
    INVOKESTATIC com/saxonica/ee/bytecode/util/ByteCodeTrace.trace (I)V
    ASTORE 2
    GOTO L18
   L7
   L19
    LDC "BlockCompiler - caseStatement"
    INVOKESTATIC com/saxonica/ee/bytecode/util/ByteCodeTrace.showMessage (Ljava/lang/String;)V
    ALOAD 0
    ICONST_2
    PUTFIELD com/saxonica/ee/bytecode/iter/CompiledBlockIterator.state : I
   L20
    LDC "BlockCompiler - caseStatement-asItem1"
    INVOKESTATIC com/saxonica/ee/bytecode/util/ByteCodeTrace.showMessage (Ljava/lang/String;)V
   L21
    LDC "ValueOfCompiler"
    INVOKESTATIC com/saxonica/ee/bytecode/util/ByteCodeTrace.showMessage (Ljava/lang/String;)V
   L22
    LDC "LiteralCompiler-Primitive"
    INVOKESTATIC com/saxonica/ee/bytecode/util/ByteCodeTrace.showMessage (Ljava/lang/String;)V
    LDC "["
    ASTORE 4
    NEW net/sf/saxon/tree/util/Orphan
    DUP
    ALOAD 1
    INVOKEINTERFACE net/sf/saxon/expr/XPathContext.getConfiguration ()Lnet/sf/saxon/Configuration;
    INVOKESPECIAL net/sf/saxon/tree/util/Orphan.<init> (Lnet/sf/saxon/Configuration;)V
    ASTORE 5
    ALOAD 5
    ICONST_3
    INVOKEVIRTUAL net/sf/saxon/tree/util/Orphan.setNodeKind (S)V
    ALOAD 5
    ALOAD 4
    INVOKEVIRTUAL net/sf/saxon/tree/util/Orphan.setStringValue (Ljava/lang/CharSequence;)V
    ALOAD 5
   L23
    SIPUSH 429
    INVOKESTATIC com/saxonica/ee/bytecode/util/ByteCodeTrace.trace (I)V
    ASTORE 2
    GOTO L18
   L8
   L24
    LDC "BlockCompiler - caseStatement"
    INVOKESTATIC com/saxonica/ee/bytecode/util/ByteCodeTrace.showMessage (Ljava/lang/String;)V
    ALOAD 0
    ICONST_3
    PUTFIELD com/saxonica/ee/bytecode/iter/CompiledBlockIterator.state : I
   L25
    LDC "BlockCompiler - caseStatement-asItem2"
    INVOKESTATIC com/saxonica/ee/bytecode/util/ByteCodeTrace.showMessage (Ljava/lang/String;)V
   L26
    LDC "ValueOfCompiler"
    INVOKESTATIC com/saxonica/ee/bytecode/util/ByteCodeTrace.showMessage (Ljava/lang/String;)V
   L27
    LDC "StringJoin-Item"
    INVOKESTATIC com/saxonica/ee/bytecode/util/ByteCodeTrace.showMessage (Ljava/lang/String;)V
   L28
    LDC "AtomicSequenceConverterCompiler-Itr"
    INVOKESTATIC com/saxonica/ee/bytecode/util/ByteCodeTrace.showMessage (Ljava/lang/String;)V
   L29
    LDC "AtomicSequenceConverterCompiler-string"
    INVOKESTATIC com/saxonica/ee/bytecode/util/ByteCodeTrace.showMessage (Ljava/lang/String;)V
    NEW net/sf/saxon/expr/ItemMappingIterator
    DUP
   L30
    LDC "AtomizerCompiler-Itr"
    INVOKESTATIC com/saxonica/ee/bytecode/util/ByteCodeTrace.showMessage (Ljava/lang/String;)V
    NEW net/sf/saxon/tree/iter/AdjacentTextNodeMergingIterator
    DUP
   L31
    LDC "LocalVariableReference-Itr - p"
    INVOKESTATIC com/saxonica/ee/bytecode/util/ByteCodeTrace.showMessage (Ljava/lang/String;)V
    LINENUMBER 13 L32
    ALOAD 1
    INVOKEINTERFACE net/sf/saxon/expr/XPathContext.getStackFrame ()Lnet/sf/saxon/expr/StackFrame;
    INVOKEVIRTUAL net/sf/saxon/expr/StackFrame.getStackFrameValues ()[Lnet/sf/saxon/om/Sequence;
    ICONST_0
    AALOAD
    INVOKEINTERFACE net/sf/saxon/om/Sequence.iterate ()Lnet/sf/saxon/om/SequenceIterator;
    INVOKESPECIAL net/sf/saxon/tree/iter/AdjacentTextNodeMergingIterator.<init> (Lnet/sf/saxon/om/SequenceIterator;)V
    ICONST_1
    INVOKESTATIC net/sf/saxon/expr/Atomizer.getAtomizingIterator (Lnet/sf/saxon/om/SequenceIterator;Z)Lnet/sf/saxon/om/SequenceIterator;
    GETSTATIC net/sf/saxon/expr/AtomicSequenceConverter.TO_STRING_MAPPER : Lnet/sf/saxon/expr/AtomicSequenceConverter$ToStringMappingFunction;
    ICONST_1
    INVOKESPECIAL net/sf/saxon/expr/ItemMappingIterator.<init> (Lnet/sf/saxon/om/SequenceIterator;Lnet/sf/saxon/expr/ItemMappingFunction;Z)V
   L33
    LDC "StringJoin-Item-1"
    INVOKESTATIC com/saxonica/ee/bytecode/util/ByteCodeTrace.showMessage (Ljava/lang/String;)V
    ASTORE 6
    ALOAD 6
    INVOKEINTERFACE net/sf/saxon/om/SequenceIterator.next ()Lnet/sf/saxon/om/Item;
    DUP
    IFNONNULL L34
    POP
    LDC ""
    GOTO L35
   L34
    SIPUSH 430
    INVOKESTATIC com/saxonica/ee/bytecode/util/ByteCodeTrace.trace (I)V
    INVOKEINTERFACE net/sf/saxon/om/Item.getStringValueCS ()Ljava/lang/CharSequence;
    ASTORE 7
    ALOAD 6
    INVOKEINTERFACE net/sf/saxon/om/SequenceIterator.next ()Lnet/sf/saxon/om/Item;
    DUP
    IFNONNULL L36
    POP
    ALOAD 7
    GOTO L35
   L36
    SIPUSH 431
    INVOKESTATIC com/saxonica/ee/bytecode/util/ByteCodeTrace.trace (I)V
    NEW net/sf/saxon/tree/util/FastStringBuffer
    DUP
    BIPUSH 64
    INVOKESPECIAL net/sf/saxon/tree/util/FastStringBuffer.<init> (I)V
    ASTORE 8
    ALOAD 8
    ALOAD 7
    INVOKEVIRTUAL net/sf/saxon/tree/util/FastStringBuffer.append (Ljava/lang/CharSequence;)V
   L37
    LDC "LiteralCompiler-Primitive"
    INVOKESTATIC com/saxonica/ee/bytecode/util/ByteCodeTrace.showMessage (Ljava/lang/String;)V
    LDC " "
    ASTORE 9
    ALOAD 8
    ALOAD 9
    INVOKEVIRTUAL net/sf/saxon/tree/util/FastStringBuffer.append (Ljava/lang/CharSequence;)V
    ALOAD 8
    SWAP
    INVOKEINTERFACE net/sf/saxon/om/Item.getStringValueCS ()Ljava/lang/CharSequence;
    INVOKEVIRTUAL net/sf/saxon/tree/util/FastStringBuffer.append (Ljava/lang/CharSequence;)V
   L38
    SIPUSH 432
    INVOKESTATIC com/saxonica/ee/bytecode/util/ByteCodeTrace.trace (I)V
    ALOAD 6
    INVOKEINTERFACE net/sf/saxon/om/SequenceIterator.next ()Lnet/sf/saxon/om/Item;
    DUP
    IFNULL L39
    ALOAD 8
    ALOAD 9
    INVOKEVIRTUAL net/sf/saxon/tree/util/FastStringBuffer.append (Ljava/lang/CharSequence;)V
    ALOAD 8
    SWAP
    INVOKEINTERFACE net/sf/saxon/om/Item.getStringValueCS ()Ljava/lang/CharSequence;
    INVOKEVIRTUAL net/sf/saxon/tree/util/FastStringBuffer.append (Ljava/lang/CharSequence;)V
    GOTO L38
   L39
    SIPUSH 433
    INVOKESTATIC com/saxonica/ee/bytecode/util/ByteCodeTrace.trace (I)V
    POP
    ALOAD 8
    INVOKEVIRTUAL net/sf/saxon/tree/util/FastStringBuffer.condense ()Ljava/lang/CharSequence;
   L35
    SIPUSH 434
    INVOKESTATIC com/saxonica/ee/bytecode/util/ByteCodeTrace.trace (I)V
    ASTORE 4
    NEW net/sf/saxon/tree/util/Orphan
    DUP
    ALOAD 1
    INVOKEINTERFACE net/sf/saxon/expr/XPathContext.getConfiguration ()Lnet/sf/saxon/Configuration;
    INVOKESPECIAL net/sf/saxon/tree/util/Orphan.<init> (Lnet/sf/saxon/Configuration;)V
    ASTORE 5
    ALOAD 5
    ICONST_3
    INVOKEVIRTUAL net/sf/saxon/tree/util/Orphan.setNodeKind (S)V
    ALOAD 5
    ALOAD 4
    INVOKEVIRTUAL net/sf/saxon/tree/util/Orphan.setStringValue (Ljava/lang/CharSequence;)V
    ALOAD 5
   L40
    SIPUSH 435
    INVOKESTATIC com/saxonica/ee/bytecode/util/ByteCodeTrace.trace (I)V
    ASTORE 2
    GOTO L18
   L9
   L41
    LDC "BlockCompiler - caseStatement"
    INVOKESTATIC com/saxonica/ee/bytecode/util/ByteCodeTrace.showMessage (Ljava/lang/String;)V
    ALOAD 0
    ICONST_4
    PUTFIELD com/saxonica/ee/bytecode/iter/CompiledBlockIterator.state : I
   L42
    LDC "BlockCompiler - caseStatement-asItem3"
    INVOKESTATIC com/saxonica/ee/bytecode/util/ByteCodeTrace.showMessage (Ljava/lang/String;)V
   L43
    LDC "ValueOfCompiler"
    INVOKESTATIC com/saxonica/ee/bytecode/util/ByteCodeTrace.showMessage (Ljava/lang/String;)V
   L44
    LDC "LiteralCompiler-Primitive"
    INVOKESTATIC com/saxonica/ee/bytecode/util/ByteCodeTrace.showMessage (Ljava/lang/String;)V
    LINENUMBER 11 L45
    LDC "]"
    ASTORE 4
    NEW net/sf/saxon/tree/util/Orphan
    DUP
    ALOAD 1
    INVOKEINTERFACE net/sf/saxon/expr/XPathContext.getConfiguration ()Lnet/sf/saxon/Configuration;
    INVOKESPECIAL net/sf/saxon/tree/util/Orphan.<init> (Lnet/sf/saxon/Configuration;)V
    ASTORE 5
    ALOAD 5
    ICONST_3
    INVOKEVIRTUAL net/sf/saxon/tree/util/Orphan.setNodeKind (S)V
    ALOAD 5
    ALOAD 4
    INVOKEVIRTUAL net/sf/saxon/tree/util/Orphan.setStringValue (Ljava/lang/CharSequence;)V
    ALOAD 5
   L46
    SIPUSH 436
    INVOKESTATIC com/saxonica/ee/bytecode/util/ByteCodeTrace.trace (I)V
    ASTORE 2
    GOTO L18
   L10
   L47
    LDC "BlockCompiler - caseStatement"
    INVOKESTATIC com/saxonica/ee/bytecode/util/ByteCodeTrace.showMessage (Ljava/lang/String;)V
    ALOAD 0
    ICONST_5
    PUTFIELD com/saxonica/ee/bytecode/iter/CompiledBlockIterator.state : I
   L48
    LDC "BlockCompiler - caseStatement-asItem4"
    INVOKESTATIC com/saxonica/ee/bytecode/util/ByteCodeTrace.showMessage (Ljava/lang/String;)V
   L49
    LDC "ValueOfCompiler"
    INVOKESTATIC com/saxonica/ee/bytecode/util/ByteCodeTrace.showMessage (Ljava/lang/String;)V
   L50
    LDC "LiteralCompiler-Primitive"
    INVOKESTATIC com/saxonica/ee/bytecode/util/ByteCodeTrace.showMessage (Ljava/lang/String;)V
    LDC ""
    ASTORE 4
    NEW net/sf/saxon/tree/util/Orphan
    DUP
    ALOAD 1
    INVOKEINTERFACE net/sf/saxon/expr/XPathContext.getConfiguration ()Lnet/sf/saxon/Configuration;
    INVOKESPECIAL net/sf/saxon/tree/util/Orphan.<init> (Lnet/sf/saxon/Configuration;)V
    ASTORE 5
    ALOAD 5
    ICONST_3
    INVOKEVIRTUAL net/sf/saxon/tree/util/Orphan.setNodeKind (S)V
    ALOAD 5
    ALOAD 4
    INVOKEVIRTUAL net/sf/saxon/tree/util/Orphan.setStringValue (Ljava/lang/CharSequence;)V
    ALOAD 5
   L51
    SIPUSH 437
    INVOKESTATIC com/saxonica/ee/bytecode/util/ByteCodeTrace.trace (I)V
    ASTORE 2
    GOTO L18
   L11
   L52
    LDC "BlockCompiler - caseStatement"
    INVOKESTATIC com/saxonica/ee/bytecode/util/ByteCodeTrace.showMessage (Ljava/lang/String;)V
   L53
    LDC "BlockCompiler - default"
    INVOKESTATIC com/saxonica/ee/bytecode/util/ByteCodeTrace.showMessage (Ljava/lang/String;)V
    ACONST_NULL
    ASTORE 2
    GOTO L18
   L12
   L18
   L5
    SIPUSH 438
    INVOKESTATIC com/saxonica/ee/bytecode/util/ByteCodeTrace.trace (I)V
    ALOAD 2
    ARETURN
    MAXSTACK = 0
    MAXLOCALS = 0
}
}
