  // compiled from: file:/Users/mike/w3c/xslt30-test-B/tests/attr/avt/avt-0301.xsl
// class version 49.0 (49)
// access flags 0x1
public class gen_SlashContextMappingFunction_27 extends com/saxonica/ee/bytecode/map/CompiledContextMappingFunction  {


  // access flags 0x1
  public <init>()V
    ALOAD 0
    INVOKESPECIAL com/saxonica/ee/bytecode/map/CompiledContextMappingFunction.<init> ()V
    RETURN
    MAXSTACK = 0
    MAXLOCALS = 0

  // access flags 0x1
  public map(Lnet/sf/saxon/expr/XPathContext;)Lnet/sf/saxon/om/SequenceIterator; throws net/sf/saxon/trans/XPathException 
    ALOAD 1
    INVOKEINTERFACE net/sf/saxon/expr/XPathContext.getReceiver ()Lnet/sf/saxon/event/SequenceReceiver;
    ASTORE 2
    LINENUMBER 10 L0
   L1
    LDC "AxisExpressionCompiler - iterate"
    INVOKESTATIC com/saxonica/ee/bytecode/util/ByteCodeTrace.showMessage (Ljava/lang/String;)V
    ALOAD 1
    INVOKEINTERFACE net/sf/saxon/expr/XPathContext.getContextItem ()Lnet/sf/saxon/om/Item;
    CHECKCAST net/sf/saxon/om/NodeInfo
   L2
    LDC "AxisExpressionCompiler - static method: iterate"
    INVOKESTATIC com/saxonica/ee/bytecode/util/ByteCodeTrace.showMessage (Ljava/lang/String;)V
    ICONST_3
    GETSTATIC gen_SlashContextMappingFunction_27.nNameTest28 : Lnet/sf/saxon/pattern/NameTest;
    LDC "calling iterateAxis"
    INVOKESTATIC com/saxonica/ee/bytecode/util/ByteCodeTrace.showMessage (Ljava/lang/String;)V
    INVOKEINTERFACE net/sf/saxon/om/NodeInfo.iterateAxis (BLnet/sf/saxon/pattern/NodeTest;)Lnet/sf/saxon/tree/iter/AxisIterator;
    LDC "returning axis iterator"
    INVOKESTATIC com/saxonica/ee/bytecode/util/ByteCodeTrace.showMessage (Ljava/lang/String;)V
    ARETURN
    MAXSTACK = 0
    MAXLOCALS = 0
}

  // access flags 0x9
  public static Lnet/sf/saxon/pattern/NameTest; nNameTest28
}
