  // compiled from: file:/Users/mike/w3c/xslt30-test-B/tests/attr/avt/avt-0101.xsl
// class version 49.0 (49)
// access flags 0x1
public class gen_CompiledBlockIterator_5 extends com/saxonica/ee/bytecode/iter/CompiledBlockIterator  {


  // access flags 0x1
  public <init>()V
    ALOAD 0
    INVOKESPECIAL com/saxonica/ee/bytecode/iter/CompiledBlockIterator.<init> ()V
    RETURN
    MAXSTACK = 0
    MAXLOCALS = 0

  // access flags 0x1
  public next()Lnet/sf/saxon/om/Item; throws net/sf/saxon/trans/XPathException 
    LINENUMBER 7 L0
    ALOAD 0
    GETFIELD com/saxonica/ee/bytecode/iter/CompiledBlockIterator.context : Lnet/sf/saxon/expr/XPathContext;
    DUP
    ASTORE 1
    INVOKEINTERFACE net/sf/saxon/expr/XPathContext.getReceiver ()Lnet/sf/saxon/event/SequenceReceiver;
    ASTORE 3
    ACONST_NULL
    ASTORE 2
   L1
    ICONST_3
    INVOKESTATIC com/saxonica/ee/bytecode/util/ByteCodeTrace.trace (I)V
    ALOAD 0
    GETFIELD com/saxonica/ee/bytecode/iter/CompiledBlockIterator.currentIterator : Lnet/sf/saxon/om/SequenceIterator;
    DUP
    IFNONNULL L2
    POP
    GOTO L3
   L2
    ICONST_4
    INVOKESTATIC com/saxonica/ee/bytecode/util/ByteCodeTrace.trace (I)V
    INVOKEINTERFACE net/sf/saxon/om/SequenceIterator.next ()Lnet/sf/saxon/om/Item;
    DUP
    ASTORE 2
    IFNONNULL L4
    ALOAD 0
    ACONST_NULL
    PUTFIELD com/saxonica/ee/bytecode/iter/CompiledBlockIterator.currentIterator : Lnet/sf/saxon/om/SequenceIterator;
    GOTO L3
   L4
    ICONST_5
    INVOKESTATIC com/saxonica/ee/bytecode/util/ByteCodeTrace.trace (I)V
    GOTO L5
   L3
    BIPUSH 6
    INVOKESTATIC com/saxonica/ee/bytecode/util/ByteCodeTrace.trace (I)V
    ALOAD 0
    GETFIELD com/saxonica/ee/bytecode/iter/CompiledBlockIterator.state : I
    TABLESWITCH
      0: L6
      1: L7
      2: L8
      default: L9
   L6
   L10
    LDC "BlockCompiler - caseStatement"
    INVOKESTATIC com/saxonica/ee/bytecode/util/ByteCodeTrace.showMessage (Ljava/lang/String;)V
    ALOAD 0
    ICONST_1
    PUTFIELD com/saxonica/ee/bytecode/iter/CompiledBlockIterator.state : I
   L11
    LDC "BlockCompiler - caseStatement0"
    INVOKESTATIC com/saxonica/ee/bytecode/util/ByteCodeTrace.showMessage (Ljava/lang/String;)V
   L12
    LDC "LiteralCompiler-itr"
    INVOKESTATIC com/saxonica/ee/bytecode/util/ByteCodeTrace.showMessage (Ljava/lang/String;)V
    GETSTATIC gen_CompiledBlockIterator_5.nSequenceExtent6 : Lnet/sf/saxon/value/SequenceExtent;
    INVOKEINTERFACE net/sf/saxon/om/Sequence.iterate ()Lnet/sf/saxon/om/SequenceIterator;
    ALOAD 0
    SWAP
    PUTFIELD com/saxonica/ee/bytecode/iter/CompiledBlockIterator.currentIterator : Lnet/sf/saxon/om/SequenceIterator;
    GOTO L1
   L7
   L13
    LDC "BlockCompiler - caseStatement"
    INVOKESTATIC com/saxonica/ee/bytecode/util/ByteCodeTrace.showMessage (Ljava/lang/String;)V
    ALOAD 0
    ICONST_2
    PUTFIELD com/saxonica/ee/bytecode/iter/CompiledBlockIterator.state : I
   L14
    LDC "BlockCompiler - caseStatement1"
    INVOKESTATIC com/saxonica/ee/bytecode/util/ByteCodeTrace.showMessage (Ljava/lang/String;)V
   L15
    LDC "AtomizerCompiler-Itr"
    INVOKESTATIC com/saxonica/ee/bytecode/util/ByteCodeTrace.showMessage (Ljava/lang/String;)V
   L16
    LDC "AxisExpressionCompiler - iterate"
    INVOKESTATIC com/saxonica/ee/bytecode/util/ByteCodeTrace.showMessage (Ljava/lang/String;)V
    ALOAD 1
    INVOKEINTERFACE net/sf/saxon/expr/XPathContext.getContextItem ()Lnet/sf/saxon/om/Item;
    CHECKCAST net/sf/saxon/om/NodeInfo
   L17
    LDC "AxisExpressionCompiler - static method: iterate"
    INVOKESTATIC com/saxonica/ee/bytecode/util/ByteCodeTrace.showMessage (Ljava/lang/String;)V
    ICONST_3
    GETSTATIC gen_CompiledBlockIterator_5.nNameTest7 : Lnet/sf/saxon/pattern/NameTest;
    LDC "calling iterateAxis"
    INVOKESTATIC com/saxonica/ee/bytecode/util/ByteCodeTrace.showMessage (Ljava/lang/String;)V
    INVOKEINTERFACE net/sf/saxon/om/NodeInfo.iterateAxis (BLnet/sf/saxon/pattern/NodeTest;)Lnet/sf/saxon/tree/iter/AxisIterator;
    LDC "returning axis iterator"
    INVOKESTATIC com/saxonica/ee/bytecode/util/ByteCodeTrace.showMessage (Ljava/lang/String;)V
    ICONST_1
    INVOKESTATIC net/sf/saxon/expr/Atomizer.getAtomizingIterator (Lnet/sf/saxon/om/SequenceIterator;Z)Lnet/sf/saxon/om/SequenceIterator;
    ALOAD 0
    SWAP
    PUTFIELD com/saxonica/ee/bytecode/iter/CompiledBlockIterator.currentIterator : Lnet/sf/saxon/om/SequenceIterator;
    GOTO L1
   L8
   L18
    LDC "BlockCompiler - caseStatement"
    INVOKESTATIC com/saxonica/ee/bytecode/util/ByteCodeTrace.showMessage (Ljava/lang/String;)V
   L19
    LDC "BlockCompiler - default"
    INVOKESTATIC com/saxonica/ee/bytecode/util/ByteCodeTrace.showMessage (Ljava/lang/String;)V
    ACONST_NULL
    ASTORE 2
    GOTO L20
   L9
   L20
   L5
    BIPUSH 7
    INVOKESTATIC com/saxonica/ee/bytecode/util/ByteCodeTrace.trace (I)V
    ALOAD 2
    ARETURN
    MAXSTACK = 0
    MAXLOCALS = 0
}

  // access flags 0x9
  public static Lnet/sf/saxon/value/SequenceExtent; nSequenceExtent6

  // access flags 0x9
  public static Lnet/sf/saxon/pattern/NameTest; nNameTest7
}
